Workbook

Sheet Resumo
A1: Mês | B1: ABASTECEDORA DE COMBUSTIVEIS SIVIERO LTD | C1: SIVIERO EMPREENDIMENTOS IMOBILIARIOS LTD | D1: TRANSPORTADORA IRMAOS SIVIERO LTDA. | E1: Total saídas | G1: Lotes vendidos | H1: Lotes com valor citado | I1: Valor citado (soma dos lotes)
A2: 45108 | B2: =SUMIFS(Consolidado!$H:$H,Consolidado!$A:$A,$A2,Consolidado!$C:$C,B$1) | C2: =SUMIFS(Consolidado!$H:$H,Consolidado!$A:$A,$A2,Consolidado!$C:$C,C$1) | D2: =SUMIFS(Consolidado!$H:$H,Consolidado!$A:$A,$A2,Consolidado!$C:$C,D$1) | E2: =SUM(B2:D2) | G2: =COUNTIFS('Lotes Vendidos (todos)'!$K:$K,$A2) | H2: =COUNTIFS('Lotes Vendidos (todos)'!$K:$K,$A2,'Lotes Vendidos (todos)'!$G:$G,"<>") | I2: =SUMIFS('Lotes Vendidos (todos)'!$G:$G,'Lotes Vendidos (todos)'!$K:$K,$A2)
A3: 45139 | B3: =SUMIFS(Consolidado!$H:$H,Consolidado!$A:$A,$A3,Consolidado!$C:$C,B$1) | C3: =SUMIFS(Consolidado!$H:$H,Consolidado!$A:$A,$A3,Consolidado!$C:$C,C$1) | D3: =SUMIFS(Consolidado!$H:$H,Consolidado!$A:$A,$A3,Consolidado!$C:$C,D$1) | E3: =SUM(B3:D3) | G3: =COUNTIFS('Lotes Vendidos (todos)'!$K:$K,$A3) | H3: =COUNTIFS('Lotes Vendidos (todos)'!$K:$K,$A3,'Lotes Vendidos (todos)'!$G:$G,"<>") | I3: =SUMIFS('Lotes Vendidos (todos)'!$G:$G,'Lotes Vendidos (todos)'!$K:$K,$A3)
A4: 45170 | B4: sem relatório | C4: sem relatório | D4: sem relatório | E4: sem relatório | G4: =COUNTIFS('Lotes Vendidos (todos)'!$K:$K,$A4) | H4: =COUNTIFS('Lotes Vendidos (todos)'!$K:$K,$A4,'Lotes Vendidos (todos)'!$G:$G,"<>") | I4: =SUMIFS('Lotes Vendidos (todos)'!$G:$G,'Lotes Vendidos (todos)'!$K:$K,$A4)
A5: 45200 | B5: =SUMIFS(Consolidado!$H:$H,Consolidado!$A:$A,$A5,Consolidado!$C:$C,B$1) | C5: =SUMIFS(Consolidado!$H:$H,Consolidado!$A:$A,$A5,Consolidado!$C:$C,C$1) | D5: =SUMIFS(Consolidado!$H:$H,Consolidado!$A:$A,$A5,Consolidado!$C:$C,D$1) | E5: =SUM(B5:D5) | G5: =COUNTIFS('Lotes Vendidos (todos)'!$K:$K,$A5) | H5: =COUNTIFS('Lotes Vendidos (todos)'!$K:$K,$A5,'Lotes Vendidos (todos)'!$G:$G,"<>") | I5: =SUMIFS('Lotes Vendidos (todos)'!$G:$G,'Lotes Vendidos (todos)'!$K:$K,$A5)
A6: 45231 | B6: =SUMIFS(Consolidado!$H:$H,Consolidado!$A:$A,$A6,Consolidado!$C:$C,B$1) | C6: =SUMIFS(Consolidado!$H:$H,Consolidado!$A:$A,$A6,Consolidado!$C:$C,C$1) | D6: =SUMIFS(Consolidado!$H:$H,Consolidado!$A:$A,$A6,Consolidado!$C:$C,D$1) | E6: =SUM(B6:D6) | G6: =COUNTIFS('Lotes Vendidos (todos)'!$K:$K,$A6) | H6: =COUNTIFS('Lotes Vendidos (todos)'!$K:$K,$A6,'Lotes Vendidos (todos)'!$G:$G,"<>") | I6: =SUMIFS('Lotes Vendidos (todos)'!$G:$G,'Lotes Vendidos (todos)'!$K:$K,$A6)
A7: 45261 | B7: =SUMIFS(Consolidado!$H:$H,Consolidado!$A:$A,$A7,Consolidado!$C:$C,B$1) | C7: =SUMIFS(Consolidado!$H:$H,Consolidado!$A:$A,$A7,Consolidado!$C:$C,C$1) | D7: =SUMIFS(Consolidado!$H:$H,Consolidado!$A:$A,$A7,Consolidado!$C:$C,D$1) | E7: =SUM(B7:D7) | G7: =COUNTIFS('Lotes Vendidos (todos)'!$K:$K,$A7) | H7: =COUNTIFS('Lotes Vendidos (todos)'!$K:$K,$A7,'Lotes Vendidos (todos)'!$G:$G,"<>") | I7: =SUMIFS('Lotes Vendidos (todos)'!$G:$G,'Lotes Vendidos (todos)'!$K:$K,$A7)
A8: 45292 | B8: =SUMIFS(Consolidado!$H:$H,Consolidado!$A:$A,$A8,Consolidado!$C:$C,B$1) | C8: =SUMIFS(Consolidado!$H:$H,Consolidado!$A:$A,$A8,Consolidado!$C:$C,C$1) | D8: =SUMIFS(Consolidado!$H:$H,Consolidado!$A:$A,$A8,Consolidado!$C:$C,D$1) | E8: =SUM(B8:D8) | G8: =COUNTIFS('Lotes Vendidos (todos)'!$K:$K,$A8) | H8: =COUNTIFS('Lotes Vendidos (todos)'!$K:$K,$A8,'Lotes Vendidos (todos)'!$G:$G,"<>") | I8: =SUMIFS('Lotes Vendidos (todos)'!$G:$G,'Lotes Vendidos (todos)'!$K:$K,$A8)
A9: 45323 | B9: =SUMIFS(Consolidado!$H:$H,Consolidado!$A:$A,$A9,Consolidado!$C:$C,B$1) | C9: =SUMIFS(Consolidado!$H:$H,Consolidado!$A:$A,$A9,Consolidado!$C:$C,C$1) | D9: =SUMIFS(Consolidado!$H:$H,Consolidado!$A:$A,$A9,Consolidado!$C:$C,D$1) | E9: =SUM(B9:D9) | G9: =COUNTIFS('Lotes Vendidos (todos)'!$K:$K,$A9) | H9: =COUNTIFS('Lotes Vendidos (todos)'!$K:$K,$A9,'Lotes Vendidos (todos)'!$G:$G,"<>") | I9: =SUMIFS('Lotes Vendidos (todos)'!$G:$G,'Lotes Vendidos (todos)'!$K:$K,$A9)
A10: 45352 | B10: =SUMIFS(Consolidado!$H:$H,Consolidado!$A:$A,$A10,Consolidado!$C:$C,B$1) | C10: =SUMIFS(Consolidado!$H:$H,Consolidado!$A:$A,$A10,Consolidado!$C:$C,C$1) | D10: =SUMIFS(Consolidado!$H:$H,Consolidado!$A:$A,$A10,Consolidado!$C:$C,D$1) | E10: =SUM(B10:D10) | G10: =COUNTIFS('Lotes Vendidos (todos)'!$K:$K,$A10) | H10: =COUNTIFS('Lotes Vendidos (todos)'!$K:$K,$A10,'Lotes Vendidos (todos)'!$G:$G,"<>") | I10: =SUMIFS('Lotes Vendidos (todos)'!$G:$G,'Lotes Vendidos (todos)'!$K:$K,$A10)
A11: 45383 | B11: =SUMIFS(Consolidado!$H:$H,Consolidado!$A:$A,$A11,Consolidado!$C:$C,B$1) | C11: =SUMIFS(Consolidado!$H:$H,Consolidado!$A:$A,$A11,Consolidado!$C:$C,C$1) | D11: =SUMIFS(Consolidado!$H:$H,Consolidado!$A:$A,$A11,Consolidado!$C:$C,D$1) | E11: =SUM(B11:D11) | G11: =COUNTIFS('Lotes Vendidos (todos)'!$K:$K,$A11) | H11: =COUNTIFS('Lotes Vendidos (todos)'!$K:$K,$A11,'Lotes Vendidos (todos)'!$G:$G,"<>") | I11: =SUMIFS('Lotes Vendidos (todos)'!$G:$G,'Lotes Vendidos (todos)'!$K:$K,$A11)
A12: 45413 | B12: =SUMIFS(Consolidado!$H:$H,Consolidado!$A:$A,$A12,Consolidado!$C:$C,B$1) | C12: =SUMIFS(Consolidado!$H:$H,Consolidado!$A:$A,$A12,Consolidado!$C:$C,C$1) | D12: =SUMIFS(Consolidado!$H:$H,Consolidado!$A:$A,$A12,Consolidado!$C:$C,D$1) | E12: =SUM(B12:D12) | G12: =COUNTIFS('Lotes Vendidos (todos)'!$K:$K,$A12) | H12: =COUNTIFS('Lotes Vendidos (todos)'!$K:$K,$A12,'Lotes Vendidos (todos)'!$G:$G,"<>") | I12: =SUMIFS('Lotes Vendidos (todos)'!$G:$G,'Lotes Vendidos (todos)'!$K:$K,$A12)
A13: 45444 | B13: =SUMIFS(Consolidado!$H:$H,Consolidado!$A:$A,$A13,Consolidado!$C:$C,B$1) | C13: =SUMIFS(Consolidado!$H:$H,Consolidado!$A:$A,$A13,Consolidado!$C:$C,C$1) | D13: =SUMIFS(Consolidado!$H:$H,Consolidado!$A:$A,$A13,Consolidado!$C:$C,D$1) | E13: =SUM(B13:D13) | G13: =COUNTIFS('Lotes Vendidos (todos)'!$K:$K,$A13) | H13: =COUNTIFS('Lotes Vendidos (todos)'!$K:$K,$A13,'Lotes Vendidos (todos)'!$G:$G,"<>") | I13: =SUMIFS('Lotes Vendidos (todos)'!$G:$G,'Lotes Vendidos (todos)'!$K:$K,$A13)
A14: 45474 | B14: =SUMIFS(Consolidado!$H:$H,Consolidado!$A:$A,$A14,Consolidado!$C:$C,B$1) | C14: =SUMIFS(Consolidado!$H:$H,Consolidado!$A:$A,$A14,Consolidado!$C:$C,C$1) | D14: =SUMIFS(Consolidado!$H:$H,Consolidado!$A:$A,$A14,Consolidado!$C:$C,D$1) | E14: =SUM(B14:D14) | G14: =COUNTIFS('Lotes Vendidos (todos)'!$K:$K,$A14) | H14: =COUNTIFS('Lotes Vendidos (todos)'!$K:$K,$A14,'Lotes Vendidos (todos)'!$G:$G,"<>") | I14: =SUMIFS('Lotes Vendidos (todos)'!$G:$G,'Lotes Vendidos (todos)'!$K:$K,$A14)
A15: 45505 | B15: =SUMIFS(Consolidado!$H:$H,Consolidado!$A:$A,$A15,Consolidado!$C:$C,B$1) | C15: =SUMIFS(Consolidado!$H:$H,Consolidado!$A:$A,$A15,Consolidado!$C:$C,C$1) | D15: =SUMIFS(Consolidado!$H:$H,Consolidado!$A:$A,$A15,Consolidado!$C:$C,D$1) | E15: =SUM(B15:D15) | G15: =COUNTIFS('Lotes Vendidos (todos)'!$K:$K,$A15) | H15: =COUNTIFS('Lotes Vendidos (todos)'!$K:$K,$A15,'Lotes Vendidos (todos)'!$G:$G,"<>") | I15: =SUMIFS('Lotes Vendidos (todos)'!$G:$G,'Lotes Vendidos (todos)'!$K:$K,$A15)
A16: 45536 | B16: =SUMIFS(Consolidado!$H:$H,Consolidado!$A:$A,$A16,Consolidado!$C:$C,B$1) | C16: =SUMIFS(Consolidado!$H:$H,Consolidado!$A:$A,$A16,Consolidado!$C:$C,C$1) | D16: =SUMIFS(Consolidado!$H:$H,Consolidado!$A:$A,$A16,Consolidado!$C:$C,D$1) | E16: =SUM(B16:D16) | G16: =COUNTIFS('Lotes Vendidos (todos)'!$K:$K,$A16) | H16: =COUNTIFS('Lotes Vendidos (todos)'!$K:$K,$A16,'Lotes Vendidos (todos)'!$G:$G,"<>") | I16: =SUMIFS('Lotes Vendidos (todos)'!$G:$G,'Lotes Vendidos (todos)'!$K:$K,$A16)
A17: 45566 | B17: =SUMIFS(Consolidado!$H:$H,Consolidado!$A:$A,$A17,Consolidado!$C:$C,B$1) | C17: =SUMIFS(Consolidado!$H:$H,Consolidado!$A:$A,$A17,Consolidado!$C:$C,C$1) | D17: =SUMIFS(Consolidado!$H:$H,Consolidado!$A:$A,$A17,Consolidado!$C:$C,D$1) | E17: =SUM(B17:D17) | G17: =COUNTIFS('Lotes Vendidos (todos)'!$K:$K,$A17) | H17: =COUNTIFS('Lotes Vendidos (todos)'!$K:$K,$A17,'Lotes Vendidos (todos)'!$G:$G,"<>") | I17: =SUMIFS('Lotes Vendidos (todos)'!$G:$G,'Lotes Vendidos (todos)'!$K:$K,$A17)
A18: Total | B18: =SUM(B2:B17) | C18: =SUM(C2:C17) | D18: =SUM(D2:D17) | E18: =SUM(E2:E17) | G18: =SUM(G2:G17) | H18: =SUM(H2:H17) | I18: =SUM(I2:I17)
A20: Notas:
A21: Saídas = coluna Valor Dupl. dos relatórios de Contas Pagas (jul/2023 a out/2024). Setembro/2023 não tem relatório na pasta.
A22: Lotes = lista "17 - LOTES VENDIDOS DE JANEIRO DE 2018 A OUTUBRO DE 2025 - REV.13.08.2026", que não tem coluna de valor.
A23: "Valor citado" é o valor em R$ que aparece no texto da observação do lote (o total quando o texto o indica; vazio quando não há valor ou há vários sem total).
A24: Esse valor pode ser parcial (só a parte em permuta ou em dinheiro) e, em vendas conjuntas, o mesmo valor se repete em cada lote; a soma mensal é só indicativa.
A25: Lotes fora do período (1992-2026) e o lote sem data estão na aba "Lotes Vendidos (todos)".

Sheet Consolidado
A1: Mês | B1: Página | C1: Empresa | D1: Fornecedor | E1: Vencimento | F1: Pagamento | G1: Valor NF | H1: Valor Dupl. | I1: Observações | K1: Mês | L1: Data | M1: Loteamento | N1: Município | O1: Lote | P1: Quadra | Q1: Comprador | R1: Valor citado | S1: Valores no texto | T1: Venda conjunta | U1: Observações
A2: 45108 | B2: 1 | C2: SIVIERO EMPREENDIMENTOS IMOBILIARIOS LTD | D2: DORVAL FRANCISCO BOFF - CAXIAS DO SUL | E2: 45110 | F2: 45110 | G2: 100000 | H2: 10000 | I2: P.04/10-CFE CONTRATO ANTECIPACAO VALORES - LO | K2: 45108 | L2: 45111 | M2: SOL NASCENTE I | N2: ANTÔNIO PRADO | O2: 24 | P2: D | Q2: Cassiano Damiani | R2: 67000 | S2: R$ 67.000,00 | U2: Vendido à vista, sendo R$ 67.000,00 em permuta veículo GM/S10 – JID 4877.
A3: 45108 | B3: 1 | C3: SIVIERO EMPREENDIMENTOS IMOBILIARIOS LTD | D3: PROGETEC - ALENCAR TRINDADE - P.FUNDO | E3: 45110 | F3: 45110 | G3: 25000 | H3: 5000 | I3: P.3/5-INSTALACAO D+ HASTES CERCA ELETRICA+INS | K3: 45108 | L3: 45113 | M3: INDUSTRIAL PEDRA LISA | N3: VERANÓPOLIS | O3: 01 | P3: 07 | Q3: Ind. Concretos Rivacci | R3: 55000 | S3: R$ 55.000,00 | T3: Sim (2 lotes) | U3: Vendido à vista, com permuta de um pavilhão pré fabricado (a entregar) e uma camionete I/Toyota Hilux e o valor em espécie de R$ 55.000,00.
A4: 45108 | B4: 1 | C4: SIVIERO EMPREENDIMENTOS IMOBILIARIOS LTD | D4: PREFEITURA MUNICIPAL DE NOVA PRATA | E4: 45110 | F4: 45110 | G4: 36.96 | H4: 36.96 | I4: CERTIDAO DE LOCALIZAÇAO AREA-BELLA VISIONE-NO | K4: 45108 | L4: 45113 | M4: INDUSTRIAL PEDRA LISA | N4: VERANÓPOLIS | O4: 02 | P4: 07 | Q4: Ind. Concretos Rivacci | R4: 55000 | S4: R$ 55.000,00 | T4: Sim (2 lotes) | U4: Vendido à vista, com permuta de um pavilhão pré fabricado (a entregar) e uma camionete I/Toyota Hilux e o valor em espécie de R$ 55.000,00.
A5: 45108 | B5: 1 | C5: SIVIERO EMPREENDIMENTOS IMOBILIARIOS LTD | D5: SIM REDE DE POSTOS LTDA. - VERANOPOLI | E5: 45109 | F5: 45110 | G5: 521.89 | H5: 521.89 | I5: ABASTECIMENTOS CARROS+CACAMBAS+OFICINA=VER | K5: 45108 | L5: 45125 | M5: CARNEVALLI | N5: NOVA PRATA | O5: 06 | P5: C | Q5: Érica Basso | U5: Vendido à prazo, em 02x.
A6: 45108 | B6: 1 | C6: SIVIERO EMPREENDIMENTOS IMOBILIARIOS LTD | D6: INES TREVISAN PICCOLI - JUROS | E6: 45108 | F6: 45110 | G6: 250000 | H6: 2500 | I6: JUROS 1.00% S/ R$ 250.000,00 - EMPRESTIMO | K6: 45139 | L6: 45146 | M6: BALDASSO | N6: CARLOS BARBOSA | O6: 40 | P6: 06 | Q6: Edmar Camillo | U6: Vendido à prazo, em 14x.
A7: 45108 | B7: 1 | C7: SIVIERO EMPREENDIMENTOS IMOBILIARIOS LTD | D7: ANDRE LUIZ SIVIERO - JUROS | E7: 45108 | F7: 45110 | G7: 100000 | H7: 800 | I7: JUROS 0,80% S/ R$ 100.000,00 - EMPRESTIMO | K7: 45139 | L7: 45149 | M7: CONDOMÍNIO MORADA DOS IPÊS | N7: PASSO FUNDO | O7: 012 | P7: 04 | Q7: Leandro Capelesso | R7: 75000 | S7: R$ 75.000,00 | U7: Vendido à prazo, em 05x, com parte em permuta de um carro pelo valor de R$ 75.000,00 e reparceladas as parcelas para viabilizar o pagamento em 21x.
A8: 45108 | B8: 1 | C8: SIVIERO EMPREENDIMENTOS IMOBILIARIOS LTD | D8: SAMIR TREVISAN PICCOLI - JUROS | E8: 45108 | F8: 45110 | G8: 350000 | H8: 3500 | I8: JUROS 1.00% S/ R$ 350.000,00 - EMPRESTIMO | K8: 45139 | L8: 45155 | M8: CONDOMÍNIO MORADA DOS IPÊS | N8: PASSO FUNDO | O8: 004 | P8: 04 | Q8: Luiz Fernando Klaus | U8: Vendido à prazo, em 07x.
A9: 45108 | B9: 1 | C9: SIVIERO EMPREENDIMENTOS IMOBILIARIOS LTD | D9: SAMIR TREVISAN PICCOLI - JUROS | E9: 45108 | F9: 45110 | G9: 150000 | H9: 1500 | I9: JUROS 1.00% S/ R$ 150.000,00 - EMPRESTIMO | K9: 45139 | L9: 45161 | M9: SOLAR NORTE | N9: VERANÓPOLIS | O9: 06 | P9: 01 | Q9: Lindolfo Lago | R9: 350000 | S9: R$ 350.000,00 | U9: Vendido, como forma de pagamento pela aquisição de uma área de 3.100,00m² junto com a área da FAMÍLIA LAGO, em Sapopema, pelo valor total de R$ 350.000,00.
A10: 45108 | B10: 1 | C10: SIVIERO EMPREENDIMENTOS IMOBILIARIOS LTD | D10: SAMIR TREVISAN PICCOLI - JUROS | E10: 45108 | F10: 45110 | G10: 250000 | H10: 2500 | I10: JUROS 1.00% S/ R$ 250.000,00 - EMPRESTIMO | K10: 45139 | L10: 45168 | M10: ALTOS DA JULIETA | N10: FARROUPILHA | O10: 01 | P10: 1734 | Q10: Gláucio da Rosa Monteiro | U10: Vendido à vista.
A11: 45108 | B11: 1 | C11: SIVIERO EMPREENDIMENTOS IMOBILIARIOS LTD | D11: SAMIR TREVISAN PICCOLI - JUROS | E11: 45108 | F11: 45110 | G11: 250000 | H11: 2500 | I11: JUROS 1.00% S/ R$ 250.000,00 - EMPRESTIMO EM | K11: 45170 | L11: 45175 | M11: ALTOS DAS GRAÇAS | N11: CAXIAS DO SUL | O11: 02 | P11: 6373 | Q11: Rosa Maria Nascimento | U11: Vendido à vista.
A12: 45108 | B12: 1 | C12: SIVIERO EMPREENDIMENTOS IMOBILIARIOS LTD | D12: BANCO SICREDI - VERANÓPOLIS | E12: 45110 | F12: 45110 | G12: 0.18 | H12: 0.18 | I12: JUROS BANCO CREDITO ROTATIVO MES JUNHO/2023 | K12: 45170 | L12: 45177 | M12: SALVADOR – FEMAÇÃ II | N12: VERANÓPOLIS | O12: 04 | P12: 04 | Q12: Prefeitura de Veranópolis | U12: Doação conforme Lei.
A13: 45108 | B13: 1 | C13: SIVIERO EMPREENDIMENTOS IMOBILIARIOS LTD | D13: IOF BANCARIO SIVIERO EMP IMOBILIARIOS | E13: 45110 | F13: 45110 | G13: 308.55 | H13: 308.55 | I13: IOF CONTA SEI MES DE JUNHO DE 2023 - BANRISUL | K13: 45170 | L13: 45182 | M13: LAGO NEGRO | N13: GRAMADO | O13: 01 | P13: 07 | Q13: Fruti Frango Adm Imóveis | U13: Vendido à vista.
A14: 45108 | B14: 1 | C14: SIVIERO EMPREENDIMENTOS IMOBILIARIOS LTD | D14: IOF BANCARIO SIVIERO EMP IMOBILIARIOS | E14: 45110 | F14: 45110 | G14: 657.74 | H14: 657.74 | I14: IOF CONTA SEI MES DE JUNHO DE 2023 - BANRISUL | K14: 45170 | L14: 45190 | M14: COLINA DO RETIRO I | N14: VERANÓPOLIS | O14: 01 | P14: 02 | Q14: Maicon A. Mikoaski | U14: Vendido à vista.
A15: 45108 | B15: 1 | C15: SIVIERO EMPREENDIMENTOS IMOBILIARIOS LTD | D15: MULTAS DE TRANSITO | E15: 45111 | F15: 45111 | G15: 156.19 | H15: 156.19 | I15: CACAMBA ILD 3959 - NAO IDENTIFICAÇÃO DE CONDU | K15: 45170 | L15: 45191 | M15: INDUSTRIAL PEDRA LISA | N15: VERANÓPOLIS | O15: 03 | P15: 03 | Q15: Ivo José Frainer | R15: 388000 | S15: R$ 388.000,00 | U15: Vendido, como forma de pagamento na aquisição de 0,67 há de terras ao lado do Loteamento Industrial Pedra Lisa, pelo valor de R$ 388.000,00.
A16: 45108 | B16: 1 | C16: SIVIERO EMPREENDIMENTOS IMOBILIARIOS LTD | D16: PORTAL EMPREENDIMENTOS IMOBILIARIOS L | E16: 45111 | F16: 45111 | G16: 10000 | H16: 2000 | I16: P.1/4-COMISSAO LT 06-QDRA 1342-SAN MARINO=DAN | K16: 45170 | L16: 45195 | M16: SALVADOR – FEMAÇÃ II | N16: VERANÓPOLIS | O16: 01 | P16: 04 | Q16: Volmir Marinello | U16: Vendido à prazo.
A17: 45108 | B17: 1 | C17: SIVIERO EMPREENDIMENTOS IMOBILIARIOS LTD | D17: PORTAL EMPREENDIMENTOS IMOBILIARIOS L | E17: 45111 | F17: 45111 | G17: 10000 | H17: 2000 | I17: P.2/4-COMISSAO LT 06-QDRA 1342-SAN MARINO=DAN | K17: 45200 | L17: 45230 | M17: MONTE VÊNETO | N17: COTIPORÃ | O17: 04 | P17: 04 | Q17: Nilton de Oliveira Vieira | T17: Sim (2 lotes) | U17: Vendido à prazo, em 26x.
A18: 45108 | B18: 1 | C18: SIVIERO EMPREENDIMENTOS IMOBILIARIOS LTD | D18: CASSIANO DAMIANI - ANTONIO PRADO | E18: 45111 | F18: 45111 | G18: 67000 | H18: 67000 | I18: LT 24-Q.D-SOL NASCEN CASSIANO DAMIANI-CAMIONE | K18: 45200 | L18: 45230 | M18: MONTE VÊNETO | N18: COTIPORÃ | O18: 05 | P18: 04 | Q18: Nilton de Oliveira Vieira | T18: Sim (2 lotes) | U18: Vendido à prazo, em 26x.
A19: 45108 | B19: 1 | C19: SIVIERO EMPREENDIMENTOS IMOBILIARIOS LTD | D19: BANCO ESTADO RIO GRANDE DO SUL - SEI | E19: 45111 | F19: 45111 | G19: 180 | H19: 180 | I19: SEI - TAXA MENSALIDADE PACOTE CONTA SEI - BAN | K19: 45231 | L19: 45231 | M19: VIERO | N19: FARROUPILHA | O19: 12 | P19: 1467 | Q19: Elizete/Rosália de Oliveira | U19: Vendido à vista.
A20: 45108 | B20: 1 | C20: SIVIERO EMPREENDIMENTOS IMOBILIARIOS LTD | D20: ANTONINHO JOSE ZANELLA - PASSO FUNDO | E20: 45112 | F20: 45112 | G20: 2000 | H20: 1000 | I20: RADIO PLANALTO-DIVULGACAO VENDAS LOTES MORAD | K20: 45231 | L20: 45238 | M20: CONDOMÍNIO MORADA DOS IPÊS | N20: PASSO FUNDO | O20: 008 | P20: 04 | Q20: Raul Martini | U20: Vendido à prazo, em 02x.
A21: 45108 | B21: 1 | C21: SIVIERO EMPREENDIMENTOS IMOBILIARIOS LTD | D21: D KEKOS COM MANGUEIRAS E CONEXOES LTI | E21: 45112 | F21: 45112 | G21: 556.5 | H21: 556.5 | I21: MANGUEIRA E CONEXAO - ESCAVADEIRA HIDRAULICA | K21: 45261 | L21: 45278 | M21: SALVADOR – FEMAÇÃ II | N21: VERANÓPOLIS | O21: 01 | P21: 03 | Q21: Rogério Binda | T21: Sim (2 lotes) | U21: Vendido à vista.
A22: 45108 | B22: 1 | C22: SIVIERO EMPREENDIMENTOS IMOBILIARIOS LTD | D22: HOTEL ARACA LTDA | E22: 45112 | F22: 45112 | G22: 11500 | H22: 6000 | I22: RAUL SIVIERO+PAGTO CONTAS INDIVIDUAIS+DIF DEP | K22: 45261 | L22: 45278 | M22: SALVADOR – FEMAÇÃ II | N22: VERANÓPOLIS | O22: 02 | P22: 03 | Q22: Rogério Binda | T22: Sim (2 lotes) | U22: Vendido à vista.
A23: 45108 | B23: 1 | C23: SIVIERO EMPREENDIMENTOS IMOBILIARIOS LTD | D23: A. R. T. | E23: 45112 | F23: 45112 | G23: 96.62 | H23: 96.62 | I23: PEDRO ELIAS SIVIERO-RELATORIO ATERRO 03 LOTES | K23: 45261 | L23: 45280 | M23: ALTOS DAS GRAÇAS | N23: CAXIAS DO SUL | O23: 14 | P23: 6369 | Q23: MSL Incorporadora Ltda. | U23: Vendido à prazo, em 02x.
A24: 45108 | B24: 1 | C24: SIVIERO EMPREENDIMENTOS IMOBILIARIOS LTD | D24: COMBUSTIVEIS | E24: 45112 | F24: 45112 | G24: 100 | H24: 100 | I24: FUNCIONARIO EVERTON-PAGTO COMBUSTIVEIS VIAGE | K24: 45292 | L24: 45292 | M24: BARBIERO | N24: NOVA PRATA | O24: 08 | P24: 02 | Q24: André Luiz Siviero | U24: Vendido, como forma de devolução de empréstimo e pagamento de juros.
A25: 45108 | B25: 1 | C25: SIVIERO EMPREENDIMENTOS IMOBILIARIOS LTD | D25: LOJA DO PARABRISA LTDA. - GOIANIA | E25: 45112 | F25: 45112 | G25: 583 | H25: 583 | I25: 01 PARABRISA - VIDRO INFERIOR ESCAVADEIRA DO | K25: 45292 | L25: 45306 | M25: CONDOMÍNIO MORADA DOS IPÊS | N25: PASSO FUNDO | O25: 001 | P25: 06 | Q25: Juliano Pretto Elton Sobiesiak | U25: Vendido, como forma de pagamento de DAÇÃO EM PAGAMENTO, referente a aquisição de uma área de terras doada para o Município de Passo Fundo, para compensação de áreas para as 02 (duas) fases do Condomínio Morada dos Ipês II, em Passo Fundo, num total de 03 (três) lotes dentro do Condomínio, em parceria com a Família Zanella.
A26: 45108 | B26: 1 | C26: SIVIERO EMPREENDIMENTOS IMOBILIARIOS LTD | D26: MULTAS DE TRANSITO | E26: 45112 | F26: 45112 | G26: 78.09 | H26: 78.09 | I26: TOYOTA IYJ 8I14-PEDRO SIVIERO-EXCESSO VELOC.- | K26: 45323 | L26: 45349 | M26: MONTE VÊNETO | N26: COTIPORÃ | O26: 09 | P26: 01 | Q26: Rovílio Antônio Dal Más | R26: 190000 | S26: R$ 190.000,00 | T26: Sim (2 lotes) | U26: Vendido à vista, com permuta de outro imóvel – Lote 03, Quadra 04 – Loteamento Femaçã II – Veranópolis, valor de R$ 190.000,00.
A27: 45108 | B27: 1 | C27: SIVIERO EMPREENDIMENTOS IMOBILIARIOS LTD | D27: PAULA FARINA - VETERINARIA | E27: 45112 | F27: 45112 | G27: 400 | H27: 400 | I27: MEDICACAO PARA CACHORROS OFICINA SIVIERO - GI | K27: 45323 | L27: 45349 | M27: MONTE VÊNETO | N27: COTIPORÃ | O27: 10 | P27: 01 | Q27: Rovílio Antônio Dal Más | R27: 190000 | S27: R$ 190.000,00 | T27: Sim (2 lotes) | U27: Vendido à vista, com permuta de outro imóvel – Lote 03, Quadra 04 – Loteamento Femaçã II – Veranópolis, valor de R$ 190.000,00.
A28: 45108 | B28: 1 | C28: SIVIERO EMPREENDIMENTOS IMOBILIARIOS LTD | D28: RESTAURANTE - CAXIAS DO SUL | E28: 45112 | F28: 45112 | G28: 1369 | H28: 1369 | I28: PAGAMENTO REFEICOES MES DE MARCO/2023 - FUNCI | K28: 45352 | L28: 45370 | M28: ALTOS DAS GRAÇAS | N28: CAXIAS DO SUL | O28: 13 | P28: 6372 | Q28: Evandro Mário Zanrosso | U28: Vendido, conforme acordo ajustado dentre as partes, no Instrumento Particular de Acordo Extrajudicial, firmado em 19 de março de 2024, na forma de DAÇÃO EM PAGAMENTO.
A29: 45108 | B29: 1 | C29: SIVIERO EMPREENDIMENTOS IMOBILIARIOS LTD | D29: BANCO ESTADO RIO GRANDE DO SUL - SEI | E29: 45112 | F29: 45112 | G29: 245.45 | H29: 245.45 | I29: CONTA SEI - SEGURO VIDA PEDRO SIVIERO MAIO/20 | K29: 45352 | L29: 45372 | M29: SALVADOR – FEMAÇÃ II | N29: VERANÓPOLIS | O29: 02 | P29: 05 | Q29: Marcos Vinicius Dalazen | U29: Vendido à vista.
A30: 45108 | B30: 1 | C30: SIVIERO EMPREENDIMENTOS IMOBILIARIOS LTD | D30: VERAPECAS - PECAS E VEICULOS LTDA | E30: 45112 | F30: 45112 | G30: 970 | H30: 970 | I30: DISCO+FLUIDO+PASTILHAS DE FREIO+PALHETAS - FO | K30: 45383 | L30: 45398 | M30: ALTOS DA JULIETA | N30: FARROUPILHA | O30: 01 | P30: 1735 | Q30: Janete Basso | U30: Vendido à vista.
A31: 45108 | B31: 1 | C31: SIVIERO EMPREENDIMENTOS IMOBILIARIOS LTD | D31: RESTAURANTE - CAXIAS DO SUL | E31: 45112 | F31: 45112 | G31: 479.5 | H31: 479.5 | I31: PAGAMENTO REFEICOES MES DE JUNHO/2023 - FUNCI | K31: 45383 | L31: 45406 | M31: ADITIVO MEDIANEIRA | N31: VERANÓPOLIS | O31: 02 | P31: 07 | Q31: Solar Serra Ltda. | U31: Vendido, como forma de pagamento placas solares Hotel Araçá Ltda.
A32: 45108 | B32: 1 | C32: SIVIERO EMPREENDIMENTOS IMOBILIARIOS LTD | D32: CHAVES XAVIER - VERANOPOLIS | E32: 45112 | F32: 45112 | G32: 50 | H32: 50 | I32: ABERTURA PORTA APARTAMENTO GENI SIVIERO-APTO | K32: 45383 | L32: 45407 | M32: SOL NASCENTE II | N32: ANTÔNIO PRADO | O32: 11 | P32: C | Q32: Sustenseg Ltda. – Diego Zulian | U32: Vendido, como forma de pagamento pela prestação serviços – Topografia, Licenciamento, Aprovação e Registro do Loteamento Sol Nascente III.
A33: 45108 | B33: 1 | C33: SIVIERO EMPREENDIMENTOS IMOBILIARIOS LTD | D33: BANCO SICREDI - VERANÓPOLIS | E33: 45112 | F33: 45112 | G33: 67 | H33: 67 | I33: PAGTO TAXA MENSALIDADE BANCARIA CONTA SEI-SIC | K33: 45413 | L33: 45418 | M33: SAN MARINO | N33: FARROUPILHA | O33: 03 | P33: 1342 | Q33: Natalina Schwaiser | R33: 270000 | S33: R$ 270.000,00 | U33: Acordo – Arlindo Píccoli – Loteamento Vale das Colinas. Dívida de R$ 270.000,00.
A34: 45108 | B34: 1 | C34: SIVIERO EMPREENDIMENTOS IMOBILIARIOS LTD | D34: LADIR MADRUGA - CAXIAS DO SUL | E34: 45113 | F34: 45113 | G34: 3500 | H34: 3500 | I34: ROCADA LOTES LOTEAMENTOS EM FARROUPILHA - AC | K34: 45413 | L34: 45439 | M34: MONTE VÊNETO | N34: COTIPORÃ | O34: 07 | P34: 02 | Q34: Leonardo R. Kazienko | U34: Vendido à vista.
A35: 45108 | B35: 1 | C35: SIVIERO EMPREENDIMENTOS IMOBILIARIOS LTD | D35: INDUSTRIA DE CONCRETOS RIVACCI LTDA. | E35: 45113 | F35: 45113 | G35: 225000 | H35: 225000 | I35: TOYOTA HILUX-IZR 2E40-PAGTO LOTES 01 E 02-Q.7 | K35: 45413 | L35: 45440 | M35: BAÚ | N35: CARLOS BARBOSA | O35: 08 | P35: 04 | Q35: Rafael de Conti | U35: Vendido à vista.
A36: 45108 | B36: 1 | C36: SIVIERO EMPREENDIMENTOS IMOBILIARIOS LTD | D36: INDUSTRIA DE CONCRETOS RIVACCI LTDA. | E36: 45113 | F36: 45113 | G36: 370000 | H36: 370000 | I36: PAVILHAO PRE FABRICADO-PAGTO LOTES 01 E 02-Q. | K36: 45413 | L36: 45440 | M36: SOL NASCENTE I | N36: ANTÔNIO PRADO | O36: 09 | P36: B | Q36: Clóvis Pedro Zulian | T36: Sim (2 lotes) | U36: Vendidos, como forma de acerto pela Divisão Lotes pela participação nas despesas e custos na implantação dos Loteamentos (Fracionamentos) Sol Nascente I e II, de Antônio Prado, conforme Termo de Acordo.
A37: 45108 | B37: 1 | C37: SIVIERO EMPREENDIMENTOS IMOBILIARIOS LTD | D37: CHIQUINHO PNEUS | E37: 45113 | F37: 45114 | G37: 6600 | H37: 3300 | I37: P.2/2-CHEQUE-COMPRA 04 PNEUS NOVOS BORRACHUD | K37: 45413 | L37: 45440 | M37: SOL NASCENTE I | N37: ANTÔNIO PRADO | O37: 23 | P37: D | Q37: Clóvis Pedro Zulian | T37: Sim (2 lotes) | U37: Vendidos, como forma de acerto pela Divisão Lotes pela participação nas despesas e custos na implantação dos Loteamentos (Fracionamentos) Sol Nascente I e II, de Antônio Prado, conforme Termo de Acordo.
A38: 45108 | B38: 1 | C38: SIVIERO EMPREENDIMENTOS IMOBILIARIOS LTD | D38: PREFEITURA MUNICIPAL DE NOVA PRATA | E38: 45114 | F38: 45114 | G38: 4825.56 | H38: 4825.56 | I38: P.1/4-IPTU ANO 2023-LOTEAMENTO CARNEVALLI-NOV | K38: 45413 | L38: 45443 | M38: ALTOS DAS GRAÇAS | N38: CAXIAS DO SUL | O38: 08 | P38: 6365 | Q38: Soraya Dias Mais | U38: Vendido à prazo, em 02x.
A39: 45108 | B39: 1 | C39: SIVIERO EMPREENDIMENTOS IMOBILIARIOS LTD | D39: PREFEITURA MUNICIPAL DE NOVA PRATA | E39: 45114 | F39: 45114 | G39: 238.32 | H39: 238.32 | I39: P.1/4-IPTU ANO 2023-LOTEAMENTO TRUCCOLLO-NOVA | K39: 45444 | L39: 45467 | M39: SAN MARINO | N39: FARROUPILHA | O39: 02 | P39: 1342 | Q39: Eduardo Rossim | U39: Vendido à vista.
A40: 45108 | B40: 1 | C40: SIVIERO EMPREENDIMENTOS IMOBILIARIOS LTD | D40: PREFEITURA MUNICIPAL DE NOVA PRATA | E40: 45114 | F40: 45114 | G40: 1528.21 | H40: 1528.21 | I40: P.1/4-IPTU ANO 2023-LOTEAMENTO COLINA DO BASA | K40: 45474 | L40: 45475 | M40: SALVADOR – FEMAÇÃ II | N40: VERANÓPOLIS | O40: 03 | P40: 02 | Q40: Inês Ansolin Pessutto | R40: 714000 | S40: R$ 714.000,00 | T40: Sim (2 lotes) | U40: Vendido, como forma pagamento área terras em Vila Azul, valor de R$ 714.000,00.
A41: 45108 | B41: 1 | C41: SIVIERO EMPREENDIMENTOS IMOBILIARIOS LTD | D41: PREFEITURA MUNICIPAL DE NOVA PRATA | E41: 45114 | F41: 45114 | G41: 2420.2 | H41: 2420.2 | I41: P.1/4-IPTU ANO 2023-LOTEAMENTO BARBIERO-NOVA | K41: 45474 | L41: 45475 | M41: FEMAÇÃ | N41: VERANÓPOLIS | O41: 05 | P41: 09 | Q41: Inês Ansolin Pessutto | R41: 714000 | S41: R$ 714.000,00 | T41: Sim (2 lotes) | U41: Vendido, como forma pagamento área terras em Vila Azul, valor de R$ 714.000,00.
A42: 45108 | B42: 1 | C42: SIVIERO EMPREENDIMENTOS IMOBILIARIOS LTD | D42: FGTS - SIVIERO EMPREEND. IMOBILIARIOS | E42: 45114 | F42: 45114 | G42: 84.57 | H42: 84.57 | I42: FGTS S/ SALARIO FUNCIONARIOS - JUNHO DE 2023 | K42: 45474 | L42: 45478 | M42: SAN MARINO | N42: FARROUPILHA | O42: 08 | P42: 1342 | Q42: Luis Filipe Severgnini | U42: Vendido à prazo, em 10x.
A43: 45108 | B43: 1 | C43: SIVIERO EMPREENDIMENTOS IMOBILIARIOS LTD | D43: GERALDO MERZONI - CARLOS BARBOSA | E43: 45115 | F43: 45117 | G43: 22800 | H43: 7500 | I43: P.2/3-COMISSAO VENDA LOTES 92/107/146-Q.49-BA | K43: 45474 | L43: 45483 | M43: SALVADOR – FEMAÇÃ II | N43: VERANÓPOLIS | O43: 03 | P43: 03 | Q43: Gilberto de Castro Júnior | U43: Vendido à prazo.
A44: 45108 | B44: 1 | C44: SIVIERO EMPREENDIMENTOS IMOBILIARIOS LTD | D44: PREFEITURA MUNICIPAL DE CAXIAS DO SUL | E44: 45117 | F44: 45117 | G44: 9395.15 | H44: 9395.15 | I44: PARC. 04/04 - IPTU ANO 2023 - ZANROSSO | K44: 45474 | L44: 45484 | M44: VIERO | N44: FARROUPILHA | O44: 09 | P44: 1469 | Q44: Maickel Moretto | U44: Vendido à prazo, em 48x.
A45: 45108 | B45: 1 | C45: SIVIERO EMPREENDIMENTOS IMOBILIARIOS LTD | D45: PREFEITURA MUNICIPAL DE CAXIAS DO SUL | E45: 45117 | F45: 45117 | G45: 10587.69 | H45: 10587.69 | I45: PARC. 04/04 - IPTU ANO 2023 - VILMA PICCOLI | K45: 45474 | L45: 45499 | M45: CONDOMÍNIO MORADA DOS IPÊS | N45: PASSO FUNDO | O45: 001 | P45: 01 | Q45: Marcelo Colussi Girardi | R45: 230000 | S45: R$ 230.000,00 | U45: Vendido à prazo, em 03x, com parte em permuta de um carro JEEP COMMANDER – ano 2023 – RXZ 7I62, pelo valor de R$ 230.000,00.
A46: 45108 | B46: 1 | C46: SIVIERO EMPREENDIMENTOS IMOBILIARIOS LTD | D46: PREFEITURA MUNICIPAL DE CAXIAS DO SUL | E46: 45117 | F46: 45117 | G46: 9711.46 | H46: 9711.46 | I46: PARC. 04/04 - IPTU ANO 2023 - ARLINDO PICCOLI | K46: 45505 | L46: 45505 | M46: CARNEVALLI | N46: NOVA PRATA | O46: 07 | P46: A | Q46: CVC Construções Ltda. | U46: Vendido, como forma de pagamento de pavimentação no Loteamento Colina do Retiro II, de Veranópolis.
A47: 45108 | B47: 1 | C47: SIVIERO EMPREENDIMENTOS IMOBILIARIOS LTD | D47: PREFEITURA MUNICIPAL DE CAXIAS DO SUL | E47: 45117 | F47: 45117 | G47: 9435.05 | H47: 9435.05 | I47: PARC. 04/04 - IPTU ANO 2023 - PEDROTTI | K47: 45505 | L47: 45505 | M47: ALTOS DA JULIETA | N47: FARROUPILHA | O47: 03 | P47: 1733 | Q47: Luiz Fabiano D dos Santos | R47: 90000 | S47: R$ 90.000,00 | U47: Vendido à vista, sendo que a importância de R$ 90.000,00 através do veículo I/VW AMAROK, ano 2016,Placa IXL 8H85 – RS.
A48: 45108 | B48: 1 | C48: SIVIERO EMPREENDIMENTOS IMOBILIARIOS LTD | D48: PREFEITURA MUNICIPAL DE CAXIAS DO SUL | E48: 45117 | F48: 45117 | G48: 3880.92 | H48: 3880.92 | I48: PARC. 04/04 - IPTU ANO 2023 - ZANANDREA | K48: 45505 | L48: 45505 | M48: ALTOS DA JULIETA | N48: FARROUPILHA | O48: 04 | P48: 1733 | Q48: Luiz Fabiano D dos Santos | U48: Vendido à vista.
A49: 45108 | B49: 1 | C49: SIVIERO EMPREENDIMENTOS IMOBILIARIOS LTD | D49: PREFEITURA MUNICIPAL DE CAXIAS DO SUL | E49: 45117 | F49: 45117 | G49: 3921.43 | H49: 3921.43 | I49: PARC. 04/04 - IPTU ANO 2023 - PAULETTI | K49: 45505 | L49: 45511 | M49: MONTE VÊNETO | N49: COTIPORÃ | O49: 13 | P49: 09 | Q49: Edegar Pellizzer | U49: Vendido à vista.
A50: 45108 | B50: 1 | C50: SIVIERO EMPREENDIMENTOS IMOBILIARIOS LTD | D50: PREFEITURA MUNICIPAL DE CAXIAS DO SUL | E50: 45117 | F50: 45117 | G50: 10240.48 | H50: 10240.48 | I50: PARC. 04/04 - IPTU ANO 2023 - GASPARIN | K50: 45505 | L50: 45512 | M50: MONTE VÊNETO | N50: COTIPORÃ | O50: 12 | P50: 09 | Q50: Djenifer Pellizzer | U50: Vendido à prazo, em 12x.
A51: 45108 | B51: 1 | C51: SIVIERO EMPREENDIMENTOS IMOBILIARIOS LTD | D51: PREFEITURA MUNICIPAL DE CAXIAS DO SUL | E51: 45117 | F51: 45117 | G51: 8303.55 | H51: 8303.55 | I51: PARC. 04/04 - IPTU ANO 2023 - CANDIDO FIOREZE | K51: 45505 | L51: 45530 | M51: CICHELERO | N51: CARLOS BARBOSA | O51: 30 | P51: C | Q51: Paulo Ely | U51: Vendido à prazo, em 30x
A52: 45108 | B52: 1 | C52: SIVIERO EMPREENDIMENTOS IMOBILIARIOS LTD | D52: PREFEITURA MUNICIPAL DE CAXIAS DO SUL | E52: 45117 | F52: 45117 | G52: 3002.96 | H52: 3002.96 | I52: PARC. 04/04 - IPTU ANO 2023 - ANDREIS | K52: 45566 | L52: 45572 | M52: SALVADOR – FEMAÇÃ II | N52: VERANÓPOLIS | O52: 09 | P52: 01 | Q52: Araceli Siviero | U52: Lote Família Adélia Siviero
A53: 45108 | B53: 1 | C53: SIVIERO EMPREENDIMENTOS IMOBILIARIOS LTD | D53: PREFEITURA MUNICIPAL DE CAXIAS DO SUL | E53: 45117 | F53: 45117 | G53: 5506.71 | H53: 5506.71 | I53: PARC. 04/04 - IPTU ANO 2023 - ANDREIS | K53: 45566 | L53: 45575 | M53: PERINI | N53: FARROUPILHA | O53: 18 | P53: 1469 | Q53: Efetiva de Imóveis Ltda. | U53: Vendido à prazo.
A54: 45108 | B54: 1 | C54: SIVIERO EMPREENDIMENTOS IMOBILIARIOS LTD | D54: PREFEITURA MUNICIPAL DE CAXIAS DO SUL | E54: 45117 | F54: 45117 | G54: 4253.18 | H54: 4253.18 | I54: PARC. 04/04 - IPTU ANO 2023 - ALTOS DAS GRACA | K54: 45566 | L54: 45575 | M54: PERINI | N54: FARROUPILHA | O54: 19 | P54: 1469 | Q54: Efetiva de Imóveis Ltda. | U54: Vendido à prazo. Diferença de área constatada do lote.
A55: 45108 | B55: 1 | C55: SIVIERO EMPREENDIMENTOS IMOBILIARIOS LTD | D55: PROMED CONSULT ASSES SEG TRABALHO LTI | E55: 45117 | F55: 45117 | G55: 240 | H55: 240 | I55: SEI - SERVICOS PRESTRADOS E-SOCIAL- 06 MESES | K55: 45566 | L55: 45575 | M55: MONTE VÊNETO | N55: COTIPORÃ | O55: 05 | P55: 05 | Q55: Cristine Franceschi | R55: 182000 | S55: R$ 182.000,00 | T55: Sim (2 lotes) | U55: Vendido à vista, com permuta de outro imóvel – Lote 04, Quadra 04 – Loteamento Aditivo Medianeira – Veranópolis, valor de R$ 182.000,00.
A56: 45108 | B56: 2 | C56: SIVIERO EMPREENDIMENTOS IMOBILIARIOS LTD | D56: ITTOL INFORMATICA LTDA. - FARROUPILHA | E56: 45117 | F56: 45117 | G56: 615 | H56: 615 | I56: MENSALIDADE PROGAMA FOLHA + CONTABIL - EMPRES | K56: 45566 | L56: 45575 | M56: MONTE VÊNETO | N56: COTIPORÃ | O56: 09 | P56: 06 | Q56: Cristine Franceschi | R56: 182000 | S56: R$ 182.000,00 | T56: Sim (2 lotes) | U56: Vendido à vista, com permuta de outro imóvel – Lote 04, Quadra 04 – Loteamento Aditivo Medianeira – Veranópolis, valor de R$ 182.000,00.
A57: 45108 | B57: 2 | C57: SIVIERO EMPREENDIMENTOS IMOBILIARIOS LTD | D57: SIM REDE DE POSTOS LTDA. - VERANOPOLI | E57: 45116 | F57: 45117 | G57: 379.77 | H57: 379.77 | I57: ABASTECIMENTOS CARROS+CACAMBAS+OFICINA=VER | K57: 45566 | L57: 45576 | M57: PRINCESA DOS VALES | N57: CARLOS BARBOSA | O57: 38 | P57: F | Q57: Ian Zonatto dos Santos | U57: Vendido à prazo.
A58: 45108 | B58: 2 | C58: SIVIERO EMPREENDIMENTOS IMOBILIARIOS LTD | D58: GUILHERME REISDORFER - ENG. FLOREST | E58: 45115 | F58: 45117 | G58: 900 | H58: 900 | I58: VISTORIA PROCESSO NASCENTES 07 LOTES -LOT LAG | K58: 45566 | L58: 45593 | M58: BALDASSO | N58: CARLOS BARBOSA | O58: 111 | P58: 48 | Q58: Fernando Luis Barth | U58: Vendido à vista.
A59: 45108 | B59: 2 | C59: SIVIERO EMPREENDIMENTOS IMOBILIARIOS LTD | D59: PRO LABORE VALTER SIVIERO | E59: 45115 | F59: 45117 | G59: 11500 | H59: 6000 | I59: PAGO EM MAOS PARA VAGNER SIVIERO
A60: 45108 | B60: 2 | C60: SIVIERO EMPREENDIMENTOS IMOBILIARIOS LTD | D60: PRO LABORE ADELIA FRIZON SIVIERO | E60: 45117 | F60: 45117 | G60: 11500 | H60: 6000 | I60: PAGO EM MAOS - LUCIANE SIVIERO
A61: 45108 | B61: 2 | C61: SIVIERO EMPREENDIMENTOS IMOBILIARIOS LTD | D61: PRO LABORE PEDRO SIVIERO | E61: 45115 | F61: 45117 | G61: 11500 | H61: 5500 | I61: PAGO EM MAOS - PEDRO ELIAS SIVIERO
A62: 45108 | B62: 2 | C62: SIVIERO EMPREENDIMENTOS IMOBILIARIOS LTD | D62: PREFEITURA MUNICIPAL DE GUAPORE | E62: 45117 | F62: 45117 | G62: 1766.14 | H62: 1766.14 | I62: IPTU ANO 2023 = 04 LOTES - LOTEAMENTO N. S. S
A63: 45108 | B63: 2 | C63: SIVIERO EMPREENDIMENTOS IMOBILIARIOS LTD | D63: PREFEITURA MUNICIPAL DE CAXIAS DO SUL | E63: 45117 | F63: 45117 | G63: 7256.06 | H63: 7256.06 | I63: P.04/04-25 LOTES-IPTU ANO 2023-LOTEAMENTO ALT
A64: 45108 | B64: 2 | C64: SIVIERO EMPREENDIMENTOS IMOBILIARIOS LTD | D64: RODOBENS ADMINISTRADORA CONSORCIOS L | E64: 45117 | F64: 45117 | G64: 952.7 | H64: 952.7 | I64: P.48/180-R$ 126.000,00=CONS. GRUPO 1767-0428
A65: 45108 | B65: 2 | C65: SIVIERO EMPREENDIMENTOS IMOBILIARIOS LTD | D65: RODOBENS ADMINISTRADORA CONSORCIOS L | E65: 45117 | F65: 45117 | G65: 952.7 | H65: 952.7 | I65: P.48/180-R$ 126.000,00=CONS. GRUPO 1767-0555
A66: 45108 | B66: 2 | C66: SIVIERO EMPREENDIMENTOS IMOBILIARIOS LTD | D66: RODOBENS ADMINISTRADORA CONSORCIOS L | E66: 45117 | F66: 45117 | G66: 1431.72 | H66: 1431.72 | I66: P.48/180-R$ 126.000,00=CONS GRUPO 1763-0149
A67: 45108 | B67: 2 | C67: SIVIERO EMPREENDIMENTOS IMOBILIARIOS LTD | D67: RODOBENS ADMINISTRADORA CONSORCIOS L | E67: 45117 | F67: 45117 | G67: 1407.83 | H67: 1407.83 | I67: P.48/180-R$ 126.000,00=CONS GRUPO 1763-0528
A68: 45108 | B68: 2 | C68: SIVIERO EMPREENDIMENTOS IMOBILIARIOS LTD | D68: RODOBENS ADMINISTRADORA CONSORCIOS L | E68: 45117 | F68: 45117 | G68: 952.7 | H68: 952.7 | I68: P.48/180-R$ 126.000,00=CONS. GRUPO 1767-0096
A69: 45108 | B69: 2 | C69: SIVIERO EMPREENDIMENTOS IMOBILIARIOS LTD | D69: EBF COMERCIO RECUP BOMBAS INJETORAS L | E69: 45118 | F69: 45118 | G69: 2780 | H69: 926.67 | I69: P.2/3-JOGO REPARO BOMBA+PISTAO+SERVICOS-CACA
A70: 45108 | B70: 2 | C70: SIVIERO EMPREENDIMENTOS IMOBILIARIOS LTD | D70: SANDRA MARIA MORO | E70: 45118 | F70: 45118 | G70: 5900 | H70: 3000 | I70: PARC. 01/02 - PAGAMENTO SERVICOS HONORARIOS M
... A3786: 45566 | B3786: 5 | C3786: ABASTECEDORA DE COMBUSTIVEIS SIVIERO LTD | D3786: CONT. SOCIAL - ABAST. COMB. SIVIERO L | E3786: 45596 | F3786: 45596 | G3786: 765.5 | H3786: 765.5 | I3786: FATURAMENTO MES SETEMBRO/2024 - R$ 26.580,00

Sheet Lotes Vendidos (todos)
A1: Data | B1: Loteamento | C1: Município | D1: Lote | E1: Quadra | F1: Comprador | G1: Valor citado | H1: Valores no texto | I1: Venda conjunta | J1: Observações | K1: Mês | L1: No período dos relatórios | M1: Página PDF
A2: 33744 | B2: SALVADOR – FEMAÇÃ II | C2: VERANÓPOLIS | D2: 02 | E2: 04 | F2: Volmir Marinello | J2: Vendido à vista. | K2: 33725 | L2: Não | M2: 3
A3: 34673 | B3: PRATA | C3: NOVA PRATA | D3: 03 | E3: E | F3: Quadri – CVC Construções / Cigano-Alfredo Estevan / Umberto Colla | J3: Lote dado como forma de pagamento pavimentação. Estava em aberto, pois faltava a cadeia de contratos. | K3: 34669 | L3: Não | M3: 1
A4: 36907 | B4: PRATA | C4: NOVA PRATA | D4: 13 | E4: K | F4: Quadri – CVC Construções Cigano-Jorge Saul / Bordignon / Vuelma / Almir Rui | J4: Lote dado como forma de pagamento pavimentação. Estava em aberto, pois faltava a cadeia de contratos. | K4: 36892 | L4: Não | M4: 1
A5: 38860 | B5: SALVADOR – FEMAÇÃ II | C5: VERANÓPOLIS | D5: 02 | E5: 01 | F5: Leonildo Marinello | J5: Vendido à vista. | K5: 38838 | L5: Não | M5: 3
A6: 39010 | B6: COLINA DO RETIRO II | C6: VERANÓPOLIS | D6: 14 | E6: 16 | F6: Cesar Sebben | J6: Julcimar Frainer, em troca de pavimentação. | K6: 38991 | L6: Não | M6: 2
A7: 39965 | B7: COLINA DO RETIRO II | C7: VERANÓPOLIS | D7: 04 | E7: 16 | F7: Cristiano Lucchetta | J7: Julcimar Frainer, em troca de pavimentação. | K7: 39965 | L7: Não | M7: 2
A8: 40592 | B8: MONTE VÊNETO | C8: COTIPORÃ | D8: 01 | E8: 09 | F8: Irineu Siviero | I8: Sim (2 lotes) | J8: Vendido, como forma de adiantamento para acerto futuro com os demais sócios da empresa. | K8: 40575 | L8: Não | M8: 10
A9: 40592 | B9: MONTE VÊNETO | C9: COTIPORÃ | D9: 02 | E9: 09 | F9: Irineu Siviero | I9: Sim (2 lotes) | J9: Vendido, como forma de adiantamento para acerto futuro com os demais sócios da empresa. | K9: 40575 | L9: Não | M9: 10
A10: 41467 | B10: INDUSTRIAL PEDRA LISA | C10: VERANÓPOLIS | D10: 06 | E10: 05 | F10: Poletto Metalúrgica Ltda. | J10: Vendido à prazo, em 06x. | K10: 41456 | L10: Não | M10: 8
A11: 41592 | B11: INDUSTRIAL PEDRA LISA | C11: VERANÓPOLIS | D11: 04 | E11: 03 | F11: Ivo José Frainer | J11: Vendido à vista. | K11: 41579 | L11: Não | M11: 8
A12: 41611 | B12: ALTOS DAS GRAÇAS | C12: CAXIAS DO SUL | D12: 12 | E12: 6370 | F12: João Daniel Pereira | J12: Vendido â vista. | K12: 41609 | L12: Não | M12: 15
A13: 41696 | B13: INDUSTRIAL VICENTINO | C13: FARROUPILHA | D13: 04 | E13: 1302 | F13: Alcides Basso Imóveis. | G13: 1427000 | H13: R$ 552.000,00; R$ 1.427.000,00 | J13: Vendido, com permuta de 03 veículos – ônibus + R$ 552.000,00 em 60 parcelas, pagas pela Siviero = R$ 1.427.000,00. | K13: 41671 | L13: Não | M13: 3
A14: 41729 | B14: INDUSTRIAL VICENTINO | C14: FARROUPILHA | D14: 04 | E14: 1303 | F14: L. F. Transportes Ltda. | G14: 1170000 | H14: R$ 1.170.000,00 | J14: Vendido à vista, com parte permuta de outro imóvel, valor de R$ 1.170.000,00. | K14: 41699 | L14: Não | M14: 3
A15: 41783 | B15: ALTOS DAS GRAÇAS | C15: CAXIAS DO SUL | D15: 09 | E15: 6371 | F15: Bruno Pinheiro Bitencourt | J15: Vendido à vista. | K15: 41760 | L15: Não | M15: 15
A16: 41815 | B16: ALTOS DAS GRAÇAS | C16: CAXIAS DO SUL | D16: 02 | E16: 6374 | F16: Pedreira SS Ltda. | I16: Sim (2 lotes) | J16: Vendido, como forma de pagamento na prestação de serviços de pavimentação do Sistema Viário do Loteamento Altos das Graças, com o fornecimento de materiais e mão-de-obra. | K16: 41791 | L16: Não | M16: 16
A17: 41815 | B17: ALTOS DAS GRAÇAS | C17: CAXIAS DO SUL | D17: 03 | E17: 6374 | F17: Pedreira SS Ltda. | I17: Sim (2 lotes) | J17: Vendido, como forma de pagamento na prestação de serviços de pavimentação do Sistema Viário do Loteamento Altos das Graças, com o fornecimento de materiais e mão-de-obra. | K17: 41791 | L17: Não | M17: 16
A18: 41844 | B18: DALLA COSTA | C18: NOVA BASSANO | D18: 05 | E18: 02 | F18: Domício Mileski | J18: Proprietário dos lotes adquiridos e instalado um bar. | K18: 41821 | L18: Não | M18: 1
A19: 41876 | B19: ALTOS DAS GRAÇAS | C19: CAXIAS DO SUL | D19: 01 | E19: 6365 | F19: Bidal Empreend.Imob.Ltda | G19: 380000 | H19: R$ 210.000,00; R$ 380.000,00 | I19: Sim (2 lotes) | J19: Vendido, como forma de pagamento de parte do apartamento de Luís Artur Siviero, em Caixas do Sul + o valor de R$ 210.000,00, pagos em 21 parcelas, totalizando R$ 380.000,00. | K19: 41852 | L19: Não | M19: 15
A20: 41876 | B20: ALTOS DAS GRAÇAS | C20: CAXIAS DO SUL | D20: 02 | E20: 6365 | F20: Bidal Empreend.Imob.Ltda | G20: 380000 | H20: R$ 210.000,00; R$ 380.000,00 | I20: Sim (2 lotes) | J20: Vendido, como forma de pagamento de parte do apartamento de Luís Artur Siviero, em Caixas do Sul + o valor de R$ 210.000,00, pagos em 21 parcelas, totalizando R$ 380.000,00. | K20: 41852 | L20: Não | M20: 15
A21: 42017 | B21: INDUSTRIAL PEDRA LISA | C21: VERANÓPOLIS | D21: 07 | E21: 05 | F21: Poletto Metalúrgica Ltda. | J21: Vendido à vista. | K21: 42005 | L21: Não | M21: 8
A22: 42166 | B22: INDUSTRIAL PEDRA LISA | C22: VERANÓPOLIS | D22: 02 | E22: 05 | F22: Poletto Metalúrgica Ltda. | G22: 170000 | H22: R$ 170.000,00 | J22: Vendido à prazo, com permuta de 01 veículo por R$ 170.000,00 e a diferença em 06x. | K22: 42156 | L22: Não | M22: 8
A23: 42719 | B23: ALTOS DAS GRAÇAS | C23: CAXIAS DO SUL | D23: 12 | E23: 6373 | F23: Via Nova Engenharia Ltda. | J23: Vendido, como forma de pagamento de prestação de serviços, PERMUTADO com 01 lote do Loteamento Caminhos do Sol, no percentual de 2,00%, conforme contratado no contrato de prestação de serviços para legalização e aprovação do Loteamento Boff. | K23: 42705 | L23: Não | M23: 16
A24: 42745 | B24: DALLA COSTA | C24: NOVA BASSANO | D24: 06 | E24: 02 | F24: Domício Mileski | J24: Proprietário dos lotes adquiridos e instalado um bar. | K24: 42736 | L24: Não | M24: 1
A25: 42814 | B25: ADITIVO MEDIANEIRA | C25: VERANÓPOLIS | D25: 05 | E25: 06 | F25: Agustinho Dall Agnol | J25: Vendido à vista. | K25: 42795 | L25: Não | M25: 4
A26: 42857 | B26: BARBIERO | C26: NOVA PRATA | D26: 09 | E26: 03 | F26: Valdecir Berlato | I26: Sim (2 lotes) | J26: Vendido à vista. | K26: 42856 | L26: Não | M26: 4
A27: 42857 | B27: BARBIERO | C27: NOVA PRATA | D27: 10 | E27: 03 | F27: Valdecir Berlato | I27: Sim (2 lotes) | J27: Vendido à vista. | K27: 42856 | L27: Não | M27: 4
A28: 42867 | B28: BARBIERO | C28: NOVA PRATA | D28: 03 | E28: 04 | F28: Paulo Rogério Belaver | J28: Vendido à vista. | K28: 42856 | L28: Não | M28: 4
A29: 42926 | B29: BAÚ | C29: CARLOS BARBOSA | D29: 03 | E29: 14 | F29: Eduardo Campanha | J29: Vendido à vista. | K29: 42917 | L29: Não | M29: 2
A30: 42983 | B30: BARBIERO | C30: NOVA PRATA | D30: 04 | E30: 03 | F30: Banco Sicredi Nova Prata | J30: Vendido à vista. | K30: 42979 | L30: Não | M30: 3
A31: 43090 | B31: BARBIERO | C31: NOVA PRATA | D31: 05 | E31: 02 | F31: Rafael Mattiuz | J31: Vendido à prazo | K31: 43070 | L31: Não | M31: 3
A32: 43102 | B32: CARNEVALLI | C32: NOVA PRATA | D32: 04 | E32: F | F32: CVC Construções Ltda. | J32: Vendido, como forma de pagamento de pavimentação no Loteamento Barbiero, de Nova Prata. | K32: 43101 | L32: Não | M32: 11
A33: 43102 | B33: CARNEVALLI | C33: NOVA PRATA | D33: 05 | E33: F | F33: CVC Construções Ltda. | I33: Sim (3 lotes) | J33: Percentual referente à Pavimentação do Loteamento Carnevalli, de Nova Prata. | K33: 43101 | L33: Não | M33: 11
A34: 43102 | B34: CARNEVALLI | C34: NOVA PRATA | D34: 06 | E34: F | F34: CVC Construções Ltda. | I34: Sim (3 lotes) | J34: Percentual referente à Pavimentação do Loteamento Carnevalli, de Nova Prata. | K34: 43101 | L34: Não | M34: 11
A35: 43102 | B35: CARNEVALLI | C35: NOVA PRATA | D35: 07 | E35: G | F35: CVC Construções Ltda. | I35: Sim (3 lotes) | J35: Percentual referente à Pavimentação do Loteamento Carnevalli, de Nova Prata. | K35: 43101 | L35: Não | M35: 11
A36: 43136 | B36: ALTOS DA JULIETA | C36: FARROUPILHA | D36: 07 | E36: 1724 | F36: Inês Colombo Bartelle | I36: Sim (2 lotes) | J36: Vendido, conforme acordo extrajudicial pelo distrato do Contrato do Loteamento, em virtude da não execução do Loteamento dentro do prazo contratual, no todo da Família Colombo. | K36: 43132 | L36: Não | M36: 12
A37: 43136 | B37: ALTOS DA JULIETA | C37: FARROUPILHA | D37: 07 | E37: 1731 | F37: Inês Colombo Bartelle | I37: Sim (2 lotes) | J37: Vendido, conforme acordo extrajudicial pelo distrato do Contrato do Loteamento, em virtude da não execução do Loteamento dentro do prazo contratual, no todo da Família Colombo. | K37: 43132 | L37: Não | M37: 12
A38: 43174 | B38: LAGO NEGRO | C38: GRAMADO | D38: 09 | E38: 05 | F38: Vanderson José Baumgratz | J38: Vendido à vista. | K38: 43160 | L38: Não | M38: 9
A39: 43202 | B39: LAGO NEGRO | C39: GRAMADO | D39: 08 | E39: 06 | F39: Ronei Alencar Ferronatto | J39: Vendido à vista. | K39: 43191 | L39: Não | M39: 9
A40: 43297 | B40: CARNEVALLI | C40: NOVA PRATA | D40: 10 | E40: A | F40: Lindomar A. dos Santos | J40: Vendido à vista. | K40: 43282 | L40: Não | M40: 11
A41: 43315 | B41: LAGO NEGRO | C41: GRAMADO | D41: 01 | E41: 10 | F41: Mitra Diocese N. Hamburgo | J41: Vendido à vista. | K41: 43313 | L41: Não | M41: 8
A42: 43315 | B42: LAGO NEGRO | C42: GRAMADO | D42: 02 | E42: 10 | F42: Mitra Diocese N. Hamburgo | J42: Vendido à prazo, em 06x. | K42: 43313 | L42: Não | M42: 8
A43: 43340 | B43: JARDIM ITÁLIA | C43: FARROUPILHA | D43: 13 | E43: 1744 | F43: Bona Incorporadora Ltda | H43: R$ 140.000,00; R$ 110.000,00 | I43: Sim (2 lotes) | J43: Vendido à vista, sendo R$ 140.000,00 em espécie e R$ 110.000,00 em permuta com caminhão entregue para Gilberto Portella. | K43: 43313 | L43: Não | M43: 8
A44: 43340 | B44: JARDIM ITÁLIA | C44: FARROUPILHA | D44: 14 | E44: 1744 | F44: Bona Incorporadora Ltda | H44: R$ 140.000,00; R$ 110.000,00 | I44: Sim (2 lotes) | J44: Vendido à vista, sendo R$ 140.000,00 em espécie e R$ 110.000,00 em permuta com caminhão entregue para Gilberto Portella. | K44: 43313 | L44: Não | M44: 8
A45: 43354 | B45: LAGO NEGRO | C45: GRAMADO | D45: 09 | E45: 03 | F45: Arnaldo Bariquello | J45: Vendido à prazo, em 06x. | K45: 43344 | L45: Não | M45: 9
A46: 43361 | B46: LAGO NEGRO | C46: GRAMADO | D46: 05 | E46: 10 | F46: Júlio Cesar dos Reis | J46: Vendido à vista. | K46: 43344 | L46: Não | M46: 8
A47: 43368 | B47: LAGO NEGRO | C47: GRAMADO | D47: 04 | E47: 10 | F47: Fernando Maniezo | J47: Vendido à vista. | K47: 43344 | L47: Não | M47: 8
A48: 43368 | B48: CARNEVALLI | C48: NOVA PRATA | D48: 12 | E48: E | F48: Jose A. Boeira dos Santos | J48: Vendido à prazo, em 02x. | K48: 43344 | L48: Não | M48: 11
A49: 43396 | B49: LAGO NEGRO | C49: GRAMADO | D49: 09 | E49: 06 | F49: Elcir Luis Becker | J49: Vendido à vista. | K49: 43374 | L49: Não | M49: 9
A50: 43403 | B50: JARDIM ITÁLIA | C50: FARROUPILHA | D50: 03 | E50: 1747 | F50: Detonasul Ltda. | I50: Sim (3 lotes) | J50: Vendido, como forma de pagamento prestação de serviços – serviços de detonação. | K50: 43374 | L50: Não | M50: 8
A51: 43403 | B51: JARDIM ITÁLIA | C51: FARROUPILHA | D51: 11 | E51: 1747 | F51: Detonasul Ltda. | I51: Sim (3 lotes) | J51: Vendido, como forma de pagamento prestação de serviços – serviços de detonação. | K51: 43374 | L51: Não | M51: 8
A52: 43403 | B52: JARDIM ITÁLIA | C52: FARROUPILHA | D52: 12 | E52: 1747 | F52: Detonasul Ltda. | I52: Sim (3 lotes) | J52: Vendido, como forma de pagamento prestação de serviços – serviços de detonação. | K52: 43374 | L52: Não | M52: 8
A53: 43416 | B53: LAGO NEGRO | C53: GRAMADO | D53: 06 | E53: 10 | F53: Henrique Pizetta | I53: Sim (2 lotes) | J53: Vendido à vista. | K53: 43405 | L53: Não | M53: 8
A54: 43416 | B54: LAGO NEGRO | C54: GRAMADO | D54: 07 | E54: 10 | F54: Henrique Pizetta | I54: Sim (2 lotes) | J54: Vendido à vista. | K54: 43405 | L54: Não | M54: 8
A55: 43430 | B55: LAGO NEGRO | C55: GRAMADO | D55: 11 | E55: 05 | F55: Sergio Galuk | J55: Vendido à vista. | K55: 43405 | L55: Não | M55: 9
A56: 43434 | B56: LAGO NEGRO | C56: GRAMADO | D56: 06 | E56: 05 | F56: Moraes e Martinelli Ltda. | J56: Vendido à prazo, em 02x. | K56: 43405 | L56: Não | M56: 9
A57: 43435 | B57: ALTOS DA JULIETA | C57: FARROUPILHA | D57: 13 | E57: 1729 | F57: Válter Siviero | J57: Vendido, com permuta de um lote localizado no Loteamento Nossa Senhora da Saúde, de Guaporé. | K57: 43435 | L57: Não | M57: 12
A58: 43435 | B58: ALTOS DA JULIETA | C58: FARROUPILHA | D58: 14 | E58: 1729 | F58: Válter Siviero | J58: Vendido, com permuta de um caminhão do frigorífico, negociado com material para rede elétrica, com o Senhor Gilberto Portella. | K58: 43435 | L58: Não | M58: 12
A59: 43438 | B59: PERINI | C59: FARROUPILHA | D59: 08 | E59: 1468 | F59: Izeu Augusto Tumelero | J59: Vendido à vista. | K59: 43435 | L59: Não | M59: 2
A60: 43438 | B60: BARBIERO | C60: NOVA PRATA | D60: 07 | E60: 04 | F60: Jucimar Brocco | I60: Sim (2 lotes) | J60: Vendido à vista. | K60: 43435 | L60: Não | M60: 4
A61: 43438 | B61: BARBIERO | C61: NOVA PRATA | D61: 08 | E61: 04 | F61: Jucimar Brocco | I61: Sim (2 lotes) | J61: Vendido à vista. | K61: 43435 | L61: Não | M61: 4
A62: 43454 | B62: ALTOS DA JULIETA | C62: FARROUPILHA | D62: 09 | E62: 1729 | F62: Família Silvestrin | G62: 177000 | H62: R$ 98.000,00; R$ 177.000,00 | J62: Vendido, como forma de Acordo Processo Judicial Indenizatório pela venda de 01 lote no Loteamento Primavera, em parceria de percentual de divisão de lotes com a Família Silvestrin + o valor de R$ 98.000,00 em espécie = R$ 177.000,00. | K62: 43435 | L62: Não | M62: 12
A63: 43481 | B63: LAGO NEGRO | C63: GRAMADO | D63: 25 | E63: 11 B | F63: Colório Comércio de Bebida | I63: Sim (2 lotes) | J63: Vendido à prazo, em 02x. | K63: 43466 | L63: Não | M63: 8
A64: 43481 | B64: LAGO NEGRO | C64: GRAMADO | D64: 26 | E64: 11 B | F64: Colório Comércio de Bebida | I64: Sim (2 lotes) | J64: Vendido à prazo, em 02x. | K64: 43466 | L64: Não | M64: 8
A65: 43501 | B65: LAGO NEGRO | C65: GRAMADO | D65: 14 | E65: 06 | F65: Jorge Ilmar Oberherr | I65: Sim (2 lotes) | J65: Vendido à prazo, em 05x | K65: 43497 | L65: Não | M65: 9
A66: 43501 | B66: LAGO NEGRO | C66: GRAMADO | D66: 15 | E66: 06 | F66: Jorge Ilmar Oberherr | I66: Sim (2 lotes) | J66: Vendido à prazo, em 05x | K66: 43497 | L66: Não | M66: 9
A67: 43501 | B67: ALTOS DAS GRAÇAS | C67: CAXIAS DO SUL | D67: 10 | E67: 6373 | F67: Arquidea Ltda. | I67: Sim (2 lotes) | J67: Vendido, em permuta de uma casa (unidade) habitacional construída sobre o lote. | K67: 43497 | L67: Não | M67: 16
A68: 43501 | B68: ALTOS DAS GRAÇAS | C68: CAXIAS DO SUL | D68: 15 | E68: 6373 | F68: Arquidea Ltda. | I68: Sim (2 lotes) | J68: Vendido, em permuta de uma casa (unidade) habitacional construída sobre o lote. | K68: 43497 | L68: Não | M68: 16
A69: 43508 | B69: CICHELERO | C69: CARLOS BARBOSA | D69: 28 | E69: C | F69: Angelo Augusto Rizzi | J69: Vendido à vista. | K69: 43497 | L69: Não | M69: 6
A70: 43535 | B70: INDUSTRIAL VICENTINO | C70: FARROUPILHA | D70: 02 | E70: 1301 | F70: Tecnofrut Agrícolas Ltda. | J70: Vendido à prazo. | K70: 43525 | L70: Não | M70: 3
A71: 43560 | B71: PERINI | C71: FARROUPILHA | D71: 09 | E71: 1468 | F71: Marivânia Piccolo | J71: Vendido à vista. | K71: 43556 | L71: Não | M71: 2
A72: 43563 | B72: PERINI | C72: FARROUPILHA | D72: 14 | E72: 1469 | F72: Fernanda Sperafico | J72: Vendido à vista. | K72: 43556 | L72: Não | M72: 2
A73: 43573 | B73: VIERO | C73: FARROUPILHA | D73: 05 | E73: 1469 | F73: Alexandre Susin | J73: Vendido, como forma de acerto de dívida de comissão, negociado com Rodrigo Razzera. | K73: 43556 | L73: Não | M73: 5
A74: 43579 | B74: LAGO NEGRO | C74: GRAMADO | D74: 05 | E74: 05 | F74: Adriana Wasen | J74: Permuta, com o lote 20, da quadra 11B – APP – Loteamento Lago Negro. | K74: 43556 | L74: Não | M74: 9
A75: 43585 | B75: JARDIM ITÁLIA | C75: FARROUPILHA | D75: 10 | E75: 1736 | F75: Josemar Pedro Rusczyk | J75: Vendido à vista. | K75: 43556 | L75: Não | M75: 8
A76: 43613 | B76: ADITIVO MEDIANEIRA | C76: VERANÓPOLIS | D76: 16 | E76: 03 | F76: HZ Comércio de Carnes | J76: Vendido à prazo. | K76: 43586 | L76: Não | M76: 4
A77: 43637 | B77: LAGO NEGRO | C77: GRAMADO | D77: 15 | E77: 05 | F77: Diego Oliveira da Silva | J77: Vendido à prazo, em 10x. | K77: 43617 | L77: Não | M77: 9
A78: 43644 | B78: LAGO NEGRO | C78: GRAMADO | D78: 06 | E78: 06 | F78: Rafael Dezordi | J78: Vendido à vista. | K78: 43617 | L78: Não | M78: 9
A79: 43658 | B79: CICHELERO | C79: CARLOS BARBOSA | D79: 35 | E79: D | F79: Luciano Kovalski | J79: Vendido à vista. | K79: 43647 | L79: Não | M79: 6
A80: 43663 | B80: CARNEVALLI | C80: NOVA PRATA | D80: 07 | E80: C | F80: Wellington Vanzeto | J80: Vendido à vista. | K80: 43647 | L80: Não | M80: 10
A81: 43663 | B81: ALTOS DA JULIETA | C81: FARROUPILHA | D81: 05 | E81: 1729 | F81: Aladyr Euclides Zattera | I81: Sim (2 lotes) | J81: Vendido, conforme acordo extrajudicial pelo distrato do Contrato do Loteamento, em virtude da inviabilidade da área para execução do Loteamento – Família Zattera. | K81: 43647 | L81: Não | M81: 12
A82: 43663 | B82: ALTOS DA JULIETA | C82: FARROUPILHA | D82: 08 | E82: 1729 | F82: Aladyr Euclides Zattera | I82: Sim (2 lotes) | J82: Vendido, conforme acordo extrajudicial pelo distrato do Contrato do Loteamento, em virtude da inviabilidade da área para execução do Loteamento – Família Zattera. | K82: 43647 | L82: Não | M82: 12
A83: 43668 | B83: LAGO NEGRO | C83: GRAMADO | D83: 01 | E83: 05 | F83: Cristina Moraes Desessards | J83: Vendido à vista. | K83: 43647 | L83: Não | M83: 9
A84: 43678 | B84: LAGO NEGRO | C84: GRAMADO | D84: 25 | E84: 06 | F84: Rudimar Foss | G84: 70000 | H84: R$ 70.000,00 | J84: Vendido à prazo, em 05x, e com permuta de uma Toyota RAV4, ano 2014, pelo valor de R$ 70.000,00. | K84: 43678 | L84: Não | M84: 9
A85: 43691 | B85: PERINI | C85: FARROUPILHA | D85: 10 | E85: 1468 | F85: Ricardo e João Farina | I85: Sim (2 lotes) | J85: Processo Judicial Loteamento Industrial Vicentino | K85: 43678 | L85: Não | M85: 2
A86: 43691 | B86: PERINI | C86: FARROUPILHA | D86: 11 | E86: 1469 | F86: Ricardo e João Farina | I86: Sim (2 lotes) | J86: Processo Judicial Loteamento Industrial Vicentino | K86: 43678 | L86: Não | M86: 2
A87: 43691 | B87: VIERO | C87: FARROUPILHA | D87: 01 | E87: 1469 | F87: Ricardo e João Farina | I87: Sim (14 lotes) | J87: Vendido, como forma de Acordo Processo Judicial Indenizatório do Loteamento Industrial Vicentino. | K87: 43678 | L87: Não | M87: 5
A88: 43691 | B88: VIERO | C88: FARROUPILHA | D88: 02 | E88: 1469 | F88: Ricardo e João Farina | I88: Sim (14 lotes) | J88: Vendido, como forma de Acordo Processo Judicial Indenizatório do Loteamento Industrial Vicentino. | K88: 43678 | L88: Não | M88: 5
A89: 43691 | B89: VIERO | C89: FARROUPILHA | D89: 05 | E89: 1468 | F89: Ricardo e João Farina | I89: Sim (14 lotes) | J89: Vendido, como forma de Acordo Processo Judicial Indenizatório do Loteamento Industrial Vicentino. | K89: 43678 | L89: Não | M89: 5
A90: 43691 | B90: VIERO | C90: FARROUPILHA | D90: 06 | E90: 1468 | F90: Ricardo e João Farina | I90: Sim (14 lotes) | J90: Vendido, como forma de Acordo Processo Judicial Indenizatório do Loteamento Industrial Vicentino. | K90: 43678 | L90: Não | M90: 5
A91: 43691 | B91: DALZÓCHIO | C91: FARROUPILHA | D91: 12 | E91: 909 | F91: Ricardo e João Farina | I91: Sim (14 lotes) | J91: Vendido, como forma de Acordo Processo Judicial Indenizatório do Loteamento Industrial Vicentino. | K91: 43678 | L91: Não | M91: 6
A92: 43691 | B92: DALZÓCHIO | C92: FARROUPILHA | D92: 13 | E92: 909 | F92: Ricardo e João Farina | I92: Sim (14 lotes) | J92: Vendido, como forma de Acordo Processo Judicial Indenizatório do Loteamento Industrial Vicentino. | K92: 43678 | L92: Não | M92: 6
A93: 43691 | B93: DALZÓCHIO | C93: FARROUPILHA | D93: 14 | E93: 909 | F93: Ricardo e João Farina | I93: Sim (14 lotes) | J93: Vendido, como forma de Acordo Processo Judicial Indenizatório do Loteamento Industrial Vicentino. | K93: 43678 | L93: Não | M93: 6
A94: 43691 | B94: DALZÓCHIO | C94: FARROUPILHA | D94: 15 | E94: 909 | F94: Ricardo e João Farina | I94: Sim (14 lotes) | J94: Vendido, como forma de Acordo Processo Judicial Indenizatório do Loteamento Industrial Vicentino. | K94: 43678 | L94: Não | M94: 6
A95: 43691 | B95: ALTOS DA JULIETA | C95: FARROUPILHA | D95: 08 | E95: 1730 | F95: Ricardo e João Farina | I95: Sim (14 lotes) | J95: Vendido, como forma de Acordo Processo Judicial Indenizatório do Loteamento Industrial Vicentino. | K95: 43678 | L95: Não | M95: 12
A96: 43691 | B96: ALTOS DA JULIETA | C96: FARROUPILHA | D96: 09 | E96: 1730 | F96: Ricardo e João Farina | I96: Sim (14 lotes) | J96: Vendido, como forma de Acordo Processo Judicial Indenizatório do Loteamento Industrial Vicentino. | K96: 43678 | L96: Não | M96: 12
... A100: 43691 | B100: ALTOS DA JULIETA | C100: FARROUPILHA | D100: 06 | E100: 1732 | F100: Ricardo e João Farina | I100: Sim (14 lotes) | J100: Vendido, como forma de Acordo Processo Judicial Indenizatório do Loteamento Industrial Vicentino. | K100: 43678 | L100: Não | M100: 12
A101: 43696 | B101: ALTOS DAS GRAÇAS | C101: CAXIAS DO SUL | D101: 05 | E101: 6372 | F101: Valdir José Angest | G101: 270000 | H101: R$ 139.500,00; R$ 270.000,00 | J101: Vendido, como forma de indenização pela compra de 03 lotes na área da Família Fioreze, pela não execução do Loteamento + o valor de R$ 139.500,00, pagos pela empresa Siviero, em 18 parcelas = R$ 270.000,00. | K101: 43678 | L101: Não | M101: 15
A102: 43697 | B102: LAGO NEGRO | C102: GRAMADO | D102: 10 | E102: 09 | F102: Michael Schneider Flack | J102: Permuta, com o lote 15, da quadra 11B – APP – Loteamento Lago Negro. | K102: 43678 | L102: Não | M102: 9
A103: 43704 | B103: FEMAÇÃ | C103: VERANÓPOLIS | D103: 14 | E103: 09 | F103: Gustavo Attolini | H103: R$ 80.000,00; R$ 130.000,00 | I103: Sim (2 lotes) | J103: Vendido à vista, sendo R$ 80.000,00 em espécie e R$ 130.000,00 permuta veículo SW4 QWB 0690, entregue para o sócio Raul Siviero. | K103: 43678 | L103: Não | M103: 4
...

Sheet Conferência
A1: Mês | B1: Arquivo | C1: Empresa | D1: Linhas | E1: Soma Valor Dupl. | F1: Subtotal impresso | G1: Diferença | H1: Notas
A2: 45108 | B2: 2023-07 | C2: SIVIERO EMPREENDIMENTOS IMOBILIARIOS LTD | D2: 177 | E2: 1165697.9 | F2: 1165697.9 | G2: 0 | H2: Periodo impresso 01/07/2023 - 31/07/2023 confere com a tag 2023-07; emissao 02/08/2023; 5 paginas; 3 secoes (SIVIERO EMPREENDIMENTOS, TRANSPORTADORA IRMAOS SIVIERO, ABASTECEDORA).; Observacoes cortadas na margem direita do scan: mantido o texto visivel; letra parcialmente cortada na borda foi mantida quando reconhecivel (ex.: 'MOTONIVELADO', 'JUNHO').; Fornecedor encostado na data de Venc.: o 37o caractere aparece pela metade. Gravado como 'LTI' quando era a metade de um D (D KEKOS, PROMED, SAO JOAO), 'MATRICU' (OPERADOR NACIONAL DO REGISTRO) e 'ELETRICO' (ENERTEC) quando a meia-letra era reconhecivel como U/O.; L.R. BETT PAVIMENTACOES (p2): Venc. impresso 13/05/23 com Pgto. 13/07/23 - mantido como impresso.; Erros de digitacao do proprio relatorio mantidos: 'EMPRREND.', 'EMPREEEND.', 'PRESTRADOS', 'RALATORIO', 'CAIXIAS', 'PROGAMA', 'MAMOMETRO'.; RADAX DO BRASIL (p4): Valor NF 3.582,13 com Valor Dupl. 358,00 (P. 02/10) - conferido com zoom, impresso assim.
A3: 45108 | B3: 2023-07 | C3: TRANSPORTADORA IRMAOS SIVIERO LTDA. | D3: 67 | E3: 170937.95 | F3: 170937.95 | G3: 0
A4: 45108 | B4: 2023-07 | C4: ABASTECEDORA DE COMBUSTIVEIS SIVIERO LTD | D4: 16 | E4: 14885.25 | F4: 14885.25 | G4: 0
A5: 45139 | B5: 2023-08 | C5: SIVIERO EMPREENDIMENTOS IMOBILIARIOS LTD | D5: 181 | E5: 668125.99 | F5: 668125.99 | G5: 0 | H5: Periodo impresso 01/08/2023 - 31/08/2023 confere com a tag 2023-08; emissao 06/09/2023; 5 paginas; 3 secoes (SIVIERO EMPREENDIMENTOS, TRANSPORTADORA IRMAOS SIVIERO, ABASTECEDORA). Nenhuma celula ilegivel.; Observacoes cortadas na margem direita do scan: mantido o texto visivel; letra parcialmente cortada na borda mantida quando reconhecivel (ex.: 'PRACA G', 'TIS/SEI/A', 'MARCO', 'RETRO+CAC', 'DE 202'); omitida quando irreconhecivel (ex.: depois de 'PAVIMENTACAO' p1 RODRIGO KAISER, 'IUV' p1 RAMPA, 'GELATINA+' p3 SUPERMERCADO FRASSUL).; Fornecedor encostado na data de Venc.: 37o caractere pela metade. Gravado como 'LTI' (D KEKOS, SAO JOAO, PROMED), 'MATRICU' (OPERADOR NACIONAL DO REGISTRO), 'ELETRICO' (ENERTEC), 'VERANOPOL' (RAMPA DE LAVAGEM VALVERDE), seguindo a convencao de 2023-07.; L.R. BETT PAVIMENTACOES (p2): Venc. impresso 13/06/23 com Pgto. 14/08/23 - conferido com zoom, mantido como impresso.; Valores conferidos com zoom e impressos assim: CARBONERA (p3) NF 2.400,00 / Dupl 819,39 (P.1/3); RADAX (p5) NF 1.542,38 / Dupl 428,51 (P. 01/04); RADAX (p4) NF 3.582,13 / Dupl 358,00; TSD (p4) 831,13 / 207,79 e (p5) 831,13 / 207,78; ANTONIO ANSOLIN (p2) NF 586.666,00.; Pontilhados copiados com a contagem impressa: LADIR MADRUGA (p2) 'EM ............. - A' (13 pontos); PREFEITURA DE GUAPORE (p3) 'QDRA ..........' (10 pontos).; 'O1' com letra O (nao zero) em 'O1 PULVERIZADOR' (p3 ORSO) e 'CONST-O1' (p3 ZANELLA), como impresso.; Erros de digitacao do proprio relatorio mantidos: 'EMPRREND.' (PIS p3), 'EMPREEEND.', 'PROGAMA', 'MAMOMETRO', 'ELETRECISTA', 'HERBECIDAS', 'P.20/22--COMPRA'.; Linhas impressas com distorcao do scan (MOLIN & SLOMP p1, POSITIVA p2, HOTEL ARACA p3) lidas sem ambiguidade.
A6: 45139 | B6: 2023-08 | C6: TRANSPORTADORA IRMAOS SIVIERO LTDA. | D6: 71 | E6: 183210.32 | F6: 183210.32 | G6: 0
A7: 45139 | B7: 2023-08 | C7: ABASTECEDORA DE COMBUSTIVEIS SIVIERO LTD | D7: 14 | E7: 4275.02 | F7: 4275.02 | G7: 0
A8: 45200 | B8: 2023-10 | C8: SIVIERO EMPREENDIMENTOS IMOBILIARIOS LTD | D8: 184 | E8: 385521.64 | F8: 385521.64 | G8: 0 | H8: Periodo impresso 01/10/2023 - 31/10/2023 confere com a tag 2023-10; emissao 07/11/2023; 6 paginas; 3 secoes (SIVIERO EMPREENDIMENTOS, TRANSPORTADORA IRMAOS SIVIERO, ABASTECEDORA). A pagina 6 contem apenas o Subtotal da ABASTECEDORA (3.790,28) e o Total; suas linhas estao todas na pagina 5. A metade inferior da pagina 6 esta em branco.; Observacoes cortadas na margem direita do scan: mantido o texto visivel; letra parcialmente cortada mantida quando reconhecivel (ex.: 'BIA', 'SETEMBRO', 'MARCO', 'VERA', 'MOTONIVELADO', 'BOBINA=V'). Fragmentos irreconheciveis na borda foram omitidos: DIGITAL WAY p3 ('COMPUTADOR SUZI' + meia letra) e ANTONINHO JOSE ZANELLA p3 25/10 ('ENTULHO O' + meia letra).; Fornecedor encostado na data de Venc.: o 37o caractere aparece pela metade. Seguindo a convencao do mes 2023-07: 'LTI' para a metade de um D (D KEKOS x3, PROMED, SAO JOAO x2), 'MATRICU' (OPERADOR NACIONAL DO REGISTRO x2), 'ELETRICO' (ENERTEC) e 'CHAPEAC' (CLAIRTON VENDRAMIN, p2). 'SIMONETTO ... LTDA' (p1 e p3) cabe inteiro antes da data.; CONSULTAMB - JAQUELINE BONATT0 (p3): o ultimo caractere e impresso como algarismo zero (mais estreito que a letra O) - mantido como impresso.; Venc. posterior ao Pgto. mantido como impresso (ex.: L.R. BETT e LUIS CARLOS MERCALI 13/10 pagos 11/10; COOPERATIVA SANTA CLARA 13/10 paga 11/10). Venc. de setembro pagos em outubro: SIMONETTO 27/09/23, CHAPEACAO BIDJA 29/09/23.; Erros de digitacao do proprio relatorio mantidos: 'EMPRREND.', 'EMPREEEND.', 'CONTRUCAO', 'CATTERPILAR', 'PROGAMA', 'MAMOMETRO', 'SETEEMBRO', 'PINHERIOS', 'THINER'. TSD LOGISTICA NF 1.146,44: Dupl. 229,28 (p4) e 229,29 (p5, duas vezes) - conferido, impresso assim. RADAX (p4) NF 3.582,13 com Dupl. 358,00 (P. 05/10), igual ao padrao de 2023-07.; Linhas RESTAURANTE - CAXIAS DO SUL (p1), POSITIVA COMUNICACAO E MARKETING LTDA (p2) e BANCO SICREDI 26/10 (p3) impressas em fonte menor; lidas com zoom.
A9: 45200 | B9: 2023-10 | C9: TRANSPORTADORA IRMAOS SIVIERO LTDA. | D9: 75 | E9: 157363.96 | F9: 157363.96 | G9: 0
A10: 45200 | B10: 2023-10 | C10: ABASTECEDORA DE COMBUSTIVEIS SIVIERO LTD | D10: 13 | E10: 3790.28 | F10: 3790.28 | G10: 0
A11: 45231 | B11: 2023-11 | C11: SIVIERO EMPREENDIMENTOS IMOBILIARIOS LTD | D11: 163 | E11: 666440.05 | F11: 666440.05 | G11: 0 | H11: Periodo impresso 01/11/2023 - 30/11/2023 confere com a tag 2023-11; emissao 12/12/2023; 5 paginas (metade inferior da p5 em branco); 3 secoes (SIVIERO EMPREENDIMENTOS, TRANSPORTADORA IRMAOS SIVIERO, ABASTECEDORA). Secao TRANSPORTADORA comeca na p4 (titulo no fim da p3) e continua na p5 sem repetir o titulo.; Anotacoes manuscritas no scan (nao transcritas): 'Visto' e rubrica no cabecalho da p1; tracos a caneta apos a data de Pgto. nas linhas 1-10 da p1.; Observacoes cortadas na margem direita do scan: mantido o texto visivel; letra parcialmente cortada na borda foi mantida quando reconhecivel (ex.: 'CHAPEAC' no fornecedor CLAIRTON, 'WOLKS', 'SAFRA', 'NOVO', 'BOFF-REPO', 'CALCAMENTO', 'OUTUB', 'BOBINA=V'). Fornecedor encostado na data de Venc.: meia-letra gravada como 'LTI' (PROMED, metade de D) e 'COL/' (CHAPEACAO TRANSFORMES), como impresso.; Linhas impressas comprimidas/achatadas verticalmente (falha de impressao, mas legiveis e conferidas com zoom): p1 FABIANO ROGERIO MINOZZO 825,00; p2 VILSON JOSE RIBEIRO 3.000,00; p3 FORUM DE NOVA PRATA 380,78; p4 BRADESCO 4.216,63/1.054,16.; p3 PREFEITURA MUNICIPAL DE PASSO FUNDO 210,33: Observacao termina em 'IPE - I' (letra I, sem a serifa do digito 1, conferido com zoom), mantido como impresso; a linha seguinte termina em 'IPE - 2'.; Erros de digitacao do proprio relatorio mantidos: 'IMOBILARIOS' (JDRX), 'BONATT0' (com zero), 'O1 PAR' (letra O), 'PROGAMA', 'CAIXAS DO SUL', 'EMPREEEND.', 'EMPRREND.', 'NOVEMRO', 'TACOGROFO', 'MAMOMETRO', 'CHAMFRADO'.; Valores NF/Dupl. de todas as paginas conferidos com recortes ampliados; nenhuma celula ilegivel.
A12: 45231 | B12: 2023-11 | C12: TRANSPORTADORA IRMAOS SIVIERO LTDA. | D12: 58 | E12: 154753.09 | F12: 154753.09 | G12: 0
A13: 45231 | B13: 2023-11 | C13: ABASTECEDORA DE COMBUSTIVEIS SIVIERO LTD | D13: 14 | E13: 4056.08 | F13: 4056.08 | G13: 0
A14: 45261 | B14: 2023-12 | C14: SIVIERO EMPREENDIMENTOS IMOBILIARIOS LTD | D14: 185 | E14: 1022872.6 | F14: 1022872.6 | G14: 0 | H14: Periodo impresso 01/12/2023 - 31/12/2023 confere com a tag 2023-12; emissao 11/01/2024; 6 paginas (p6 so com 5 linhas da ABASTECEDORA, Subtotal e Total; metade inferior da p6 em branco); 3 secoes (SIVIERO EMPREENDIMENTOS, TRANSPORTADORA IRMAOS SIVIERO, ABASTECEDORA).; Observacoes cortadas na margem direita do scan: mantido o texto visivel; letra parcialmente cortada mantida quando reconhecivel (ex.: 'NOVEMBR', 'VAGNER', 'RESERVATORIOS', 'MATRICULA', 'BOBINA=V'); fragmento irreconhecivel omitido (ex.: 'CAMPES' p3) ou gravado como aparece ('NOVEMBRO DI' p5, 'FRANCEL' p4).; Fornecedor encostado na data de Venc.: gravado 'LTI' para meia-letra D (D KEKOS p1, SAO JOAO TRANSPORTES p4, PROMED p5), 'MATRICU' (OPERADOR NACIONAL DO REGISTRO p1/p2), 'VERANOPOL' (MARCOS ROSSA p2, RAMPA DE LAVAGEM p4), 'L' (RODOBENS), 'PRA' (CVC CONSTRUCOES), 'LTD' (ARDRILL, D inteiro visivel), 'LTDA' (EQUIPAMENTOS ESCRITORIO REGIONAL).; ANTONINHO JOSE ZANELLA (p1, venc 01/12/23): Valor Dupl. 910,05 maior que Valor NF 887,00 - conferido com zoom, impresso assim.; Vencimentos anteriores ao periodo mantidos como impressos (29/11/23, 24/11/23, 28/11/23 na p1); PARANA EQUIPAMENTOS e SIM REDE (p4) e SIM REDE FLORES DA CU (p5) com Venc. 31/12/23 e Pgto. 28/12/23, e ANTONINHO ZANELLA (p4) Venc. 29/12/23 Pgto. 28/12/23 - mantidos como impressos.; Erros de digitacao do proprio relatorio mantidos: 'EMPRREND.', 'EMPREEEND.', 'EMPREED.', 'PROGAMA', 'DEZEMRO', 'MAMOMETRO', 'RENOVAAO', 'PLAHET'.; Varias linhas repetidas identicas impressas (ex.: 4x e 7x BANCO ESTADO - TIS 11,50; 3x BANCO ESTADO - SEI 207,87; 2x DIANA FIORI 100,59) - todas transcritas; a soma confere com os subtotais.
A15: 45261 | B15: 2023-12 | C15: TRANSPORTADORA IRMAOS SIVIERO LTDA. | D15: 78 | E15: 216221.5 | F15: 216221.5 | G15: 0
A16: 45261 | B16: 2023-12 | C16: ABASTECEDORA DE COMBUSTIVEIS SIVIERO LTD | D16: 14 | E16: 3840.28 | F16: 3840.28 | G16: 0
A17: 45292 | B17: 2024-01 | C17: SIVIERO EMPREENDIMENTOS IMOBILIARIOS LTD | D17: 148 | E17: 343100.52 | F17: 343100.52 | G17: 0 | H17: Periodo impresso 01/01/2024 - 31/01/2024 confere com a tag 2024-01; emissao 21/02/2024; 5 paginas (pagina 5 so tem a metade superior impressa; metade inferior em branco); 3 secoes (SIVIERO EMPREENDIMENTOS, TRANSPORTADORA IRMAOS SIVIERO, ABASTECEDORA).; Observacoes cortadas na margem direita do scan: mantido o texto visivel; letra parcialmente cortada mantida quando reconhecivel (ex.: 'FORD RANGE', 'CONTAS-TIS/SEI/A', 'SENHORA DE LOUR', 'FLORES DA CUNHA', 'PERTO DO', 'CONTRATO FAMILIA', 'MORADA DO', 'CARRO-ACIDENT', 'PNEUS CACAM', 'RS.COM.BR-DEZEM', 'CONTABEIS-DEZEMBRO DE'). Traco vertical solto nao identificavel na borda foi omitido (p1 'ANTAS=24 M', 'TABELIONATO/VERANOPOLIS-', 'FRETES+CORREIOS+'; p2 'LOTE PERTO HOSPI' (resto de possivel T), 'RECONHECIMENTOS = DEZEMBRO/'; p4 'ESCRITORIO SIVIERO-VERANOPOLI').; Fornecedor encostado na data de Venc.: o 37o caractere aparece pela metade. Gravado como 'LTI' quando era a metade de um D (PROMED, SAO JOAO), 'ELETRICO' (ENERTEC), 'MATRICU' (OPERADOR NACIONAL DO REGISTRO) e 'CHAPEAC' (CLAIRTON VENDRAMIN) conforme a meia-letra visivel.; PAULO RICARDO PALUDO (p1, 04/01/24, 770,00): Observacao comeca com 'O1' (letra O, como impresso, nao zero) - conferido com zoom.; CONSULTAMB - JAQUELINE BONATT0 (p1): ultimo caractere impresso como digito zero ('BONATT0'), mantido.; BANCO ESTADO RIO GRANDE DO SUL - TIS (p5, 30/01/24, 43,44): mancha sobre o O de 'ESCRITORIO' parece sujeira do scan, nao acento; gravado 'ESCRITORIO' (mesmo texto da linha de 02/01/24 na p3).; MULTI CELTACAR (p2): Valor NF 1.005,00 com Valor Dupl. 502,00 (P. 1/2) - conferido com zoom, impresso assim (nao 502,50).; SUL TURBOS (p1 P.2/3 = 833,33; p3 P.3/3 = 833,34) e RSC COMERCIO KIT EMBREAGEM (p4 P.01/03 = 1.108,34; P.02/03 = 1.108,33) - centavos de arredondamento conferidos.; MARQUESFRIO (p3): Venc. impresso 28/12/23 com Pgto. 24/01/24 - mantido como impresso.; Erros de digitacao do proprio relatorio mantidos: 'EMPRREND.', 'EMPREEEND.', 'PRESTRADOS', 'PROGAMA', 'MAMOMETRO', 'UINICA', 'JEPP', 'ESPUMATES', 'TRASSEIRA', 'MOTOSSERA', 'VIVIERO', 'SIVIEROU', 'RAVA', '1.00%'.; Acentos impressos mantidos: 'VERANÓPOLIS' (BANCO SICREDI), 'INFORMÁTICA' (RS MICRO), 'PAVILHÃO', 'QUÍMICA' (BOFF ENGENHARIA), 'IPÊS', 'ÁREA', 'M²'.; Espacos duplos estimados pelo espacamento visivel: 'ADYL NET - INTERNET LTDA.' (p1, p4), 'FLAVIA MANICA - ENGENHEIRA CIVIL' (p2), 'LADIR MADRUGA - CAXIAS DO SUL' (p3), 'CH 024074' (p3, MARQUESFRIO).
A18: 45292 | B18: 2024-01 | C18: TRANSPORTADORA IRMAOS SIVIERO LTDA. | D18: 73 | E18: 154069.3 | F18: 154069.3 | G18: 0
A19: 45292 | B19: 2024-01 | C19: ABASTECEDORA DE COMBUSTIVEIS SIVIERO LTD | D19: 13 | E19: 3812.25 | F19: 3812.25 | G19: 0
A20: 45323 | B20: 2024-02 | C20: SIVIERO EMPREENDIMENTOS IMOBILIARIOS LTD | D20: 140 | E20: 295923.8 | F20: 295923.8 | G20: 0 | H20: Periodo impresso 01/02/2024 - 29/02/2024 confere com a tag 2024-02; emissao 28/03/2024; 4 paginas; 3 secoes (SIVIERO EMPREENDIMENTOS, TRANSPORTADORA IRMAOS SIVIERO, ABASTECEDORA).; Observacoes cortadas na margem direita do scan: mantido o texto visivel; letra parcialmente cortada na borda mantida quando reconhecivel.; Fornecedor encostado na data de Venc.: gravado 'LTI' para meia-letra D (D KEKOS p2, PROMED p4, SAO JOAO p4), como na referencia 2023-07; 'CONSORCIOS L', 'DE IMOV', 'TOPOGRAFI', 'LTDA.' gravados como visiveis.; L.R. BETT PAVIMENTACOES (p1): Venc. impresso 13/07/23 com Pgto. 14/02/24, mesmo valor e obs (P. 07/10) que a linha L.R. BETT de 21/02/24 na p2 - mantido como impresso.; Venc. posterior ao Pgto. impresso em OFICINA MECANICA VACCARI (p1, 02/02/24 x 01/02/24) e MARANGONI (p3, 02/02/24 x 01/02/24) - mantido.; Erros de digitacao do proprio relatorio mantidos: 'EMPRREND.', 'EMPREEEND.', 'EMPREED.', 'PROGAMA', 'MAMOMETRO', 'REREAPROVACAO', 'ELETRECISTA', 'FRANCELICIOC'.; RADAX DO BRASIL (p4): Valor NF 3.582,13 com Valor Dupl. 358,00 (P. 10/10); RGE (p4) 0,01; BANCO SICREDI (p1) 0,17 - conferidos com zoom, impressos assim.
A21: 45323 | B21: 2024-02 | C21: TRANSPORTADORA IRMAOS SIVIERO LTDA. | D21: 58 | E21: 158589.35 | F21: 158589.35 | G21: 0
A22: 45323 | B22: 2024-02 | C22: ABASTECEDORA DE COMBUSTIVEIS SIVIERO LTD | D22: 13 | E22: 5319.73 | F22: 5319.73 | G22: 0
A23: 45352 | B23: 2024-03 | C23: SIVIERO EMPREENDIMENTOS IMOBILIARIOS LTD | D23: 177 | E23: 674950.76 | F23: 674950.76 | G23: 0 | H23: Periodo impresso 01/03/2024 - 31/03/2024 confere com a tag 2024-03; emissao 17/05/2024; 5 paginas; 3 secoes (SIVIERO EMPREENDIMENTOS, TRANSPORTADORA IRMAOS SIVIERO, ABASTECEDORA). Pagina 5 (metade inferior) contem apenas o Total.; Observacoes cortadas na margem direita do scan: mantido o texto visivel; meia-letra na borda gravada conforme a forma visivel/reconhecivel (ex.: 'COMPRA A', 'CALCADA', 'FEVEREIRO/202', 'ARQUIVO', 'ESPACO SO', 'ESPACO SOC', 'AREA CAMP', 'GESSO ESP', 'VERANOPOLIS OU'); quando so aparece um traco vertical foi gravado 'I' (ex.: 'ARBORIZACAO UI', 'CAMIONETI', 'LOTEAMENTO I', 'RETROESCAVAI', 'TANQUI', 'FEVEREIRO DI').; Fornecedor encostado na data de Venc.: 'OPERADOR NACIONAL DO REGISTRO-MATRICU' (p1 e p4, meia-letra lida como U, mesma convencao de 2023-07); 'RAMPA DE LAVAGEM VALVERDE - VERANOPOL' (p3, L meio visivel).; Linhas com impressao achatada/cortada na base mas legiveis (conferidas com zoom): INST. ELETRICA LIDER LTDA. (p1), SAO LUIZ CONSTRUCOES E SERVICOS LTDA. x2 (p3), COMABE AUTOMACAO ... 18/03/24 (p4).; Venc. anterior ao mes mantido como impresso: INST. ELETRICA LIDER (p1) venc 10/02/24; ROVILIO ANTONIO DAL MAS (p1) venc 27/02/24; L.R. BETT PAVIMENTACOES (p3) venc 13/10/23; SAO LUIZ CONSTRUCOES x2 (p3) venc 27/11/23.; Erros/grafias do proprio relatorio mantidos: 'EMPRREND.' (PIS p3), 'EMPREEEND.', 'LEMPEZA', 'PROGAMA', 'PINHERIOS', 'QADRA', 'PLAHET', 'VIVIERO NPR', 'NPQ 0I67', 'IYJ 8I14', 'MATRICULA ATUALIZADA 28. 118 ......... ???' (p2, impresso assim).; Valor NF x Valor Dupl. atipicos conferidos com zoom e impressos assim: SUPER PNEUS (p2) NF 4.900,00 / Dupl 1.634,00 (P.01/03); CARBONERA (p3) NF 4.057,28 / Dupl 1.012,28 (P.4/4); EDIR DAL SASSO (p2) duas linhas NF 1.300,00 com Dupl 1.050,00 e 250,00; LUBIA CORSO (p1) duas linhas P.2/2 NF 7.800,00 com Dupl 3.100,00 e 800,00; SAO LUIZ (p3) NF 18.500,00 com Dupl 6.000,00 e 1.500,00; SANDRA MARIA MORO NF 8.200,00 com Dupl 4.200,00 (p2) e 4.000,00 (p3).
A24: 45352 | B24: 2024-03 | C24: TRANSPORTADORA IRMAOS SIVIERO LTDA. | D24: 47 | E24: 148559.03 | F24: 148559.03 | G24: 0
A25: 45352 | B25: 2024-03 | C25: ABASTECEDORA DE COMBUSTIVEIS SIVIERO LTD | D25: 13 | E25: 5867.78 | F25: 5867.78 | G25: 0
A26: 45383 | B26: 2024-04 | C26: SIVIERO EMPREENDIMENTOS IMOBILIARIOS LTD | D26: 192 | E26: 881710.15 | F26: 881710.16 | G26: -0.01 | H26: Diferenca de -0,01 no subtotal SIVIERO EMPREENDIMENTOS confirmada no proprio relatorio (releitura independente das 192 linhas): AZUL COMPANHIA DE SEGUROS GERAIS (p3) imprime 1.500,17 como parcela P.4/4 de NF 6.000,72 (6.000,72/4 = 1.500,18); o sistema provavelmente somou 1.500,18 no subtotal. Mantido o valor impresso.; Periodo impresso 01/04/2024 - 30/04/2024 confere com a tag 2024-04; emissao 22/05/2024; 5 paginas; 3 secoes (SIVIERO EMPREENDIMENTOS, TRANSPORTADORA IRMAOS SIVIERO, ABASTECEDORA).; SIVIERO EMPREENDIMENTOS: soma das 192 linhas = 881.710,15, subtotal impresso = 881.710,16 (diferenca de 0,01 nao reconciliada). Todos os Valor Dupl. da secao foram relidos com zoom (2,5x-4x) e conferem com o impresso; parcelas nao exatas (ex.: SUL TURBOS 766,66 = 2.300,00/3; DELL 291,35; SUHAI 479,42; RADAX 781,09) sugerem arredondamento de centavos interno do sistema. Nenhum valor foi ajustado. As outras duas secoes e o Total (881.710,16 + 168.891,18 + 7.283,77 = 1.057.885,11) conferem.; Observacoes cortadas na margem direita do scan: mantido o texto visivel; letra parcialmente cortada mantida quando reconhecivel (ex.: 'BARBIERO' p1, 'MOTONIVELADORA' p2, 'EQUIPAMENT' p2, 'HIDRAUL' p2). Meia-letra irreconhecivel omitida: 'LISA-NA' (p2 FEPAM), 'MANGUEIRA' (p2 CAVEMAQ 188,20), 'ESCAVADEIRA - O' (p3 D KEKOS 822,25), 'DAS EMP' (p4 DIGITAL WAY 50,00), 'MARC' (p5 PRESSA), 'IKR 2' (p5 INSPESUL), 'MARCO DE 20' (p5 MERCATO/ABASTECEDORA).; Fornecedor encostado na data de Venc.: meia-letra final gravada como 'LTI' (D KEKOS p2/p3, SAO JOAO p4, PROMED p4), seguindo a convencao do mes de referencia; 'CONSORCIOS L', 'LTD' (CAVEMAQ), 'NOVA PRA', 'VALVER', 'VERANOPO', 'REGIONAL LTDA' como impressos.; Datas fora do padrao mantidas como impressas: PEDRO SIVIERO venc 30/11/23 (p2 e p3) e 28/12/23 (p3); HOTEL ARACA LTDA venc 28/04/24 com pgto 24/04/24 (p3); RAUL SIVIERO venc 28/04/24 e IRINEU SIVIERO venc 25/04/24 com pgto 24/04/24 (p3).; Erros de digitacao do proprio relatorio mantidos: 'EMPREEEND.', 'EMPRREND.' (PIS p3), 'PROGAMA', 'D0S' (zero, p3 MARCIO FRESCHI), 'RETICIACAO', 'TONNER', 'VIVIERO NPR'.; BANCO ESTADO RIO GRANDE DO SUL - SEI 25/04/24 232,26 aparece na ultima linha da p3 e na primeira da p4: sao linhas distintas no impresso (cada uma em sua pagina), ambas transcritas.; Valores pequenos conferidos com zoom: BANCO SICREDI 0,16 (p1) e RGE 0,01 (p5).
A27: 45383 | B27: 2024-04 | C27: TRANSPORTADORA IRMAOS SIVIERO LTDA. | D27: 55 | E27: 168891.18 | F27: 168891.18 | G27: 0
A28: 45383 | B28: 2024-04 | C28: ABASTECEDORA DE COMBUSTIVEIS SIVIERO LTD | D28: 14 | E28: 7283.77 | F28: 7283.77 | G28: 0
A29: 45413 | B29: 2024-05 | C29: SIVIERO EMPREENDIMENTOS IMOBILIARIOS LTD | D29: 187 | E29: 824089.36 | F29: 824089.36 | G29: 0 | H29: Periodo impresso 01/05/2024 - 31/05/2024 confere com a tag 2024-05; emissao 18/07/2024; 5 paginas; 3 secoes (SIVIERO EMPREENDIMENTOS, TRANSPORTADORA IRMAOS SIVIERO, ABASTECEDORA).; MARIA TEREZA FILIPPIN DAL PONTE/FAMIL (p3, 2 linhas): Valor NF impresso '1.010.000,0' - o numero excede a largura da coluna e o ultimo digito nao foi impresso (conferido com zoom). Mantido como impresso; o validador acusa formato nesses 2 campos. Valor Dupl. (70.000,00 e 8.750,74) legivel e conferido.; MARIA TEREZA FILIPPIN DAL PONTE/FAMIL (p3): segunda linha com Venc. 10/06/24 e Pgto. 20/05/24 - mantido como impresso.; CONNECT SISTEMAS LTDA. - NICOLAS SART (p4): Venc. impresso 12/09/24 com Pgto. 28/05/24 - mantido como impresso.; ABASTECEDORA (p5): BANCO ESTADO RIO GRANDE DO SUL - ABA 09/05/24 127,79 aparece duas vezes (ultima linha de p5_a e primeira de p5_b); conferido na emenda das metades: sao duas linhas distintas, e o subtotal 7.726,51 so fecha com as duas.; Observacoes cortadas na margem direita do scan: mantido o texto visivel; letra parcialmente cortada mantida quando reconhecivel (ex.: 'TOYOTAIWB 5G54', 'LTDA', 'CAMPO', 'PAVILHAO', 'ENCHEN', 'TIS/SEI/A', 'PEDRO SIVIERO', 'ESCAVA', 'LOT COL', 'PARTIDA', 'PECA', 'MOTONIVELADO', '- ES'); tracos nao reconheciveis na borda foram omitidos (ex.: apos 'LOTEAMENTO SOLAR', 'AUTENTICACOES', 'CASA FUNCIONARIOS PASSO').; Fornecedor encostado na data de Venc. (37o caractere pela metade), seguindo a convencao de 2023-07: 'LTI' (D KEKOS), 'MATRICU' (OPERADOR NACIONAL DO REGISTRO), 'ELETRICO' (ENERTEC). RODOBENS ADMINISTRADORA CONSORCIOS L: o 'L' aparece inteiro, encostado na data.; Erros de digitacao/grafias do proprio relatorio mantidos: 'PROGAMA', 'EMPREEEND.', 'EMPRREND.', 'TACOGROFOS', 'MOTOSSERA', 'TONNER', 'MAUSES', 'VIVIERO NPR', 'O1 PLACA', '2024-O1 AREA' (letra O no lugar de zero), 'MORADA D0S' (zero no lugar de O, conferido com zoom).
A30: 45413 | B30: 2024-05 | C30: TRANSPORTADORA IRMAOS SIVIERO LTDA. | D30: 50 | E30: 148233.29 | F30: 148233.29 | G30: 0
A31: 45413 | B31: 2024-05 | C31: ABASTECEDORA DE COMBUSTIVEIS SIVIERO LTD | D31: 16 | E31: 7726.51 | F31: 7726.51 | G31: 0
A32: 45444 | B32: 2024-06 | C32: SIVIERO EMPREENDIMENTOS IMOBILIARIOS LTD | D32: 167 | E32: 472050.79 | F32: 472050.79 | G32: 0 | H32: Periodo impresso 01/06/2024 - 30/06/2024 confere com a tag 2024-06; emissao 18/07/2024; 5 paginas (p5 sem linhas da TRANSPORTADORA: so o Subtotal dela no topo); 3 secoes (SIVIERO EMPREENDIMENTOS, TRANSPORTADORA IRMAOS SIVIERO, ABASTECEDORA).; MARIA TEREZA FILIPPIN DAL PONTE/FAMIL (p1): Valor NF impresso '1.010.000,0' (coluna estreita cortou o ultimo digito decimal) - mantido exatamente como impresso; nao completado para ',00'. Unico campo fora do formato 1.234,56 do validador.; Observacoes cortadas na margem direita do scan (campo de 45 caracteres): mantido o texto visivel; letra parcialmente cortada mantida quando reconhecivel (ex.: 'CACAMBAS', 'F.CUNHA', 'DESMEMBRAMENTO A', 'RETIFICACAO A', 'SALVADOR / S', 'KLEITON CANSAN - PF', 'OFICINA=VE', 'PASQUAL-RE', 'PARTIDA', 'ESCA'). Fragmento irreconhecivel omitido em: 'LAVAGEM MOTOR -' (p1), 'ANTONIO PRADO/FLORES' (p2 e p3), 'AUTENTICACOES' (p3), 'HIDRAULICA NO' (p3).; Fornecedor encostado na data de Venc.: meia-letra gravada como 'MATRICU' (OPERADOR NACIONAL DO REGISTRO, p1), 'SERVICOS' (ROBSON DAMMER, p2) e 'LTI' para a metade de um D (D KEKOS, p2), seguindo a convencao de 2023-07.; ROBSON DAMMER - PRESTADOR DE SERVICOS (p2): Venc. 14/06/24 posterior ao Pgto. 13/06/24 - mantido como impresso. IVO JOSE FRAINER (p1): Venc. 25/05/24 com Pgto. 05/06/24 - impresso assim.; Letra O no lugar do zero mantida como impressa: 'O1 AREA' (NOVA PRATA, p2) e 'O2 LOTES' (DESPESAS DIVERSAS, p2).; Erros de digitacao do proprio relatorio mantidos: 'EMPRREND.', 'EMPREEEND.', 'PROGAMA', 'MOTOSSERA', 'TONNER', 'CONEXAO', 'FERRAMENTAIS'.; I.C.M.S. - IMPOSTO ESTADUAL (p4): linha impressa mais clara/fina que as demais, mas legivel (115,93 / 115,93).
A33: 45444 | B33: 2024-06 | C33: TRANSPORTADORA IRMAOS SIVIERO LTDA. | D33: 52 | E33: 142941.11 | F33: 142941.11 | G33: 0
A34: 45444 | B34: 2024-06 | C34: ABASTECEDORA DE COMBUSTIVEIS SIVIERO LTD | D34: 13 | E34: 5867.77 | F34: 5867.77 | G34: 0
A35: 45474 | B35: 2024-07 | C35: SIVIERO EMPREENDIMENTOS IMOBILIARIOS LTD | D35: 192 | E35: 425155.67 | F35: 425155.67 | G35: 0 | H35: Periodo impresso 01/07/2024 - 31/07/2024 confere com a tag 2024-07; emissao 19/11/2024; 6 paginas (a pagina 6 contem apenas o Total : 605.892,81 e uma rubrica manuscrita); 3 secoes (SIVIERO EMPREENDIMENTOS, TRANSPORTADORA IRMAOS SIVIERO, ABASTECEDORA).; MARIA TEREZA FILIPPIN DAL PONTE/FAMIL (p2, Venc. 10/07/24): Valor NF impresso '1.010.000,0' - o valor nao cabe na coluna e o ultimo digito dos centavos foi cortado pela propria impressao (conferido com zoom). Mantido exatamente como impresso; nao segue o formato 1.234,56 e por isso o validador acusa erro de formato nesta celula. Valor Dupl. 13.800,00 legivel e normal.; Observacoes cortadas na margem direita do scan: mantido o texto visivel. Meia-letra na borda: gravada como a letra quando reconhecivel pelo formato+contexto (=VE, CONTRAT, CAMPEST, VENDA LO, GEOLOG, MERCADO, RETRO, ESCA, INDENIZAC, SEI/A, JUNHO); gravada como 'I' quando so aparece uma haste vertical, seguindo a convencao de 'LTI' (FLORES I, COMPRADOI, PAGTO COI, SERVI, COMBUSTIVEI).; Fornecedor encostado na data de Venc.: 'D KEKOS COM MANGUEIRAS E CONEXOES LTI' (p1) e 'PROMED CONSULT ASSES SEG TRABALHO LTI' (p2 e p4) gravados como 'LTI' (meia-letra D), mesma convencao do mes de referencia; 'EQUIPAMENTOS ESCRITORIO REGIONAL LTDA', 'SEUBONE ... PERSONALIZ', 'ALEXANDRA ... IMOV', 'RODOBENS ... L' e 'CVC ... NOVA PRA' encostam na data mas com ultima letra legivel.; Duas linhas impressas em fonte diferente (menor, espacada): LUIS CARLOS MERCALI (p2) e CLAUDIO LUCIANO RISSI - NOVA PRATA (p3); transcritas normalmente.; SANDRA MARIA MORO (p3): Venc. impresso 26/07/24 com Pgto. 25/07/24 (vencimento posterior ao pagamento) - mantido como impresso. Varias linhas tem Venc. em 30/06/24 com Pgto. em 01/07/24 (SIM REDE DE POSTOS, p1 e p4) - normal.; COOPERATIVA SANTA CLARA (p5, P.01/02): obs impressa 'RAUL SIVIER0' com o algarismo zero no lugar da letra O (glifo mais estreito, conferido com zoom) - mantido. 'O1', 'O2', 'O3' nas observacoes (ex.: 'O3 LOTES', 'O1 ALMOCO', 'O2 JANTAS', '2024-O1 AREA') gravados com a letra O, como aparentam no impresso.; Erros de digitacao do proprio relatorio mantidos: 'EMPRREND.' (PIS p3), 'EMPREEEND.' (obs p3/p4), 'PRESTRADOS', 'DESPEAS', 'CILINDO', 'TONNER', 'PARC,' (Antonio Prado p4), 'LUIZ,A BATTISTELLA' (p4; nas linhas da p5 aparece 'LUIZ A').; Valor NF bem diferente de Valor Dupl. x parcelas, impresso assim e conferido com zoom: PARANA EQUIPAMENTOS S/A (p3) NF 887.000,00 com obs 'R$ 377.000,00'; LINDOLFO LAGO MACHADO DE SOUZA (p3) NF 350.000,00 Dupl. 10.000,00 (PARC.10/10); INES ANSOLIN PESSUTTO (p3) NF 714.000,00 Dupl. 10.000,00; CVC CONSTRUCOES (p2) NF 54.000,00 Dupl. 13.000,00 (PARC. 04/04); CONCRESUL (p1) NF 2.475,00 Dupl. 1.188,00 (P.1/3), duas vezes (04/07 e 07/07).
A36: 45474 | B36: 2024-07 | C36: TRANSPORTADORA IRMAOS SIVIERO LTDA. | D36: 66 | E36: 175646.25 | F36: 175646.25 | G36: 0
A37: 45474 | B37: 2024-07 | C37: ABASTECEDORA DE COMBUSTIVEIS SIVIERO LTD | D37: 13 | E37: 5090.89 | F37: 5090.89 | G37: 0
A38: 45505 | B38: 2024-08 | C38: SIVIERO EMPREENDIMENTOS IMOBILIARIOS LTD | D38: 188 | E38: 539462.61 | F38: 539462.61 | G38: 0 | H38: Periodo impresso 01/08/2024 - 31/08/2024 confere com a tag 2024-08; emissao 19/11/2024; 5 paginas; 3 secoes (SIVIERO EMPREENDIMENTOS p1-p4, TRANSPORTADORA IRMAOS SIVIERO p4-p5, ABASTECEDORA p5).; MARIA TEREZA FILIPPIN DAL PONTE/FAMIL (p2, venc 10/08/24): Valor NF impresso '1.010.000,0' - o ultimo digito dos centavos foi cortado pela largura da coluna no proprio relatorio; mantido como impresso (conferido com zoom). Valor Dupl. 13.800,00 legivel.; VANTAGGIO CORRETORA DE SEGUROS LTDA. (p2): Valor NF 4.554,00 com Valor Dupl. 1.554,00 (P.1/3) - conferido com zoom, impresso assim.; INSS e ISSQN (p2, N.F. 09) e IRPJ (p3): Venc. 20/08/24 com Pgto. 16/08/24 (pagamento antes do vencimento) - mantido como impresso.; Fornecedor encostado na data de Venc.: meia-letra gravada como 'I' quando era so um traco vertical ('AFIF GHANNAM GUIMARAES-COMISSÃO-PAROI' p1; 'PROMED CONSULT ASSES SEG TRABALHO LTI' p5, mesma convencao de 2023-07).; Observacoes cortadas na margem direita do scan: mantido o texto visivel; letra parcialmente cortada mantida quando reconhecivel (ex.: '=VE', 'VAGNE', 'ELENIC', 'TRABALH', 'PROJET', 'RETRO', 'LOTES', 'SIVIERO', '8D09') e omitida quando era so um traco irreconhecivel (ex.: 'HIDRAU', 'JOAO C', 'LOTE SEL', '5G54-', 'CONDOMINIO M', 'CERC', 'DRAGA', 'MECA', 'AUTENTICACOES', 'JULHO DE 202').; Acentos impressos mantidos: 'VERANÓPOLIS', 'INFORMÁTICA', 'COMISSÃO', 'PAVILHÃO', 'QUÍMICA', 'IPÊS', 'M²', '2ª'.; Erros de digitacao do proprio relatorio mantidos: 'REGULARIZAZAO', 'EMPREED.', 'EMPREEEND.', 'EMPRREND.', 'COORETOR', 'MOTOSSERA STHIL', 'CAIXA2', 'TONNER', 'PARC, 02/03', 'SIVIER0' (zero no lugar de O, p4 COOPERATIVA SANTA CLARA), 'MAO-DE-0BRA' (zero, p3 FAGANELLO), 'O1' (letra O no lugar de zero em O1 TRENA / O1 BOTINA / O1 BUJAO / 2024-O1 AREA).; Linhas com fonte menor/diferente no scan (DESPESAS DIVERSAS p1 e p2, BANCO ESTADO ... 216,03 p3, ADYL NET p4) - legiveis, transcritas normalmente.; p5: rubrica manuscrita sobre a area do Subtotal/Total da ABASTECEDORA; nao encobre valores.
A39: 45505 | B39: 2024-08 | C39: TRANSPORTADORA IRMAOS SIVIERO LTDA. | D39: 59 | E39: 194956.31 | F39: 194956.31 | G39: 0
A40: 45505 | B40: 2024-08 | C40: ABASTECEDORA DE COMBUSTIVEIS SIVIERO LTD | D40: 12 | E40: 4933.15 | F40: 4933.15 | G40: 0
A41: 45536 | B41: 2024-09 | C41: SIVIERO EMPREENDIMENTOS IMOBILIARIOS LTD | D41: 177 | E41: 707103.09 | F41: 707103.09 | G41: 0 | H41: Tag do arquivo 2023-09, mas o periodo impresso no cabecalho e 01/09/2024 - 30/09/2024 (setembro de 2024), emissao 19/11/2024; mantido arquivo_tag '2023-09' e periodo do cabecalho. 5 paginas; 3 secoes (SIVIERO EMPREENDIMENTOS, TRANSPORTADORA IRMAOS SIVIERO, ABASTECEDORA).; MARIA TEREZA FILIPPIN DAL PONTE/FAMIL (p1): Valor NF impresso truncado pela largura da coluna como '1.010.000,0' (ultimo digito nao impresso) - mantido exatamente como impresso; nao segue o formato 1.234,56. Valor Dupl. 13.800,00 normal.; PEDRO SIVIERO (p3, 27/09/24): Valor NF 15.000,00 menor que Valor Dupl. 25.000,00 - conferido com zoom, impresso assim.; BENS MOVEIS - IMOVEIS - VEICULOS - SE (p1): linha em fonte menor/diferente; Venc. impresso 31/07/24 com Pgto. 11/09/24 - mantido como impresso. Obs com 'RXZ 7I62' (letra I, sem o serifa do 1). Linhas COMPANHIA EXCELSIOR (p2) e LAIRTON FRISON (p3) tambem em fonte menor.; BANCO ESTADO RIO GRANDE DO SUL - ABA 09/09/24 127,79 aparece duas vezes (ultima linha de p5 metade superior e primeira da metade inferior); as duas sao linhas distintas - confirmado pelo Subtotal 4.933,15, que so fecha com ambas.; Fornecedor encostado na data de Venc.: seguida a convencao de 2023-07 - 'LTI' para meia letra D (D KEKOS, PROMED, TRANSPORTADORA PRINCESA), 'MATRICU' (OPERADOR NACIONAL DO REGISTRO), 'CONSORCIOS L' (RODOBENS), 'NUVE' (GOOGLE PLAY).; Observacoes cortadas na margem direita: mantido o texto visivel; meia-letra mantida quando reconhecivel (ex.: 'OFICINA=VE', 'COTIPORA', 'TRILHA', 'MARCIANO', 'SIVIERO', 'LOTEAMENTO', 'PASSO', 'E MA', 'AGOST', 'LOTEAMENTO FEM'); meia-letra arredondada ambigua C/O/G gravada como 'C' quando a palavra seguinte e desconhecida ('LOTEAMENTO C', 'ESCAVADEIRAS - C', 'PECAS C'); meia-letra irreconhecivel omitida ('ANTONIO PRADO/FLORES', 'EVERTON+RUB').; Letra O no lugar de zero mantida como impresso: 'R$ 126.590,0O' (PIS, COFINS p3; IR, CONTRIBUICAO SOCIAL p4), 'R$ 297.145,O0' (PIS/COFINS - SIVIERO p3), 'O1 PLACA' (COMUNICA p3), 'O1 BUJAO' (COMERCIO DE GAS FAVERO p4); placas 'OYB 0G90' e 'IYJ 8I14' como impressas.; Erros de digitacao do proprio relatorio mantidos: 'EMPRREND.' (PIS - SIVIERO), 'EMPREEEND.' (BANCO ESTADO - SEI), 'PLAYGROOUND', 'CONTRUCAO', 'TONNER', 'PARC, 03/03', 'JEPP'. Espacos duplos impressos mantidos (ADYL NET - INTERNET, FLAVIA MANICA - ENGENHEIRA, LADIR MADRUGA - CAXIAS, EBAZAR. COM. BR LTDA., 'PECAS LTDA', 'FERIAS PERIO').; PDF renomeado de 2023-09_... para 2024-09_... em 26/10/2026 (o periodo impresso e setembro/2024).
A42: 45536 | B42: 2024-09 | C42: TRANSPORTADORA IRMAOS SIVIERO LTDA. | D42: 59 | E42: 193804.09 | F42: 193804.09 | G42: 0
A43: 45536 | B43: 2024-09 | C43: ABASTECEDORA DE COMBUSTIVEIS SIVIERO LTD | D43: 12 | E43: 4933.15 | F43: 4933.15 | G43: 0
A44: 45566 | B44: 2024-10 | C44: SIVIERO EMPREENDIMENTOS IMOBILIARIOS LTD | D44: 206 | E44: 805019.42 | F44: 805019.42 | G44: 0 | H44: Periodo impresso 01/10/2024 - 31/10/2024 confere com a tag 2024-10; emissao 19/11/2024; 5 paginas; 3 secoes (SIVIERO EMPREENDIMENTOS, TRANSPORTADORA IRMAOS SIVIERO, ABASTECEDORA). Subtotais e Total conferem na primeira passada; Valor NF e datas reconferidos com recorte ampliado das colunas.; MARIA TEREZA FILIPPIN DAL PONTE/FAMIL (p2 1 linha, p3 3 linhas): Valor NF impresso truncado na coluna como '1.010.000,0' (so um decimal) - mantido como impresso, nao completado.; MARIA TEREZA FILIPPIN DAL PONTE/FAMIL (p3): Venc. impressos 15/05/24, 10/11/24 e 10/12/24 com Pgto. 21/10/24 - mantidos como impressos.; PRO LABORE ADELIA FRIZON SIVIERO (p1): Venc. 10/10/24 posterior ao Pgto. 09/10/24 - mantido como impresso.; Fornecedor encostado na data de Venc.: meia-letra final gravada como 'LTI' quando era a metade de um D (PROMED p1, D KEKOS p2 e p4), 'GRAMAI' (DIRLEI MAURO PACHOLSKI-ROCADOR-GRAMA[D], p3) e 'ELETRICO' (ENERTEC p5, O pela metade).; Observacoes cortadas na margem direita do scan: mantido o texto visivel; letra parcialmente cortada mantida quando reconhecivel (ex.: 'DANUSA' p1, 'AGOSTO' p1, 'JO' p2, 'PROTETOR-CA' p3, '=VE' nas linhas SIM REDE). Letra cortada nao reconhecivel foi omitida: 'SECADOR A' (LUIZ A BATTISTELLA p1, letra seguinte ilegivel: E/F/P/R), 'HIDR' (D KEKOS p2/p4), 'OFICI' (ENERTEC p5).; Grafias do proprio relatorio mantidas: 'BONATT0' (com zero, CONSULTAMB p1), 'IYJ 8I14' (com I), 'R$ 290.092,0O' (com letra O, p4), 'EMPREEEND.' (BANCO ESTADO SEI p3/p4), 'EMPRREND.' (PIS p3), 'PLAYGROOUND', 'VIVIERO NPR', 'MATERIAS+S', 'PAVILHÃO'/'IPÊS'/'VERANÓPOLIS'/'INFORMÁTICA'/'QUÍMICA' com acento como impresso.
A45: 45566 | B45: 2024-10 | C45: TRANSPORTADORA IRMAOS SIVIERO LTDA. | D45: 51 | E45: 162235.91 | F45: 162235.91 | G45: 0
A46: 45566 | B46: 2024-10 | C46: ABASTECEDORA DE COMBUSTIVEIS SIVIERO LTD | D46: 12 | E46: 4949.97 | F46: 4949.97 | G46: 0

Sheet 2023-07
A1: Mês | B1: Página | C1: Empresa | D1: Fornecedor | E1: Vencimento | F1: Pagamento | G1: Valor NF | H1: Valor Dupl. | I1: Observações | K1: Data | L1: Loteamento | M1: Município | N1: Lote | O1: Quadra | P1: Comprador | Q1: Valor citado | R1: Valores no texto | S1: Venda conjunta | T1: Observações
A2: 45108 | B2: 1 | C2: SIVIERO EMPREENDIMENTOS IMOBILIARIOS LTD | D2: DORVAL FRANCISCO BOFF - CAXIAS DO SUL | E2: 45110 | F2: 45110 | G2: 100000 | H2: 10000 | I2: P.04/10-CFE CONTRATO ANTECIPACAO VALORES - LO | K2: 45111 | L2: SOL NASCENTE I | M2: ANTÔNIO PRADO | N2: 24 | O2: D | P2: Cassiano Damiani | Q2: 67000 | R2: R$ 67.000,00 | T2: Vendido à vista, sendo R$ 67.000,00 em permuta veículo GM/S10 – JID 4877.
A3: 45108 | B3: 1 | C3: SIVIERO EMPREENDIMENTOS IMOBILIARIOS LTD | D3: PROGETEC - ALENCAR TRINDADE - P.FUNDO | E3: 45110 | F3: 45110 | G3: 25000 | H3: 5000 | I3: P.3/5-INSTALACAO D+ HASTES CERCA ELETRICA+INS | K3: 45113 | L3: INDUSTRIAL PEDRA LISA | M3: VERANÓPOLIS | N3: 01 | O3: 07 | P3: Ind. Concretos Rivacci | Q3: 55000 | R3: R$ 55.000,00 | S3: Sim (2 lotes) | T3: Vendido à vista, com permuta de um pavilhão pré fabricado (a entregar) e uma camionete I/Toyota Hilux e o valor em espécie de R$ 55.000,00.
A4: 45108 | B4: 1 | C4: SIVIERO EMPREENDIMENTOS IMOBILIARIOS LTD | D4: PREFEITURA MUNICIPAL DE NOVA PRATA | E4: 45110 | F4: 45110 | G4: 36.96 | H4: 36.96 | I4: CERTIDAO DE LOCALIZAÇAO AREA-BELLA VISIONE-NO | K4: 45113 | L4: INDUSTRIAL PEDRA LISA | M4: VERANÓPOLIS | N4: 02 | O4: 07 | P4: Ind. Concretos Rivacci | Q4: 55000 | R4: R$ 55.000,00 | S4: Sim (2 lotes) | T4: Vendido à vista, com permuta de um pavilhão pré fabricado (a entregar) e uma camionete I/Toyota Hilux e o valor em espécie de R$ 55.000,00.
A5: 45108 | B5: 1 | C5: SIVIERO EMPREENDIMENTOS IMOBILIARIOS LTD | D5: SIM REDE DE POSTOS LTDA. - VERANOPOLI | E5: 45109 | F5: 45110 | G5: 521.89 | H5: 521.89 | I5: ABASTECIMENTOS CARROS+CACAMBAS+OFICINA=VER | K5: 45125 | L5: CARNEVALLI | M5: NOVA PRATA | N5: 06 | O5: C | P5: Érica Basso | T5: Vendido à prazo, em 02x.
A6: 45108 | B6: 1 | C6: SIVIERO EMPREENDIMENTOS IMOBILIARIOS LTD | D6: INES TREVISAN PICCOLI - JUROS | E6: 45108 | F6: 45110 | G6: 250000 | H6: 2500 | I6: JUROS 1.00% S/ R$ 250.000,00 - EMPRESTIMO
A7: 45108 | B7: 1 | C7: SIVIERO EMPREENDIMENTOS IMOBILIARIOS LTD | D7: ANDRE LUIZ SIVIERO - JUROS | E7: 45108 | F7: 45110 | G7: 100000 | H7: 800 | I7: JUROS 0,80% S/ R$ 100.000,00 - EMPRESTIMO
A8: 45108 | B8: 1 | C8: SIVIERO EMPREENDIMENTOS IMOBILIARIOS LTD | D8: SAMIR TREVISAN PICCOLI - JUROS | E8: 45108 | F8: 45110 | G8: 350000 | H8: 3500 | I8: JUROS 1.00% S/ R$ 350.000,00 - EMPRESTIMO
A9: 45108 | B9: 1 | C9: SIVIERO EMPREENDIMENTOS IMOBILIARIOS LTD | D9: SAMIR TREVISAN PICCOLI - JUROS | E9: 45108 | F9: 45110 | G9: 150000 | H9: 1500 | I9: JUROS 1.00% S/ R$ 150.000,00 - EMPRESTIMO
A10: 45108 | B10: 1 | C10: SIVIERO EMPREENDIMENTOS IMOBILIARIOS LTD | D10: SAMIR TREVISAN PICCOLI - JUROS | E10: 45108 | F10: 45110 | G10: 250000 | H10: 2500 | I10: JUROS 1.00% S/ R$ 250.000,00 - EMPRESTIMO
A11: 45108 | B11: 1 | C11: SIVIERO EMPREENDIMENTOS IMOBILIARIOS LTD | D11: SAMIR TREVISAN PICCOLI - JUROS | E11: 45108 | F11: 45110 | G11: 250000 | H11: 2500 | I11: JUROS 1.00% S/ R$ 250.000,00 - EMPRESTIMO EM
A12: 45108 | B12: 1 | C12: SIVIERO EMPREENDIMENTOS IMOBILIARIOS LTD | D12: BANCO SICREDI - VERANÓPOLIS | E12: 45110 | F12: 45110 | G12: 0.18 | H12: 0.18 | I12: JUROS BANCO CREDITO ROTATIVO MES JUNHO/2023
A13: 45108 | B13: 1 | C13: SIVIERO EMPREENDIMENTOS IMOBILIARIOS LTD | D13: IOF BANCARIO SIVIERO EMP IMOBILIARIOS | E13: 45110 | F13: 45110 | G13: 308.55 | H13: 308.55 | I13: IOF CONTA SEI MES DE JUNHO DE 2023 - BANRISUL
A14: 45108 | B14: 1 | C14: SIVIERO EMPREENDIMENTOS IMOBILIARIOS LTD | D14: IOF BANCARIO SIVIERO EMP IMOBILIARIOS | E14: 45110 | F14: 45110 | G14: 657.74 | H14: 657.74 | I14: IOF CONTA SEI MES DE JUNHO DE 2023 - BANRISUL
A15: 45108 | B15: 1 | C15: SIVIERO EMPREENDIMENTOS IMOBILIARIOS LTD | D15: MULTAS DE TRANSITO | E15: 45111 | F15: 45111 | G15: 156.19 | H15: 156.19 | I15: CACAMBA ILD 3959 - NAO IDENTIFICAÇÃO DE CONDU
A16: 45108 | B16: 1 | C16: SIVIERO EMPREENDIMENTOS IMOBILIARIOS LTD | D16: PORTAL EMPREENDIMENTOS IMOBILIARIOS L | E16: 45111 | F16: 45111 | G16: 10000 | H16: 2000 | I16: P.1/4-COMISSAO LT 06-QDRA 1342-SAN MARINO=DAN
A17: 45108 | B17: 1 | C17: SIVIERO EMPREENDIMENTOS IMOBILIARIOS LTD | D17: PORTAL EMPREENDIMENTOS IMOBILIARIOS L | E17: 45111 | F17: 45111 | G17: 10000 | H17: 2000 | I17: P.2/4-COMISSAO LT 06-QDRA 1342-SAN MARINO=DAN
... A261: 45108 | B261: 5 | C261: ABASTECEDORA DE COMBUSTIVEIS SIVIERO LTD | D261: CONT. SOCIAL - ABAST. COMB. SIVIERO L | E261: 45138 | F261: 45138 | G261: 456.71 | H261: 456.71 | I261: FATURAMENTO MES JUNHO/2023 - R$ 15.858,00 X 2
A263: Total | G263: =SUBTOTAL(9,G2:G261) | H263: =SUBTOTAL(9,H2:H261)

Sheet 2023-08
A1: Mês | B1: Página | C1: Empresa | D1: Fornecedor | E1: Vencimento | F1: Pagamento | G1: Valor NF | H1: Valor Dupl. | I1: Observações | K1: Data | L1: Loteamento | M1: Município | N1: Lote | O1: Quadra | P1: Comprador | Q1: Valor citado | R1: Valores no texto | S1: Venda conjunta | T1: Observações
A2: 45139 | B2: 1 | C2: SIVIERO EMPREENDIMENTOS IMOBILIARIOS LTD | D2: CORSAN - NOVA PRATA | E2: 45139 | F2: 45139 | G2: 2468.2 | H2: 2468.2 | I2: TAXA APROVACAO REDE AGUA LOT BELLA VISIONE - | K2: 45146 | L2: BALDASSO | M2: CARLOS BARBOSA | N2: 40 | O2: 06 | P2: Edmar Camillo | T2: Vendido à prazo, em 14x.
A3: 45139 | B3: 1 | C3: SIVIERO EMPREENDIMENTOS IMOBILIARIOS LTD | D3: RS MICRO INFORMÁTICA LTDA. | E3: 45133 | F3: 45139 | G3: 3066 | H3: 1533 | I3: P.01/02-CH 023948-COMPRA 02 IMPRESSORAS (RICO | K3: 45149 | L3: CONDOMÍNIO MORADA DOS IPÊS | M3: PASSO FUNDO | N3: 012 | O3: 04 | P3: Leandro Capelesso | Q3: 75000 | R3: R$ 75.000,00 | T3: Vendido à prazo, em 05x, com parte em permuta de um carro pelo valor de R$ 75.000,00 e reparceladas as parcelas para viabilizar o pagamento em 21x.
A4: 45139 | B4: 1 | C4: SIVIERO EMPREENDIMENTOS IMOBILIARIOS LTD | D4: ANDRE LUIZ SIVIERO - JUROS | E4: 45139 | F4: 45139 | G4: 100000 | H4: 800 | I4: JUROS 0,80% S/ R$ 100.000,00 - EMPRESTIMO | K4: 45155 | L4: CONDOMÍNIO MORADA DOS IPÊS | M4: PASSO FUNDO | N4: 004 | O4: 04 | P4: Luiz Fernando Klaus | T4: Vendido à prazo, em 07x.
A5: 45139 | B5: 1 | C5: SIVIERO EMPREENDIMENTOS IMOBILIARIOS LTD | D5: INES TREVISAN PICCOLI - JUROS | E5: 45139 | F5: 45139 | G5: 250000 | H5: 2500 | I5: JUROS 1.00% S/ R$ 250.000,00 - EMPRESTIMO | K5: 45161 | L5: SOLAR NORTE | M5: VERANÓPOLIS | N5: 06 | O5: 01 | P5: Lindolfo Lago | Q5: 350000 | R5: R$ 350.000,00 | T5: Vendido, como forma de pagamento pela aquisição de uma área de 3.100,00m² junto com a área da FAMÍLIA LAGO, em Sapopema, pelo valor total de R$ 350.000,00.
A6: 45139 | B6: 1 | C6: SIVIERO EMPREENDIMENTOS IMOBILIARIOS LTD | D6: INES TREVISAN PICCOLI - JUROS | E6: 45139 | F6: 45139 | G6: 100000 | H6: 1000 | I6: JUROS 1.00% S/ R$ 100.000,00 - EMPRESTIMO EM | K6: 45168 | L6: ALTOS DA JULIETA | M6: FARROUPILHA | N6: 01 | O6: 1734 | P6: Gláucio da Rosa Monteiro | T6: Vendido à vista.
A7: 45139 | B7: 1 | C7: SIVIERO EMPREENDIMENTOS IMOBILIARIOS LTD | D7: SAMIR TREVISAN PICCOLI - JUROS | E7: 45139 | F7: 45139 | G7: 250000 | H7: 2500 | I7: JUROS 1.00% S/ R$ 250.000,00 - EMPRESTIMO EM
A8: 45139 | B8: 1 | C8: SIVIERO EMPREENDIMENTOS IMOBILIARIOS LTD | D8: SAMIR TREVISAN PICCOLI - JUROS | E8: 45139 | F8: 45139 | G8: 250000 | H8: 2500 | I8: JUROS 1.00% S/ R$ 250.000,00 - EMPRESTIMO
A9: 45139 | B9: 1 | C9: SIVIERO EMPREENDIMENTOS IMOBILIARIOS LTD | D9: SAMIR TREVISAN PICCOLI - JUROS | E9: 45139 | F9: 45139 | G9: 350000 | H9: 3500 | I9: JUROS 1.00% S/ R$ 350.000,00 - EMPRESTIMO
A10: 45139 | B10: 1 | C10: SIVIERO EMPREENDIMENTOS IMOBILIARIOS LTD | D10: SAMIR TREVISAN PICCOLI - JUROS | E10: 45139 | F10: 45139 | G10: 150000 | H10: 1500 | I10: JUROS 1.00% S/ R$ 150.000,00 - EMPRESTIMO
A11: 45139 | B11: 1 | C11: SIVIERO EMPREENDIMENTOS IMOBILIARIOS LTD | D11: TABELIONATO MARCOS - CAXIAS DO SUL | E11: 45139 | F11: 45139 | G11: 421.77 | H11: 421.77 | I11: CUSTAS PENDENTES ESCRITURAS GASPARIN E ZANR
A12: 45139 | B12: 1 | C12: SIVIERO EMPREENDIMENTOS IMOBILIARIOS LTD | D12: DESPESAS DIVERSAS | E12: 45139 | F12: 45139 | G12: 2440 | H12: 2440 | I12: MARCOS A SIVIERO-DESP DIVERSAS CFE NOTAS+COM
A13: 45139 | B13: 1 | C13: SIVIERO EMPREENDIMENTOS IMOBILIARIOS LTD | D13: BANCO SICREDI - VERANÓPOLIS | E13: 45139 | F13: 45139 | G13: 0.17 | H13: 0.17 | I13: JUROS BANCO CREDITO ROTATIVO MES JULHO/2023
A14: 45139 | B14: 1 | C14: SIVIERO EMPREENDIMENTOS IMOBILIARIOS LTD | D14: IOF BANCARIO SIVIERO EMP IMOBILIARIOS | E14: 45139 | F14: 45139 | G14: 271.63 | H14: 271.63 | I14: IOF CONTA SEI MES DE JULHO DE 2023 - BANRISUL
A15: 45139 | B15: 1 | C15: SIVIERO EMPREENDIMENTOS IMOBILIARIOS LTD | D15: IOF BANCARIO SIVIERO EMP IMOBILIARIOS | E15: 45139 | F15: 45139 | G15: 1629.4 | H15: 1629.4 | I15: IOF CONTA SEI MES DE JULHO DE 2023 - BANRISUL
A16: 45139 | B16: 1 | C16: SIVIERO EMPREENDIMENTOS IMOBILIARIOS LTD | D16: RESTAURANTE - CAXIAS DO SUL | E16: 45140 | F16: 45140 | G16: 798.5 | H16: 798.5 | I16: PAGAMENTO REFEICOES MES DE JULHO/2023 - FUNCI
A17: 45139 | B17: 1 | C17: SIVIERO EMPREENDIMENTOS IMOBILIARIOS LTD | D17: JUNTA COMERCIAL - RS | E17: 45140 | F17: 45140 | G17: 59.92 | H17: 59.92 | I17: CERTIDAO SIMPLIFICADA - SIVIERO EMPREED. IMOB
A18: 45139 | B18: 1 | C18: SIVIERO EMPREENDIMENTOS IMOBILIARIOS LTD | D18: BANCO ESTADO RIO GRANDE DO SUL - SEI | E18: 45140 | F18: 45140 | G18: 180 | H18: 180 | I18: SEI - TAXA MENSALIDADE PACOTE CONTA SEI - BAN
... A267: 45139 | B267: 5 | C267: ABASTECEDORA DE COMBUSTIVEIS SIVIERO LTD | D267: CONT. SOCIAL - ABAST. COMB. SIVIERO L | E267: 45169 | F267: 45169 | G267: 456.71 | H267: 456.71 | I267: FATURAMENTO MES JULHO/2023 - R$ 15.858,00 X 2
A269: Total | G269: =SUBTOTAL(9,G2:G267) | H269: =SUBTOTAL(9,H2:H267)

Sheet 2023-09
A1: Sem relatório de contas pagas para este mês na pasta Relatórios Mensais. | K1: Data | L1: Loteamento | M1: Município | N1: Lote | O1: Quadra | P1: Comprador | Q1: Valor citado | R1: Valores no texto | S1: Venda conjunta | T1: Observações
K2: 45175 | L2: ALTOS DAS GRAÇAS | M2: CAXIAS DO SUL | N2: 02 | O2: 6373 | P2: Rosa Maria Nascimento | T2: Vendido à vista.
K3: 45177 | L3: SALVADOR – FEMAÇÃ II | M3: VERANÓPOLIS | N3: 04 | O3: 04 | P3: Prefeitura de Veranópolis | T3: Doação conforme Lei.
K4: 45182 | L4: LAGO NEGRO | M4: GRAMADO | N4: 01 | O4: 07 | P4: Fruti Frango Adm Imóveis | T4: Vendido à vista.
K5: 45190 | L5: COLINA DO RETIRO I | M5: VERANÓPOLIS | N5: 01 | O5: 02 | P5: Maicon A. Mikoaski | T5: Vendido à vista.
K6: 45191 | L6: INDUSTRIAL PEDRA LISA | M6: VERANÓPOLIS | N6: 03 | O6: 03 | P6: Ivo José Frainer | Q6: 388000 | R6: R$ 388.000,00 | T6: Vendido, como forma de pagamento na aquisição de 0,67 há de terras ao lado do Loteamento Industrial Pedra Lisa, pelo valor de R$ 388.000,00.
K7: 45195 | L7: SALVADOR – FEMAÇÃ II | M7: VERANÓPOLIS | N7: 01 | O7: 04 | P7: Volmir Marinello | T7: Vendido à prazo.

Sheet 2023-10
A1: Mês | B1: Página | C1: Empresa | D1: Fornecedor | E1: Vencimento | F1: Pagamento | G1: Valor NF | H1: Valor Dupl. | I1: Observações | K1: Data | L1: Loteamento | M1: Município | N1: Lote | O1: Quadra | P1: Comprador | Q1: Valor citado | R1: Valores no texto | S1: Venda conjunta | T1: Observações
A2: 45200 | B2: 1 | C2: SIVIERO EMPREENDIMENTOS IMOBILIARIOS LTD | D2: SIM REDE DE POSTOS LTDA. - VERANOPOLI | E2: 45200 | F2: 45201 | G2: 859.08 | H2: 859.08 | I2: ABASTECIMENTOS CARROS+CACAMBAS+OFICINA=VER | K2: 45230 | L2: MONTE VÊNETO | M2: COTIPORÃ | N2: 04 | O2: 04 | P2: Nilton de Oliveira Vieira | S2: Sim (2 lotes) | T2: Vendido à prazo, em 26x.
A3: 45200 | B3: 1 | C3: SIVIERO EMPREENDIMENTOS IMOBILIARIOS LTD | D3: INES TREVISAN PICCOLI - JUROS | E3: 45200 | F3: 45201 | G3: 100000 | H3: 1000 | I3: JUROS 1.00% S/ R$ 100.000,00 - EMPRESTIMO EM | K3: 45230 | L3: MONTE VÊNETO | M3: COTIPORÃ | N3: 05 | O3: 04 | P3: Nilton de Oliveira Vieira | S3: Sim (2 lotes) | T3: Vendido à prazo, em 26x.
A4: 45200 | B4: 1 | C4: SIVIERO EMPREENDIMENTOS IMOBILIARIOS LTD | D4: INES TREVISAN PICCOLI - JUROS | E4: 45200 | F4: 45201 | G4: 250000 | H4: 2500 | I4: JUROS 1.00% S/ R$ 250.000,00 - EMPRESTIMO
A5: 45200 | B5: 1 | C5: SIVIERO EMPREENDIMENTOS IMOBILIARIOS LTD | D5: ANDRE LUIZ SIVIERO - JUROS | E5: 45200 | F5: 45201 | G5: 100000 | H5: 800 | I5: JUROS 0,80% S/ R$ 100.000,00 - EMPRESTIMO
A6: 45200 | B6: 1 | C6: SIVIERO EMPREENDIMENTOS IMOBILIARIOS LTD | D6: SAMIR TREVISAN PICCOLI - JUROS | E6: 45200 | F6: 45201 | G6: 250000 | H6: 2500 | I6: JUROS 1.00% S/ R$ 250.000,00 - EMPRESTIMO EM
A7: 45200 | B7: 1 | C7: SIVIERO EMPREENDIMENTOS IMOBILIARIOS LTD | D7: SAMIR TREVISAN PICCOLI - JUROS | E7: 45200 | F7: 45201 | G7: 250000 | H7: 2500 | I7: JUROS 1.00% S/ R$ 250.000,00 - EMPRESTIMO
A8: 45200 | B8: 1 | C8: SIVIERO EMPREENDIMENTOS IMOBILIARIOS LTD | D8: SAMIR TREVISAN PICCOLI - JUROS | E8: 45200 | F8: 45201 | G8: 350000 | H8: 3500 | I8: JUROS 1.00% S/ R$ 350.000,00 - EMPRESTIMO
A9: 45200 | B9: 1 | C9: SIVIERO EMPREENDIMENTOS IMOBILIARIOS LTD | D9: SAMIR TREVISAN PICCOLI - JUROS | E9: 45200 | F9: 45201 | G9: 150000 | H9: 1500 | I9: JUROS 1.00% S/ R$ 150.000,00 - EMPRESTIMO
A10: 45200 | B10: 1 | C10: SIVIERO EMPREENDIMENTOS IMOBILIARIOS LTD | D10: PORTAL EMPREENDIMENTOS IMOBILIARIOS L | E10: 45201 | F10: 45201 | G10: 10000 | H10: 4000 | I10: P.1/3-COMISSAO LT 01-QDRA 1748-JARDIM ITALIA-
A11: 45200 | B11: 1 | C11: SIVIERO EMPREENDIMENTOS IMOBILIARIOS LTD | D11: PORTAL EMPREENDIMENTOS IMOBILIARIOS L | E11: 45201 | F11: 45201 | G11: 10000 | H11: 3500 | I11: P.2/3-COMISSAO LT 01-QDRA 1748-JARDIM ITALIA-
A12: 45200 | B12: 1 | C12: SIVIERO EMPREENDIMENTOS IMOBILIARIOS LTD | D12: PORTAL EMPREENDIMENTOS IMOBILIARIOS L | E12: 45201 | F12: 45201 | G12: 10000 | H12: 2500 | I12: P.3/3-COMISSAO LT 01-QDRA 1748-JARDIM ITALIA-
A13: 45200 | B13: 1 | C13: SIVIERO EMPREENDIMENTOS IMOBILIARIOS LTD | D13: BANCO SICREDI - VERANÓPOLIS | E13: 45201 | F13: 45201 | G13: 0.17 | H13: 0.17 | I13: JUROS BANCO CREDITO ROTATIVO MES SETEMBRO/20
A14: 45200 | B14: 1 | C14: SIVIERO EMPREENDIMENTOS IMOBILIARIOS LTD | D14: LOCAWEB SERVICOS DE INTERNET SA | E14: 45201 | F14: 45201 | G14: 64.9 | H14: 64.9 | I14: TAXA ANUAL DO DOMINIO-CONDOMINIO MORADA DO IP
A15: 45200 | B15: 1 | C15: SIVIERO EMPREENDIMENTOS IMOBILIARIOS LTD | D15: BANCO SICREDI - VERANÓPOLIS | E15: 45201 | F15: 45201 | G15: 16.74 | H15: 16.74 | I15: JUROS BANCO CONTA LIMITE EMPRESARIAL MES SETE
... A273: 45200 | B273: 5 | C273: ABASTECEDORA DE COMBUSTIVEIS SIVIERO LTD | D273: CONT. SOCIAL - ABAST. COMB. SIVIERO L | E273: 45230 | F273: 45230 | G273: 456.71 | H273: 456.71 | I273: FATURAMENTO MES SETEMBRO/2023 - R$ 15.858,00
A275: Total | G275: =SUBTOTAL(9,G2:G273) | H275: =SUBTOTAL(9,H2:H273)

Sheet 2023-11
A1: Mês | B1: Página | C1: Empresa | D1: Fornecedor | E1: Vencimento | F1: Pagamento | G1: Valor NF | H1: Valor Dupl. | I1: Observações | K1: Data | L1: Loteamento | M1: Município | N1: Lote | O1: Quadra | P1: Comprador | Q1: Valor citado | R1: Valores no texto | S1: Venda conjunta | T1: Observações
A2: 45231 | B2: 1 | C2: SIVIERO EMPREENDIMENTOS IMOBILIARIOS LTD | D2: JDRX NEGOCIOS IMOBILARIOS LTDA.- P.FU | E2: 45231 | F2: 45231 | G2: 11750 | H2: 11750 | I2: COMISSAO VENDA LT 12-QUADRA 04-MORADA IPE-LEA | K2: 45231 | L2: VIERO | M2: FARROUPILHA | N2: 12 | O2: 1467 | P2: Elizete/Rosália de Oliveira | T2: Vendido à vista.
A3: 45231 | B3: 1 | C3: SIVIERO EMPREENDIMENTOS IMOBILIARIOS LTD | D3: CLAIRTON VENDRAMIN-NOVA PRATA-CHAPEAC | E3: 45231 | F3: 45231 | G3: 2700 | H3: 1350 | I3: PARC. 02/02 - CONSERTOS E CHAPEACAO TOYOTA PR | K3: 45238 | L3: CONDOMÍNIO MORADA DOS IPÊS | M3: PASSO FUNDO | N3: 008 | O3: 04 | P3: Raul Martini | T3: Vendido à prazo, em 02x.
A4: 45231 | B4: 1 | C4: SIVIERO EMPREENDIMENTOS IMOBILIARIOS LTD | D4: PARANA EQUIPAMENTOS SA | E4: 45231 | F4: 45231 | G4: 1578.37 | H4: 526.12 | I4: P. 01/03 - 02 MANCAL - ESCAVADEIRA ROMPEDOR-O
A5: 45231 | B5: 1 | C5: SIVIERO EMPREENDIMENTOS IMOBILIARIOS LTD | D5: ANDRE LUIZ SIVIERO - JUROS | E5: 45231 | F5: 45231 | G5: 100000 | H5: 800 | I5: JUROS 0,80% S/ R$ 100.000,00 - EMPRESTIMO
A6: 45231 | B6: 1 | C6: SIVIERO EMPREENDIMENTOS IMOBILIARIOS LTD | D6: INES TREVISAN PICCOLI - JUROS | E6: 45231 | F6: 45231 | G6: 100000 | H6: 1000 | I6: JUROS 1.00% S/ R$ 100.000,00 - EMPRESTIMO EM
A7: 45231 | B7: 1 | C7: SIVIERO EMPREENDIMENTOS IMOBILIARIOS LTD | D7: INES TREVISAN PICCOLI - JUROS | E7: 45231 | F7: 45231 | G7: 250000 | H7: 2500 | I7: JUROS 1.00% S/ R$ 250.000,00 - EMPRESTIMO
A8: 45231 | B8: 1 | C8: SIVIERO EMPREENDIMENTOS IMOBILIARIOS LTD | D8: SAMIR TREVISAN PICCOLI - JUROS | E8: 45231 | F8: 45231 | G8: 250000 | H8: 2500 | I8: JUROS 1.00% S/ R$ 250.000,00 - EMPRESTIMO EM
A9: 45231 | B9: 1 | C9: SIVIERO EMPREENDIMENTOS IMOBILIARIOS LTD | D9: SAMIR TREVISAN PICCOLI - JUROS | E9: 45231 | F9: 45231 | G9: 250000 | H9: 2500 | I9: JUROS 1.00% S/ R$ 250.000,00 - EMPRESTIMO EM
A10: 45231 | B10: 1 | C10: SIVIERO EMPREENDIMENTOS IMOBILIARIOS LTD | D10: SAMIR TREVISAN PICCOLI - JUROS | E10: 45231 | F10: 45231 | G10: 350000 | H10: 3500 | I10: JUROS 1.00% S/ R$ 350.000,00 - EMPRESTIMO EM
A11: 45231 | B11: 1 | C11: SIVIERO EMPREENDIMENTOS IMOBILIARIOS LTD | D11: SAMIR TREVISAN PICCOLI - JUROS | E11: 45231 | F11: 45231 | G11: 150000 | H11: 1500 | I11: JUROS 1.00% S/ R$ 150.000,00 - EMPRESTIMO EM
A12: 45231 | B12: 1 | C12: SIVIERO EMPREENDIMENTOS IMOBILIARIOS LTD | D12: BANCO SICREDI - VERANÓPOLIS | E12: 45231 | F12: 45231 | G12: 0.16 | H12: 0.16 | I12: JUROS BANCO CREDITO ROTATIVO MES OUTUBRO/202
A13: 45231 | B13: 1 | C13: SIVIERO EMPREENDIMENTOS IMOBILIARIOS LTD | D13: BANCO SICREDI - VERANÓPOLIS | E13: 45231 | F13: 45231 | G13: 5.9 | H13: 5.9 | I13: TAXA BANCO TED/DOC PESSOA JURIDICA - TRANSFER
A14: 45231 | B14: 1 | C14: SIVIERO EMPREENDIMENTOS IMOBILIARIOS LTD | D14: IOF BANCARIO SIVIERO EMP IMOBILIARIOS | E14: 45231 | F14: 45231 | G14: 64.99 | H14: 64.99 | I14: IOF CONTA SEI MES DE OUTUBRO DE 2023 - BANRIS
A15: 45231 | B15: 1 | C15: SIVIERO EMPREENDIMENTOS IMOBILIARIOS LTD | D15: IOF BANCARIO SIVIERO EMP IMOBILIARIOS | E15: 45231 | F15: 45231 | G15: 1125.93 | H15: 1125.93 | I15: IOF CONTA SEI MES DE OUTUBRO DE 2023 - BANRIS
... A236: 45231 | B236: 5 | C236: ABASTECEDORA DE COMBUSTIVEIS SIVIERO LTD | D236: CONT. SOCIAL - ABAST. COMB. SIVIERO L | E236: 45260 | F236: 45260 | G236: 456.71 | H236: 456.71 | I236: FATURAMENTO MES OUTUBRO/2023 - R$ 15.858,00 X
A238: Total | G238: =SUBTOTAL(9,G2:G236) | H238: =SUBTOTAL(9,H2:H236)

Sheet 2023-12
A1: Mês | B1: Página | C1: Empresa | D1: Fornecedor | E1: Vencimento | F1: Pagamento | G1: Valor NF | H1: Valor Dupl. | I1: Observações | K1: Data | L1: Loteamento | M1: Município | N1: Lote | O1: Quadra | P1: Comprador | Q1: Valor citado | R1: Valores no texto | S1: Venda conjunta | T1: Observações
A2: 45261 | B2: 1 | C2: SIVIERO EMPREENDIMENTOS IMOBILIARIOS LTD | D2: PARANA EQUIPAMENTOS SA | E2: 45261 | F2: 45261 | G2: 1578.37 | H2: 526.12 | I2: P. 02/03 - 02 MANCAL - ESCAVADEIRA ROMPEDOR-O | K2: 45278 | L2: SALVADOR – FEMAÇÃ II | M2: VERANÓPOLIS | N2: 01 | O2: 03 | P2: Rogério Binda | S2: Sim (2 lotes) | T2: Vendido à vista.
A3: 45261 | B3: 1 | C3: SIVIERO EMPREENDIMENTOS IMOBILIARIOS LTD | D3: MULTI CELTACAR PECAS SERVICOS LTDA. | E3: 45261 | F3: 45261 | G3: 350 | H3: 350 | I3: BIELETA+BUCHA DIANTEIRA+MAO DE OBRA -IWB 5G54 | K3: 45278 | L3: SALVADOR – FEMAÇÃ II | M3: VERANÓPOLIS | N3: 02 | O3: 03 | P3: Rogério Binda | S3: Sim (2 lotes) | T3: Vendido à vista.
A4: 45261 | B4: 1 | C4: SIVIERO EMPREENDIMENTOS IMOBILIARIOS LTD | D4: LOCAWEB SERVICOS DE INTERNET SA | E4: 45261 | F4: 45261 | G4: 473.59 | H4: 473.59 | I4: TAXA ANUAL 2023/2024 DO DOMINIO - SIVIEROURBA | K4: 45280 | L4: ALTOS DAS GRAÇAS | M4: CAXIAS DO SUL | N4: 14 | O4: 6369 | P4: MSL Incorporadora Ltda. | T4: Vendido à prazo, em 02x.
A5: 45261 | B5: 1 | C5: SIVIERO EMPREENDIMENTOS IMOBILIARIOS LTD | D5: INES TREVISAN PICCOLI - JUROS | E5: 45261 | F5: 45261 | G5: 250000 | H5: 2500 | I5: JUROS 1.00% S/ R$ 250.000,00 - EMPRESTIMO EM
A6: 45261 | B6: 1 | C6: SIVIERO EMPREENDIMENTOS IMOBILIARIOS LTD | D6: INES TREVISAN PICCOLI - JUROS | E6: 45261 | F6: 45261 | G6: 100000 | H6: 1000 | I6: JUROS 1.00% S/ R$ 100.000,00 - EMPRESTIMO EM
A7: 45261 | B7: 1 | C7: SIVIERO EMPREENDIMENTOS IMOBILIARIOS LTD | D7: SAMIR TREVISAN PICCOLI - JUROS | E7: 45261 | F7: 45261 | G7: 150000 | H7: 1500 | I7: JUROS 1.00% S/ R$ 150.000,00 - EMPRESTIMO EM
A8: 45261 | B8: 1 | C8: SIVIERO EMPREENDIMENTOS IMOBILIARIOS LTD | D8: SAMIR TREVISAN PICCOLI - JUROS | E8: 45261 | F8: 45261 | G8: 350000 | H8: 3500 | I8: JUROS 1.00% S/ R$ 350.000,00 - EMPRESTIMO EM
A9: 45261 | B9: 1 | C9: SIVIERO EMPREENDIMENTOS IMOBILIARIOS LTD | D9: SAMIR TREVISAN PICCOLI - JUROS | E9: 45261 | F9: 45261 | G9: 250000 | H9: 2500 | I9: JUROS 1.00% S/ R$ 250.000,00 - EMPRESTIMO EM
A10: 45261 | B10: 1 | C10: SIVIERO EMPREENDIMENTOS IMOBILIARIOS LTD | D10: SAMIR TREVISAN PICCOLI - JUROS | E10: 45261 | F10: 45261 | G10: 250000 | H10: 2500 | I10: JUROS 1.00% S/ R$ 250.000,00 - EMPRESTIMO EM
A11: 45261 | B11: 1 | C11: SIVIERO EMPREENDIMENTOS IMOBILIARIOS LTD | D11: TORNEARIA RD LTDA | E11: 45261 | F11: 45261 | G11: 150 | H11: 150 | I11: SERVICOS TORNO E SOLDAS EM GERAL - RETRO - OF
A12: 45261 | B12: 1 | C12: SIVIERO EMPREENDIMENTOS IMOBILIARIOS LTD | D12: SOLLARE EMP IMOB LTDA. - NATAL LACERD | E12: 45261 | F12: 45261 | G12: 15000 | H12: 15000 | I12: COMISSAO AREA CONGREGACAO SAO CARLOS - PASS
A13: 45261 | B13: 1 | C13: SIVIERO EMPREENDIMENTOS IMOBILIARIOS LTD | D13: DESPESAS DIVERSAS | E13: 45261 | F13: 45261 | G13: 500 | H13: 500 | I13: JUAREZ ROCHA-SERV REPOSICAO CALCAMENTO+COR
A14: 45261 | B14: 1 | C14: SIVIERO EMPREENDIMENTOS IMOBILIARIOS LTD | D14: PEDRONES OFICINA DIESEL | E14: 45261 | F14: 45261 | G14: 100 | H14: 100 | I14: FILTRO DIESEL - FORD RANGER DA SEI - MARCOS S
A15: 45261 | B15: 1 | C15: SIVIERO EMPREENDIMENTOS IMOBILIARIOS LTD | D15: ADELIA FRIZON SIVIERO | E15: 45261 | F15: 45261 | G15: 100000 | H15: 100000 | I15: DEVOLUCAO EMPRESTIMO REF. VENDA LOTE LOT. BAU
A16: 45261 | B16: 1 | C16: SIVIERO EMPREENDIMENTOS IMOBILIARIOS LTD | D16: PEDRO SIVIERO | E16: 45261 | F16: 45261 | G16: 300000 | H16: 80000 | I16: P.1/4-DEV EMPRESTIMO FEITO ESPECIE DE R$ 200.
... A278: 45261 | B278: 6 | C278: ABASTECEDORA DE COMBUSTIVEIS SIVIERO LTD | D278: CONT. SOCIAL - ABAST. COMB. SIVIERO L | E278: 45288 | F278: 45288 | G278: 456.71 | H278: 456.71 | I278: FATURAMENTO MES NOVEMBRO/2023 - R$ 15.858,00
A280: Total | G280: =SUBTOTAL(9,G2:G278) | H280: =SUBTOTAL(9,H2:H278)

Sheet 2024-01
A1: Mês | B1: Página | C1: Empresa | D1: Fornecedor | E1: Vencimento | F1: Pagamento | G1: Valor NF | H1: Valor Dupl. | I1: Observações | K1: Data | L1: Loteamento | M1: Município | N1: Lote | O1: Quadra | P1: Comprador | Q1: Valor citado | R1: Valores no texto | S1: Venda conjunta | T1: Observações
A2: 45292 | B2: 1 | C2: SIVIERO EMPREENDIMENTOS IMOBILIARIOS LTD | D2: INES TREVISAN PICCOLI - JUROS | E2: 45292 | F2: 45293 | G2: 250000 | H2: 2500 | I2: JUROS 1.00% S/ R$ 250.000,00 - EMPRESTIMO EM | K2: 45292 | L2: BARBIERO | M2: NOVA PRATA | N2: 08 | O2: 02 | P2: André Luiz Siviero | T2: Vendido, como forma de devolução de empréstimo e pagamento de juros.
A3: 45292 | B3: 1 | C3: SIVIERO EMPREENDIMENTOS IMOBILIARIOS LTD | D3: INES TREVISAN PICCOLI - JUROS | E3: 45292 | F3: 45293 | G3: 100000 | H3: 1000 | I3: JUROS 1.00% S/ R$ 100.000,00 - EMPRESTIMO EM | K3: 45306 | L3: CONDOMÍNIO MORADA DOS IPÊS | M3: PASSO FUNDO | N3: 001 | O3: 06 | P3: Juliano Pretto Elton Sobiesiak | T3: Vendido, como forma de pagamento de DAÇÃO EM PAGAMENTO, referente a aquisição de uma área de terras doada para o Município de Passo Fundo, para compensação de áreas para as 02 (duas) fases do Condomínio Morada dos Ipês II, em Passo Fundo, num total de 03 (três) lotes dentro do Condomínio, em parceria com a Família Zanella.
A4: 45292 | B4: 1 | C4: SIVIERO EMPREENDIMENTOS IMOBILIARIOS LTD | D4: SAMIR TREVISAN PICCOLI - JUROS | E4: 45292 | F4: 45293 | G4: 150000 | H4: 1500 | I4: JUROS 1.00% S/ R$ 150.000,00 - EMPRESTIMO EM
A5: 45292 | B5: 1 | C5: SIVIERO EMPREENDIMENTOS IMOBILIARIOS LTD | D5: SAMIR TREVISAN PICCOLI - JUROS | E5: 45292 | F5: 45293 | G5: 350000 | H5: 3500 | I5: JUROS 1.00% S/ R$ 350.000,00 - EMPRESTIMO EM
A6: 45292 | B6: 1 | C6: SIVIERO EMPREENDIMENTOS IMOBILIARIOS LTD | D6: SAMIR TREVISAN PICCOLI - JUROS | E6: 45292 | F6: 45293 | G6: 250000 | H6: 2500 | I6: JUROS 1.00% S/ R$ 250.000,00 - EMPRESTIMO EM
A7: 45292 | B7: 1 | C7: SIVIERO EMPREENDIMENTOS IMOBILIARIOS LTD | D7: SAMIR TREVISAN PICCOLI - JUROS | E7: 45292 | F7: 45293 | G7: 250000 | H7: 2500 | I7: JUROS 1.00% S/ R$ 250.000,00 - EMPRESTIMO EM
A8: 45292 | B8: 1 | C8: SIVIERO EMPREENDIMENTOS IMOBILIARIOS LTD | D8: MULTAS DE TRANSITO | E8: 45293 | F8: 45293 | G8: 104.12 | H8: 104.12 | I8: TOYOTA IZR 2E40-SEM LUZ NEBLINA ACESSA- CARLO
A9: 45292 | B9: 1 | C9: SIVIERO EMPREENDIMENTOS IMOBILIARIOS LTD | D9: MULTAS DE TRANSITO | E9: 45293 | F9: 45293 | G9: 78.09 | H9: 78.09 | I9: TOYOTA-ELCIO SIVIERO-IWB 8F46-EXCESSO VELOC.
A10: 45292 | B10: 1 | C10: SIVIERO EMPREENDIMENTOS IMOBILIARIOS LTD | D10: BANCO SICREDI - VERANÓPOLIS | E10: 45293 | F10: 45293 | G10: 0.18 | H10: 0.18 | I10: JUROS BANCO CREDITO ROTATIVO MES DEZEMBRO/20
A11: 45292 | B11: 1 | C11: SIVIERO EMPREENDIMENTOS IMOBILIARIOS LTD | D11: DORVAL FRANCISCO BOFF - CAXIAS DO SUL | E11: 45294 | F11: 45294 | G11: 100000 | H11: 5000 | I11: P.10/10-CFE CONTRATO ANTECIPACAO VALORES - LO
A12: 45292 | B12: 1 | C12: SIVIERO EMPREENDIMENTOS IMOBILIARIOS LTD | D12: AZUL COMPANHIA DE SEGUROS GERAIS | E12: 45294 | F12: 45294 | G12: 5399.23 | H12: 1349.8 | I12: P.03/04 - SEGURO TOYOTA HILUX CINZA NCD 3J24
A13: 45292 | B13: 1 | C13: SIVIERO EMPREENDIMENTOS IMOBILIARIOS LTD | D13: SUL TURBOS TRANSP. E IMPORT. LTDA. | E13: 45294 | F13: 45294 | G13: 2500 | H13: 833.33 | I13: P. 2/3 - TURBO - RETROESCAVADEIRA
A14: 45292 | B14: 1 | C14: SIVIERO EMPREENDIMENTOS IMOBILIARIOS LTD | D14: BANCO ESTADO RIO GRANDE DO SUL - SEI | E14: 45294 | F14: 45294 | G14: 146.25 | H14: 146.25 | I14: SEI - TAXA MENSALIDADE PACOTE CONTA SEI - BAN
A15: 45292 | B15: 1 | C15: SIVIERO EMPREENDIMENTOS IMOBILIARIOS LTD | D15: PAULO RICARDO PALUDO - BATERIAS | E15: 45295 | F15: 45295 | G15: 770 | H15: 770 | I15: O1 BATERIA CARRO JEPP COMPASS DA SEI-AD. TROC
... A235: 45292 | B235: 5 | C235: ABASTECEDORA DE COMBUSTIVEIS SIVIERO LTD | D235: CONT. SOCIAL - ABAST. COMB. SIVIERO L | E235: 45322 | F235: 45322 | G235: 456.71 | H235: 456.71 | I235: FATURAMENTO MES DEZEMBRO/2023 - R$ 15.858,00
A237: Total | G237: =SUBTOTAL(9,G2:G235) | H237: =SUBTOTAL(9,H2:H235)

Sheet 2024-02
A1: Mês | B1: Página | C1: Empresa | D1: Fornecedor | E1: Vencimento | F1: Pagamento | G1: Valor NF | H1: Valor Dupl. | I1: Observações | K1: Data | L1: Loteamento | M1: Município | N1: Lote | O1: Quadra | P1: Comprador | Q1: Valor citado | R1: Valores no texto | S1: Venda conjunta | T1: Observações
A2: 45323 | B2: 1 | C2: SIVIERO EMPREENDIMENTOS IMOBILIARIOS LTD | D2: OFICINA MECANICA VACCARI LTDA. - CAXI | E2: 45324 | F2: 45323 | G2: 1055 | H2: 527.5 | I2: SENSOR+OLEO DIFERENCIAL+SERVICOS=FORD RAN | K2: 45349 | L2: MONTE VÊNETO | M2: COTIPORÃ | N2: 09 | O2: 01 | P2: Rovílio Antônio Dal Más | Q2: 190000 | R2: R$ 190.000,00 | S2: Sim (2 lotes) | T2: Vendido à vista, com permuta de outro imóvel – Lote 03, Quadra 04 – Loteamento Femaçã II – Veranópolis, valor de R$ 190.000,00.
A3: 45323 | B3: 1 | C3: SIVIERO EMPREENDIMENTOS IMOBILIARIOS LTD | D3: INES TREVISAN PICCOLI - JUROS | E3: 45323 | F3: 45323 | G3: 100000 | H3: 1000 | I3: JUROS 1.00% S/ R$ 100.000,00 - EMPRESTIMO EM | K3: 45349 | L3: MONTE VÊNETO | M3: COTIPORÃ | N3: 10 | O3: 01 | P3: Rovílio Antônio Dal Más | Q3: 190000 | R3: R$ 190.000,00 | S3: Sim (2 lotes) | T3: Vendido à vista, com permuta de outro imóvel – Lote 03, Quadra 04 – Loteamento Femaçã II – Veranópolis, valor de R$ 190.000,00.
A4: 45323 | B4: 1 | C4: SIVIERO EMPREENDIMENTOS IMOBILIARIOS LTD | D4: INES TREVISAN PICCOLI - JUROS | E4: 45323 | F4: 45323 | G4: 250000 | H4: 2500 | I4: JUROS 1.00% S/ R$ 250.000,00 - EMPRESTIMO EM
A5: 45323 | B5: 1 | C5: SIVIERO EMPREENDIMENTOS IMOBILIARIOS LTD | D5: SAMIR TREVISAN PICCOLI - JUROS | E5: 45323 | F5: 45323 | G5: 250000 | H5: 2500 | I5: JUROS 1.00% S/ R$ 250.000,00 - EMPRESTIMO EM
A6: 45323 | B6: 1 | C6: SIVIERO EMPREENDIMENTOS IMOBILIARIOS LTD | D6: SAMIR TREVISAN PICCOLI - JUROS | E6: 45323 | F6: 45323 | G6: 250000 | H6: 2500 | I6: JUROS 1.00% S/ R$ 250.000,00 - EMPRESTIMO EM
A7: 45323 | B7: 1 | C7: SIVIERO EMPREENDIMENTOS IMOBILIARIOS LTD | D7: SAMIR TREVISAN PICCOLI - JUROS | E7: 45323 | F7: 45323 | G7: 350000 | H7: 3500 | I7: JUROS 1.00% S/ R$ 350.000,00 - EMPRESTIMO EM
A8: 45323 | B8: 1 | C8: SIVIERO EMPREENDIMENTOS IMOBILIARIOS LTD | D8: SAMIR TREVISAN PICCOLI - JUROS | E8: 45323 | F8: 45323 | G8: 150000 | H8: 1500 | I8: JUROS 1.00% S/ R$ 150.000,00 - EMPRESTIMO EM
A9: 45323 | B9: 1 | C9: SIVIERO EMPREENDIMENTOS IMOBILIARIOS LTD | D9: SAMIR TREVISAN PICCOLI - JUROS | E9: 45323 | F9: 45323 | G9: 150000 | H9: 1500 | I9: JUROS 1.00% S/ R$ 150.000,00 - EMPRESTIMO EM
A10: 45323 | B10: 1 | C10: SIVIERO EMPREENDIMENTOS IMOBILIARIOS LTD | D10: DESPESAS DIVERSAS | E10: 45323 | F10: 45323 | G10: 2200 | H10: 2200 | I10: MARCOS A SIVIERO-DESP DIVERSAS CFE NOTAS+CO
A11: 45323 | B11: 1 | C11: SIVIERO EMPREENDIMENTOS IMOBILIARIOS LTD | D11: CIELLO E MARIN IND E COM DE ARTESANAT | E11: 45323 | F11: 45323 | G11: 155 | H11: 155 | I11: QUADRO CERTIDAO DE CASAMENTO DE LUIZ E ANGE
A12: 45323 | B12: 1 | C12: SIVIERO EMPREENDIMENTOS IMOBILIARIOS LTD | D12: BANCO SICREDI - VERANÓPOLIS | E12: 45323 | F12: 45323 | G12: 0.17 | H12: 0.17 | I12: JUROS BANCO CREDITO ROTATIVO MES JANEIRO/20
A13: 45323 | B13: 1 | C13: SIVIERO EMPREENDIMENTOS IMOBILIARIOS LTD | D13: RESTAURANTE E CHURRASCARIA SERRANA | E13: 45323 | F13: 45323 | G13: 33 | H13: 33 | I13: PAGO ALMOCO FUNCIONARIO MARCIANO EM 29.01.20
A14: 45323 | B14: 1 | C14: SIVIERO EMPREENDIMENTOS IMOBILIARIOS LTD | D14: L.R. BETT PAVIMENTACOES E OBRAS LTDA | E14: 45324 | F14: 45324 | G14: 5250 | H14: 5250 | I14: CONSERTO 21 CAIXAS DE PASSAGEM E BOCA DE LO
A15: 45323 | B15: 1 | C15: SIVIERO EMPREENDIMENTOS IMOBILIARIOS LTD | D15: DAVENIR ANTONIO DA SILVA-FLORES DA CU | E15: 45324 | F15: 45324 | G15: 3000 | H15: 3000 | I15: MAO DE OBRA CONSTRUCAO MURO DE TAIPA PARQU
... A212: 45323 | B212: 4 | C212: ABASTECEDORA DE COMBUSTIVEIS SIVIERO LTD | D212: CONT. SOCIAL - ABAST. COMB. SIVIERO L | E212: 45351 | F212: 45351 | G212: 765.5 | H212: 765.5 | I212: FATURAMENTO MES JANEIRO/2024 - R$ 26.580,00 X
A214: Total | G214: =SUBTOTAL(9,G2:G212) | H214: =SUBTOTAL(9,H2:H212)

Sheet 2024-03
A1: Mês | B1: Página | C1: Empresa | D1: Fornecedor | E1: Vencimento | F1: Pagamento | G1: Valor NF | H1: Valor Dupl. | I1: Observações | K1: Data | L1: Loteamento | M1: Município | N1: Lote | O1: Quadra | P1: Comprador | Q1: Valor citado | R1: Valores no texto | S1: Venda conjunta | T1: Observações
A2: 45352 | B2: 1 | C2: SIVIERO EMPREENDIMENTOS IMOBILIARIOS LTD | D2: SAMIR TREVISAN PICCOLI - JUROS | E2: 45352 | F2: 45352 | G2: 150000 | H2: 1500 | I2: JUROS 1.00% S/ R$ 150.000,00 - EMPRESTIMO EM | K2: 45370 | L2: ALTOS DAS GRAÇAS | M2: CAXIAS DO SUL | N2: 13 | O2: 6372 | P2: Evandro Mário Zanrosso | T2: Vendido, conforme acordo ajustado dentre as partes, no Instrumento Particular de Acordo Extrajudicial, firmado em 19 de março de 2024, na forma de DAÇÃO EM PAGAMENTO.
A3: 45352 | B3: 1 | C3: SIVIERO EMPREENDIMENTOS IMOBILIARIOS LTD | D3: SAMIR TREVISAN PICCOLI - JUROS | E3: 45352 | F3: 45352 | G3: 150000 | H3: 1500 | I3: JUROS 1.00% S/ R$ 150.000,00 - EMPRESTIMO EM | K3: 45372 | L3: SALVADOR – FEMAÇÃ II | M3: VERANÓPOLIS | N3: 02 | O3: 05 | P3: Marcos Vinicius Dalazen | T3: Vendido à vista.
A4: 45352 | B4: 1 | C4: SIVIERO EMPREENDIMENTOS IMOBILIARIOS LTD | D4: SAMIR TREVISAN PICCOLI - JUROS | E4: 45352 | F4: 45352 | G4: 350000 | H4: 3500 | I4: JUROS 1.00% S/ R$ 350.000,00 - EMPRESTIMO EM
A5: 45352 | B5: 1 | C5: SIVIERO EMPREENDIMENTOS IMOBILIARIOS LTD | D5: SAMIR TREVISAN PICCOLI - JUROS | E5: 45352 | F5: 45352 | G5: 250000 | H5: 2500 | I5: JUROS 1.00% S/ R$ 250.000,00 - EMPRESTIMO EM
A6: 45352 | B6: 1 | C6: SIVIERO EMPREENDIMENTOS IMOBILIARIOS LTD | D6: SAMIR TREVISAN PICCOLI - JUROS | E6: 45352 | F6: 45352 | G6: 250000 | H6: 2500 | I6: JUROS 1.00% S/ R$ 250.000,00 - EMPRESTIMO EM
A7: 45352 | B7: 1 | C7: SIVIERO EMPREENDIMENTOS IMOBILIARIOS LTD | D7: INES TREVISAN PICCOLI - JUROS | E7: 45352 | F7: 45352 | G7: 100000 | H7: 1000 | I7: JUROS 1.00% S/ R$ 100.000,00 - EMPRESTIMO EM
A8: 45352 | B8: 1 | C8: SIVIERO EMPREENDIMENTOS IMOBILIARIOS LTD | D8: INES TREVISAN PICCOLI - JUROS | E8: 45352 | F8: 45352 | G8: 250000 | H8: 2500 | I8: JUROS 1.00% S/ R$ 250.000,00 - EMPRESTIMO EM
A9: 45352 | B9: 1 | C9: SIVIERO EMPREENDIMENTOS IMOBILIARIOS LTD | D9: REGISTRO IMOVEIS DE NOVA PRATA - RS | E9: 45352 | F9: 45352 | G9: 190.69 | H9: 190.69 | I9: 04 MATRICULAS: 26.255 26.256 26.456 21.413-LO
A10: 45352 | B10: 1 | C10: SIVIERO EMPREENDIMENTOS IMOBILIARIOS LTD | D10: DESPESAS DIVERSAS | E10: 45352 | F10: 45352 | G10: 38 | H10: 38 | I10: RESTAURANTE-ALMOCO MARCIANO VIAGEM COMPRA A
A11: 45352 | B11: 1 | C11: SIVIERO EMPREENDIMENTOS IMOBILIARIOS LTD | D11: PEDAGIOS | E11: 45352 | F11: 45352 | G11: 17.4 | H11: 17.4 | I11: PEDAGIO COMPRA CARGA DE AREIA MARCIANO DIA 27
A12: 45352 | B12: 1 | C12: SIVIERO EMPREENDIMENTOS IMOBILIARIOS LTD | D12: PEDAGIOS | E12: 45352 | F12: 45352 | G12: 17.4 | H12: 17.4 | I12: PEDAGIO COMPRA CARGA DE AREIA MARCIANO DIA 27
A13: 45352 | B13: 1 | C13: SIVIERO EMPREENDIMENTOS IMOBILIARIOS LTD | D13: DESPESAS DIVERSAS | E13: 45352 | F13: 45352 | G13: 880 | H13: 880 | I13: CAIO-ROCADOR-ROCADA RUAS E AREAS DAS CALCADA
A14: 45352 | B14: 1 | C14: SIVIERO EMPREENDIMENTOS IMOBILIARIOS LTD | D14: DESPESAS DIVERSAS | E14: 45352 | F14: 45352 | G14: 100 | H14: 100 | I14: CONTRIBUICAO AJUDA CIRURGIA OLHO DE UM PEDINT
A15: 45352 | B15: 1 | C15: SIVIERO EMPREENDIMENTOS IMOBILIARIOS LTD | D15: BANCO SICREDI - VERANÓPOLIS | E15: 45352 | F15: 45352 | G15: 0.14 | H15: 0.14 | I15: JUROS BANCO CREDITO ROTATIVO MES FEVEREIRO/202
... A238: 45352 | B238: 5 | C238: ABASTECEDORA DE COMBUSTIVEIS SIVIERO LTD | D238: CONT. SOCIAL - ABAST. COMB. SIVIERO L | E238: 45379 | F238: 45379 | G238: 765.5 | H238: 765.5 | I238: FATURAMENTO MES FEVEREIRO/2024 - R$ 26.580,00
A240: Total | G240: =SUBTOTAL(9,G2:G238) | H240: =SUBTOTAL(9,H2:H238)

Sheet 2024-04
A1: Mês | B1: Página | C1: Empresa | D1: Fornecedor | E1: Vencimento | F1: Pagamento | G1: Valor NF | H1: Valor Dupl. | I1: Observações | K1: Data | L1: Loteamento | M1: Município | N1: Lote | O1: Quadra | P1: Comprador | Q1: Valor citado | R1: Valores no texto | S1: Venda conjunta | T1: Observações
A2: 45383 | B2: 1 | C2: SIVIERO EMPREENDIMENTOS IMOBILIARIOS LTD | D2: CREA - RS-CONSELHO REGIONAL ENGENHARI | E2: 45382 | F2: 45383 | G2: 64.77 | H2: 64.77 | I2: ANUIDADE ANO 2024 - ENGENHEIRO PEDRO SIVIERO | K2: 45398 | L2: ALTOS DA JULIETA | M2: FARROUPILHA | N2: 01 | O2: 1735 | P2: Janete Basso | T2: Vendido à vista.
A3: 45383 | B3: 1 | C3: SIVIERO EMPREENDIMENTOS IMOBILIARIOS LTD | D3: SIM REDE DE POSTOS LTDA. - VERANOPOLI | E3: 45382 | F3: 45383 | G3: 1223.38 | H3: 1223.38 | I3: ABASTECIMENTOS CARROS+CACAMBAS+OFICINA=VER | K3: 45406 | L3: ADITIVO MEDIANEIRA | M3: VERANÓPOLIS | N3: 02 | O3: 07 | P3: Solar Serra Ltda. | T3: Vendido, como forma de pagamento placas solares Hotel Araçá Ltda.
A4: 45383 | B4: 1 | C4: SIVIERO EMPREENDIMENTOS IMOBILIARIOS LTD | D4: ANTONINHO JOSE ZANELLA - PASSO FUNDO | E4: 45382 | F4: 45383 | G4: 1121.66 | H4: 1121.66 | I4: TITULO - JR COM CIMENTO E CONCRETO LTDA. - PO | K4: 45407 | L4: SOL NASCENTE II | M4: ANTÔNIO PRADO | N4: 11 | O4: C | P4: Sustenseg Ltda. – Diego Zulian | T4: Vendido, como forma de pagamento pela prestação serviços – Topografia, Licenciamento, Aprovação e Registro do Loteamento Sol Nascente III.
A5: 45383 | B5: 1 | C5: SIVIERO EMPREENDIMENTOS IMOBILIARIOS LTD | D5: ANTONINHO JOSE ZANELLA - PASSO FUNDO | E5: 45383 | F5: 45383 | G5: 345.7 | H5: 345.7 | I5: TITULO - ECOSOLUTION - LOCACAO DE TELEENTULH
A6: 45383 | B6: 1 | C6: SIVIERO EMPREENDIMENTOS IMOBILIARIOS LTD | D6: INES TREVISAN PICCOLI - JUROS | E6: 45383 | F6: 45383 | G6: 250000 | H6: 2500 | I6: JUROS 1.00% S/ R$ 250.000,00 - EMPRESTIMO EM
A7: 45383 | B7: 1 | C7: SIVIERO EMPREENDIMENTOS IMOBILIARIOS LTD | D7: INES TREVISAN PICCOLI - JUROS | E7: 45383 | F7: 45383 | G7: 100000 | H7: 1000 | I7: JUROS 1.00% S/ R$ 100.000,00 - EMPRESTIMO EM
A8: 45383 | B8: 1 | C8: SIVIERO EMPREENDIMENTOS IMOBILIARIOS LTD | D8: SAMIR TREVISAN PICCOLI - JUROS | E8: 45383 | F8: 45383 | G8: 250000 | H8: 2500 | I8: JUROS 1.00% S/ R$ 250.000,00 - EMPRESTIMO EM
A9: 45383 | B9: 1 | C9: SIVIERO EMPREENDIMENTOS IMOBILIARIOS LTD | D9: SAMIR TREVISAN PICCOLI - JUROS | E9: 45383 | F9: 45383 | G9: 250000 | H9: 2500 | I9: JUROS 1.00% S/ R$ 250.000,00 - EMPRESTIMO EM
A10: 45383 | B10: 1 | C10: SIVIERO EMPREENDIMENTOS IMOBILIARIOS LTD | D10: SAMIR TREVISAN PICCOLI - JUROS | E10: 45383 | F10: 45383 | G10: 150000 | H10: 1500 | I10: JUROS 1.00% S/ R$ 150.000,00 - EMPRESTIMO EM
A11: 45383 | B11: 1 | C11: SIVIERO EMPREENDIMENTOS IMOBILIARIOS LTD | D11: SAMIR TREVISAN PICCOLI - JUROS | E11: 45383 | F11: 45383 | G11: 350000 | H11: 3500 | I11: JUROS 1.00% S/ R$ 350.000,00 - EMPRESTIMO EM
A12: 45383 | B12: 1 | C12: SIVIERO EMPREENDIMENTOS IMOBILIARIOS LTD | D12: SAMIR TREVISAN PICCOLI - JUROS | E12: 45383 | F12: 45383 | G12: 150000 | H12: 1500 | I12: JUROS 1.00% S/ R$ 150.000,00 - EMPRESTIMO EM
A13: 45383 | B13: 1 | C13: SIVIERO EMPREENDIMENTOS IMOBILIARIOS LTD | D13: BANCO SICREDI - VERANÓPOLIS | E13: 45383 | F13: 45383 | G13: 0.16 | H13: 0.16 | I13: JUROS BANCO CREDITO ROTATIVO MES MARCO/2024
A14: 45383 | B14: 1 | C14: SIVIERO EMPREENDIMENTOS IMOBILIARIOS LTD | D14: ANTONINHO JOSE ZANELLA - PASSO FUNDO | E14: 45384 | F14: 45384 | G14: 1220.46 | H14: 1220.46 | I14: TITULO - BRIANCINI - MATERIAIS MANUT CALCADAS
A15: 45383 | B15: 1 | C15: SIVIERO EMPREENDIMENTOS IMOBILIARIOS LTD | D15: ANTONINHO JOSE ZANELLA - PASSO FUNDO | E15: 45384 | F15: 45384 | G15: 118.17 | H15: 118.17 | I15: TITULO - BRIANCINI - ARGAMASSA MANUT CALCADAS
A16: 45383 | B16: 1 | C16: SIVIERO EMPREENDIMENTOS IMOBILIARIOS LTD | D16: BANCO ESTADO RIO GRANDE DO SUL - SEI | E16: 45384 | F16: 45384 | G16: 195 | H16: 195 | I16: SEI - TAXA MENSALIDADE PACOTE CONTA SEI - BAN
... A262: 45383 | B262: 5 | C262: ABASTECEDORA DE COMBUSTIVEIS SIVIERO LTD | D262: CONT. SOCIAL - ABAST. COMB. SIVIERO L | E262: 45412 | F262: 45412 | G262: 765.5 | H262: 765.5 | I262: FATURAMENTO MES MARCO/2024 - R$ 26.580,00 X 2
A264: Total | G264: =SUBTOTAL(9,G2:G262) | H264: =SUBTOTAL(9,H2:H262)

Sheet 2024-05
A1: Mês | B1: Página | C1: Empresa | D1: Fornecedor | E1: Vencimento | F1: Pagamento | G1: Valor NF | H1: Valor Dupl. | I1: Observações | K1: Data | L1: Loteamento | M1: Município | N1: Lote | O1: Quadra | P1: Comprador | Q1: Valor citado | R1: Valores no texto | S1: Venda conjunta | T1: Observações
A2: 45413 | B2: 1 | C2: SIVIERO EMPREENDIMENTOS IMOBILIARIOS LTD | D2: MULTI CELTACAR PECAS SERVICOS LTDA. | E2: 45413 | F2: 45414 | G2: 1400 | H2: 700 | I2: P.1/2-AMORTECEDORES DIANTEIROS-TOYOTAIWB 5G54 | K2: 45418 | L2: SAN MARINO | M2: FARROUPILHA | N2: 03 | O2: 1342 | P2: Natalina Schwaiser | Q2: 270000 | R2: R$ 270.000,00 | T2: Acordo – Arlindo Píccoli – Loteamento Vale das Colinas. Dívida de R$ 270.000,00.
A3: 45413 | B3: 1 | C3: SIVIERO EMPREENDIMENTOS IMOBILIARIOS LTD | D3: DESPESAS DIVERSAS | E3: 45415 | F3: 45414 | G3: 3180 | H3: 3180 | I3: MARCOS A SIVIERO-DESP DIVERSAS CFE NOTAS+COMI | K3: 45439 | L3: MONTE VÊNETO | M3: COTIPORÃ | N3: 07 | O3: 02 | P3: Leonardo R. Kazienko | T3: Vendido à vista.
A4: 45413 | B4: 1 | C4: SIVIERO EMPREENDIMENTOS IMOBILIARIOS LTD | D4: ASSOCIACAO COM. IND. DE VERANOPOLIS | E4: 45415 | F4: 45414 | G4: 390 | H4: 390 | I4: E-CNPJ CEVAL TERRAPLANAGEM E ESCAVACOES LTDA | K4: 45440 | L4: BAÚ | M4: CARLOS BARBOSA | N4: 08 | O4: 04 | P4: Rafael de Conti | T4: Vendido à vista.
A5: 45413 | B5: 1 | C5: SIVIERO EMPREENDIMENTOS IMOBILIARIOS LTD | D5: ASSOCIACAO COM. IND. DE VERANOPOLIS | E5: 45415 | F5: 45414 | G5: 390 | H5: 390 | I5: E-CNPJ AGROPECUARIA FAZENDA SAO CRISPIN LTDA. | K5: 45440 | L5: SOL NASCENTE I | M5: ANTÔNIO PRADO | N5: 09 | O5: B | P5: Clóvis Pedro Zulian | S5: Sim (2 lotes) | T5: Vendidos, como forma de acerto pela Divisão Lotes pela participação nas despesas e custos na implantação dos Loteamentos (Fracionamentos) Sol Nascente I e II, de Antônio Prado, conforme Termo de Acordo.
A6: 45413 | B6: 1 | C6: SIVIERO EMPREENDIMENTOS IMOBILIARIOS LTD | D6: ASSOCIACAO COM. IND. DE VERANOPOLIS | E6: 45415 | F6: 45414 | G6: 390 | H6: 390 | I6: E-CNPJ SIVIERO EMPREENDIMENTOS IMOB LTDA. - C | K6: 45440 | L6: SOL NASCENTE I | M6: ANTÔNIO PRADO | N6: 23 | O6: D | P6: Clóvis Pedro Zulian | S6: Sim (2 lotes) | T6: Vendidos, como forma de acerto pela Divisão Lotes pela participação nas despesas e custos na implantação dos Loteamentos (Fracionamentos) Sol Nascente I e II, de Antônio Prado, conforme Termo de Acordo.
A7: 45413 | B7: 1 | C7: SIVIERO EMPREENDIMENTOS IMOBILIARIOS LTD | D7: ANTONINHO JOSE ZANELLA - PASSO FUNDO | E7: 45413 | F7: 45414 | G7: 1218.19 | H7: 1218.19 | I7: F. BERLATTO LTDA - PAGTO 43 UNIDADES MEIO FIO | K7: 45443 | L7: ALTOS DAS GRAÇAS | M7: CAXIAS DO SUL | N7: 08 | O7: 6365 | P7: Soraya Dias Mais | T7: Vendido à prazo, em 02x.
A8: 45413 | B8: 1 | C8: SIVIERO EMPREENDIMENTOS IMOBILIARIOS LTD | D8: INES TREVISAN PICCOLI - JUROS | E8: 45413 | F8: 45414 | G8: 250000 | H8: 2500 | I8: JUROS 1.00% S/ R$ 250.000,00 - EMPRESTIMO EM
A9: 45413 | B9: 1 | C9: SIVIERO EMPREENDIMENTOS IMOBILIARIOS LTD | D9: INES TREVISAN PICCOLI - JUROS | E9: 45413 | F9: 45414 | G9: 100000 | H9: 1000 | I9: JUROS 1.00% S/ R$ 100.000,00 - EMPRESTIMO EM
A10: 45413 | B10: 1 | C10: SIVIERO EMPREENDIMENTOS IMOBILIARIOS LTD | D10: SAMIR TREVISAN PICCOLI - JUROS | E10: 45413 | F10: 45414 | G10: 250000 | H10: 2500 | I10: JUROS 1.00% S/ R$ 250.000,00 - EMPRESTIMO EM
A11: 45413 | B11: 1 | C11: SIVIERO EMPREENDIMENTOS IMOBILIARIOS LTD | D11: SAMIR TREVISAN PICCOLI - JUROS | E11: 45413 | F11: 45414 | G11: 250000 | H11: 2500 | I11: JUROS 1.00% S/ R$ 250.000,00 - EMPRESTIMO EM
A12: 45413 | B12: 1 | C12: SIVIERO EMPREENDIMENTOS IMOBILIARIOS LTD | D12: SAMIR TREVISAN PICCOLI - JUROS | E12: 45413 | F12: 45414 | G12: 150000 | H12: 1500 | I12: JUROS 1.00% S/ R$ 150.000,00 - EMPRESTIMO EM
A13: 45413 | B13: 1 | C13: SIVIERO EMPREENDIMENTOS IMOBILIARIOS LTD | D13: SAMIR TREVISAN PICCOLI - JUROS | E13: 45413 | F13: 45414 | G13: 350000 | H13: 3500 | I13: JUROS 1.00% S/ R$ 350.000,00 - EMPRESTIMO EM
A14: 45413 | B14: 1 | C14: SIVIERO EMPREENDIMENTOS IMOBILIARIOS LTD | D14: SAMIR TREVISAN PICCOLI - JUROS | E14: 45413 | F14: 45414 | G14: 150000 | H14: 1500 | I14: JUROS 1.00% S/ R$ 150.000,00 - EMPRESTIMO EM
A15: 45413 | B15: 1 | C15: SIVIERO EMPREENDIMENTOS IMOBILIARIOS LTD | D15: D KEKOS COM MANGUEIRAS E CONEXOES LTI | E15: 45414 | F15: 45414 | G15: 120 | H15: 120 | I15: 04 CONEXOES MJ 8 MJ 8 = ESCAVADEIRA - OFICINA
A16: 45413 | B16: 1 | C16: SIVIERO EMPREENDIMENTOS IMOBILIARIOS LTD | D16: MAZZA AUTOMOTIVE SERVICE - NOVA PRATA | E16: 45413 | F16: 45414 | G16: 2253.96 | H16: 751.32 | I16: P.1/3-IYJ 8I14-TOYOTA PEDRO SIVIERO=FILTROS+O
A17: 45413 | B17: 1 | C17: SIVIERO EMPREENDIMENTOS IMOBILIARIOS LTD | D17: SEBASTIAO MAZETO - ROCADOR - VERANOPO | E17: 45415 | F17: 45414 | G17: 500 | H17: 500 | I17: PAGTO SERVICO ROCADA 05 LOTES LOT ADITIVO MED
A18: 45413 | B18: 1 | C18: SIVIERO EMPREENDIMENTOS IMOBILIARIOS LTD | D18: AGROPECUARIA MATTIUZ LTDA. - VERANOPO | E18: 45415 | F18: 45414 | G18: 55 | H18: 55 | I18: UM PAR DE SAPATOS DE SEGURANCA - JORGE NODAR
A19: 45413 | B19: 1 | C19: SIVIERO EMPREENDIMENTOS IMOBILIARIOS LTD | D19: BANCO SICREDI - VERANÓPOLIS | E19: 45414 | F19: 45414 | G19: 0.14 | H19: 0.14 | I19: JUROS BANCO CREDITO ROTATIVO MES ABRIL/2024
... A254: 45413 | B254: 5 | C254: ABASTECEDORA DE COMBUSTIVEIS SIVIERO LTD | D254: CONT. SOCIAL - ABAST. COMB. SIVIERO L | E254: 45443 | F254: 45443 | G254: 765.5 | H254: 765.5 | I254: FATURAMENTO MES ABRIL/2024 - R$ 26.580,00 X 2
A256: Total | G256: =SUBTOTAL(9,G2:G254) | H256: =SUBTOTAL(9,H2:H254)

Sheet 2024-06
A1: Mês | B1: Página | C1: Empresa | D1: Fornecedor | E1: Vencimento | F1: Pagamento | G1: Valor NF | H1: Valor Dupl. | I1: Observações | K1: Data | L1: Loteamento | M1: Município | N1: Lote | O1: Quadra | P1: Comprador | Q1: Valor citado | R1: Valores no texto | S1: Venda conjunta | T1: Observações
A2: 45444 | B2: 1 | C2: SIVIERO EMPREENDIMENTOS IMOBILIARIOS LTD | D2: MULTI CELTACAR PECAS SERVICOS LTDA. | E2: 45444 | F2: 45446 | G2: 1400 | H2: 700 | I2: P.2/2-AMORTECEDORES DIANTEIROS-TOYOTAIWB 5G54 | K2: 45467 | L2: SAN MARINO | M2: FARROUPILHA | N2: 02 | O2: 1342 | P2: Eduardo Rossim | T2: Vendido à vista.
A3: 45444 | B3: 1 | C3: SIVIERO EMPREENDIMENTOS IMOBILIARIOS LTD | D3: MAZZA AUTOMOTIVE SERVICE - NOVA PRATA | E3: 45444 | F3: 45446 | G3: 2253.96 | H3: 751.32 | I3: P.2/3-IYJ 8I14-TOYOTA PEDRO SIVIERO=FILTROS+O
A4: 45444 | B4: 1 | C4: SIVIERO EMPREENDIMENTOS IMOBILIARIOS LTD | D4: SIM REDE DE POSTOS LTDA. - VERANOPOLI | E4: 45445 | F4: 45446 | G4: 445.2 | H4: 445.2 | I4: ABASTECIMENTOS CARROS+CACAMBAS+OFICINA=VER
A5: 45444 | B5: 1 | C5: SIVIERO EMPREENDIMENTOS IMOBILIARIOS LTD | D5: INES TREVISAN PICCOLI - JUROS | E5: 45444 | F5: 45446 | G5: 100000 | H5: 1000 | I5: JUROS 1.00% S/ R$ 100.000,00 - EMPRESTIMO EM
A6: 45444 | B6: 1 | C6: SIVIERO EMPREENDIMENTOS IMOBILIARIOS LTD | D6: INES TREVISAN PICCOLI - JUROS | E6: 45444 | F6: 45446 | G6: 250000 | H6: 2500 | I6: JUROS 1.00% S/ R$ 250.000,00 - EMPRESTIMO EM
A7: 45444 | B7: 1 | C7: SIVIERO EMPREENDIMENTOS IMOBILIARIOS LTD | D7: SAMIR TREVISAN PICCOLI - JUROS | E7: 45444 | F7: 45446 | G7: 150000 | H7: 1500 | I7: JUROS 1.00% S/ R$ 150.000,00 - EMPRESTIMO EM
A8: 45444 | B8: 1 | C8: SIVIERO EMPREENDIMENTOS IMOBILIARIOS LTD | D8: SAMIR TREVISAN PICCOLI - JUROS | E8: 45444 | F8: 45446 | G8: 350000 | H8: 3500 | I8: JUROS 1.00% S/ R$ 350.000,00 - EMPRESTIMO EM
A9: 45444 | B9: 1 | C9: SIVIERO EMPREENDIMENTOS IMOBILIARIOS LTD | D9: SAMIR TREVISAN PICCOLI - JUROS | E9: 45444 | F9: 45446 | G9: 150000 | H9: 1500 | I9: JUROS 1.00% S/ R$ 150.000,00 - EMPRESTIMO EM
A10: 45444 | B10: 1 | C10: SIVIERO EMPREENDIMENTOS IMOBILIARIOS LTD | D10: SAMIR TREVISAN PICCOLI - JUROS | E10: 45444 | F10: 45446 | G10: 250000 | H10: 2500 | I10: JUROS 1.00% S/ R$ 250.000,00 - EMPRESTIMO EM
A11: 45444 | B11: 1 | C11: SIVIERO EMPREENDIMENTOS IMOBILIARIOS LTD | D11: SAMIR TREVISAN PICCOLI - JUROS | E11: 45444 | F11: 45446 | G11: 250000 | H11: 2500 | I11: JUROS 1.00% S/ R$ 250.000,00 - EMPRESTIMO EM
A12: 45444 | B12: 1 | C12: SIVIERO EMPREENDIMENTOS IMOBILIARIOS LTD | D12: BANCO SICREDI - VERANÓPOLIS | E12: 45446 | F12: 45446 | G12: 0.13 | H12: 0.13 | I12: JUROS BANCO CREDITO ROTATIVO MES MAIO/2024
A13: 45444 | B13: 1 | C13: SIVIERO EMPREENDIMENTOS IMOBILIARIOS LTD | D13: ANDRE RAMOS CARDOSO - CAXIAS DO SUL | E13: 45447 | F13: 45447 | G13: 4500 | H13: 1500 | I13: P. 01/03 - DEFESA PROCESSO PEDROTTI VENDA LOT
A14: 45444 | B14: 1 | C14: SIVIERO EMPREENDIMENTOS IMOBILIARIOS LTD | D14: OPERADOR NACIONAL DO REGISTRO-MATRICU | E14: 45447 | F14: 45447 | G14: 300 | H14: 300 | I14: CREDITOS JUNTO REGISTRO IMOVEIS P/ BUSCAS DE
... A233: 45444 | B233: 5 | C233: ABASTECEDORA DE COMBUSTIVEIS SIVIERO LTD | D233: CONT. SOCIAL - ABAST. COMB. SIVIERO L | E233: 45471 | F233: 45471 | G233: 765.5 | H233: 765.5 | I233: FATURAMENTO MES MAIO/2024 - R$ 26.580,00 X 2,
A235: Total | G235: =SUBTOTAL(9,G2:G233) | H235: =SUBTOTAL(9,H2:H233)

Sheet 2024-07
A1: Mês | B1: Página | C1: Empresa | D1: Fornecedor | E1: Vencimento | F1: Pagamento | G1: Valor NF | H1: Valor Dupl. | I1: Observações | K1: Data | L1: Loteamento | M1: Município | N1: Lote | O1: Quadra | P1: Comprador | Q1: Valor citado | R1: Valores no texto | S1: Venda conjunta | T1: Observações
A2: 45474 | B2: 1 | C2: SIVIERO EMPREENDIMENTOS IMOBILIARIOS LTD | D2: MAZZA AUTOMOTIVE SERVICE - NOVA PRATA | E2: 45474 | F2: 45474 | G2: 2253.96 | H2: 751.32 | I2: P.3/3-IYJ 8I14-TOYOTA PEDRO SIVIERO=FILTROS+O | K2: 45475 | L2: SALVADOR – FEMAÇÃ II | M2: VERANÓPOLIS | N2: 03 | O2: 02 | P2: Inês Ansolin Pessutto | Q2: 714000 | R2: R$ 714.000,00 | S2: Sim (2 lotes) | T2: Vendido, como forma pagamento área terras em Vila Azul, valor de R$ 714.000,00.
A3: 45474 | B3: 1 | C3: SIVIERO EMPREENDIMENTOS IMOBILIARIOS LTD | D3: MULTAS DE TRANSITO | E3: 45474 | F3: 45474 | G3: 78.09 | H3: 78.09 | I3: TOYOTA - ELCIO SIVIERO - IWB 8F46 - EXCESSO V | K3: 45475 | L3: FEMAÇÃ | M3: VERANÓPOLIS | N3: 05 | O3: 09 | P3: Inês Ansolin Pessutto | Q3: 714000 | R3: R$ 714.000,00 | S3: Sim (2 lotes) | T3: Vendido, como forma pagamento área terras em Vila Azul, valor de R$ 714.000,00.
A4: 45474 | B4: 1 | C4: SIVIERO EMPREENDIMENTOS IMOBILIARIOS LTD | D4: INES TREVISAN PICCOLI - JUROS | E4: 45474 | F4: 45474 | G4: 100000 | H4: 1000 | I4: JUROS 1.00% S/ R$ 100.000,00 - EMPRESTIMO EM | K4: 45478 | L4: SAN MARINO | M4: FARROUPILHA | N4: 08 | O4: 1342 | P4: Luis Filipe Severgnini | T4: Vendido à prazo, em 10x.
A5: 45474 | B5: 1 | C5: SIVIERO EMPREENDIMENTOS IMOBILIARIOS LTD | D5: INES TREVISAN PICCOLI - JUROS | E5: 45474 | F5: 45474 | G5: 250000 | H5: 2500 | I5: JUROS 1.00% S/ R$ 250.000,00 - EMPRESTIMO EM | K5: 45483 | L5: SALVADOR – FEMAÇÃ II | M5: VERANÓPOLIS | N5: 03 | O5: 03 | P5: Gilberto de Castro Júnior | T5: Vendido à prazo.
A6: 45474 | B6: 1 | C6: SIVIERO EMPREENDIMENTOS IMOBILIARIOS LTD | D6: SAMIR TREVISAN PICCOLI - JUROS | E6: 45474 | F6: 45474 | G6: 150000 | H6: 1500 | I6: JUROS 1.00% S/ R$ 150.000,00 - EMPRESTIMO EM | K6: 45484 | L6: VIERO | M6: FARROUPILHA | N6: 09 | O6: 1469 | P6: Maickel Moretto | T6: Vendido à prazo, em 48x.
A7: 45474 | B7: 1 | C7: SIVIERO EMPREENDIMENTOS IMOBILIARIOS LTD | D7: SAMIR TREVISAN PICCOLI - JUROS | E7: 45474 | F7: 45474 | G7: 350000 | H7: 3500 | I7: JUROS 1.00% S/ R$ 350.000,00 - EMPRESTIMO EM | K7: 45499 | L7: CONDOMÍNIO MORADA DOS IPÊS | M7: PASSO FUNDO | N7: 001 | O7: 01 | P7: Marcelo Colussi Girardi | Q7: 230000 | R7: R$ 230.000,00 | T7: Vendido à prazo, em 03x, com parte em permuta de um carro JEEP COMMANDER – ano 2023 – RXZ 7I62, pelo valor de R$ 230.000,00.
A8: 45474 | B8: 1 | C8: SIVIERO EMPREENDIMENTOS IMOBILIARIOS LTD | D8: SAMIR TREVISAN PICCOLI - JUROS | E8: 45474 | F8: 45474 | G8: 150000 | H8: 1500 | I8: JUROS 1.00% S/ R$ 150.000,00 - EMPRESTIMO EM
A9: 45474 | B9: 1 | C9: SIVIERO EMPREENDIMENTOS IMOBILIARIOS LTD | D9: SAMIR TREVISAN PICCOLI - JUROS | E9: 45474 | F9: 45474 | G9: 250000 | H9: 2500 | I9: JUROS 1.00% S/ R$ 250.000,00 - EMPRESTIMO EM
A10: 45474 | B10: 1 | C10: SIVIERO EMPREENDIMENTOS IMOBILIARIOS LTD | D10: SAMIR TREVISAN PICCOLI - JUROS | E10: 45474 | F10: 45474 | G10: 250000 | H10: 2500 | I10: JUROS 1.00% S/ R$ 250.000,00 - EMPRESTIMO EM
A11: 45474 | B11: 1 | C11: SIVIERO EMPREENDIMENTOS IMOBILIARIOS LTD | D11: SIM REDE DE POSTOS LTDA. - VERANOPOLI | E11: 45473 | F11: 45474 | G11: 479.82 | H11: 479.82 | I11: ABASTECIMENTOS CARROS+CAMIONETES+OFICINA=VE
A12: 45474 | B12: 1 | C12: SIVIERO EMPREENDIMENTOS IMOBILIARIOS LTD | D12: BANCO SICREDI - VERANÓPOLIS | E12: 45474 | F12: 45474 | G12: 0.11 | H12: 0.11 | I12: JUROS BANCO CREDITO ROTATIVO MES JUNHO / 2024
A13: 45474 | B13: 1 | C13: SIVIERO EMPREENDIMENTOS IMOBILIARIOS LTD | D13: IOF BANCARIO SIVIERO EMP IMOBILIARIOS | E13: 45474 | F13: 45474 | G13: 6.59 | H13: 6.59 | I13: IOF CONTA SEI MES DE JUNHO DE 2024 - BANRISUL
A14: 45474 | B14: 1 | C14: SIVIERO EMPREENDIMENTOS IMOBILIARIOS LTD | D14: IOF BANCARIO SIVIERO EMP IMOBILIARIOS | E14: 45474 | F14: 45474 | G14: 250.49 | H14: 250.49 | I14: IOF CONTA SEI MES DE JUNHO DE 2024 - BANRISUL
A15: 45474 | B15: 1 | C15: SIVIERO EMPREENDIMENTOS IMOBILIARIOS LTD | D15: FERNANDO BERTOQUE DOS SANTOS-PASSO F | E15: 45475 | F15: 45475 | G15: 400 | H15: 400 | I15: IMAGENS+VIDEO C/ DRONE - ANUNCIOS VENDAS M.IP
A16: 45474 | B16: 1 | C16: SIVIERO EMPREENDIMENTOS IMOBILIARIOS LTD | D16: SEUBONE COMERCIO DE BONES PERSONALIZ | E16: 45475 | F16: 45475 | G16: 681 | H16: 681 | I16: BONES-MATERIAL PUBLICITARIO BRINDES COMPRADOI
A17: 45474 | B17: 1 | C17: SIVIERO EMPREENDIMENTOS IMOBILIARIOS LTD | D17: RESTAURANTE - CAXIAS DO SUL | E17: 45475 | F17: 45475 | G17: 500 | H17: 500 | I17: PAGAMENTO REFEICOES MES JUNHO / 2024 - FUNCIO
A18: 45474 | B18: 1 | C18: SIVIERO EMPREENDIMENTOS IMOBILIARIOS LTD | D18: CAMINHOS DA SERRA GAUCHA SA - PEDAGIO | E18: 45475 | F18: 45475 | G18: 150 | H18: 150 | I18: CREDITO PRACA PEDAGIOS ANTONIO PRADO/FLORES I
A19: 45474 | B19: 1 | C19: SIVIERO EMPREENDIMENTOS IMOBILIARIOS LTD | D19: PAULA FARINA - VETERINARIA | E19: 45475 | F19: 45475 | G19: 104 | H19: 104 | I19: TRATAMENTO MES JUNHO/2024 DOS CACHORROS - OF
... A272: 45474 | B272: 5 | C272: ABASTECEDORA DE COMBUSTIVEIS SIVIERO LTD | D272: CONT. SOCIAL - ABAST. COMB. SIVIERO L | E272: 45504 | F272: 45504 | G272: 765.5 | H272: 765.5 | I272: FATURAMENTO MES JUNHO/2024 - R$ 26.580,00 X 2
A274: Total | G274: =SUBTOTAL(9,G2:G272) | H274: =SUBTOTAL(9,H2:H272)

Sheet 2024-08
A1: Mês | B1: Página | C1: Empresa | D1: Fornecedor | E1: Vencimento | F1: Pagamento | G1: Valor NF | H1: Valor Dupl. | I1: Observações | K1: Data | L1: Loteamento | M1: Município | N1: Lote | O1: Quadra | P1: Comprador | Q1: Valor citado | R1: Valores no texto | S1: Venda conjunta | T1: Observações
A2: 45505 | B2: 1 | C2: SIVIERO EMPREENDIMENTOS IMOBILIARIOS LTD | D2: HOTEL ARACA LTDA | E2: 45505 | F2: 45505 | G2: 13000 | H2: 6500 | I2: RAUL SIVIERO+PAGTO CONTAS INDIVIDUAIS+DIF DEP | K2: 45505 | L2: CARNEVALLI | M2: NOVA PRATA | N2: 07 | O2: A | P2: CVC Construções Ltda. | T2: Vendido, como forma de pagamento de pavimentação no Loteamento Colina do Retiro II, de Veranópolis.
A3: 45505 | B3: 1 | C3: SIVIERO EMPREENDIMENTOS IMOBILIARIOS LTD | D3: RAUL SIVIERO | E3: 45505 | F3: 45505 | G3: 3500 | H3: 3500 | I3: DIVISAO DE ALUGUEIS MES DE JUNHO DE 2024 | K3: 45505 | L3: ALTOS DA JULIETA | M3: FARROUPILHA | N3: 03 | O3: 1733 | P3: Luiz Fabiano D dos Santos | Q3: 90000 | R3: R$ 90.000,00 | T3: Vendido à vista, sendo que a importância de R$ 90.000,00 através do veículo I/VW AMAROK, ano 2016,Placa IXL 8H85 – RS.
A4: 45505 | B4: 1 | C4: SIVIERO EMPREENDIMENTOS IMOBILIARIOS LTD | D4: INES TREVISAN PICCOLI - JUROS | E4: 45505 | F4: 45505 | G4: 100000 | H4: 1000 | I4: JUROS 1.00% S/ R$ 100.000,00 - EMPRESTIMO EM | K4: 45505 | L4: ALTOS DA JULIETA | M4: FARROUPILHA | N4: 04 | O4: 1733 | P4: Luiz Fabiano D dos Santos | T4: Vendido à vista.
A5: 45505 | B5: 1 | C5: SIVIERO EMPREENDIMENTOS IMOBILIARIOS LTD | D5: INES TREVISAN PICCOLI - JUROS | E5: 45505 | F5: 45505 | G5: 250000 | H5: 2500 | I5: JUROS 1.00% S/ R$ 250.000,00 - EMPRESTIMO EM | K5: 45511 | L5: MONTE VÊNETO | M5: COTIPORÃ | N5: 13 | O5: 09 | P5: Edegar Pellizzer | T5: Vendido à vista.
A6: 45505 | B6: 1 | C6: SIVIERO EMPREENDIMENTOS IMOBILIARIOS LTD | D6: SAMIR TREVISAN PICCOLI - JUROS | E6: 45505 | F6: 45505 | G6: 250000 | H6: 2500 | I6: JUROS 1.00% S/ R$ 250.000,00 - EMPRESTIMO EM | K6: 45512 | L6: MONTE VÊNETO | M6: COTIPORÃ | N6: 12 | O6: 09 | P6: Djenifer Pellizzer | T6: Vendido à prazo, em 12x.
A7: 45505 | B7: 1 | C7: SIVIERO EMPREENDIMENTOS IMOBILIARIOS LTD | D7: SAMIR TREVISAN PICCOLI - JUROS | E7: 45505 | F7: 45505 | G7: 250000 | H7: 2500 | I7: JUROS 1.00% S/ R$ 250.000,00 - EMPRESTIMO EM | K7: 45530 | L7: CICHELERO | M7: CARLOS BARBOSA | N7: 30 | O7: C | P7: Paulo Ely | T7: Vendido à prazo, em 30x
A8: 45505 | B8: 1 | C8: SIVIERO EMPREENDIMENTOS IMOBILIARIOS LTD | D8: SAMIR TREVISAN PICCOLI - JUROS | E8: 45505 | F8: 45505 | G8: 150000 | H8: 1500 | I8: JUROS 1.00% S/ R$ 150.000,00 - EMPRESTIMO EM
A9: 45505 | B9: 1 | C9: SIVIERO EMPREENDIMENTOS IMOBILIARIOS LTD | D9: SAMIR TREVISAN PICCOLI - JUROS | E9: 45505 | F9: 45505 | G9: 350000 | H9: 3500 | I9: JUROS 1.00% S/ R$ 350.000,00 - EMPRESTIMO EM
A10: 45505 | B10: 1 | C10: SIVIERO EMPREENDIMENTOS IMOBILIARIOS LTD | D10: SAMIR TREVISAN PICCOLI - JUROS | E10: 45505 | F10: 45505 | G10: 150000 | H10: 1500 | I10: JUROS 1.00% S/ R$ 150.000,00 - EMPRESTIMO EM
A11: 45505 | B11: 1 | C11: SIVIERO EMPREENDIMENTOS IMOBILIARIOS LTD | D11: NADIR MANFREDI | E11: 45505 | F11: 45505 | G11: 50 | H11: 50 | I11: FRETE CAXIAS DO SUL - PECAS BRASDIESEL - OFIC
A12: 45505 | B12: 1 | C12: SIVIERO EMPREENDIMENTOS IMOBILIARIOS LTD | D12: ESTOFARIA BENE AUTOCAPAS LTDA. | E12: 45505 | F12: 45505 | G12: 200 | H12: 200 | I12: PAGAMENTO CONSERTO FORO ESCAVADEIRA HIDRAU
A13: 45505 | B13: 1 | C13: SIVIERO EMPREENDIMENTOS IMOBILIARIOS LTD | D13: BORRACHARIA | E13: 45505 | F13: 45505 | G13: 60 | H13: 60 | I13: CONSERTO 01 PNEU CACAMBA EM COTIPORA-IUV 8D09
A14: 45505 | B14: 1 | C14: SIVIERO EMPREENDIMENTOS IMOBILIARIOS LTD | D14: ANTONINHO JOSE ZANELLA - PASSO FUNDO | E14: 45505 | F14: 45505 | G14: 1538 | H14: 1538 | I14: PAGTO DESPESAS DIVERSAS P/ ROVILIO SIVIERO -
A15: 45505 | B15: 1 | C15: SIVIERO EMPREENDIMENTOS IMOBILIARIOS LTD | D15: REGISTRO DE IMOVEIS - VERANOPOLIS | E15: 45505 | F15: 45505 | G15: 52.74 | H15: 52.74 | I15: CERTIDAO RENATO LAGO - AREA FAMILIA LAGO - SA
A16: 45505 | B16: 1 | C16: SIVIERO EMPREENDIMENTOS IMOBILIARIOS LTD | D16: BANCO SICREDI - VERANÓPOLIS | E16: 45505 | F16: 45505 | G16: 0.14 | H16: 0.14 | I16: JUROS BANCO CREDITO ROTATIVO MES JULHO / 2024
A17: 45505 | B17: 1 | C17: SIVIERO EMPREENDIMENTOS IMOBILIARIOS LTD | D17: IOF BANCARIO SIVIERO EMP IMOBILIARIOS | E17: 45505 | F17: 45505 | G17: 7.67 | H17: 7.67 | I17: IOF CONTA SEI MES DE JULHO DE 2024 - BANRISUL
A18: 45505 | B18: 1 | C18: SIVIERO EMPREENDIMENTOS IMOBILIARIOS LTD | D18: IOF BANCARIO SIVIERO EMP IMOBILIARIOS | E18: 45505 | F18: 45505 | G18: 258.4 | H18: 258.4 | I18: IOF CONTA SEI MES DE JULHO DE 2024 - BANRISUL
A19: 45505 | B19: 1 | C19: SIVIERO EMPREENDIMENTOS IMOBILIARIOS LTD | D19: LUIZ FABIANO DOS SANTOS/ELENICE SACAR | E19: 45505 | F19: 45505 | G19: 90000 | H19: 90000 | I19: AMAROK PLACA IXL 8H85-REF. VENDA LTS 03/04-Q.
... A260: 45505 | B260: 5 | C260: ABASTECEDORA DE COMBUSTIVEIS SIVIERO LTD | D260: CONT. SOCIAL - ABAST. COMB. SIVIERO L | E260: 45534 | F260: 45534 | G260: 765.5 | H260: 765.5 | I260: FATURAMENTO MES JULHO/2024 - R$ 26.580,00 X 2
A262: Total | G262: =SUBTOTAL(9,G2:G260) | H262: =SUBTOTAL(9,H2:H260)

Sheet 2024-09
A1: Mês | B1: Página | C1: Empresa | D1: Fornecedor | E1: Vencimento | F1: Pagamento | G1: Valor NF | H1: Valor Dupl. | I1: Observações | K1: Data | L1: Loteamento | M1: Município | N1: Lote | O1: Quadra | P1: Comprador | Q1: Valor citado | R1: Valores no texto | S1: Venda conjunta | T1: Observações
A2: 45536 | B2: 1 | C2: SIVIERO EMPREENDIMENTOS IMOBILIARIOS LTD | D2: SIM REDE DE POSTOS LTDA. - VERANOPOLI | E2: 45536 | F2: 45537 | G2: 1497.37 | H2: 1497.37 | I2: ABASTECIMENTOS CARROS+CAMIONETES+OFICINA=VE | K2: Nenhum lote vendido neste mês.
A3: 45536 | B3: 1 | C3: SIVIERO EMPREENDIMENTOS IMOBILIARIOS LTD | D3: RGE - RIO GRANDE ENERGIA | E3: 45537 | F3: 45537 | G3: 14017.05 | H3: 14017.05 | I3: PAGTO SERVICOS TROCA DE POSTE MEIO DA RUA LOT
A4: 45536 | B4: 1 | C4: SIVIERO EMPREENDIMENTOS IMOBILIARIOS LTD | D4: BANCO SICREDI - VERANÓPOLIS | E4: 45537 | F4: 45537 | G4: 0.15 | H4: 0.15 | I4: JUROS BANCO CREDITO ROTATIVO MES AGOSTO / 202
A5: 45536 | B5: 1 | C5: SIVIERO EMPREENDIMENTOS IMOBILIARIOS LTD | D5: RS MICRO INFORMÁTICA LTDA. | E5: 45536 | F5: 45538 | G5: 7650 | H5: 2000 | I5: P.03/04-CH 024109-COMPRA 01 COMPUTADOR ESCRIT
A6: 45536 | B6: 1 | C6: SIVIERO EMPREENDIMENTOS IMOBILIARIOS LTD | D6: BANCO ESTADO RIO GRANDE DO SUL - SEI | E6: 45538 | F6: 45538 | G6: 195 | H6: 195 | I6: SEI - TAXA MENSALIDADE PACOTE CONTA SEI - BAN
A7: 45536 | B7: 1 | C7: SIVIERO EMPREENDIMENTOS IMOBILIARIOS LTD | D7: RADAX DO BRASIL COM FERRAGENS LTDA | E7: 45540 | F7: 45540 | G7: 7810.94 | H7: 781.09 | I7: P. 08/10 - CARRO FERRAMENTAS+MACACOS JACARE E
A8: 45536 | B8: 1 | C8: SIVIERO EMPREENDIMENTOS IMOBILIARIOS LTD | D8: PREFEITURA MUNICIPAL DE VERANOPOLIS | E8: 45540 | F8: 45540 | G8: 14794.08 | H8: 14794.08 | I8: TAXA APROVACAO PROJETO DEFINITIVO LOT COLINA
A9: 45536 | B9: 1 | C9: SIVIERO EMPREENDIMENTOS IMOBILIARIOS LTD | D9: FABIANO ROGERIO MINOZZO - VIVIERO NPR | E9: 45540 | F9: 45540 | G9: 4000 | H9: 2000 | I9: P. 01/02 - 800 MUDAS DOACAO DIA DA ARVORE-P.M
A10: 45536 | B10: 1 | C10: SIVIERO EMPREENDIMENTOS IMOBILIARIOS LTD | D10: INES TREVISAN PICCOLI - JUROS | E10: 45536 | F10: 45540 | G10: 250000 | H10: 2500 | I10: JUROS 1.00% S/ R$ 250.000,00 - EMPRESTIMO EM
A11: 45536 | B11: 1 | C11: SIVIERO EMPREENDIMENTOS IMOBILIARIOS LTD | D11: INES TREVISAN PICCOLI - JUROS | E11: 45536 | F11: 45540 | G11: 100000 | H11: 1000 | I11: JUROS 1.00% S/ R$ 100.000,00 - EMPRESTIMO EM
A12: 45536 | B12: 1 | C12: SIVIERO EMPREENDIMENTOS IMOBILIARIOS LTD | D12: SAMIR TREVISAN PICCOLI - JUROS | E12: 45536 | F12: 45540 | G12: 250000 | H12: 2500 | I12: JUROS 1.00% S/ R$ 250.000,00 - EMPRESTIMO EM
A13: 45536 | B13: 1 | C13: SIVIERO EMPREENDIMENTOS IMOBILIARIOS LTD | D13: SAMIR TREVISAN PICCOLI - JUROS | E13: 45536 | F13: 45540 | G13: 250000 | H13: 2500 | I13: JUROS 1.00% S/ R$ 250.000,00 - EMPRESTIMO EM
A14: 45536 | B14: 1 | C14: SIVIERO EMPREENDIMENTOS IMOBILIARIOS LTD | D14: SAMIR TREVISAN PICCOLI - JUROS | E14: 45536 | F14: 45540 | G14: 150000 | H14: 1500 | I14: JUROS 1.00% S/ R$ 150.000,00 - EMPRESTIMO EM
... A249: 45536 | B249: 5 | C249: ABASTECEDORA DE COMBUSTIVEIS SIVIERO LTD | D249: CONT. SOCIAL - ABAST. COMB. SIVIERO L | E249: 45565 | F249: 45565 | G249: 765.5 | H249: 765.5 | I249: FATURAMENTO MES AGOSTO/2024 - R$ 26.580,00 X
A251: Total | G251: =SUBTOTAL(9,G2:G249) | H251: =SUBTOTAL(9,H2:H249)

Sheet 2024-10
A1: Mês | B1: Página | C1: Empresa | D1: Fornecedor | E1: Vencimento | F1: Pagamento | G1: Valor NF | H1: Valor Dupl. | I1: Observações | K1: Data | L1: Loteamento | M1: Município | N1: Lote | O1: Quadra | P1: Comprador | Q1: Valor citado | R1: Valores no texto | S1: Venda conjunta | T1: Observações
A2: 45566 | B2: 1 | C2: SIVIERO EMPREENDIMENTOS IMOBILIARIOS LTD | D2: INES TREVISAN PICCOLI - JUROS | E2: 45566 | F2: 45566 | G2: 250000 | H2: 2500 | I2: JUROS 1.00% S/ R$ 250.000,00 - EMPRESTIMO EM | K2: 45572 | L2: SALVADOR – FEMAÇÃ II | M2: VERANÓPOLIS | N2: 09 | O2: 01 | P2: Araceli Siviero | T2: Lote Família Adélia Siviero
A3: 45566 | B3: 1 | C3: SIVIERO EMPREENDIMENTOS IMOBILIARIOS LTD | D3: INES TREVISAN PICCOLI - JUROS | E3: 45566 | F3: 45566 | G3: 100000 | H3: 1000 | I3: JUROS 1.00% S/ R$ 100.000,00 - EMPRESTIMO EM | K3: 45575 | L3: PERINI | M3: FARROUPILHA | N3: 18 | O3: 1469 | P3: Efetiva de Imóveis Ltda. | T3: Vendido à prazo.
A4: 45566 | B4: 1 | C4: SIVIERO EMPREENDIMENTOS IMOBILIARIOS LTD | D4: SAMIR TREVISAN PICCOLI - JUROS | E4: 45566 | F4: 45566 | G4: 250000 | H4: 2500 | I4: JUROS 1.00% S/ R$ 250.000,00 - EMPRESTIMO EM | K4: 45575 | L4: PERINI | M4: FARROUPILHA | N4: 19 | O4: 1469 | P4: Efetiva de Imóveis Ltda. | T4: Vendido à prazo. Diferença de área constatada do lote.
A5: 45566 | B5: 1 | C5: SIVIERO EMPREENDIMENTOS IMOBILIARIOS LTD | D5: SAMIR TREVISAN PICCOLI - JUROS | E5: 45566 | F5: 45566 | G5: 250000 | H5: 2500 | I5: JUROS 1.00% S/ R$ 250.000,00 - EMPRESTIMO EM | K5: 45575 | L5: MONTE VÊNETO | M5: COTIPORÃ | N5: 05 | O5: 05 | P5: Cristine Franceschi | Q5: 182000 | R5: R$ 182.000,00 | S5: Sim (2 lotes) | T5: Vendido à vista, com permuta de outro imóvel – Lote 04, Quadra 04 – Loteamento Aditivo Medianeira – Veranópolis, valor de R$ 182.000,00.
A6: 45566 | B6: 1 | C6: SIVIERO EMPREENDIMENTOS IMOBILIARIOS LTD | D6: SAMIR TREVISAN PICCOLI - JUROS | E6: 45566 | F6: 45566 | G6: 150000 | H6: 1500 | I6: JUROS 1.00% S/ R$ 150.000,00 - EMPRESTIMO EM | K6: 45575 | L6: MONTE VÊNETO | M6: COTIPORÃ | N6: 09 | O6: 06 | P6: Cristine Franceschi | Q6: 182000 | R6: R$ 182.000,00 | S6: Sim (2 lotes) | T6: Vendido à vista, com permuta de outro imóvel – Lote 04, Quadra 04 – Loteamento Aditivo Medianeira – Veranópolis, valor de R$ 182.000,00.
A7: 45566 | B7: 1 | C7: SIVIERO EMPREENDIMENTOS IMOBILIARIOS LTD | D7: SAMIR TREVISAN PICCOLI - JUROS | E7: 45566 | F7: 45566 | G7: 350000 | H7: 3500 | I7: JUROS 1.00% S/ R$ 350.000,00 - EMPRESTIMO EM | K7: 45576 | L7: PRINCESA DOS VALES | M7: CARLOS BARBOSA | N7: 38 | O7: F | P7: Ian Zonatto dos Santos | T7: Vendido à prazo.
A8: 45566 | B8: 1 | C8: SIVIERO EMPREENDIMENTOS IMOBILIARIOS LTD | D8: SAMIR TREVISAN PICCOLI - JUROS | E8: 45566 | F8: 45566 | G8: 150000 | H8: 1500 | I8: JUROS 1.00% S/ R$ 150.000,00 - EMPRESTIMO EM | K8: 45593 | L8: BALDASSO | M8: CARLOS BARBOSA | N8: 111 | O8: 48 | P8: Fernando Luis Barth | T8: Vendido à vista.
A9: 45566 | B9: 1 | C9: SIVIERO EMPREENDIMENTOS IMOBILIARIOS LTD | D9: AGROPECUARIA AGROVITORIA LTDA. | E9: 45566 | F9: 45566 | G9: 200 | H9: 200 | I9: RACAO PARA CACHORROS - PAVILHÃO LOTEAMENTO C
A10: 45566 | B10: 1 | C10: SIVIERO EMPREENDIMENTOS IMOBILIARIOS LTD | D10: LOCAWEB SERVICOS DE INTERNET SA | E10: 45566 | F10: 45566 | G10: 59.9 | H10: 59.9 | I10: TAXA ANUAL DO DOMINIO-CONDOMINIO MORADA DO IP
A11: 45566 | B11: 1 | C11: SIVIERO EMPREENDIMENTOS IMOBILIARIOS LTD | D11: NELSON BARBIERI - COMISSAO - NOVA PRA | E11: 45566 | F11: 45566 | G11: 1620 | H11: 1620 | I11: PAGTOS FINAIS ACERTOS COMISSAO=LETICIA+DANUSA
A12: 45566 | B12: 1 | C12: SIVIERO EMPREENDIMENTOS IMOBILIARIOS LTD | D12: SANDRA MARIA MORO | E12: 45567 | F12: 45567 | G12: 5050 | H12: 1750 | I12: P.1/2-REVISAO E ADAPTACAO CONTRATOS DA SIVIER
A13: 45566 | B13: 1 | C13: SIVIERO EMPREENDIMENTOS IMOBILIARIOS LTD | D13: SANDRA MARIA MORO | E13: 45567 | F13: 45567 | G13: 5050 | H13: 300 | I13: TERMO E RECIBO DE PAGAMENTO SALARIO FAMILIA H
A14: 45566 | B14: 1 | C14: SIVIERO EMPREENDIMENTOS IMOBILIARIOS LTD | D14: PREFEITURA MUNICIPAL DE VERANOPOLIS | E14: 45567 | F14: 45567 | G14: 11960 | H14: 11960 | I14: ITBI LOTE RUA GENERAL FLORES DA CUNHA-MARIA T
A15: 45566 | B15: 1 | C15: SIVIERO EMPREENDIMENTOS IMOBILIARIOS LTD | D15: CARBONERA COMERCIO DE PNEUS LTDA | E15: 45567 | F15: 45567 | G15: 174 | H15: 174 | I15: 04 MONTAGEM PNEU + 02 BALANCEAMENTO RODA CAM
A16: 45566 | B16: 1 | C16: SIVIERO EMPREENDIMENTOS IMOBILIARIOS LTD | D16: CONSULTAMB - JAQUELINE BONATT0 | E16: 45567 | F16: 45567 | G16: 1800 | H16: 1800 | I16: RENOVACAO LICENCA INSTALACAO LOT. BELLA VISIO
A17: 45566 | B17: 1 | C17: SIVIERO EMPREENDIMENTOS IMOBILIARIOS LTD | D17: REGISTRO DE IMOVEIS - VERANOPOLIS | E17: 45567 | F17: 45567 | G17: 1600 | H17: 1600 | I17: ENTRADA - REGISTRO ESCRITURA LOTE ADQUIRIDO M
A18: 45566 | B18: 1 | C18: SIVIERO EMPREENDIMENTOS IMOBILIARIOS LTD | D18: REGISTRO DE IMOVEIS DE FLORES DA CUNH | E18: 45567 | F18: 45567 | G18: 120.62 | H18: 120.62 | I18: OBTENCAO 01 MATRICULA LOTE DO LOT RES FALAVIG
A19: 45566 | B19: 1 | C19: SIVIERO EMPREENDIMENTOS IMOBILIARIOS LTD | D19: A. R. T. | E19: 45567 | F19: 45567 | G19: 99.64 | H19: 99.64 | I19: PEDRO ELIAS SIVIERO - PROJETO URBANISTICO - L
A20: 45566 | B20: 1 | C20: SIVIERO EMPREENDIMENTOS IMOBILIARIOS LTD | D20: RADAX DO BRASIL COM FERRAGENS LTDA | E20: 45568 | F20: 45568 | G20: 7810.94 | H20: 781.09 | I20: P. 09/10 - CARRO FERRAMENTAS+MACACOS JACARE E
... A270: 45566 | B270: 5 | C270: ABASTECEDORA DE COMBUSTIVEIS SIVIERO LTD | D270: CONT. SOCIAL - ABAST. COMB. SIVIERO L | E270: 45596 | F270: 45596 | G270: 765.5 | H270: 765.5 | I270: FATURAMENTO MES SETEMBRO/2024 - R$ 26.580,00
A272: Total | G272: =SUBTOTAL(9,G2:G270) | H272: =SUBTOTAL(9,H2:H270)
