Workbook

Sheet GERAL
A1: 11 | B1: SIVIERO EMPREENDIMENTOS IMOBILIÁRIOS LTDA. | C1: =C3+C664 -> 1.3747126e+08 | D1: =D3 -> 2.672202e+08 | E1: =E3+E664 -> 1.0087403e+08
C2: valores 2018 -> 2025: | F2: Estudo Rafael (Valter) | G2: Dif. Rafael − Inv. 2025 | J2: =IF(J1<0,"patrimônio diminuiu","patrimônio aumentou") -> patrimônio aumentou
A3: 11.1 | B3: PATRIMÔNIO | C3: =C5+C29+C47+C62+C66+C73+C92 -> 1.3747126e+08 | D3: =D5+D29+D47+D66+D73+D92 -> 2.672202e+08 | E3: =E5+E29+E47+E66+E73+E92 -> 1.5279626e+08 | J3: =E3-D3 -> -1.1442394e+08
D4: =(D3/C3)-1 -> 0.94382591 | J4: =IF(#REF!<0,"patrimônio diminuiu","patrimônio aumentou") -> #REF!
A5: 11.1.1 | B5: Veículos | C5: =SUM(C7:C27) -> 983000 | D5: =SUM(D7:D27) -> 963000 | E5: =SUM(E7:E27) -> 1217000 | J5: =SUM(J7:J27) -> 254000
C6: =COUNTIF(C7:C28,">1") -> 18 | D6: =(D5/C5)-1 -> -0.02034588 | E6: =COUNTIF(E7:E28,">1") -> 15
A7: 1 | B7: Um veículo caminhão basculante, marca VW = PLACA IUV 8D25, cor branca, ano 2013, adquirido da empresa Dalfovo. | valor: R$ 198.000,00 | C7: 198000 | D7: 198000 | E7: 198000 | J7: =E7-D7 -> 0
A8: 2 | B8: Um veículo caminhão basculante, marca VW = PLACA IUV 8D09, cor branca, ano 2013, adquirido da empresa Dalfovo. | valor: R$ 198.000,00 | C8: 198000 | D8: 198000 | E8: 198000 | J8: =E8-D8 -> 0
A9: 3 | B9: Um veículo caminhão basculante, marca MERCEDES BENZ, L1620 = PLACA ILQ 1739, cor cinza, ano 2003. | valor: R$ 98.000,00 | C9: 98000 | D9: 98000 | E9: 98000 | J9: =E9-D9 -> 0
A10: 4 | B10: Um veículo caminhão basculante, marca MERCEDES BENZ, = PLACA IBP 3873, cor vermelha, ano 1990. | valor: R$ 53.000,00 | C10: 53000 | D10: 53000 | E10: 53000 | J10: =E10-D10 -> 0
A11: 5 | B11: Um veículo caminhão SCANIA = PLACA IIQ 0751, cor laranja, ano 1963. | valor: R$ 28.000,00 | C11: 28000 | D11: 28000 | E11: 25000 | J11: =E11-D11 -> -3000
A12: 6 | B12: Um semirreboque RANDON = PLACA IHP 6632, cor amarelo, ano 1990. | valor: R$ 25.000,00 | C12: 25000 | D12: 25000 | E12: 25000 | J12: =E12-D12 -> 0
A13: 7 | B13: Um veículo Mercedinha, marca MERCEDES BENZ, L608 = PLACA BWF 0672, cor vermelha, ano 1979. | valor: R$ 20.000,00 | C13: 20000 | D13: 20000 | E13: 20000 | J13: =E13-D13 -> 0
A14: 8 | B14: Um veículo caminhão basculante, marca MERCEDES BENZ, L1316 = PLACA IHZ 0172, cor vermelha, ano 1984. | valor: R$ 50.000,00 | C14: 50000 | D14: 50000 | E14: 50000 | J14: =E14-D14 -> 0
A15: 9 | B15: Um veículo caminhão basculante, marca MERCDES BENZ = PLACA IHW 8294, cor grená, ano 1974. | valor: R$ 30.000,00 | C15: 30000 | D15: 30000 | E15: 30000 | J15: =E15-D15 -> 0
A16: 10 | B16: Um veículo caminhão, marca SCÂNIA = PLACA IHK 2435, cor laranja, ano 1967. | valor: R$ 0.000,00 | C16: 40000 | D16: 25000 | E16: 25000 | J16: =E16-D16 -> 0 | K16: Em 2018 valia R$40mil. Diferença provável depreciação
A17: 11 | B17: Uma camionete TOYOTA HILUX, cor preta, ano 2018 = PLACA IYJ 8I14. | valor: R$ 188.000,00 | C17: 0 | D17: 0 | E17: 188000 | J17: =E17-D17 -> 188000
A18: 12 | B18: Um veículo caminhão, marca SCÂNIA = PLACA IIX 8288, cor laranja, ano 1963. | valor: R$ 30.000,00 | C18: 30000 | D18: 25000 | E18: 25000 | J18: =E18-D18 -> 0 | K18: Em 2018 valia R$35mil. Diferença provável depreciação
A19: 13 | B19: Um carro automóvel FORD, cor vermelha, ano 1929 = PLACA IKR 3B22 – FUBICA. | valor: R$ 40.000,00 | C19: 40000 | D19: 40000 | E19: 60000 | J19: =E19-D19 -> 20000
A20: 14 | B20: Uma camionete FORD RANGER, cor prata, ano 2010 = PLACA NPQ OI67. | valor: R$ 67.000,00 | C20: 0 | D20: 0 | E20: 67000 | J20: =E20-D20 -> 67000
A21: 15 | B21: Um veículo JEEP COMPASS = PLACA GHX 9I84, cor cinza, ano 2022. | valor: R$ 150.000,00 | C21: 0 | D21: 0 | E21: 155000 | I21: Inventário 11, veículo 15: TOYOTA RAV4, placa IZQ 9H36, prata, 2019, R$ 155.000,00. A planilha descreve um JEEP COMPASS GHX 9I84 2022. Valor igual, bem diferente. | J21: =E21-D21 -> 155000
A22: 1 | B22: Um veículo DODGE = PLACA IQJ 5001, cor azul, ano 1978. VENDIDO PELO VALOR DE R$ 30.000,00, EM TROCA DE PALANQUES E POSTES DE MADEIRA. | C22: 30000 | D22: 30000 | E22: 0 | J22: =E22-D22 -> -30000
A23: =A22+1 -> 2 | B23: Um semirreboque ARTESANAL = PLACA IIH 6326, cor branca, ano 1986. | valor: R$ 20.000,00 | C23: 20000 | D23: 20000 | E23: 0 | J23: =E23-D23 -> -20000
A24: =A23+1 -> 3 | B24: Um veículo camionete, marca FORD, F1000 TURBO XL = PLACA IIO 5901, cor prata, ano 1998 – Pedro Siviero. | C24: 35000 | D24: 35000 | E24: 0 | J24: =E24-D24 -> -35000
A25: =A24+1 -> 4 | B25: Um veículo camionete, marca FORD, F1000 4x4 = PLACA IHP 6607, cor prata, ano 1994 – Válter Siviero. | C25: 33000 | D25: 33000 | E25: 0 | J25: =E25-D25 -> -33000
A26: =A25+1 -> 5 | B26: Um veículo GOL, marca VW 1.6 = PLACA IQS 7696, cor cinza, ano 2010 – João Lunelli. | C26: 25000 | D26: 25000 | E26: 0 | J26: =E26-D26 -> -25000
A27: =A26+1 -> 6 | B27: Um veículo caminhão, marca SCÂNIA = PLACA IIX 8288, cor laranja, ano 1963. | valor: R$ 30.000,00 | C27: 30000 | D27: 30000 | E27: 0 | J27: =E27-D27 -> -30000
J28: =IF(or(#REF!=0,#REF!=""),"",IF((#REF!-#REF!)=0,"",IF(AND(#REF!<>0,or(#REF!=0,#REF!="")),"verificar situação",IF((#REF!-#REF!)<>0,#REF!-#REF!,"ERRO")))) -> #REF!
A29: 11.1.2 | B29: Máquinas | C29: =SUM(C31:C45) -> 1350000 | D29: =SUM(D31:D45) -> 1180000 | E29: =SUM(E31:E45) -> 2517000 | J29: =E29-D29 -> 1337000
C30: =COUNTIF(C31:C45,">1") -> 12 | D30: =(D29/C29)-1 -> -0.12592593 | E30: =COUNTIF(E31:E45,">1") -> 14
A31: 1 | B31: Uma Escavadeira Hidráulica, ano 2024, modelo 320, CATERPILLAR. | valor: R$ 887.000,00 | C31: 0 | D31: 0 | E31: 887000 | J31: =E31-D31 -> 887000
A32: =A31+1 -> 2 | B32: Uma Escavadeira Hidráulica, ano 2014, modelo 320DL, CATERPILLAR. | valor: R$ 400.000,00 | C32: 400000 | D32: 350000 | E32: 350000 | J32: =E32-D32 -> 0 | K32: Em 2018 valia R$400mil. Diferença provável depreciação
A33: =A32+1 -> 3 | B33: Uma Escavadeira Hidráulica, ano 2009, modelo 320D, CATERPILLAR – SEI. | valor: R$ 200.000,00 | C33: 250000 | D33: 200000 | E33: 200000 | J33: =E33-D33 -> 0 | K33: Em 2018 valia R$250mil. Diferença provável depreciação
A34: =A33+1 -> 4 | B34: Um Trator de Esteira D6, ano 1980. | valor: R$ 80.000,00 | C34: 80000 | D34: 80000 | E34: 80000 | J34: =E34-D34 -> 0
A35: =A34+1 -> 5 | B35: Um Trator de Esteira D6, ano..... | valor: R$ 100.000,00 | C35: 100000 | D35: 80000 | E35: 80000 | J35: =E35-D35 -> 0 | K35: Em 2018 valia R$100mil. Diferença provável depreciação
A36: =A35+1 -> 6 | B36: Um Trator de Esteira D6, ano..... | valor: R$ 100.000,00 | C36: 100000 | D36: 50000 | E36: 50000 | J36: =E36-D36 -> 0 | K36: Em 2018 valia R$100mil. Diferença provável depreciação
A37: =A36+1 -> 7 | B37: Uma Retroescavadeira CASE 580L, ano 2001, PLACA IKI 4827. | valor: R$ 60.000,00 | C37: 60000 | D37: 60000 | E37: 60000 | J37: =E37-D37 -> 0
A38: =A37+1 -> 8 | B38: Uma Pá carregadeira, ano 1980. | valor: R$ 60.000,00 | C38: 60000 | D38: 60000 | E38: 60000 | J38: =E38-D38 -> 0
A39: =A38+1 -> 9 | B39: Um Compressor, ano 2012, marca ATLAS COPCO. | valor: R$ 150.000,00 | C39: 150000 | D39: 150000 | E39: 150000 | J39: =E39-D39 -> 0
A40: =A39+1 -> 10 | B40: Um Compressor, ano 1980, a ar, CA80, marca ATLAS COPCO. Adquirido por leilão da Prefeitura de Bento Gonçalves. | valor: R$ 10.000,00 | C40: 10000 | D40: 10000 | E40: 10000 | J40: =E40-D40 -> 0
A41: =A40+1 -> 11 | B41: Um Compressor, ano....., cor verde. | valor: R$ 30.000,00 | C41: 30000 | D41: 30000 | E41: 30000 | J41: =E41-D41 -> 0
A42: =A41+1 -> 12 | B42: Uma Perfuratriz, ano..... | valor: R$ 10.000,00 | C42: 10000 | D42: 10000 | E42: 10000 | J42: =E42-D42 -> 0
A43: =A42+1 -> 13 | B43: Um Rompedor Hidráulico, ano 2014, adquirido da ATLAS COPCO, modelo MB 1700. | valor: R$ 100.000,00 | C43: 100000 | D43: 100000 | E43: 100000 | J43: =E43-D43 -> 0
A44: =A43+1 -> 14 | B44: Um Trator de Esteira, ano 2014, modelo D6N XL, CATERPILLAR, adquirido em setembro de 2025. | C44: 0 | D44: 0 | E44: 450000 | J44: =E44-D44 -> 450000
A47: 11.1.3 | B47: Lotes urbanos em Veranópolis e Bento Gonçalves | C47: =SUM(C49:C60) -> 2820000 | D47: =SUM(D49:D60) -> 3070000 | E47: =SUM(E49:E60) -> 3290000 | F47: =SUM(F49:F60) -> 3510000 | G47: =F47-E47 -> 220000 | J47: =SUM(J49:J60) -> 220000
C48: =COUNTIF(C49:C60,">1") -> 11 | D48: =(D47/C47)-1 -> 0.088652482 | E48: =COUNTIF(E49:E60,">1") -> 8
A49: 1 | B49: Um lote urbano, localizado na Avenida Pinheiro Machado, Bairro Centro – Casa da Nina – Casa onde mora o Senhor Rubens Baldissera. Área de 330,00m², devidamente Registrado no Ofício de Registro de Imóveis da Comarca de Veranópolis – RS, sob Matrícula nº 1.597. | valor: R$ 150.000,00 | C49: 150000 | D49: 280000 | E49: 280000 | F49: 280000 | G49: =F49-E49 -> 0 | J49: =E49-D49 -> 0
A50: =A49+1 -> 2 | B50: Um lote urbano com casa, localizado na Avenida Dr. José Montaury, Bairro São Pelegrino – Casa da Nona – onde morava a Senhora Geni Siviero Mattiuz. 14,50m X 25,00m = área de 362,50m², devidamente Registrado no Ofício de Registro de Imóveis da Comarca de Veranópolis – RS, sob Matrícula nº 1.335. | valor: R$ 220.000,00 | C50: 220000 | D50: 250000 | E50: 250000 | F50: 450000 | G50: =F50-E50 -> 200000 | J50: =E50-D50 -> 0
A51: =A50+1 -> 3 | B51: Um lote urbano com casa/prédio, localizado na Avenida Osvaldo Aranha, nº 1398, Bairro Palugana – escritório velho – alugado para o Senhor André – BAR DO ANDRÉ. 19,00m X 30,00 = área de 570,00m², devidamente Registrado no Ofício de Registro de Imóveis da Comarca de Veranópolis – RS, sob Matrícula nº 9. | valor: R$ 850.000,00 | C51: 850000 | D51: 850000 | E51: 850000 | F51: 850000 | G51: =F51-E51 -> 0 | J51: =E51-D51 -> 0
A52: =A51+1 -> 4 | B52: Um lote urbano, localizado na Rua General Flores da Cunha, que era do Mercali, na subida para o Bairro Femaçã – Hipotecado em favor da Receita Estadual – Dívida do ICMS. 13,00m X 20,00m = área de 260,00m², devidamente Registrado no Ofício de Registro de Imóveis da Comarca de Veranópolis – RS, sob Matrícula nº 1.053. | valor: R$ 60.000,00 | C52: 60000 | D52: 60000 | E52: 60000 | F52: 60000 | G52: =F52-E52 -> 0 | J52: =E52-D52 -> 0
A53: =A52+1 -> 5 | B53: Um lote urbano, localizado na Avenida Osvaldo Aranha, esquina com a Rua Eduardo Duarte, alugado para o Sr. Paulinho, das baterias. 23,00m X 15,00m = área de 345,00m², devidamente Registrado no Ofício de Registro de Imóveis da Comarca de Veranópolis – RS, sob Matrícula nº 1.507. | valor: R$ 850.000,00 | C53: 850000 | D53: 850000 | E53: 550000 | F53: 550000 | G53: =F53-E53 -> 0 | J53: =E53-D53 -> -300000
A54: =A53+1 -> 6 | B54: Um lote urbano, localizado na Rua General Flores da Cunha, Bairro Centro, na cidade de Veranópolis – RS, adquirido da Família Dal Ponte, denominado de lote nº 0092, da quadra nº 020, zona nº 02, distrito nº 01, com área de 750,00m², devidamente registrado no Ofício de Registro de Imóveis da Comarca de Veranópolis, sob Matrícula nº 3.788. | valor: R$ 1.010.000,00 | C54: 0 | D54: 0 | E54: 1010000 | F54: 1010000 | G54: =F54-E54 -> 0 | J54: =E54-D54 -> 1010000 | K54: Quando foi Adquirido?
A55: =A54+1 -> 7 | B55: Um lote urbano, localizado na cidade de Bento Gonçalves – RS, denominado de lote nº 569/46 – Quadra 216 /D – Cadastro na P. M. de Bento Gonçalves sob nº 13082200, no LOTEAMENTO OURO VERDE II. Área de .........m², Registrado no Ofício de Registro de Imóveis da Comarca de Bento Gonçalves – RS, sob Matrícula nº ........... | valor: R$ 159.000,00 | C55: 100000 | D55: 130000 | E55: 130000 | F55: 150000 | G55: =F55-E55 -> 20000 | J55: =E55-D55 -> 0
A56: =A55+1 -> 8 | B56: Um lote urbano, localizado na cidade de Bento Gonçalves – RS, denominado de lote nº 188/62 – Quadra 163/G – Cadastro na P. M. de Bento Gonçalves sob nº 12482700, no LOTEAMENTO VERONA. Área de .........m², Registrado no Ofício de Registro de Imóveis da Comarca de Bento Gonçalves – RS, sob Matrícula nº ........... | valor: R$ 100.000,00 | C56: 100000 | D56: 160000 | E56: 160000 | F56: 160000 | G56: =F56-E56 -> 0 | J56: =E56-D56 -> 0
A57: A.1 | B57: Um lote urbano, localizado na Rua Bento Gonçalves, Bairro São Pelegrino – Fundos da Casa da Nona – adquirido de Michelle Tedesco, medindo: 12,50m X 30,00m = área de 375,00m², devidamente Registrado no Ofício de Registro de Imóveis da Comarca de Veranópolis – RS, sob Matrícula nº 2325. | valor: R$ 220.000,00 | C57: 220000 | D57: 220000 | E57: 0 | J57: =E57-D57 -> -220000
A58: A.2 | B58: Um lote urbano, localizado na Rua Fioravante Boff, no Bairro Femaçã – que ainda está em nome da Senhora Cleri Fávero. LOTEAMENTO BOFF. ........,.....m X .........,......m = área de .................m², devidamente Registrado no Ofício de Registro de Imóveis da Comarca de Veranópolis – RS, sob Matrícula nº ..................... | C58: 70000 | D58: 70000 | E58: 0 | J58: =E58-D58 -> -70000
A59: A.3 | B59: Um lote urbano, localizado na cidade de Bento Gonçalves – RS, denominado de lote nº 559/47 – Quadra 216 – Cadastro na P. M. de Bento Gonçalves sob nº 13082100, no LOTEAMENTO OURO VERDE. Área de .........m², Registrado no Ofício de Registro de Imóveis da Comarca de Bento Gonçalves – RS, sob Matrícula nº ........... | C59: 100000 | D59: 100000 | E59: 0 | J59: =E59-D59 -> -100000
A60: A.4 | B60: Um lote urbano, localizado na cidade de Bento Gonçalves – RS, denominado de lote nº 247/169 – Quadra 221 – Cadastro na P. M. de Bento Gonçalves sob nº 13092200, no LOTEAMENTO OURO VERDE. Área de .........m², Registrado no Ofício de Registro de Imóveis da Comarca de Bento Gonçalves – RS, sob Matrícula nº ........... | C60: 100000 | D60: 100000 | E60: 0 | J60: =E60-D60 -> -100000
A62: 11.1.3.A | B62: Descrição do(s) bem(ns) - Imóveis e Móveis | C62: =SUM(C64:C65) -> 110000 | D62: =SUM(D64:D65) -> 110000 | E62: =SUM(E64:E65) -> 0 | J62: =SUM(J64:J65) -> -110000
C63: 2 | D63: =(D62/C62)-1 -> 0 | E63: 0
A64: 1 | B64: Um apartamento residencial denominado de nº 303, do Edifício BOA ESPERANÇA, localizado na Rua Eduardo Reginato, n° 48, Bairro Valverde, na cidade de Veranópolis – RS, adquirido do Senhor Valmir Antônio Sottili. Área de 89,73m², devidamente Registrado no Ofício de Registro de Imóveis da Comarca de Veranópolis – RS, sob Matrícula nº 17.399, adquirido por R$ 85.000,00. | C64: 100000 | D64: 100000 | E64: 0 | J64: =E64-D64 -> -100000
A65: 2 | B65: Móveis, materiais diversos (mesas, cadeiras, telefone, impressora, etc...), informática e outros equipamentos instalados no Escritório da empresa Siviero, na cidade de Caxias do Sul – RS, na Rua Feijó Júnior, nº 318 – Sala nº 01, Bairro São Pelegrino – SALA ALUGADA. - E, no decorrer do ano de 2018, foi transferido o Escritório para outra Sala, de propriedade do Senhor Válter Siviero. - Os móveis e divisórias instalados no Escritório permaneceram, como forma de pagamento pelas obras de conservação da sala. - Mesas e cadeiras foram transferidas para uma casa localizada no Loteamento Zanandréa. - Impressoras e computadores foram para o novo endereço. | C65: 10000 | D65: 10000 | E65: 0 | J65: =E65-D65 -> -10000
A66: 11.1.4 | B66: Áreas urbanas em Veranópolis | C66: =SUM(C68:C72) -> 26629395 | D66: =SUM(D68:D72) -> 26929395 | E66: =SUM(E68:E72) -> 26929395 | J66: =SUM(J68:J72) -> 0
C67: =COUNTIF(C68:C71,">1") -> 4 | D67: =(D66/C66)-1 -> 0.011265746 | E67: =COUNTIF(E68:E71,">1") -> 4
A68: 1 | B68: Uma área de terras urbanas, denominada de LOTE Nº 1054, com área total de 16.913,9670m², ou 1,6 hectares, localizada no Município de Veranópolis – RS, próximo a Abastecedora de Combustíveis Siviero Ltda., adquirida do Senhor MOACIR ZANINI, área esta registrada sob Matrícula nº.: 17.038. Matrícula nº 17.038 = 1,60 hectares. 95,00 metros de frente. | valor: R$ 900.000,00 | C68: 900000 | D68: 1200000 | E68: 1200000 | J68: =E68-D68 -> 0
A69: 2 | B69: Um terreno – lote urbano, localizado na Rodovia BR 470, ao lado da Abastecedora de Combustíveis Siviero Ltda., devidamente registrado no Ofício de Registro de Imóveis da Comarca de Veranópolis, sob Matrícula nº 3.751, com área de 7.200,00m², onde está instalada a ANTENA de TRANSMISSÃO da RÁDIO, ao valor de mercado considerado sua localização e referência comercial = R$ 992,78, ao metro quadrado. | valor: R$ 7.148.016,00 | C69: 7148016 | D69: 7148016 | E69: 7148016 | J69: =E69-D69 -> 0 | K69: Em 2018 estava na relação "9.1. RÁDIO COMUNIDADE..."
A70: 3 | B70: Um terreno urbano, com a área de 4.986,00m², localizado na Rodovia BR 470, Km 175,4, no Bairro São Pelegrino, devidamente registrado no Ofício de Registro de Imóveis da Comarca de Veranópolis, sob Matrícula nº 3.754, localizado na lateral da Abastecedora de Combustíveis Siviero Ltda., onde estava instalada a SERRARIA, considerado o valor de R$ 992,78, ao metro quadrado, conforme sua localização e referência comercial. | valor: R$ 4.950.000,00 | C70: 4950000 | D70: 4950000 | E70: 4950000 | J70: =E70-D70 -> 0
A71: 4 | B71: Um imóvel urbano, com a área de 4.792,03m², localizado na Rodovia BR 470, Km 175,4, no Bairro Valverde, devidamente registrado no Ofício de Registro de Imóveis da Comarca de Veranópolis, sob a Matrícula nº 29.954 – (oriunda da unificação das Matrículas nº 17.409 e 6.136), ao lado da empresa Oleoplan S/A, considerado o valor de R$ 2.000,00, ao metro quadrado, conforme sua localização e referência comercial. = R$ 9.584.060,00. Sob estes imóveis estão construídos os PAVILHÕES, com área total construída de 4.170,00m², atualmente locados para a empresa Oleoplan S/A, avaliado conforme o CUB da construção civil referente ao mês de AGOSTO/2017 = R$ 746,60, ao metro quadrado = R$ 3.113.322,00. Valor dos Pavilhões construídos – obra civil = 30,00% (Trinta por cento) da obra feita: R$ 933.996,60 (considerado o valor agregado à coisa feita, como tal se encontra). | C71: 13631379 | D71: 13631379 | E71: 13631379 | J71: =E71-D71 -> 0 | K71: Valor do aluguel?
A73: 11.1.5 | B73: Áreas rurais em Veranópolis, Cotiporã, Fagundes Varela e Caxias do Sul | C73: =SUM(C75:C89) -> 7838866 | D73: =SUM(D75:D89) -> 8155866 | E73: =SUM(E75:E89) -> 7663866 | F73: =SUM(F75:F89) -> 10918666 | G73: =F73-E73 -> 3254800 | J73: =SUM(J75:J89) -> -492000
C74: =COUNTIF(C75:C90,">1") -> 11 | D74: =(D73/C73)-1 -> 0.040439523 | E74: =COUNTIF(E75:E90,">1") -> 12
A75: 1 | B75: Uma área de terras rurais, denominada de PARTES DOS LOTES RURAIS Nº 05, 06 e 76/A, com área total de 3,4 hectares, localizada na Linha Tomás Flores e Linha Afonso Pena, no Município de Veranópolis – RS, adquirida da Senhora ERMELINDA MOSSI REMOR, área esta registrada sob Matrícula nº.: Matrícula nº 14.443, 14.444, 14.576 = 3,4 hectares. Cadastrada no CCIR – Receita Federal sob nº 6.206.801-6. 90,00 metros de frente. | valor: R$ 1.200.000,00 | C75: 1200000 | D75: 1200000 | E75: 1200000 | F75: 1200000 | G75: =F75-E75 -> 0 | J75: =E75-D75 -> 0
A76: 2 | B76: Uma área de terras URBANAS, denominada de UM IMÓVEL URBANO, com a denominação administrativa de lote nº 0292, da quadra nº 009, zona 12, distrito 01, com área total de 4,0 hectares, conforme Registro e área medida, com 40.027,41m², localizada na Linha Tomaz Flores, Estrada Velha da Vacaria, no Município de Veranópolis – RS, na localidade de Sapopema, próxima ao CTG Rincão da Roça Reúna, adquirida da FAMÍLIA LAGO, área registrada sob Matrícula nº.: 33.516 | C76: 0 | D76: 0 | E76: 1500000 | F76: 1500000 | G76: =F76-E76 -> 0 | J76: =E76-D76 -> 1500000
A77: 3 | B77: Uma área de terras rurais, denominada de PARTE DO LOTE RURAL Nº 14, da linha Dr. Júlio de Castilhos, com área total de 7,5 hectares, ou 75.550,00m², localizada no Município de Veranópolis – RS, na localidade de Santa Rita, adquirida da FAMÍLIA SANGALI – VALDIR SANGALI, área registrada sob Matrícula nº.: 4.194. Matrícula nº 4.194 = 7,5 hectares, adquirida pelo valor de R$ 50.000,00. | valor: R$ 280.000,00 | C77: 280000 | D77: 220000 | E77: 220000 | F77: 375000 | G77: =F77-E77 -> 155000 | J77: =E77-D77 -> 0
A78: 4 | B78: Uma área de terras rurais, denominada de PARTE DO LOTE RURAL Nº 12, com área total de 13,0 hectares, localizada na Linha Júlio de Castilhos, no Município de Veranópolis – RS, adquirida da FAMÍLIA SANGALI, área registrada sob Matrícula nº.: 3.062. Matrícula nº 3.062 = 13,0 hectares X 40.000,00 Cadastrada no CCIR – Receita Federal sob nº 2.481.950-6 | C78: =13*11000 -> 143000 | D78: 520000 | E78: 520000 | F78: 650000 | G78: =F78-E78 -> 130000 | J78: =E78-D78 -> 0 | K78: Mudou valor
A79: 5 | B79: Uma área de terras rurais, denominada de PARTE DO LOTE RURAL LETRA B, com área total de 1,8 hectares, ou 18.326,89m², localizada na Linha Carlos Gomes, no Município de Veranópolis – RS, na localidade de Vila Azul, adquirida da FAMÍLIA FOGALI, área esta registrada sob Matrícula nº.: 14.945. Matrícula nº 14.945 = 1,8 hectares, adquirida pelo valor de R$ 305.000,00. | valor: R$ 1.000.000,00 | C79: 1000000 | D79: 1000000 | E79: 1000000 | F79: 1800000 | G79: =F79-E79 -> 800000 | J79: =E79-D79 -> 0
A80: 6 | B80: Uma área de terras rurais, denominada de PARTE DO LOTE RURAL nº 73, da Linha Tomaz Flores, Vila Azul, no Município de Veranópolis, registrada na Matrícula nº 30.390, do Ofício de Registro de Imóveis da Comarca de Veranópolis – RS, com área de 202.435,22m², adquirida da FAMÍLIA ANSOLIN, adquirida a área total, da seguinte forma: área de 6,0 hectares = 60.000,00m², pelo valor de R$ 525.000,00, do Senhor Antônio Ansolin. área de 7,0 hectares = 70.519,78m², pelo valor de R$ 586.666,00, do Senhor Antônio Ansolin. área de 4,9 hectares = 49.787,44m², pelo valor de R$ 714.000,00, da Senhora Inês Ansolin Pessutto. área de 0,67 hectares = 6.700,00m², pelo valor de R$ 388.000,00, do Senhor Ivo José Frainer. área de 0,2 hectares = 2.128,00m², pelo valor de R$ 50.000,00, do Senhor Antônio Ansolin. área pertencente ao Senhor Antônio Ansolin.....................2,0 hectares = 20.000,00m². Área da empresa Siviero Empreendimentos Imobiliários Ltda. é de 18,2 hectares = 182.435,22m². | valor: R$ 2.263.666,00 | C80: 2263666 | D80: 2263666 | E80: 2263666 | F80: 2263666 | G80: =F80-E80 -> 0 | J80: =E80-D80 -> 0
A81: 7 | B81: Uma área de terras rurais, denominadas de LOTES RURAIS Nº 26 e 27, CONDOMÍNIO HORIZONTAL, composto por chácaras, localizadas na Linha Tiradentes, na Barra do Jabuticaba, no Rio das Antas, no Município de Veranópolis – RS, composto por 25 (vinte e cinco) chácaras, sendo já vendidas 15 chácaras. Matrícula nº 36 = 10 chácaras. R$ 2.000,00 cada chácara. | C81: 0 | D81: 0 | E81: 20000 | F81: 20000 | G81: =F81-E81 -> 0 | J81: =E81-D81 -> 20000 | K81: data da compra?
A82: 8 | B82: Uma área de terras rurais, denominada de PARTE DO LOTE RURAL Nº 89, com área total de 27,8 hectares, localizada na Linha Barão do Triunfo, no Município de Fagundes Varela – RS, adquirida do Senhor SÉRGIO BALDISSERA, área esta registrada sob Matrícula nº.: 8.486. Matrícula nº 8.486 = 27,8 hectares X R$ 9.000,00 Cadastrada no CCIR – Receita Federal sob nº 2.481.951-4 | valor: R$ 250.200,00 | C82: =27.8*9000 -> 250200 | D82: 250200 | E82: 250200 | F82: 1500000 | G82: =F82-E82 -> 1249800 | J82: =E82-D82 -> 0
A83: 9 | B83: Uma área de terras rurais de MATO NATIVO, denominada de LOTE Nº 33, com área total de 15,1 hectares, localizada no Município de Cotiporã – RS, na Linha Júlio de Castilhos, adquirida do Senhor ARMELINDO CALZA, área esta registrada sob Matrícula nº.: 1.218. Matrícula nº 1.218 = 15,1 hectares X R$ 2.650,00 | C83: 75500 | D83: 75500 | E83: 40000 | F83: 250000 | G83: =F83-E83 -> 210000 | J83: =E83-D83 -> -35500
A84: 10 | B84: Uma área de terras rurais, ADQUIRIDA em 2014, DA FAMÍLIA CECCONELLO, localizada no Município de Caxias do Sul – RS, composto por 2,0 (Dois) hectares, dentro de um todo maior, que compõem o Loteamento = 130.446,00m². | valor: R$ 600.000,00 | C84: 600000 | D84: 600000 | E84: 600000 | F84: 600000 | G84: =F84-E84 -> 0 | J84: =E84-D84 -> 0
A85: 11 | B85: Uma área de terras rurais, denominada de PARTE DO LOTE RURAL Nº 47, com área total de 7,5 hectares = 75.625,00m², localizada na Linha Ernesto Alves, no Município de Veranópolis – RS, adquirida da FAMÍLIA PICCOLO, por contrato em 06 de outubro de 2022, área ainda não registrada em nome da empresa, com título da propriedade através de Escritura Pública de Cessão de Direitos de Posse nº 4.856 - 092, datada de 13 de março de 2006, lavrada no Serviço Notarial de Veranópolis. Cadastrada no ITR – Receita Federal sob nº 1.893.570-2 INCRA/CCIR nº 854.093.042.013-5 Adquirida pelo valor de R$ 45.000,00. Parte da área foi destinada para compensação ambiental do Loteamento Colina do Retiro II. | C85: 0 | D85: 0 | E85: 20000 | F85: 380000 | G85: =F85-E85 -> 360000 | J85: =E85-D85 -> 20000 | K85: data da compra?
A86: 12 | B86: Uma área de terras rurais, denominada de PARTE DO LOTE RURAL Nº 47, com área total de 7,5 hectares = 75.625,00m², localizada na Linha Ernesto Alves, no Município de Veranópolis – RS, adquirida da FAMÍLIA SCALCO, por contrato em 01 de novembro de 2022, área ainda não registrada em nome da empresa, com título da propriedade através de Escritura Pública de Cessão de Direitos de Posse nº 5.857 - 045, datada de 06 de outubro de 2009, lavrada no Serviço Notarial de Veranópolis. Cadastrada no ITR – Receita Federal sob nº 1.731.666-9 INCRA/CCIR nº 854.093.030.619-7 Adquirida pelo valor de R$ 50.000,00. Parte da área foi destinada para compensação ambiental do Loteamento Colina do Retiro II. | C86: 0 | D86: 0 | E86: 30000 | F86: 380000 | G86: =F86-E86 -> 350000 | J86: =E86-D86 -> 30000 | K86: data da compra?
A87: A.1 | B87: Uma área de terras urbanas, denominada de LOTE Nº 1543, com área total de 1,9 hectares, localizada no Município de Veranópolis – RS, na Rodovia BR 470, esquina com a Estrada da Linha República, próximo a empresa Oleoplan S/A, adquirida da FAMÍLIA BISSANI, área esta registrada sob Matrícula nº.: 21.819. Matrícula nº 21.819 = 1,9 hectares. Adquirida por R$ 400.000,00. 17.604,00m² + 2.000,00m² = 19.604,00m². | valor: R$ 900.000,00 | C87: 900000 | D87: 900000 | E87: 0 | J87: =E87-D87 -> -900000
A88: A.2 | B88: Uma área de terras rurais, denominada de PARTE DO LOTE RURAL LETRA “M”, com área total de 3,6 hectares, conforme contrato e área medida conforme croqui, com 33.742,78m², localizada na Linha Tomaz Flores, no Município de Veranópolis – RS, na localidade de Sapopema, próxima ao CTG Rincão da Roça Reiuna, adquirida da FAMÍLIA LAGO, área esta registrada sob Matrícula nº.: 14.319. Matrícula nº 14.319 = 3,6 hectares. | valor: R$ 900.000,00 | C88: 900000 | D88: 900000 | E88: 0 | J88: =E88-D88 -> -900000 | K88: Mesma área do item 2?
A89: A.3 | B89: Uma área de terras rurais, denominada de PARTE DO LOTE RURAL Nº 52, com área total de 15,1 hectares, localizada na Linha Júlio de Castilhos, no Município de Cotiporã – RS, adquirida da Senhora GLORIA E GERALDO BASSANI, área esta registrada sob Matrícula nº.: 7.391 - Matrícula nº 7.391 = 15,1 hectares X R$ 15.000,00 Cadastrada no CCIR – Receita Federal sob nº 2.481.952-2 | valor: R$ 226.500,00 | C89: 226500 | D89: 226500 | E89: 0 | J89: =E89-D89 -> -226500
A92: 11.1.6 | B92: Loteamentos executados e registrados | C92: =C94+C115+C120+C127+C136+C154+C170+C207+C316+C350+C354+C362+C379+C385+C392+C396+C403+C419+C425+C439+C451+C457+C461+C469+C499+C512+C575+C582+C599+C633+C637 -> 97740000 | D92: =D94+D111+D115+D120+D127+D136+D154+D170+D207+D316+D350+D354+D362+D379+D385+D392+D396+D403+D419+D425+D439+D451+D457+D461+D469+D499+D512+D575+D582+D599+D633+D637 -> 2.2692194e+08 | E92: =E94+E111+E115+E120+E127+E136+E154+E170+E207+E316+E350+E354+E362+E379+E385+E392+E396+E403+E419+E425+E439+E451+E457+E461+E469+E499+E512+E575+E582+E599+E633+E637 -> 111179000 | F92: =F94+F111+F115+F120+F127+F136+F154+F170+F207+F316+F350+F354+F362+F379+F385+F392+F396+F403+F419+F425+F439+F451+F457+F461+F469+F499+F512+F575+F582+F599+F633+F637 -> 113178000 | G92: =F92-E92 -> 1999000 | J92: =J94+J111+J115+J120+J127+J136+J154+J170+J207+J316+J350+J354+J362+J379+J385+J392+J396+J403+J419+J425+J439+J451+J457+J461+J469+J499+J512+J575+J582+J599+J633+J637 -> -1.0923294e+08 | K92: Comparação com 2018: 48.14% do patrimônio e 55.73% do número de lotes
C93: =C95+C112+C116+C121+C128+C137+C155+C171+C208+C317+C351+C355+C363+C380+C386+C393+C397+C404+C420+C426+C440+C452+C458+C462+C470+C500+C513+C576+C583+C600+C634+C638 -> 751 | D93: =(D92/C92)-1 -> 1.3216896 | E93: =E95+E112+E116+E121+E128+E137+E155+E171+E208+E317+E351+E355+E363+E380+E386+E393+E397+E404+E420+E426+E440+E452+E458+E462+E470+E500+E513+E576+E583+E600+E634+E638 -> 418
A94: 1 | B94: Loteamento Sol Nascente I, localizado na cidade de Antônio Prado – RS, num saldo de 11 lotes. | C94: =B95*C95 -> 2800000 | D94: =C95*J95 -> 5130363.6 | E94: =SUM(E96:E106) -> 4031000 | F94: =SUM(F96:F106) -> 4031000 | G94: =F94-E94 -> 0 | J94: =E94-D94 -> -1099363.6
B95: 200000 | C95: 14 | D95: =(D94/C94)-1 -> 0.83227273 | E95: =COUNT(E96:E106) -> 11 | J95: =E94/E95 -> 366454.55
A96: 1.1 | B96: Lote:1 | Quadra:A | valor:R$ 351.000,00 | E96: 351000 | F96: 351000 | G96: =F96-E96 -> 0
A97: 1.2 | B97: Lote:2 | Quadra:A | valor:R$ 351.000,00 | E97: 351000 | F97: 351000 | G97: =F97-E97 -> 0
A98: 1.3 | B98: Lote:3 | Quadra:A | valor:R$ 351.000,00 | E98: 351000 | F98: 351000 | G98: =F98-E98 -> 0
A99: 1.4 | B99: Lote:10 | Quadra:B | valor:R$ 369.000,00 | E99: 369000 | F99: 369000 | G99: =F99-E99 -> 0
A100: 1.5 | B100: Lote:11 | Quadra:B | valor:R$ 369.000,00 | E100: 369000 | F100: 369000 | G100: =F100-E100 -> 0
A101: 1.6 | B101: Lote:12 | Quadra:B | valor:R$ 389.000,00 | E101: 389000 | F101: 389000 | G101: =F101-E101 -> 0
A102: 1.7 | B102: Lote:20 | Quadra:C | valor:R$ 389.000,00 | E102: 389000 | F102: 389000 | G102: =F102-E102 -> 0
A103: 1.8 | B103: Lote:21 | Quadra:D | valor:R$ 389.000,00 | E103: 389000 | F103: 389000 | G103: =F103-E103 -> 0
A104: 1.9 | B104: Lote:22 | Quadra:D | valor:R$ 354.000,00 | E104: 354000 | F104: 354000 | G104: =F104-E104 -> 0
A105: 1.10 | B105: Lote:30 | Quadra:E | valor:R$ 389.000,00 | E105: 389000 | F105: 389000 | G105: =F105-E105 -> 0
A106: 1.11 | B106: Lote:39 | Quadra:E | valor:R$ 330.000,00 | E106: 330000 | F106: 330000 | G106: =F106-E106 -> 0
...

Sheet Rafael × Inventário
A1: Estudo 2 do Rafael comparado ao inventário 11 (Siviero Empreendimentos Imobiliários, 31.12.2024)
A2: Valores a 100% da empresa. Inventário 2025 = coluna E da GERAL; Estudo Rafael = coluna F da GERAL (valores do Valter). Resultado para a Valter: crédito (+) ou valor a complementar (−) informado no quadro-resumo de cada PDF.
A4: Seção | B4: Item | C4: Linha na GERAL | D4: Inventário 2025 (R$) | E4: Estudo Rafael (R$) | F4: Diferença (R$) | G4: Resultado p/ Valter no PDF (R$) | H4: Observação
A5: 11.1.3 | B5: Lotes urbanos em Veranópolis e Bento Gonçalves | C5: 47 | D5: =GERAL!E47 -> 3290000 | E5: =GERAL!F47 -> 3510000 | F5: =E5-D5 -> 220000 | G5: -1985000 | H5: Coluna G: R$ 1.985.000 da linha "Diferença nominal a complementar da Valter" do quadro-resumo (p. 11), com sinal negativo por ser valor a complementar. Valter reavalia os itens 02 (+R$ 200.000) e 07 (+R$ 20.000). Escolhe os itens 03, 05, 06 e 08 (R$ 2.570.000) contra 1/6 de R$ 585.000.
A6: 11.1.5 | B6: Áreas rurais em Veranópolis, Cotiporã, Fagundes Varela e Caxias do Sul | C6: 73 | D6: =GERAL!E73 -> 7663866 | E6: =GERAL!F73 -> 10918666 | F6: =E6-D6 -> 3254800 | G6: 319776.66 | H6: Coluna G: linha "Crédito patrimonial da Valter" do quadro-resumo (p. 25). Valter reavalia 7 dos 12 itens. Escolhe o item 02 (R$ 1.500.000) contra 1/6 de R$ 1.819.776,66.
A7: 11.1.6 | B7: Loteamentos executados e registrados (31) | C7: 92 | D7: =GERAL!E92 -> 111179000 | E7: =GERAL!F92 -> 113178000 | F7: =E7-D7 -> 1999000 | H7: Coluna G vazia: o PDF não traz um resultado único para os 31 loteamentos; o saldo de cada um está na coluna G da tabela de loteamentos (linhas 31 a 61). Valter só altera o Lago Negro (+R$ 1.479.000) e o Fracionamento Simioni (+R$ 520.000).
A8: 11.2.1 | B8: Caminhos do Sol | C8: 667 | D8: =GERAL!E667 -> 0 | E8: =GERAL!F667 -> 8601000 | F8: =E8-D8 -> 8601000 | G8: 1433500 | H8: Coluna G: linha "Crédito patrimonial da Valter" do quadro-resumo (p. 6). No inventário o valor é o placeholder R$ 00.000.000,00. Valter: 61 lotes x R$ 141.000.
A9: 11.2.1 | B9: Vale das Colinas | C9: 668 | D9: =GERAL!E668 -> -4211035 | E9: =GERAL!F668 -> 808565 | F9: =E9-D9 -> 5019600 | G9: 134160.84 | H9: Coluna G: linha "Crédito patrimonial da Valter" do quadro-resumo (p. 7). O crédito correto seria R$ 134.760,83 (erro no 1/6 dos encargos).
A10: 11.2.1 | B10: Vista da Colina | C10: 669 | D10: =GERAL!E669 -> -2664900 | E10: =GERAL!F669 -> 719100 | F10: =E10-D10 -> 3384000 | G10: 119850 | H10: Coluna G: linha "Crédito patrimonial da Valter" do quadro-resumo (p. 8). Multa de R$ 2.556.900 difere de 20% do custo (R$ 2.420.000).
A11: 11.2.1 | B11: Famílias Pedrotti, Andreis e Lorandi | C11: 670 | D11: =GERAL!E670 -> -2588646 | E11: =GERAL!F670 -> 795354 | F11: =E11-D11 -> 3384000 | G11: 132559 | H11: Coluna G: linha "Crédito patrimonial da Valter" do quadro-resumo (p. 7). Mesmo número de lotes (242) e custo (R$ 12,1 mi) que Vista da Colina.
A12: 11.2.1 | B12: Família Cecconello | C12: 671 | D12: =GERAL!E671 -> -1300000 | E12: =GERAL!F671 -> 7865000 | F12: =E12-D12 -> 9165000 | G12: 1310833.3 | H12: Coluna G: linha "Valor líquido hipotético" do quadro da p. 5 (R$ 1.310.833,33); o quadro-resumo da p. 6 arredonda para R$ 1.310.834. A p. 1 estima 130 lotes; as pp. 2-5 usam 180.
A13: 11.2.1 | B13: Bonetto | C13: 672 | D13: =GERAL!E672 -> -782000 | E13: =GERAL!F672 -> 2329000 | F13: =E13-D13 -> 3111000 | G13: 388167 | H13: Coluna G: linha "Crédito patrimonial da Valter 1/6" do quadro-resumo (p. 6).
A14: 11.2.1 | B14: Pasqual | C14: 673 | D14: =GERAL!E673 -> -1500000 | E14: =GERAL!F673 -> -21000 | F14: =E14-D14 -> 1479000 | G14: -3500 | H14: Coluna G: linha "Diferença nominal a complementar da Valter" do quadro-resumo (p. 6), negativa no próprio PDF. O valor vem de arredondamento (2,41 x 2,4167 bens).
A15: 11.2.1 | B15: Industrial Dr. Letti | C15: 674 | D15: =GERAL!E674 -> -1650000 | E15: =GERAL!F674 -> -1650000 | F15: =E15-D15 -> 0 | G15: -275000 | H15: Coluna G: "parcela potencial da Valter" (1/6 da multa) no quadro de consolidação dos riscos (p. 4), com sinal negativo por ser obrigação. O quadro-resumo (p. 7) soma Dr. Letti e Sol Nascente III: R$ 451.333,33 a complementar. Sem estimativa de lotes (aparece como ???).
A16: 11.2.1 | B16: Sol Nascente III | C16: 675 | D16: =GERAL!E675 -> -1058000 | E16: =GERAL!F675 -> -1058000 | F16: =E16-D16 -> 0 | G16: -176333.33 | H16: Coluna G: "parcela potencial da Valter" (1/6 da multa) no quadro de consolidação dos riscos (p. 4), com sinal negativo por ser obrigação. Município aparece como Antônio Prado e como Farroupilha.
A17: 11.2.2 | B17: Lotes de terceiros passíveis de indenização | C17: 677 | D17: =GERAL!E677 -> -16240000 | E17: =GERAL!F677 -> -16240000 | F17: =E17-D17 -> 0 | H17: Coluna G vazia: o PDF (p. 5) traz R$ 2.706.333,33 como "crédito patrimonial de referência, 1/6", sem dizer se soma ou subtrai. Mesmos 26 lotes.
A18: 11.2.3 | B18: Obras finais no Colina do Retiro II | C18: 719 | D18: =GERAL!E719 -> -3800000 | E18: =GERAL!F719 -> -3800000 | F18: =E18-D18 -> 0 | H18: Coluna G vazia: o 1/6 da obra (R$ 633.333,33, PDF do Colina do Retiro II, pp. 3 e 9) já está descontado no crédito de R$ 2.730.166,67 desse loteamento.
A19: 11.2.4 e 11.2.5 | B19: Demais compromissos e empréstimos | C19: 721 | D19: =GERAL!E721+GERAL!E738 -> -16127652 | E19: =GERAL!F721 -> -16127652 | F19: =E19-D19 -> 0.030000001 | G19: -2687942 | H19: Coluna G: linha "Reflexo proporcional das obrigações" (1/6) do quadro-resumo do PDF DEMAIS COMPROMISSOS (p. 3), com sinal negativo por ser obrigação. O estudo só traz o total dos itens 1 a 24.
B20: Total dos itens comparados | D20: =SUM(D5:D19) -> 70210633 | E20: =SUM(E5:E19) -> 109828033 | F20: =SUM(F5:F19) -> 39617400
A22: Itens da GERAL sem estudo correspondente
A23: 11.1.1 | B23: Veículos | C23: 5 | D23: =GERAL!E5 -> 1217000
A24: 11.1.2 | B24: Máquinas | C24: 29 | D24: =GERAL!E29 -> 2517000
A25: 11.1.3.A | B25: Imóveis e móveis (11.1.3.A) | C25: 62 | D25: =GERAL!E62 -> 0
A26: 11.1.4 | B26: Áreas urbanas em Veranópolis | C26: 66 | D26: =GERAL!E66 -> 26929395
B27: Total sem estudo | D27: =SUM(D23:D26) -> 30663395
A29: Loteamentos executados: 1/6 da Valter e lotes escolhidos | H29: Coluna F: soma dos lotes que a Valter escolheu, listados no PDF LOTES LOTEAMENTOS EXECUTADOS E REGISTRADOS (sem os lotes em possível APP). Coluna G: calculada nesta aba, 1/6 (coluna E) menos escolhidos (coluna F). Positivo: crédito da Valter; negativo: escolhidos acima do 1/6. O resultado confere com a "diferença nominal" citada no PDF de cada loteamento, exceto no Salvador.
A30: Item | B30: Loteamento | C30: Linha na GERAL | D30: Estudo Rafael (R$) | E30: 1/6 da Valter (R$) | F30: Lotes escolhidos pela Valter (R$) | G30: Saldo da Valter (R$) | H30: Observação
A31: 01 | B31: Loteamento Sol Nascente I | C31: 94 | D31: =GERAL!F94 -> 4031000 | E31: =D31/6 -> 671833.33 | F31: 743000 | G31: =E31-F31 -> -71166.667
A32: 02 | B32: Loteamento Boito | C32: 111 | D32: =GERAL!F111 -> 136000 | E32: =D32/6 -> 22666.667 | F32: 0 | G32: =E32-F32 -> 22666.667
A33: 03 | B33: Condomínio Morada do Ipê I | C33: 115 | D33: =GERAL!F115 -> 629000 | E33: =D33/6 -> 104833.33 | F33: 0 | G33: =E33-F33 -> 104833.33
A34: 04 | B34: Loteamento Fracionamento Simioni | C34: 120 | D34: =GERAL!F120 -> 520000 | E34: =D34/6 -> 86666.667 | F34: 0 | G34: =E34-F34 -> 86666.667 | H34: Grupo: 4 lotes em APP, total R$ 0. Valter: R$ 520.000 para o conjunto e diferença em seu favor de R$ 520.000.
A35: 05 | B35: Loteamento Solar Norte I e II | C35: 127 | D35: =GERAL!F127 -> 1171000 | E35: =D35/6 -> 195166.67 | F35: 0 | G35: =E35-F35 -> 195166.67
A36: 06 | B36: Loteamento Aditivo Medianeira | C36: 136 | D36: =GERAL!F136 -> 2647000 | E36: =D36/6 -> 441166.67 | F36: 678000 | G36: =E36-F36 -> -236833.33 | H36: O quadro traz R$ 236.833,34 como valor dos escolhidos (é a diferença entre R$ 678.000 e o 1/6).
A37: 07 | B37: Loteamento Colina do Retiro I | C37: 154 | D37: =GERAL!F154 -> 2585000 | E37: =D37/6 -> 430833.33 | F37: 478000 | G37: =E37-F37 -> -47166.667
A38: 08 | B38: Loteamento Salvador – Alberto Salvador – FEMAÇÃ II | C38: 170 | D38: =GERAL!F170 -> 8374000 | E38: =D38/6 -> 1395666.7 | F38: 1789000 | G38: =E38-F38 -> -393333.33 | H38: O texto diz que os escolhidos ficam R$ 47.166,67 acima do 1/6 (número do Colina do Retiro I); pelos valores do quadro a diferença é R$ 393.333,33.
A39: 09 | B39: Loteamento Colina do Retiro II | C39: 207 | D39: =GERAL!F207 -> 20181000 | E39: =D39/6 -> 3363500 | F39: 3881000 | G39: =E39-F39 -> -517500 | H39: O crédito informado (R$ 2.730.166,67) usa o 1/6 de referência menos 1/6 da obra, e não a seleção de 20 lotes.
A40: 10 | B40: Loteamento Industrial Pedra Lisa | C40: 316 | D40: =GERAL!F316 -> 10985000 | E40: =D40/6 -> 1830833.3 | F40: 2295000 | G40: =E40-F40 -> -464166.67
A41: 11 | B41: Loteamento Monte Vêneto | C41: 350 | D41: =GERAL!F350 -> 241000 | E41: =D41/6 -> 40166.667 | F41: 0 | G41: =E41-F41 -> 40166.667
A42: 12 | B42: Loteamento Baldasso | C42: 354 | D42: =GERAL!F354 -> 1419000 | E42: =D42/6 -> 236500 | F42: 272000 | G42: =E42-F42 -> -35500
A43: 13 | B43: Loteamento Colina do Basalto | C43: 362 | D43: =GERAL!F362 -> 2180000 | E43: =D43/6 -> 363333.33 | F43: 778000 | G43: =E43-F43 -> -414666.67
A44: 14 | B44: Loteamento Carnevalli | C44: 379 | D44: =GERAL!F379 -> 617000 | E44: =D44/6 -> 102833.33 | F44: 241000 | G44: =E44-F44 -> -138166.67
A45: 15 | B45: Loteamento Barbiero | C45: 385 | D45: =GERAL!F385 -> 822000 | E45: =D45/6 -> 137000 | F45: 0 | G45: =E45-F45 -> 137000
A46: 16 | B46: Loteamento Araçá | C46: 392 | D46: =GERAL!F392 -> 142000 | E46: =D46/6 -> 23666.667 | F46: 0 | G46: =E46-F46 -> 23666.667
A47: 17 | B47: Loteamento Dalla Costa | C47: 396 | D47: =GERAL!F396 -> 650000 | E47: =D47/6 -> 108333.33 | F47: 0 | G47: =E47-F47 -> 108333.33
A48: 18 | B48: Loteamento Lago Negro | C48: 403 | D48: =GERAL!F403 -> 5500000 | E48: =D48/6 -> 916666.67 | F48: 1100000 | G48: =E48-F48 -> -183333.33 | H48: Valter reavalia os lotes 001 a 005 para R$ 1.100.000 cada. O quadro usa R$ 1.100.000 como 1/6, e o texto cita R$ 7.700.000 em seu favor.
A49: 19 | B49: Loteamento Perini | C49: 419 | D49: =GERAL!F419 -> 4560000 | E49: =D49/6 -> 760000 | F49: 0 | G49: =E49-F49 -> 760000
A50: 20 | B50: Loteamento San Marino | C50: 425 | D50: =GERAL!F425 -> 2080000 | E50: =D50/6 -> 346666.67 | F50: 517000 | G50: =E50-F50 -> -170333.33 | H50: 3 lotes em possível APP (R$ 730.000) listados como escolhidos; o texto cita R$ 7.700.000 em favor da Valter.
A51: 21 | B51: Loteamento Firminio Dalzóchio | C51: 439 | D51: =GERAL!F439 -> 1790000 | E51: =D51/6 -> 298333.33 | F51: 745000 | G51: =E51-F51 -> -446666.67 | H51: 1 lote em possível APP (R$ 131.000) listado como escolhido, com diferença em favor da Valter.
A52: 22 | B52: Loteamento Primavera | C52: 451 | D52: =GERAL!F451 -> 148000 | E52: =D52/6 -> 24666.667 | F52: 0 | G52: =E52-F52 -> 24666.667 | H52: 2 lotes em possível APP (R$ 335.000) listados como escolhidos, com diferença em favor da Valter.
A53: 23 | B53: Loteamento Vila Vicenza | C53: 457 | D53: =GERAL!F457 -> 157000 | E53: =D53/6 -> 26166.667 | F53: 0 | G53: =E53-F53 -> 26166.667 | H53: O quadro considera patrimônio de R$ 148.000 em vez de R$ 157.000.
A54: 24 | B54: Loteamento Industrial Vicentino | C54: 461 | D54: =GERAL!F461 -> 5420000 | E54: =D54/6 -> 903333.33 | F54: 1355000 | G54: =E54-F54 -> -451666.67 | H54: 1 lote em possível APP (R$ 1.125.000) listado como escolhido, com diferença em favor da Valter.
A55: 25 | B55: Loteamento Jardim Itália I – II – III | C55: 469 | D55: =GERAL!F469 -> 5823000 | E55: =D55/6 -> 970500 | F55: 2150000 | G55: =E55-F55 -> -1179500
A56: 26 | B56: Loteamento Altos da Julieta I – II | C56: 499 | D56: =GERAL!F499 -> 2086000 | E56: =D56/6 -> 347666.67 | F56: 627000 | G56: =E56-F56 -> -279333.33
A57: 27 | B57: Loteamento Monte Vêneto I – II | C57: 512 | D57: =GERAL!F512 -> 5336000 | E57: =D57/6 -> 889333.33 | F57: 876000 | G57: =E57-F57 -> 13333.333 | H57: Escolhidos abaixo do 1/6.
A58: 28 | B58: Loteamento Nossa Senhora da Saúde | C58: 575 | D58: =GERAL!F575 -> 533000 | E58: =D58/6 -> 88833.333 | F58: 0 | G58: =E58-F58 -> 88833.333
A59: 29 | B59: Loteamento Alto das Graças I | C59: 582 | D59: =GERAL!F582 -> 3699000 | E59: =D59/6 -> 616500 | F59: 1424000 | G59: =E59-F59 -> -807500
A60: 30 | B60: Loteamento da Família Falavigna | C60: 599 | D60: =GERAL!F599 -> 18216000 | E60: =D60/6 -> 3036000 | F60: 4571000 | G60: =E60-F60 -> -1535000
A61: 31 | B61: Loteamento Reserva Paradiso | C61: 633 | D61: =GERAL!F633 -> 500000 | E61: =D61/6 -> 83333.333 | F61: 0 | G61: =E61-F61 -> 83333.333 | H61: O 1/6 aparece como R$ 83.833,33 (correto R$ 83.333,33).
B62: Total | D62: =SUM(D31:D61) -> 113178000 | E62: =SUM(E31:E61) -> 18863000 | F62: =SUM(F31:F61) -> 24520000 | G62: =SUM(G31:G61) -> -5657000
A64: Principais diferenças
A65: 1. Os valores do Grupo copiados no estudo batem com a coluna E da GERAL em todos os itens comparados (R$ 0,03 de diferença nos demais compromissos). As diferenças vêm da reavaliação feita pelo Valter.
A66: 2. Áreas contratadas (11.2.1): o inventário registra só multas e despesas; o Valter também atribui valor aos lotes que cabem ao Grupo, e o saldo da seção passa de negativo a positivo. É a maior diferença do estudo.
A67: 3. Áreas rurais: 7 dos 12 itens sobem de valor, com destaque para o item 08 (de R$ 250.200 para R$ 1.500.000). Lotes urbanos: sobem os itens 02 e 07.
A68: 4. Loteamentos executados: os 31 loteamentos têm os mesmos lotes e valores do inventário, exceto Lago Negro (lotes 001 a 005 a R$ 1.100.000) e Simioni (R$ 520.000 para lotes em APP). Em 18 loteamentos a Valter escolhe lotes; nos demais o 1/6 fica como crédito.
A69: 5. Lotes em possível APP aparecem entre os escolhidos em San Marino, Firminio Dalzóchio, Primavera e Industrial Vicentino, sempre como diferença em favor da Valter, a confirmar pela documentação das APPs.
A70: 6. Passivos (lotes de terceiros, obras do Colina do Retiro II e demais compromissos) ficam iguais; o estudo só calcula a parcela de 1/6 da Valter.
A71: 7. O estudo não cobre veículos, máquinas e áreas urbanas.
A72: 8. As inconsistências encontradas nos PDFs estão nas notas da coluna F da GERAL e nas colunas de observação desta aba.

Sheet Resumo
B2: imóveis que precisam ser avaliados
B3: pedir valor de todas vendas no período (+comissão, +impostos e etc)
B4: questionar diferença entre a avaliação do patrimônio da cisão do Rovílio e a nossa
B5: pedir processos multas ambientais: listar quais
B6: questionar lógica de cobrar multas e processos ainda não pagos (ex.: lot.caxias / lotes farroupilha)
B7: casa joel capão da canoa (condomínio Condado de Capão) + lotes comprados de Cândido Boff e etc
B8: cópia dos contratos buriti
B9: todos urbanísticos e licenças dos loteamentos em execução os contratados
B10: achar contrato da compra de 2 lotes no Caminhos do Sol feitos pelo Dante. Acredito que eles diminuiram os lotes vendidos
A16: =MAX($A$7:A15)+1 -> 1 | B16: VALUATIONS NECESSÁRIAS
B18: A íntegra dos documentos:
B19: 01. Abastecedora
B20: 05. Hotel Princesa dos Vales
B21: 06. Hotel Araçá
B22: 07. Rádio Comunidade
B23: 08. Transportadora
B25: Da Siviero Empreendimentos
B26: Empreendimentos não executados
B27: Contratos com Buriti
B28: Imóveis de valor não corrigido (itens 1.3 / 1.4 / 1.5)
A34: =MAX($A$7:A33)+1 -> 2 | B34: LOTEAMENTOS EXECUTADOS E REGISTRADOS | C34: 2018 | D34: 2025 | E34: Diferença | F34: (%)
B36: Número de lotes apresentados: | C36: =GERAL!C93 -> 751 | D36: =GERAL!E93 -> 418 | E36: =C36-D36 -> 333 | F36: =D36/C36 -> 0.55659121
B37: Valores Atualizado para 2025: | C37: =GERAL!D92 -> 2.2692194e+08 | D37: =GERAL!E92 -> 111179000 | E37: =D37-C37 -> -1.1574294e+08 | F37: =D37/C37 -> 0.48994382
B39: Obs.: | C39: As diferenças de patrimônio e lotes parece grande demais. Seria uma média de 4 lotes vendidos por mês.
C40: Talvez lotes vendidos e não registrados antes de 2018 ainda constem nessa relação.
C42: Para esses números pegamos a média de preço dos lotes que a Siviero ainda possui e aplicamos
A44: =MAX($A$7:A43)+1 -> 3 | B44: LOTEAMENTOS EXECUTADOS E REGISTRADOS QUE CONSTAM APENAS NA RELAÇÃO DE 2018 | C44: 2018 | D44: 2025
B46: Número de Loteamentos | C46: 24 | D46: -
B47: Número de Lotes | D47: -
B48: Número de Loteamentos com ZERO lotes: | C48: 15 | D48: -
B50: Obs.: | C50: Suponho que sejam loteamentos que foram completamente vendidos
C51: Por que loteamentos com ZERO lotes constam na relação? Apenas para informar o nome ou outro motivo?
A53: =MAX($A$7:A52)+1 -> 4 | B53: Ref. 11.2.3 - Item 1: PAGAMENTO DE COTAS DE ROVÍLIO SIVIERO
B55: Sócio tem direito à 2% das empresas: | C55: Ele recebeu: | D55: 3440082 | E55: =D55*50 -> 172004100
D57: Avaliação das Empresas | E57: 2% da avaliação das Empresas
C58: Siviero Emp. Imob. Ltda.: | D58: 1.0087403e+08 | E58: =D58*0.02 -> 2017480.6
C59: Abastecedora de Combustíveis: | D59: 9661414 | E59: =D59*0.02 -> 193228.28
C60: Transportadora Irmãos Siviero: | D60: 16374986 | E60: =D60*0.02 -> 327499.72
D61: =SUM(D58:D60) -> 1.2691043e+08 | E61: =SUM(E58:E60) -> 2538208.6
B63: Obs.: | C63: Diferença de 36.53%
B67: Sócio tem direito à 2% das empresas: Ele recebeu: R$ 3,440,082.00 2% das empresas Siviero Emp. Imob. Ltda.: R$ 2,017,480.55 Abastecedora de Combustíveis: R$ 193,228.28 Transportadora Irmãos Siviero: R$ 327,499.72 R$ 2,538,208.55 Obs.: Diferença de 36.53%
A70: =MAX($A$7:A69)+1 -> 5 | B70: PATRIMÔNIO QUE TEVE DIMINUIÇÃO DO VALOR NA AVALIAÇÃO | C70: 2018 | D70: 2025 | E70: Diferença
B72: Abastecedora | C72: =#REF! -> #REF! | D72: =#REF! -> #REF! | E72: =D72-C72 -> #REF!
B73: Hotel Princesa dos Vales | C73: =#REF! -> #REF! | D73: =#REF! -> #REF! | E73: =D73-C73 -> #REF!
A78: =MAX($A$7:A77)+1 -> 6 | B78: FAZENDA SÃO CRISPIN
A79: 1
B80: Valor por hectare em 2025 é o mesmo, independente da produtividade da área | C80: 2018 | D80: 2025 | E80: Avaliação por produtividade?
B81: Área Dona Rita (100,0 ha): parte produtiva =35,00% | C81: R$ 44.000,00/ha | D81: R$ 110.000,00/ha
B82: Área Dona Rita (186,0 ha): parte não produtiva=65,00% | C82: R$ 22.000,00/ha (50% do valor) | D82: R$ 110.000,00/ha (valor cheio)
B83: Área Zancheta (45,6 ha): parte produtiva=80,00% | C83: R$ 44.000,00/ha | D83: R$ 110.000,00/ha
B84: Área Zancheta (11,4 ha): parte não produtiva=20,00% | C84: R$ 22.000,00/ha (50% do valor) | D84: R$ 110.000,00/ha (valor cheio)
B85: Área Jane/João Paulo (148,0 ha): parte produtiva=100,00% | C85: R$ 44.000,00/ha | D85: R$ 110.000,00/ha
B87: Melhor avaliação é verificada pelo preço do arrendo (produtividade):
B88: Arrendos com base na saca de soja: | C88: anual | D88: média anual | E88: saca de soja ~R$ 120 | F88: *60 e 100 sacas por ha. (provavelmente)
B89: 155 | C89: 2790 | D89: =C89/B89 -> 18 | E89: =C89*120 -> 334800 | F89: =D89/60 -> 0.3
B90: 30 | C90: 900 | D90: =C90/B90 -> 30 | E90: =C90*120 -> 108000 | F90: =D90/100 -> 0.3
F91: * pegar contratos
B92: Arrendos com base em kg de boi: | C92: anual | D92: média anual | E92: kg do boi ~R$ 11
B93: 157 | C93: 3000 | D93: =3000/100 -> 30 | E93: =11*30*157 -> 51810
C94: * verficar se arrendo sobre toda área ou parcial
B96: Não arrendada (improdutiva) | C96: anual | D96: média anual | E96: kg do boi ~R$ 11
B97: 68.9 | C97: 0 | D97: 0 | E97: =11*30*157 -> 51810
A99: 2
B100: Vendas: valor médio por hectare está maior em 2025 do que o apresentado em 2018
B101: venda em 2018:
B102: venda em 2025:
A106: =MAX($A$7:A105)+1 -> 7 | B106: VALORES NÃO CONTABILIZADOS POR LOTES DE POSSÍVEL APP
B108: Áreas de possível APP estão sendo zerados antes de uma decisão judicial.
B109: Confirmar a situação dos lotes marcados como definitivamente APP
A111: 20 | B111: Loteamento San Marino | C111: 3 | D111: 952004 | E111: -952004
A112: 20.5 | B112: Lote:12 | Quadra:1650 | valor:R$ 244.000,00 | C112: 244000 | F112: Área de possível de APP
A113: 20.6 | B113: Lote:13 | Quadra:1650 | valor:R$ 233.000,00 | C113: 233000 | F113: Área de possível de APP
A114: 20.11 | B114: Lote:4 | Quadra:1676 | valor:R$ 253.000,00 | C114: 253000 | F114: Área de possível de APP
A115: 21 | B115: Loteamento Firminio Dalzóchio | C115: 1 | D115: 131000 | E115: -131000
A116: 21.9 | B116: Lote:2 | Quadra:1292 | valor:R$ 131.000,00 | C116: 131000 | F116: Área de possível de APP
A117: 22 | B117: Loteamento Primavera | C117: 2 | D117: 335000 | E117: -335000
A118: 22.1 | B118: Lote:8 | Quadra:1193 | valor:R$ 170.000,00 | C118: 170000 | F118: Área possível de APP
A119: 22.2 | B119: Lote:9 | Quadra:1193 | valor:R$ 165.000,00 | C119: 165000 | F119: Área possível de APP
A120: 24 | B120: Loteamento Industrial Vicentino | C120: 1 | D120: 1125000 | E120: -1125000
A121: 24.5 | B121: Lote:13 | Quadra:1303 | valor:R$ 1.125.000,00 | C121: 1125000 | F121: Área passível de APP
A125: =MAX($A$7:A124)+1 -> 8 | B125: RELATÓRIOS MENSAIS
B127: Tenho apenas os levantamentos de Jul.2023 até Out.2024
B128: Antes de pedir todos relatórios para conferência, fiz de gasto desde 2018 com a média desse período
B130: média | C130: 832951.26
B131: TOTAL para 8 anos (96 meses) | C131: 79963321
C134: Empreendimentos | D134: Transportadora | E134: Abastecedora | F134: TOTAL
B135: 45108 | C135: 1165697.9 | D135: 170937.95 | E135: 14885.25 | F135: =SUM(C135:E135) -> 1351521.1
B136: ago.2023 | C136: 668125.99 | D136: 183210.32 | E136: 4275.02 | F136: =SUM(C136:E136) -> 855611.33
B137: Set. 2023 | C137: 707103.09 | D137: 193804.09 | E137: 4933.15 | F137: =SUM(C137:E137) -> 905840.33
B138: Out. 2023 | C138: 385521.64 | D138: 157363.96 | E138: 3790.28 | F138: =SUM(C138:E138) -> 546675.88
B139: 45231 | C139: 666440.05 | D139: 154753.09 | E139: 4056.08 | F139: =SUM(C139:E139) -> 825249.22
B140: Dez. 2023 | C140: 1022872.6 | D140: 216221.5 | E140: 3840.28 | F140: =SUM(C140:E140) -> 1242934.4
B141: 45292 | C141: 343100.52 | D141: 154069.3 | E141: 3812.25 | F141: =SUM(C141:E141) -> 500982.07
B142: Fev. 2024 | C142: 295923.8 | D142: 158589.35 | E142: 5319.73 | F142: =SUM(C142:E142) -> 459832.88
B143: 45352 | C143: 674950.76 | D143: 148559.03 | E143: 5867.78 | F143: =SUM(C143:E143) -> 829377.57
B144: Abr. 2024 | C144: 881710.16 | D144: 168891.18 | E144: 7283.77 | F144: =SUM(C144:E144) -> 1057885.1
B145: Mai. 2024 | C145: 824089.36 | D145: 148233.29 | E145: 7726.51 | F145: =SUM(C145:E145) -> 980049.16
B146: 45444 | C146: 472050.79 | D146: 142941.11 | E146: 5867.77 | F146: =SUM(C146:E146) -> 620859.67
B147: 45474 | C147: 425155.67 | D147: 175646.25 | E147: 5090.89 | F147: =SUM(C147:E147) -> 605892.81
B148: Ago. 2024 | C148: 539462.61 | D148: 194956.31 | E148: 4933.16 | F148: =SUM(C148:E148) -> 739352.08
...

Sheet questionamentos
B2: Dúvida:
B3: Houve uma redução de 751 lotes para
B5: TOTAIS: | C5: 751 | D5: 421 | E5: 331
B6: Nome do Loteamento | C6: Lotes 2018 | D6: Lotes 2025 | E6: Negociados
B7: Loteamento Sol Nascente I - Antônio Prado – RS | C7: 14 | D7: 11 | E7: 3
B8: Loteamento Boito - Nova Prata – RS | C8: 0 | D8: 1 | E8: 0
B9: Condomínio Morada do Ipê I - Passo Fundo – RS | C9: 29 | D9: 2 | E9: 27
B10: Loteamento Fracionamento Simioni - Veranópolis – RS | C10: 4 | D10: 4 | E10: 0
B11: Loteamento Solar Norte - Veranópolis – RS | C11: 10 | D11: 6 | E11: 4
B12: Loteamento Aditivo Medianeira - Veranópolis – RS | C12: 20 | D12: 15 | E12: 5
B13: Loteamento Colina do Retiro I – Veranópolis – RS | C13: 23 | D13: 15 | E13: 8
B14: Loteamento Salvador - Veranópolis – RS | C14: 36 | D14: 26 | E14: 10
B15: Loteamento Colina do Retiro II - Frainer - Veranópolis – RS | C15: 105 | D15: 102 | E15: 3
B16: Loteamento Industrial Pedra Lisa - Veranópolis – RS | C16: 39 | D16: 31 | E16: 8
B17: Loteamento Monte Vêneto - Carlos Barbosa – RS | C17: 1 | D17: 1 | E17: 0
B18: Loteamento Baldasso - Carlos Barbosa – RS | C18: 15 | D18: 5 | E18: 10
... B46: Loteamento Viero - Farroupilha – RS | C46: 8 | D46: 0 | E46: 8
B48: Situação dos empreendimentos citados em 2018
B49: Loteamento Morada da Colina - Veranópolis
B50: Loteamento Bella Visione - Carlos Barbosa
B51: Loteamento Lovison - Nova Prata
B52: Loteamento São Roque
B53: Loteamento Desmembramento Tedesco I - Veranópolis
B54: Loteamento Desmembramento Tedesco II - Veranópolis
B55: Loteamento Colina do Lindóia - Farroupilha
B56: Loteamento Fracionamento Pagliari - Carlos Barbosa
B57: Loteamento Fracionamento Primavera - Farroupilha
B61: Multas de Distratos | C61: =SUM(C62:C70) -> 15754581
B62: Loteamento Caminhos do Sol | C62: 0
B63: Loteamento Vale das Colinas | C63: 4211035
B64: Loteamento Vista da Colina | C64: 2664900
B65: Loteamento Pedrotti + Andreis + Lorandi | C65: 2588646
B66: Loteamento Cecconello | C66: 1300000
B67: Loteamento Bonetto | C67: 782000
B68: Loteamento Pasqual | C68: 1500000
B69: Loteamento Industrial Dr. Letti | C69: 1650000
B70: Loteamento Sol Nascente II | C70: 1058000
B73: Lotes de terceiros passíveis de indenização por APP em Farroupilha | C73: -16240000
B74: Loteamento Firminio Dalzóchio, num saldo de 03 lotes. | C74: -400000
B75: Loteamento Jardim Itália I – II – III, num saldo de 05 lotes. | C75: -986000
... B78: Loteamento Industrial Vicentino, num saldo de 10 lotes. | C78: -13550000
B81: Multas Ambientais | C81: =SUM(C82:C86) -> 7910000
B82: Loteamento Perini | C82: 5000000
B83: Loteamento Dalzóchio | C83: 2200000
B84: Loteamento San Marino | C84: 530000
B85: Loteamento Lago Negro | C85: 80000
B86: Família Acordi | C86: 100000
B89: Empreendimentos não concluídos
B90: Loteamento Alto das Graças II.
B91: Loteamento Santa Corona III.
B92: Condomínio Morada dos Ipês II
B93: Loteamento da Congregação das Irmãos de São Carlos.
B94: Loteamento Bella Visione.
B95: Loteamento Bonetto.
B96: Loteamento Pascoal.
B97: Loteamento Letti.
B98: Loteamento Colombo.
B99: Loteamento Champagnat.
B100: Loteamento Simioni.
B101: Loteamento Sol Nascente.
B103: Investimentos (não corrigido) | C103: =SUM(C104:C111) -> 3226000
B104: Compra de lotes no Loteamento Industrial Pedra Lisa. | C104: 625000
B105: Pago dívida do Senhor Leonildo Anzolin, em troca de 01 lote – Nota Promissória. | C105: 90000
B106: Compra de lotes da Família Fioreze. | C106: 148000
B107: Pago despesas do Senhor Arlindo Piccoli – dívidas bancárias e de terceiros em troca de lotes. | C107: 300000
B108: Aquisição da área de terras da Família Fogali, em Vila Azul. | C108: 205000
B109: Compra de lotes no Loteamento Caminhos do Sol – Dorval Boff. | C109: 165000
B110: Pago uma dívida trabalhista do Senhor Dorval Boff, em troca de lotes no Loteamento Caminhos do Sol. | C110: 220000
B111: Compra de lotes no Loteamento Caminhos do Sol – Ludovico Boff e mais pagamento de dívidas de impostos. | C111: 1473000

Sheet Relatórios Mensais
B1: Empreendimentos | C1: Transportadora | D1: Abastecedora
A2: 45108 | B2: 1165697.9 | C2: 170937.95 | D2: 14885.25 | E2: =SUM(B2:D2) -> 1351521.1
A3: ago.2023 | B3: 668125.99 | C3: 183210.32 | D3: 4275.02 | E3: =SUM(B3:D3) -> 855611.33
A4: Set. 2023 | B4: 707103.09 | C4: 193804.09 | D4: 4933.15 | E4: =SUM(B4:D4) -> 905840.33
A5: Out. 2023 | B5: 385521.64 | C5: 157363.96 | D5: 3790.28 | E5: =SUM(B5:D5) -> 546675.88
A6: 45231 | B6: 666440.05 | C6: 154753.09 | D6: 4056.08 | E6: =SUM(B6:D6) -> 825249.22
A7: Dez. 2023 | B7: 1022872.6 | C7: 216221.5 | D7: 3840.28 | E7: =SUM(B7:D7) -> 1242934.4
A8: 45292 | B8: 343100.52 | C8: 154069.3 | D8: 3812.25 | E8: =SUM(B8:D8) -> 500982.07
A9: Fev. 2024 | B9: 295923.8 | C9: 158589.35 | D9: 5319.73 | E9: =SUM(B9:D9) -> 459832.88
A10: 45352 | B10: 674950.76 | C10: 148559.03 | D10: 5867.78 | E10: =SUM(B10:D10) -> 829377.57
A11: Abr. 2024 | B11: 881710.16 | C11: 168891.18 | D11: 7283.77 | E11: =SUM(B11:D11) -> 1057885.1
A12: Mai. 2024 | B12: 824089.36 | C12: 148233.29 | D12: 7726.51 | E12: =SUM(B12:D12) -> 980049.16
A13: 45444 | B13: 472050.79 | C13: 142941.11 | D13: 5867.77 | E13: =SUM(B13:D13) -> 620859.67
A14: 45474 | B14: 425155.67 | C14: 175646.25 | D14: 5090.89 | E14: =SUM(B14:D14) -> 605892.81
A15: Ago. 2024 | B15: 539462.61 | C15: 194956.31 | D15: 4933.16 | E15: =SUM(B15:D15) -> 739352.08
A16: Out. 2024 | B16: 805019.42 | C16: 162235.91 | D16: 4949.97 | E16: =SUM(B16:D16) -> 972205.3
E17: =SUM(E2:E16)/COUNT(E2:E16) -> 832951.26 | F17: média
A19: =8*12 -> 96 | B19: =A19*E17 -> 79963321

Sheet 1.Abastecedora
B1: ESTUDO SIVIERO | C1: 2018: apresentado | D1: 2018: atualizado | E1: dezembro 2024 | G1: outubro 2025 | H1: Diferença | I1: OBSERVAÇÕES
B3: patrimônio (sem desconto) | C3: =C5+#REF!+#REF!+#REF!+#REF!+#REF!+#REF!+#REF!+#REF!+#REF!+#REF! -> #REF! | D3: =D5+#REF!+#REF!+#REF!+#REF!+#REF!+#REF!+#REF!+#REF!+#REF!+#REF! -> #REF! | E3: =E5+#REF!+#REF!+#REF!+#REF!+#REF!+#REF!+#REF!+#REF!+#REF!+#REF! -> #REF! | F3: =F5+#REF!+#REF!+#REF!+#REF!+#REF!+#REF!+#REF!+#REF!+#REF!+#REF! -> #REF! | G3: =G5+#REF!+#REF!+#REF!+#REF!+#REF!+#REF!+#REF!+#REF!+#REF!+#REF! -> #REF! | H3: =G3-D3 -> #REF!
A5: 1 | B5: ABASTECEDORA DE COMBUSTÍVEIS SIVIERO LTDA. | C5: =SUM(C7:C10) -> 12361852 | D5: =SUM(D7:D10) -> 9806414 | E5: =SUM(E7:E10) -> 0 | F5: =SUM(F7:F10) -> 9661414 | G5: =SUM(G7:G10) -> 9661414 | H5: =SUM(H7:H10) -> -145000
C6: valores 2018 -> 2025: | D6: =(D5/C5)-1 -> -0.20671967 | F6: =SUM(F7:F10) -> 9661414 | H6: =IF(H5<0,"patrimônio diminuiu","patrimônio aumentou") -> patrimônio diminuiu
A7: 1 | B7: Um imóvel urbano sob Matrícula nº 3.752, com área de 3.450,00m², que compreende um lote urbano e instalação de um Posto de Combustíveis, totalmente equipado e em pleno funcionamento. O contrato com a Companhia Ipiranga está cumprido e com condições de renegociação e/ou renegociação com outra Companhia e/ou também com a possibilidade de exploração direta. Agrega ao valor do Posto, o aluguel da Lancharia/Restaurante. Valor do Terreno e Pavimentação: 3.450,00m² x R$ 2.100,00 = R$ 7.245.000,00 (considerado o valor ao metro quadrado da pavimentação e o valor da área conforme sua localização comercial). Valor do Posto em área construída: 292,85m² x R$ 1.500,00 = R$ 439.275,00 (valor do CUB da construção – agosto de 2017). Valor do Posto em área coberta: 699,55m² x R$ 1.100,00 = R$ 769.505,00 (valor do CUB da construção – agosto de 2017). Valor do Posto com equipamentos, bombas, quadros, tanques, sistema elétrico e licenciamento, etc. = R$ 650.000,00. Valor do Posto em vantagem da coisa feita: 30,00% x R$ 557.634,00. | VALOR R$ 9.661.414,00 | C7: 12216852 | D7: =G7 -> 9661414 | F7: 9661414 | G7: 9661414 | H7: =G7-D7 -> 0 | I7: Por que reduziu R$2.555.437,89
A8: A.1 | B8: Um caminhão carro tanque placa: ICW 8342, ano: 1995, modelo: MERCEBES BENZ/L 1618. | C8: 145000 | D8: =C8 -> 145000 | G8: 0 | H8: =G8-D8 -> -145000
A9: - | B9: Observações: Aprovado o PROJETO do Posto junto a Prefeitura de Veranópolis para fins de legalização da obra e posterior procedimento de averbação da obra junto ao Ofício de Registro de Imóveis, da Comarca de Veranópolis. Aguardando o prazo de 05 (cinco) anos para pagamento dos impostos junto à Receita Federal – INSS, contados a partir de 14 de março de 2022. Processo Judicial em tramitação no Fórum de Veranópolis – CRISTIANO RODRIGO LUCCHETTA – Ação de Indenização = Ponto e pagamento de aluguéis. O valor real acima apontado não é líquido, à medida que: a) O valor patrimonial lançado sofrerá redução pela regularização dos imóveis, o que se estima numa redução de 0,70% (ZERO VÍRGULA SETENTA POR CENTO) do valor acima apontado, afora os ônus de eventual dissolução da empresa em relação a parte de algum(ns) sócio(s). b) Há que se ter em mente, que haverá ônus de eventual dissolução da empresa em relação a parte de algum(ns) sócio(s), não podendo serem considerados como líquidos os valores alcançados na avaliação patrimonial. Conforme INSTRUMENTO PARTICULAR DE COMPRA E VENDA DE QUOTAS DE CAPITAL, NA SOCIEDADE DE EMPRESAS DE RESPONSABILIDADE LIMITADA, datado de 28 de agosto de 2025, o Sócio ROVÍLIO SIVIERO, brasileiro, natural de Veranópolis – RS, Odontólogo, residente e domiciliado na Rua Carijós, nº 427, Bairro Vila Fátima, na cidade de Passo Fundo – RS, CEP.: 99.020-110, inscrito no CPF/MF sob nº 225.676.150-91 e portador da Carteira de Identidade nº 4017098015, emitida pela SSP – RS, casado pelo Regime de Comunhão Universal de Bens com Maristela Pretto Siviero, brasileira, professora, filha de Alberto José Pretto e de Iracema Antônia Pretto, inscrita no CPF/MF sob nº 260.949.670/20 e portadora da Carteira de Identidade nº 22.827.317-1, emitida pela SSP – SC, efetuaram a VENDA das quotas que lhes pertenciam à empresa, diluídas em partes iguais aos demais sócios remanescentes.

Sheet 2.São Crispin
B1: ESTUDO SIVIERO | C1: 2018: apresentado | D1: 2018: atualizado | E1: dezembro 2024 | G1: outubro 2025 | H1: Diferença | I1: OBSERVAÇÕES
A2: 2 | B2: AGROPECUÁRIA FAZENDA SÃO CRISPIN LTDA. | C2: =C4 -> 116600 | D2: =D4 -> 116600 | E2: =E4 | F2: =F4 | G2: =G4 -> 0 | H2: =H4 -> -116600
F3: =SUM(F4:F6) -> 0 | H3: =IF(H2<0,"patrimônio diminuiu","patrimônio aumentou") -> patrimônio diminuiu
A4: A.1 | B4: Um trator agrícola da marca VALTRA, modelo BM100, 4 x 4 – TURBO, ano 2010. | C4: 116600 | D4: 116600 | G4: 0 | H4: =G4-D4 -> -116600
B5: Atualmente, através de CONTRATO PARTICULAR DE ARRENDAMENTO, a área total está arrendada para a FAMÍLIA LORENZETTI, pelo prazo de 03 (três) anos seguidos e ininterruptos, iniciando-se no ano de 2023 (02 de maio de 2023) e tendo como última safra o ano de 2026 (30 de abril de 2026). As áreas estas inseridas dentro da FAZENDA SÃO CRISPIN, localizada na Capela de São Sebastião, no Distrito do Chimarrão, no Município de André da Rocha – RS, dentro de uma área total de 411,4 ha (Quatrocentos e onze hectares + quatro mil metros quadrados). a.) 155,0 hectares = 18 (DEZOITO) sacas de soja, ao hectare plantado = 2.790 (DUAS MIL, SETECENTAS E NOVENTA) sacas de soja, ao ano. b.) 30,0 hectares = 30 (TRINTA) sacas de soja, ao hectare plantado = 900 (NOVECENTAS) sacas de soja, ao ano. Esta área será utilizada para o plantio de batatas. c.) 157,5 hectares, desde o ano de 2023, ficou dentre as partes estabelecido, que os ARREDANTÁRIOS usarão a área do campo nativo – área da fazenda não utilizada para o plantio de produtos agrícolas – para a criação de bovinos, que por este arrendamento de área do campo nativo, pagarão para a ARRENDADORA a quantia de 3.000,00 (TRÊS MIL QUILOS) de BOI, ao ano, ao preço da época, para cada invernada de 100,0 ha (CEM HECTARES) alugada, devendo ser paga no MÊS DE DEZEMBRO, de cada ano. d.) 68,9 hectares, não incidirá qualquer pagamento, visto que se trata de áreas isoladas em toda a extensão da fazenda impróprias para qualquer cultivo agrícola ou uso para pecuária. Trata-se de áreas que são compostas por matos, capões e pedras. | C5: 0 | D5: 0 | G5: 0 | I5: Valor desses custos estão no documento: B.) HOTEL PRINCESA DOS VALES LTDA. - ÁREA DE TERRAS VENDIDAS + LOTEAMENTOS CONTRATADOS PELA SEI - SEM OBRAS

Sheet 4.Ceval
B1: ESTUDO SIVIERO | C1: 2018: apresentado | D1: 2018: atualizado | E1: dezembro 2024 | G1: outubro 2025 | H1: Diferença | I1: OBSERVAÇÕES
A2: 4 | B2: CEVAL TERRAPLENAGEM E ESCAVAÇÕES LTDA. | C2: =SUM(C4:C8) -> 391000 | D2: =SUM(D4:D8) -> 408000 | E2: =SUM(E4:E8) -> 0 | F2: =SUM(F4:F8) -> 315000 | G2: =SUM(G4:G8) -> 315000 | H2: =SUM(H4:H8) -> -93000
C3: valores 2018 -> 2025: | D3: =(D2/C2)-1 -> 0.043478261 | F3: =SUM(F4:F9) -> 315000 | H3: =IF(H2<0,"patrimônio diminuiu","patrimônio aumentou") -> patrimônio diminuiu
A4: 1 | B4: Uma ESCAVADEIRA HIDRÁULICA – MARCA CATERPILLAR – MODELO 320 D, ano 2009 – modelo 2010, adquirida conforme Nota Fiscal nº 4946, avaliada na data da compra no valor de R$ 200.000,00 (Duzentos mil reais). | C4: 200000 | D4: 200000 | F4: 200000 | G4: 200000 | H4: =G4-D4 -> 0
A5: 2 | B5: Uma RETROESCAVADEIRA – CASE / M A 580 L, ano 2001, modelo 2001, placa IKI 4325, chassi nº JHF0048344, avaliada nesta data no valor de R$ 70.000,00 (Setenta mil reais). | C5: 60000 | D5: 70000 | F5: 70000 | G5: 70000 | H5: =G5-D5 -> 0
A6: 3 | B6: Um CAMINHÃO CAÇAMBA MERCEDES, marca-modelo M.BENZ/LK 1313, combustível DIESEL, ano 1982, modelo 1982, cor predominante VERMELHA, placa IHM 0033, chassi nº 34500312579515, Renavam nº 54294247-0, emplacado na cidade de Veranópolis – RS, avaliado na data da compra no valor de R$ 45.000,00 (Quarenta e cinco mil reais). | C6: 38000 | D6: 45000 | F6: 45000 | G6: 45000 | H6: =G6-D6 -> 0
A7: A.1 | B7: Um CAMINHÃO CAÇAMBA MERCEDES, marca-modelo M.BENZ/2423 K, combustível DIESEL, ano 2003, modelo 2003, cor predominante BRANCA, placa ILD 3959, chassi nº 9BM6933863B334489, Renavam nº 802204996, emplacado na cidade de Veranópolis – RS, avaliado na data da compra no valor de R$ 93.000,00 (Noventa e três mil reais). | C7: 93000 | D7: 93000 | G7: 0 | H7: =G7-D7 -> -93000
A8: - | B8: Observações: O valor real acima apontado não é líquido, à medida que: a) O valor patrimonial lançado sofrerá redução pela regularização dos imóveis, o que se estima numa redução de 0,00% (ZERO POR CENTO) do valor acima apontado, afora os ônus de eventual dissolução da empresa em relação a parte de algum(ns) sócio(s). b) Há que se ter em mente, que haverá ônus de eventual dissolução da empresa em relação a parte de algum(ns) sócio(s), não podendo serem considerados como líquidos os valores alcançados na avaliação patrimonial. | H8: =G8-D8 -> 0

Sheet 5.Hotel Princesa
B1: ESTUDO SIVIERO | C1: 2018: apresentado | D1: 2018: atualizado | E1: dezembro 2024 | G1: outubro 2025 | H1: Estudo Rafael | I1: Diferença | J1: OBSERVAÇÕES
A2: 5 | B2: HOTEL PRINCESA DOS VALES LTDA. | C2: =C4+C13+C15+C17+C24+C35+C39+C41 -> 48730898 | D2: =D4+D13+D15+D17+D24+D35+D39+D41 -> 75444030 | E2: =E4+E13+E15+E17+E24+E35+E39+E41 -> 0 | F2: =F4+F13+F15+F17+F24+F35+F39+F41 -> 22198515 | G2: =G4+G13+G15+G17+G24+G35+G39+G41 -> 75410201 | H2: =SUM(H3:H42) -> 50914158 | I2: =I4+I13+I15+I17+I24+I35+I39+I41 -> -33828.5
C3: valores 2018 -> 2025: | D3: =(D2/C2)-1 -> 0.54817647 | F3: =SUM(F4:F9) -> 0 | I3: =IF(I2<0,"patrimônio diminuiu","patrimônio aumentou") -> patrimônio diminuiu
A4: 1 | B4: HOTEL PRINCESA DOS PRINCESA DOS VALES | C4: =SUM(C6:C12) -> 17475786 | D4: =SUM(D6:D12) -> 13504244 | E4: =SUM(E6:E12) -> 0 | F4: =SUM(F6:F12) -> 0 | G4: =SUM(G6:G12) -> 13504244 | J4: Porque a referêcia do valor/m² é o CUB/DEZEMBRO DE 2022
C5: valores 2018 -> 2025: | D5: =(D4/C4)-1 -> -0.22725974
A6: 1.1. | B6: Um terreno urbano, com a área de 1.800,00m² = 30,00m X 60,00m, localizado na esquina da Avenida Osvaldo Aranha com a Rua Mal. Deodoro da Fonseca, devidamente registrado no Ofício de Registro de Imóveis da Comarca de Veranópolis, sob Matrícula nº 1.412, onde possui uma área para PÁTIO DE ESTACIONAMENTO e a área onde está instalado o HOTEL, prédio de 04 andares e subsolo, composto por 48 apartamentos, restaurante, sala de convenções, cozinha, lavanderia, totalmente equipado e em pleno funcionamento.
A7: 1.2. | B7: Valor do terreno onde está construído o Edifício – HOTEL = 12,00m X 60,00m, de terreno: 720,00m² x R$ 6.000,00 = R$ 4.320.000,00 (considerado o valor ao metro quadrado do mercado no centro da cidade e o valor da área conforme sua localização comercial). | C7: 5760000 | D7: =G7 -> 4320000 | G7: 4320000 | I7: =G7-D7 -> 0
A8: 1.3. | B8: Valor do Edifício Construído – obra civil = 04 andares = 510,00m² de área construída: 2.040,00m² x R$ 2.356,10 = R$ 4.806.444,00 (considerado o valor ao metro quadrado da construção – CUB/DEZEMBRO DE 2022 e o valor da área conforme sua localização comercial) = com depreciação de 20,00% (- R$ 961.288,80) = R$ 3.845.155,20. | C8: 4394343.6 | D8: =G8 -> 3845155.2 | G8: 3845155.2 | I8: =G8-D8 -> 0 | J8: Porque CUB 2022
A9: 1.4. | B9: Valor do Edifício Construído – obra civil = 01 andar – SUBSOLO = 510,00m² de área construída: 510,00m² x R$ 1.407,45 = R$ 717.799,50 (considerado o valor ao metro quadrado da construção – CUB/AGOSTO DE 2017 e o valor da área conforme sua localização comercial) = com depreciação de 20,00% (-R$ 143.559,90) = R$ 574.239,60. | C9: 717799.5 | D9: =G9 -> 574239.6 | G9: 574239.6 | I9: =G9-D9 -> 0 | J9: Porque CUB 2017
A10: 1.5. | B10: Reforma de 48 apartamentos do HOTEL: 48 x R$ 45.000,00 = R$ 2.160.000,00 (considerado o valor atualizado no custo da reforma de cada apartamento) = com depreciação de 20,00% = (-R$ 432.000,00) = R$ 1.728.000,00. | C10: 2400000 | D10: =G10 -> 1728000 | G10: 1728000 | I10: =G10-D10 -> 0
A11: 1.6. | B11: Móveis e Equipamentos instalados no HOTEL: cozinha, restaurante, sala de convenções, lavanderia, recepção, etc. = R$ 1.500.000,00 = com depreciação de 20,00% (-R$ 300.000,00) = R$ 1.200.000,00. | C11: 1500000 | D11: =G11 -> 1200000 | G11: 1200000 | I11: =G11-D11 -> 0
A12: 1.7. | B12: Valor do Edifício Construído – obra civil = 05 andares = 25,00% (Vinte e cinco por cento) da obra feita: R$ 7.347.394,80 (considerado o valor agregado à coisa feita, como tal se encontra) = R$ 1.836.848,70. | C12: 2703642.9 | D12: =G12 -> 1836848.7 | G12: 1836848.7 | I12: =G12-D12 -> 0 | J12: Que obra é essa?
A13: 2 | B13: Um terreno urbano, com a área de 1.080,00m² = 18,00m X 60,00m, localizado na esquina da Avenida Osvaldo Aranha com a Rua Marechal Deodoro da Fonseca, devidamente registrado no Ofício de Registro de Imóveis da Comarca de Veranópolis, sob Matrícula nº 1.412 = 1.080,00m² X R$ 7.500,00, ao metro. | C13: 10800000 | D13: =G13 -> 8100000 | F13: 8100000 | G13: 8100000 | I13: =G13-D13 -> 0
C14: valores 2018 -> 2025: | D14: =(D13/C13)-1 -> -0.25
A15: 3 | B15: Um terreno urbano, com a área de 750,00m², localizado na Rua Marechal Deodoro da Fonseca, devidamente registrado no Ofício de Registro de Imóveis da Comarca de Veranópolis, sob Matrícula nº 6.262, fundos do HOTEL, adquirido do Senhor Roberto Munaretti, considerando sua localização e uso construtivo = R$ 3.333,34 ao metro quadrado (considerado os 15,00 metros de frente). | C15: 2250000 | D15: =G15 -> 2500000 | F15: 2500000 | G15: 2500000 | I15: =G15-D15 -> 0
C16: valores 2018 -> 2025: | D16: =(D15/C15)-1 -> 0.11111111
A17: 4 | B17: SEDE CAMPESTRE | C17: =SUM(C19:C23) -> 3879091.8 | D17: =SUM(D19:D23) -> 5294686 | F17: 5560857.5 | G17: =SUM(G19:G23) -> 5560857.5 | H17: 5560857.5 | I17: =G17-D17 -> 266171.5
C18: valores 2018 -> 2025: | D18: =(D17/C17)-1 -> 0.36492929
A19: 4.1. | B19: Um terreno rural, com a área de 9,4 hectares, localizado na Rua Luiz Siviero, no Bairro Femaçã, devidamente registrado no Ofício de Registro de Imóveis da Comarca de Veranópolis, sob Matrículas nº 1.941 e 7.104, conhecido como SEDE CAMPESTRE, composta por pavilhão, piscinas, casa, campos de futebol, lagos e alicerces para construção de cabanas. Cadastrada no CCIR – Receita Federal sob nº 2.481.947-6. Valor da área de terras = 9,4ha X R$ 450.000,00 ao hectare = R$ 4.230.000,00. | C19: 2820000 | D19: =G19 -> 4230000 | G19: 4230000
A20: 4.2. | B20: Valor do Pavilhão Construído – obra civil = 01 andar = 891,00m² de área construída: 891,00m² x R$ 746,00 = R$ 664.686,00 (considerado o valor ao metro quadrado da construção – CUB/AGOSTO DE 2017 e o valor da área conforme sua localização comercial). | C20: 664686 | D20: =G20 -> 664686 | G20: 664686 | J20: Por que CUB/AGOSTO DE 2017
A21: 4.3. | B21: Valor da benfeitoria denominada de Quiosque: R$ 150.000,00. | C21: 150000 | D21: =G21 -> 150000 | G21: 150000
A22: 4.4. | B22: Valor da casa de alvenaria localizada nos fundos da Sede Campestre = ...............m² de área construída: R$ 250.000,00. | C22: 244405.8 | D22: =G22 -> 250000 | G22: 250000
A23: 4.5. | B23: Valor das obras feitas e infraestrutura = 25,00% (Vinte por cento) da obra feita: R$ 1.064.686,00 (considerado o valor agregado à coisa feita, como tal se encontra) = R$ 266.171,50. | C23: 0 | D23: 0 | G23: 266171.5
A24: 5 | B24: FAZENDA SÃO CRISPIN | C24: =C27+C30+C33 -> 13588520 | D24: =D27+D30+D33 -> 44828300 | F24: 5560857.5 | G24: =G27+G30+G33 -> 44828300 | H24: 44828300 | I24: =G24-D24 -> 0
C25: valores 2018 -> 2025: | D25: =(D24/C24)-1 -> 2.2989833
A26: 5.1. | B26: Uma área de terras rurais, denominada de FAZENDA SÃO CRISPIN, localizada na Capela de São Sebastião, no Distrito do Chimarrão, no Município de André da Rocha – RS, com área total de 491,0 hectares, áreas estas registradas sob Matrículas nº.: Matrícula nº 14.221 = 50,0 hectares. - Matrícula nº 13.615 = 37,2 hectares. Matrícula nº 13.650 = 49,0 hectares. - Matrícula nº 00.760 = 48,0 hectares. Matrícula nº 11.462 = 100,0 hectares. - Matrícula nº 05.435 = 25,0 hectares. Matrícula nº 09.959 = 6,8 hectares. - Matrícula nº 04.443 = 25,0 hectares. Matrícula nº 00.760 = 100,0 hectares. - Matrícula nº 12.473 = 50,0 hectares. Cadastrada no CCIR – Receita Federal sob nº 2.898.196-0 | F26: 52978900 | J26: Não bate com 2025 versão anterior
A27: 5.2. | B27: Área Dona Rita | C27: =C28+C29 -> 8492000 | D27: =D28+D29 -> 31460000 | G27: =G28+G29 -> 31460000
A28: 5.2.1. | B28: parte produtiva=35,00% = 100,0 ha – R$ 110.000,00 = R$ 11.000.000,00 | C28: =100*44000 -> 4400000 | D28: =G28 -> 11000000 | G28: =110000*100 -> 11000000
A29: 5.2.2. | B29: parte não produtiva=65,00%=186,0 ha–R$ 110.000,00= R$ 20.460.000,00 | C29: =186*22000 -> 4092000 | D29: =G29 -> 20460000 | G29: =186*110000 -> 20460000
A30: 5.3. | B30: Área Zancheta | C30: =C31+C32 -> 2257200 | D30: =D31+D32 -> 6270000 | G30: =G31+G32 -> 6270000
A31: 5.3.1. | B31: parte produtiva=80,00% = 45,6 ha – R$ 110.000,00 = R$ 5.016.000,00 | C31: =45.6*44000 -> 2006400 | D31: =G31 -> 5016000 | G31: =45.6*110000 -> 5016000
A32: 5.3.2. | B32: parte não produtiva=20,00% = 11,4 ha – R$ 110.000,00 = R$ 1.254.000,00 | C32: =11.4*22000 -> 250800 | D32: =G32 -> 1254000 | G32: =11.4*110000 -> 1254000
A33: 5.4. | B33: Área Jane/João Paulo | C33: =C34 -> 2839320 | D33: =D34 -> 7098300 | G33: =G34 -> 7098300
A34: 5.4.1. | B34: parte produtiva=100,00%=148,0 ha (-) 83,47ha = 64,53 ha – R$ 110.000,00 = R$ 7.098.300,00 | C34: =(148-83.47)*44000 -> 2839320 | D34: =G34 -> 7098300 | G34: =110000*64.53 -> 7098300
A35: 6 | B35: CHIMARRÃO | C35: =C37+C38 -> 476000 | D35: =D37+D38 -> 740000 | G35: =G37 -> 440000 | H35: 440000 | I35: =SUM(I37:I38) -> -300000
C36: valores 2018 -> 2025: | D36: =(D35/C35)-1 -> 0.55462185
A37: 6.1. | B37: Uma área de terras rurais, denominada de FAZENDA SÃO CRISPIN, com área total de 4,0 hectares, DENTRO DE UM TODO MAIOR, localizada na Capela de São Sebastião, no Distrito do Chimarrão, no Município de André da Rocha – RS, adquirida do Senhor Dirceu Prestes e Lairton, área esta registrada sob Matrícula nº.: 11.090. Matrícula nº 11.090 = 4,0 hectares. Cadastrada no CCIR – Receita Federal sob nº ..... Adquirida por CONTRATO DE COMPRA E VENDA, em dezembro de 2015. Área Dirceu/Lairton–parte produtiva=100,00%=4,0 ha – R$ 110.000,00 = R$ 440.000,00 | C37: =4*44000 -> 176000 | D37: =G37 -> 440000 | F37: 520000 | G37: 440000 | I37: =G37-D37 -> 0 | J37: Não bate com 2025 versão anterior
A38: 6.2. | B38: Benfeitorias existentes, como: cercas, terraplenagem de lavouras, construções, banheiras de gado, galpão, implementos agrícolas, roçadeira, moinho, etc. | C38: 300000 | D38: 300000 | G38: 0 | I38: =G38-D38 -> -300000
A39: 7 | B39: Uma área de terras rurais, denominada de PARTE DO LOTE RURAL Nº 52, com área total de 15,1 hectares, localizada na Linha Júlio de Castilhos, no Município de Cotiporã – RS, adquirida da Senhora GLORINHA E GERALDO BASSANI, área está registrada sob Matrícula nº.: 7.391 - Matrícula nº 7.391 = 15,1 hectares X R$ 28.000,00 Cadastrada no CCIR – Receita Federal sob nº 2.481.952-2 | C39: 226500 | D39: =G39 -> 422800 | F39: 422800 | G39: 422800 | I39: =G39-D39 -> 0
C40: valores 2018 -> 2025: | D40: =(D39/C39)-1 -> 0.86666667
A41: 8 | B41: Um veículo Mercedinha MB 709, com boiadeiro, marca MERCEDES BENZ, ano 1991, modelo 1991, placa JTB 8585. | C41: 35000 | D41: =G41 -> 54000 | F41: 54000 | G41: 54000 | H41: 85000 | I41: =G41-D41 -> 0
C42: valores 2018 -> 2025: | D42: =(D41/C41)-1 -> 0.54285714
B43: OBSERVAÇÕES | J43: OBSERVAÇÕES: É necessário transmitir todas as Escrituras Públicas das Propriedades Rurais, para a empresa AGROPECUÁRIA FAZENDA SÃO CRISPIN LTDA., que estão em nome da empresa HOTEL PRINCESA DOS VALES LTDA. e de TERCEIROS, POR CONTRATO. É necessário fazer o levantamento topográfico completo de todas as áreas que perfazem o total da FAZENDA SÃO CRISPIN para unificação em uma ÚNICA MATRÍCULA. (MDE - MURILO MINOZZO – Orçamento + Serviços do Senhor LAIRTON FRIZON = georreferenciamento – inventário – regularização – impostos de transmissão – serviços notarial e registral). a) Conforme consulta verbal com os profissionais, possíveis para serem contratados para realizar os serviços, estimam que os custos administrativos para a execução dos serviços de legalização das áreas ficam em torno de R$ 80.000,00 (OITENTA MIL REAIS) e com despesas extras em torno de R$ 20.000,00 (VINTE MIL REAIS), totalizando aproximadamente um custo de R$ 100.000,00 (CEM MIL REAIS). b) No tangente às despesas de impostos, notariais e registrais, conforme contato mantido com o Senhor Lairton – Fiscal Tributário da Prefeitura de André da Rocha, informou que os valores mínimos exigidos para fins de cálculo do imposto I.T.B.I – IMPOSTO DE TRANSMISSÃO DE BENS IMÓVEIS, são considerados e aplicados conforme a realidade produtiva das áreas, sendo: - para área de terras utilizadas para lavoura: R$ 40.000,00 (QUARENTA MIL REAIS), ao hectare. - para área de terras utilizadas para campo nativo: R$ 18.000,00 (DEZOITO MIL REAIS) a R$ 20.000,00 (VINTE MIL REAIS), ao hectare. - para área de terras de mato: R$ 8.000,00 (OITO MIL REAIS), ao hectare c) Custo com o Serviço Notarial para lavratura das Escrituras Públicas: aproximadamente R$ 5.000,00 (CINCO MIL REAIS). d) Custo com o Serviço Registral para registro das Escrituras Públicas: aproximadamente R$ 5.000,00 (CINCO MIL REAIS). e) O total de hectares que perfazem a área de terras da FAZENDA SÃO CRISPIN é de 411,4 ha ao custo médio de R$ 30.000,00 (TRINTA MIL REAIS), ao hectare, totalizando um valor atribuído para fins de cálculo de imposto, a importância de R$ 12.342.000,00 (DOZE MILHÕES, TREZENTOS E QUARENTA E DOIS MIL REAIS) X o percentual do imposto de 2,00 (DOIS POR CENTO), incidindo um total de aproximadamente R$ 246.840,00 (DUZENTOS E QUARENTA E SEIS MIL, OITOCENTOS E QUARENTA E REAIS). f) Perfazem todas as despesas, um TOTAL de R$ 400.000,00 (QUATROCENTOS MIL REAIS), que deverão ser satisfeitas pela atual credora e proprietária das áreas de terras HOTEL PRINCESA DOS VALES LTDA. Atualmente, através de CONTRATO PARTICULAR DE ARRENDAMENTO, a área total está arrendada para a FAMÍLIA LORENZETTI, pelo prazo de 03 (três) anos seguidos e ininterruptos, iniciando-se no ano de 2023 (02 de maio de 2023) e tendo como última safra o ano de 2026 (30 de abril de 2026). As áreas estas inseridas dentro da FAZENDA SÃO CRISPIN, localizada na Capela de São Sebastião, no Distrito do Chimarrão, no Município de André da Rocha – RS, dentro de uma área total de 411,4 ha (Quatrocentos e onze hectares + quatro mil metros quadrados). a) 155,0 hectares = 18 (DEZOITO) sacas de soja, ao hectare plantado = 2.790 (DUAS MIL, SETECENTAS E NOVENTA) sacas de soja, ao ano. b) 30,0 hectares = 30 (TRINTA) sacas de soja, ao hectare plantado = 900 (NOVECENTAS) sacas de soja, ao ano. Esta área será utilizada para o plantio de batatas. c) 157,5 hectares, desde o ano de 2023, ficou dentre as partes estabelecido, que os ARREDANTÁRIOS usarão a área do campo nativo – área da fazenda não utilizada para o plantio de produtos agrícolas – para a criação de bovinos, que por este arrendamento de área do campo nativo, pagarão para a ARRENDADORA a quantia de 3.000,00 (TRÊS MIL QUILOS) de BOI, ao ano, ao preço da época, para cada invernada de 100,0 ha (CEM HECTARES) alugada, devendo ser paga no MÊS DE DEZEMBRO, de cada ano. d) 68,9 hectares, não incidirá qualquer pagamento, visto que se trata de áreas isoladas em toda a extensão da fazenda impróprias para qualquer cultivo agrícola ou uso para pecuária. Trata-se de áreas que são compostas por matos, capões e pedras. O valor real acima apontado não é líquido, à medida que: a) O valor patrimonial lançado sofrerá redução pela regularização dos imóveis, o que se estima numa redução de R$ 400.000,00 (QUATROCENTOS MIL REAIS) do valor avalizado da FAZENDA SÃO CRISPÍN, afora os ônus de eventual dissolução da empresa em relação a parte de algum(ns) sócio(s). b) Há que se ter em mente, que haverá ônus de eventual dissolução da empresa em relação a parte de algum(ns) sócio(s), não podendo serem considerados como líquidos os valores alcançados na avaliação patrimonial.
B44: VENDAS SÃO CRISPIN | C44: =C45+C46+C47+C48+C49+C50+C51 -> 11320570 | D44: =D45+D46+D47+D48+D49+D50+D51 -> 4484840 | E44: =E45+E46+E47+E48+E49+E50+E51 -> 0 | F44: =F45+F46+F47+F48+F49+F50+F51 -> 0 | G44: =G45+G46+G47+G48+G49+G50+G51 -> 13932840 | I44: =I45+I46+I47+I48+I49+I50+I51 -> 0
B45: 2025 -> Descrição da venda de 190 hectares: (média R$ 49.726.30 – aumento de 38.19%) Vendido em 2018, uma área de terras de 190,0 hectares para a FAMILIA RIGO, ao valor de R$ 49.726,30, ao hectare, de forma parcelada = R$ 9.448.000,00 = 118.100 SC SOJA. R$ 3.000.000,00 – À VISTA, equivalente a 37.500 SACAS DE SOJA. 20.150 SACAS DE SOJA em MAIO DE 2019. O valor da saca de soja 20.150 SACAS DE SOJA em MAIO DE 2020. considerado foi de R$ 80,00 20.150 SACAS DE SOJA em MAIO DE 2021. (FALTA RECEBER) à saca, conforme preço de 20.150 SACAS DE SOJA em MAIO DE 2022. (FALTA RECEBER) cotação em Outubro/2018 | 2018 -> Descrição da mesma venda: (média R$ 35,983.21) | Uma área de terras rurais, denominada de FAZENDA SÃO CRISPIN, com área total de 106,53 hectares, | DENTRO DE UM TODO MAIOR, localizada na Capela de São Sebastião, no Distrito do Chimarrão, no Município de | André da Rocha – RS, adquirida do Senhor ALZIR CHIARADIA e AQUILES PIO FRANCESCHETTE, | área esta registrada sob Matrícula nº.: 11.090. = 106,53 hectares. | área esta registrada sob Matrícula nº.: _____?. = 83,47 hectares | Cadastrada no CCIR – Receita Federal sob nº ..... | Adquirida por CONTRATO DE COMPRA E VENDA, datado de 05 de setembro de 2005. | Área Alzir – parte produtiva = 35,00% : 37,275 ha – R$ 44.000,00 = R$ 1.640.100,00 | Área Alzir – parte não produtiva = 65,00%: 69,225 ha – R$ 22.000,00 = R$ 1.522.950,00 | Área Jane/João Paulo – 100% produtiva: 83,47ha – R$ 44.000,00 = R$ 3.672.680,00. | TOTAL = R$ 6,835,730.00 | C45: 6835730 | G45: 9448000
B46: Uma área de terras rurais, denominada de PARTE DO LOTE RURAL Nº 24 e 24/E, com área total de 10,2 hectares, localizada na Linha Júlio de Castilhos, no Município de Cotiporã – RS, adquirida do Senhor CELITO PIEROZAN, área esta registrada sob Matrículas nº.: 2.424 e 2.425. = Matrículas nº 2.424 e 2.425 = 10,2 hectares X R$ 50.000,00 = Cadastrada no CCIR – Receita Federal sob nº 2.481.949-2. Vendido em 2018, a área total para o Senhor ANGELI, pelo valor de R$ 510.000,00 (Quinhentos e dez mil reais), de forma, À VISTA. | C46: 510000 | D46: 510000 | G46: 510000
B47: 2025 Vendido em 2018, uma área de terras de 85,32 hectares para a FAMILIA PELLEGRINI, ao valor de R$ 2.100.000,00 (Dois milhões e cem mil reais), de forma parcelada e mais a quantidade de 41 (Quarenta e uma) cabeças de gado. R$ 100.000,00 – 41 cabeças de gado. R$ 2.000.000,00 – 85,32 ha, sendo valor de R$ 23.441,16, ao hectare. R$ 1.100.000,00 – À VISTA. R$ 1.000.000,00 – JUNHO/2019. | C47: 2100000 | D47: 2100000 | G47: 2100000
B48: 2018 Uma área de terras rurais, denominada de FAZENDA SÃO CRISPIN, com área total de 4,9 hectares, localizada na Capela de São Sebastião, no Distrito do Chimarrão, no Município de André da Rocha – RS, adquirida do Senhor JOÃO ANASTÁCIO ANTÔNIO RODRIGUES, área esta registrada sob Matrícula nº.: 982. Matrícula nº 982 = 4,9 hectares. Cadastrada no CCIR – Receita Federal sob nº 6.213.278-4 Área Anastácio – parte não produtiva = 100,00% = 4,9 ha – R$ 22.000,00 = R$ 107.800,00 Vendido para Família Pelegrini | C48: 107800 | D48: 107800 | G48: 107800
B49: 2018 Uma área de terras rurais, denominada de FRAÇÃO IDEAL, com área total de 10,0 hectares, DENTRO DE UM TODO MAIOR, localizada na Capela de São Sebastião, no Distrito do Chimarrão, no Município de André da Rocha – RS, adquirida do Senhor AITO ANTÔNIO DA SILVERIRA VIEIRA, área esta registrada sob Matrícula nº 11.661 = 10,0 hectares. Cadastrada no CCIR – Receita Federal sob nº........... Adquirida por CONTRATO DE COMPRA E VENDA, datado de 26 de setembro de 2007. Área Aito – parte não produtiva = 100,00% = 10,0 ha – R$ 22.000,00 = R$ 220.000,00 Vendido para Família Pelegrini | C49: 220000 | D49: 220000 | G49: 220000
B50: 2018 Uma área de terras rurais, denominada de FAZENDA SÃO CRISPIN, com área total de 26,16 hectares, localizada na Capela de São Sebastião, no Distrito do Chimarrão, no Município de André da Rocha – RS, adquirida do Senhor ADEMAR RIBEIRO, área esta registrada sob Matrícula nº.: ............... Matrícula nº ................ = 26,16 hectares. Cadastrada no CCIR – Receita Federal sob nº .......................... Área Ademar–parte não produtiva = 100,00% = 26,16 ha – R$ 22.000,00 = R$ 575.520,00 Vendido para Família Pelegrini | C50: 575520 | D50: =C50 -> 575520 | G50: =D50 -> 575520
B51: 2018 Uma área de terras rurais, denominada de FAZENDA TRÊS PORTEIRAS, com área total de 44,16 hectares, localizada na Capela de São Sebastião, no Distrito do Chimarrão, no Município de André da Rocha – RS, área esta registrada sob Matrícula nº.: Matrícula nº ......... = 44,1 hectares. Cadastrada no CCIR – Receita Federal sob nº 2.566.238-4 Área Garbin – parte não produtiva = 100,00% = 44,16 ha – R$ 22.000,00 = R$ 971.520,00 Vendido para Família Pelegrini | C51: 971520 | D51: =C51 -> 971520 | G51: =D51 -> 971520

Sheet 6.Hotel Araçá
B1: ESTUDO SIVIERO | C1: 2018: apresentado | D1: 2018: atualizado | E1: dezembro 2024 | G1: outubro 2025 | H1: Estudo Rafael | I1: Diferença | J1: OBSERVAÇÕES
A2: 6 | B2: HOTEL ARAÇÁ LTDA. | C2: =C4+C12 -> 49484243 | D2: =D4+D12 -> 56576823 | E2: =E4+E12 -> 0 | F2: =F4+F12 -> 61790460 | G2: =G4+G12 -> 58076823 | H2: =SUM(H3:H34) -> 1880000 | I2: =I4+I12 -> 1500000
C3: valores 2018 -> 2025: | D3: =(D2/C2)-1 -> 0.14333007 | F3: =SUM(F4:F18) -> 63630460 | I3: =IF(I2<0,"patrimônio diminuiu","patrimônio aumentou") -> patrimônio aumentou
A4: 1 | B4: Dezoito (18) terrenos urbanos, localizados dentro da Quadra 37, registrados junto ao Ofício de Registros de Imóveis em 12 (Doze) Matrículas, com a área total de 6.900,00m² (Seis mil e novecentos metros quadrados), localizado na Rua Miguel Main Felo, nº 333, na Praia do Araçá, todos devidamente registrados no Ofício de Registro de Imóveis da Comarca de Capão da Canoa – RS, sob Matrículas nº.: 34.768, 34.769, 34.770, 34.771, 6.411, 29.855, 24.584, 24.585, 33.101, 29.856, 0672 e 34.772, onde está instalado o HOTEL, prédio de 04 andares, composto por 144 apartamentos, restaurante, cozinha, sala de convenções, duas piscinas, bar interno e externo, sala de jogos, sauna, mezanino, etc., totalmente equipado e em pleno funcionamento. 04 lotes de 450,00m², cada um. (Lotes nº 01-02-03-04 – Matrícula nº 34.768). 13 lotes de 360,00m², cada um. (Lotes nº 05-22 – Matrícula nº 34.769). (Lotes nº 06-21 – Matrícula nº 34.770). (Lote nº 07 – Matrícula nº 34.771). (Lote nº 08 – Matrícula nº 6.411). (Lote nº 09 – Matrícula nº 29.855). (Lote nº 10 – Matrícula nº 24.584). (Lote nº 11 – Matrícula nº 24.585). (Lote nº 12 – Matrícula nº 33.101). (Lote nº 18 – Matrícula nº 29.856). (Lote nº 19 – Matrícula nº 0672). (Lote nº 20 – Matrícula nº 34.772). 01 lote de 420,00m² - lote da Nesga – sobra com muro. (Parte do Lote nº 12 – Matrícula nº 33.101). | C4: =SUM(C6:C11) -> 45274243 | D4: =SUM(D6:D11) -> 49606823 | F4: 53320460 | G4: =SUM(G6:G11) -> 49606823 | I4: =G4-D4 -> 0
C5: valores 2018 -> 2025: | D5: =(D4/C4)-1 -> 0.095696354
A6: 1.1 | B6: Considerado o valor comercial de R$ 1.000,00, ao metro quadrado. Valor do terreno onde está construído o Edifício – HOTEL = 6.900,00m² de terreno = R$ 6.900.000,00 (considerado o valor ao metro quadrado do mercado no Bairro Araçá e o valor da área conforme sua localização comercial). | C6: 3800000 | D6: =G6 -> 6900000 | G6: 6900000 | I6: =G6-D6 -> 0
A7: 1.2 | B7: Móveis e Equipamentos – novos, instalados nos 36 apartamentos do HOTEL, no valor unitário de R$ 42.000,00, cada apartamento = sem depreciação = R$ 1.512.000,00. | C7: 1800000 | D7: =G7 -> 1512000 | G7: 1512000 | I7: =G7-D7 -> 0
A8: 1.3 | B8: Móveis e Equipamentos, instalados nos 108 apartamentos do HOTEL, no valor unitário de R$ 30.000,00, cada apartamento = R$ 3.240.000,00 = com depreciação de 20,00% = (-) R$ 648.000,00 = R$ 2.592.000,00. | C8: 3024000 | D8: =G8 -> 2592000 | G8: 2592000 | I8: =G8-D8 -> 0
A9: 1.4 | B9: Valor do Edifício Construído – obra civil = 04 andares, com 144 apartamentos do HOTEL, cozinha, restaurante, sala de convenções, lavanderia, bares, piscinas, sala de jogos, sauna, mezanino, = 10.500,00m² de área construída X R$ 3.170,52 = R$ 33.290.460,00 (considerado o valor ao metro quadrado da construção – CUB/DEZEMBRO DE 2022 e o valor da área conforme sua localização comercial) = com depreciação de 20,00% = (-) R$ 6.658.092,00 = R$ 26.632.368,00. | C9: 20679264 | D9: =G9 -> 26632368 | G9: 26632368 | I9: =G9-D9 -> 0
A10: 1.5 | B10: Móveis e Equipamentos Diversos instalados no HOTEL: cozinha, restaurante, sala de convenções, lavanderia, recepção, poço artesiano com outorga, etc. = R$ 8.000.000,00 = com depreciação de 20,00% = (-) R$ 1.600.000,00 = R$ 6.400.000,00. | C10: 6400000 | D10: =G10 -> 6400000 | G10: 6400000 | I10: =G10-D10 -> 0
A11: 1.6 | B11: Valor do Edifício Construído – obra civil = 04 andares = 15,00% (Quinze por cento) da obra feita: R$ 37.136.368,00 (considerado o valor agregado à coisa feita, como tal se encontra) = R$ 5.570.455,20. | C11: 9570979.2 | D11: =G11 -> 5570455.2 | G11: 5570455.2 | I11: =G11-D11 -> 0
B12: Lotes | C12: =SUM(C14:C34) -> 4210000 | D12: =SUM(D14:D34) -> 6970000 | E12: =SUM(E14:E34) -> 0 | F12: =SUM(F14:F34) -> 8470000 | G12: =SUM(G14:G34) -> 8470000 | I12: =SUM(I14:I34) -> 1500000
C13: valores 2018 -> 2025: | D13: =(D12/C12)-1 -> 0.65558195
A14: 2 | B14: Um lote urbano nº 03 – Quadra nº 19, com área de 450,00m², devidamente registrado no Ofício de Registro de Imóveis da Comarca de Capão da Canoa – RS, sob Matrícula nº 77.832 (antiga matrícula 37.549), com a Inscrição Imobiliária nº 360.0019.003.000 e Código de Imóvel nº 038998, localizado nas proximidades do Hotel Araçá Ltda. – Casa da Praça. | C14: 250000 | D14: =G14 -> 400000 | F14: 400000 | G14: 400000 | H14: 400000 | I14: =G14-D14 -> 0
A15: 3 | B15: Um lote urbano nº 16 – Quadra nº 37, com área de 360,00m², devidamente registrado no Ofício de Registro de Imóveis da Comarca de Capão da Canoa – RS, sob Matrícula nº 64.782, com a Inscrição Imobiliária nº 360.0037.016.000 e Código de Imóvel nº 039395 localizado nas proximidades do Hotel Araçá Ltda. – Fundos do Hotel. | C15: 180000 | D15: =G15 -> 360000 | F15: 360000 | G15: 360000 | I15: =G15-D15 -> 0
A16: 4 | B16: Um lote urbano nº 23 – Quadra nº 37, com área de 360,00m², devidamente registrado no Ofício de Registro de Imóveis da Comarca de Capão da Canoa – RS, sob Matrícula nº 26.373, com a Inscrição Imobiliária nº 360.0071.023.000 e Código de Imóvel nº 039839 localizado nas proximidades do Hotel Araçá Ltda. – Fundos do Hotel. | C16: 180000 | D16: =G16 -> 360000 | F16: 360000 | G16: 360000 | I16: =G16-D16 -> 0
A17: 5 | B17: Um lote urbano nº 24 – Quadra nº 37, com área de 307,80m², devidamente registrado no Ofício de Registro de Imóveis da Comarca de Capão da Canoa – RS, sob Matrícula nº 26.374, com a Inscrição Imobiliária nº 360.0071.024.000 e Código de Imóvel nº 039840 localizado nas proximidades do Hotel Araçá Ltda. – Fundos do Hotel. | C17: 180000 | D17: =G17 -> 360000 | F17: 360000 | G17: 360000 | I17: =G17-D17 -> 0
A18: 6 | B18: Um lote urbano nº 25 – Quadra nº 37, com área de 307,80m², devidamente registrado no Ofício de Registro de Imóveis da Comarca de Capão da Canoa – RS, sob Matrícula nº 26.375, com a Inscrição Imobiliária nº 360.0071.025.000 e Código de Imóvel nº 039841 localizado nas proximidades do Hotel Araçá Ltda. – Fundos do Hotel. | C18: 180000 | D18: =G18 -> 360000 | F18: 360000 | G18: 360000 | I18: =G18-D18 -> 0
A19: 7 | B19: Um lote urbano nº 26 – Quadra nº 37, com área de 307,80m², devidamente registrado no Ofício de Registro de Imóveis da Comarca de Capão da Canoa – RS, sob Matrícula nº 26.376, com a Inscrição Imobiliária nº 360.0071.026.000 e Código de Imóvel nº 039842 localizado nas proximidades do Hotel Araçá Ltda. – Fundos do Hotel. | C19: 180000 | D19: =G19 -> 360000 | F19: 360000 | G19: 360000 | I19: =G19-D19 -> 0
A20: 8 | B20: Um lote urbano nº 27 – Quadra nº 37, com área de 307,80m², devidamente registrado no Ofício de Registro de Imóveis da Comarca de Capão da Canoa – RS, sob Matrícula nº 26.377, com a Inscrição Imobiliária nº 360.0071.027.000 e Código de Imóvel nº 039843 localizado nas proximidades do Hotel Araçá Ltda. – Fundos do Hotel. | C20: 180000 | D20: =G20 -> 360000 | F20: 360000 | G20: 360000 | I20: =G20-D20 -> 0
A21: 9 | B21: Um lote urbano nº 28 – Quadra nº 37, com área de 307,80m², devidamente registrado no Ofício de Registro de Imóveis da Comarca de Capão da Canoa – RS, sob Matrícula nº 26.378, com a Inscrição Imobiliária nº 360.0071.028.000 e Código de Imóvel nº 039844 localizado nas proximidades do Hotel Araçá Ltda. – Fundos do Hotel. | C21: 180000 | D21: =G21 -> 360000 | F21: 360000 | G21: 360000 | I21: =G21-D21 -> 0
A22: 10 | B22: Um lote urbano nº 29 – Quadra nº 37, com área de 360,00m², devidamente registrado no Ofício de Registro de Imóveis da Comarca de Capão da Canoa – RS, sob Matrícula nº 26.379, com a Inscrição Imobiliária nº 360.0071.029.000 e Código de Imóvel nº 039845 localizado nas proximidades do Hotel Araçá Ltda. – Fundos do Hotel. | C22: 180000 | D22: =G22 -> 360000 | F22: 360000 | G22: 360000 | I22: =G22-D22 -> 0
A23: 11 | B23: Um lote urbano nº 09 – Quadra nº 38, com área de 360,00m², devidamente registrado no Ofício de Registro de Imóveis da Comarca de Capão da Canoa – RS, sob Matrícula nº 37.846, com a Inscrição Imobiliária nº 360.0038.009.000 e Código de Imóvel nº 039410 localizado nas proximidades do Hotel Araçá Ltda. Adquirido do Senhor Hugo Ferri. | C23: 220000 | D23: =G23 -> 390000 | F23: 390000 | G23: 390000 | H23: 390000 | I23: =G23-D23 -> 0
A24: 12 | B24: Um lote urbano nº 10 – Quadra nº 38, com área de 360,00m², devidamente registrado no Ofício de Registro de Imóveis da Comarca de Capão da Canoa – RS, sob Matrícula nº 11.990, com a Inscrição Imobiliária nº 360.0038.010.000 e Código de Imóvel nº 039411 localizado nas proximidades do Hotel Araçá Ltda. Adquirido do Senhor Hugo Ferri. | C24: 220000 | D24: =G24 -> 390000 | F24: 390000 | G24: 390000 | H24: 390000 | I24: =G24-D24 -> 0
A25: 13 | B25: Um lote urbano nº 11 – Quadra nº 38, com área de 360,00m², devidamente registrado no Ofício de Registro de Imóveis da Comarca de Capão da Canoa – RS, sob Matrícula nº 43.389, com a Inscrição Imobiliária nº 360.0038.011.000 e Código de Imóvel nº 039412 localizado nas proximidades do Hotel Araçá Ltda. Adquirido do Senhor Hugo Ferri. | C25: 220000 | D25: =G25 -> 390000 | F25: 390000 | G25: 390000 | I25: =G25-D25 -> 0
A26: 14 | B26: Um lote urbano nº 12 – Quadra nº 38, com área de 360,00m², devidamente registrado no Ofício de Registro de Imóveis da Comarca de Capão da Canoa – RS, sob Matrícula nº 29.803, com a Inscrição Imobiliária nº 360.0038.012.000 e Código de Imóvel nº 039413 localizado nas proximidades do Hotel Araçá Ltda. Adquirido do Senhor Hugo Ferri. | C26: 220000 | D26: =G26 -> 390000 | F26: 390000 | G26: 390000 | I26: =G26-D26 -> 0
A27: 15 | B27: Um lote urbano nº 13 – Quadra nº 38, com área de 360,00m², devidamente registrado no Ofício de Registro de Imóveis da Comarca de Capão da Canoa – RS, sob Matrícula nº 30.294, com a Inscrição Imobiliária nº 360.0038.013.000 e Código de Imóvel nº 039414 localizado nas proximidades do Hotel Araçá Ltda. Adquirido do Senhor Hugo Ferri. | C27: 220000 | D27: =G27 -> 390000 | F27: 390000 | G27: 390000 | I27: =G27-D27 -> 0
A28: 16 | B28: Um lote urbano nº 14 – Quadra nº 38, com área de 360,00m², devidamente registrado no Ofício de Registro de Imóveis da Comarca de Capão da Canoa – RS, sob Matrícula nº 29.802, com a Inscrição Imobiliária nº 360.0038.014.000 e Código de Imóvel nº 039415 localizado nas proximidades do Hotel Araçá Ltda. Adquirido do Senhor Hugo Ferri. | C28: 220000 | D28: =G28 -> 390000 | F28: 390000 | G28: 390000 | I28: =G28-D28 -> 0
A29: 17 | B29: Um lote urbano nº 15 – Quadra nº 38, com área de 360,00m², devidamente registrado no Ofício de Registro de Imóveis da Comarca de Capão da Canoa – RS, sob Matrícula nº 33.003, com a Inscrição Imobiliária nº 360.0038.015.000 e Código de Imóvel nº 039416 localizado nas proximidades do Hotel Araçá Ltda. Adquirido do Senhor Hugo Ferri. | C29: 0 | D29: 0 | F29: 390000 | G29: 390000 | I29: =G29-D29 -> 390000
A30: 18 | B30: Um lote urbano nº 27 – Quadra nº 38, com área de 360,00m², devidamente registrado no Ofício de Registro de Imóveis da Comarca de Capão da Canoa – RS, sob Matrícula nº 73.482, com a Inscrição Imobiliária nº 360.0038.027.000 e Código de Imóvel nº 039426 localizado nas proximidades do Hotel Araçá Ltda. Lote Estacionamento do Bigode. | C30: 200000 | D30: =G30 -> 350000 | F30: 350000 | G30: 350000 | H30: 350000 | I30: =G30-D30 -> 0
A31: 19 | B31: Um lote urbano nº 28 – Quadra nº 38, com área de 360,00m², devidamente registrado no Ofício de Registro de Imóveis da Comarca de Capão da Canoa – RS, sob Matrícula nº 73.482, com a Inscrição Imobiliária nº 360.0038.028.000 e Código de Imóvel nº 039427 localizado nas proximidades do Hotel Araçá Ltda. Lote Estacionamento do Bigode. | C31: 0 | D31: 0 | F31: 350000 | G31: 350000 | H31: 350000 | I31: =G31-D31 -> 350000
A32: 20 | B32: Um lote urbano denominado de lote nº 15, da quadra nº 02, com área total de 725,39m², devidamente registrado no Ofício de Registro de Imóveis da Comarca de Capão da Canoa – RS, sob Matrícula nº 69.488, com a Inscrição Imobiliária nº 645.0027.015.000 e Código de Imóvel nº 076891 localizado no CONDADO DE CAPÃO, com casa de alvenaria com 158,18m² de área construída, adquirida em maio de 2014, por Contrato de Particular Compra e Venda, com móveis e utensílios, no valor total global de R$ 750.000,00, totalmente quitada | C32: 1000000 | D32: =G32 -> 1000000 | F32: 1000000 | G32: 1000000 | I32: =G32-D32 -> 0
A33: 21 | B33: Um lote urbano nº 15 – Quadra nº 37, com área de 360,00m², devidamente registrado no Ofício de Registro de Imóveis da Comarca de Capão da Canoa – RS, sob Matrícula nº 86.669, com a Inscrição Imobiliária nº 360.0037.015.000.000 e Código de Imóvel nº 39394, localizado nas proximidades do Hotel Araçá Ltda. – Lateral do Hotel. | C33: 0 | D33: 0 | F33: 380000 | G33: 380000 | I33: =G33-D33 -> 380000
A34: 22 | B34: Um lote urbano nº 17 – Quadra nº 37, com área de 360,00m², devidamente registrado no Ofício de Registro de Imóveis da Comarca de Osório – RS, sob Matrícula nº 124.906, com a Inscrição Imobiliária nº 360.0037.017.000.000 e Código de Imóvel nº 39396, localizado nas proximidades do Hotel Araçá Ltda. – Lateral do Hotel. | C34: 0 | D34: 0 | F34: 380000 | G34: 380000 | I34: =G34-D34 -> 380000
A35: - | B35: OBSERVAÇÕES: É necessário UNIFICAR OS LOTES ONDE ESTÁ CONSTRUÍDO O HOTEL, com mais os lotes que fazem parte do mesmo quarteirão, conforme o interesse e necessidade, para fins de efetuar a averbação da obra – prédio – na Matrícula unificada no Ofício de Registro de Imóveis da Comarca de Capão da Canoa – RS. É necessário APROVAR todos os PROJETOS DO HOTEL (arquitetônico, elétrico, hidrossanitário, etc.), conforme como a obra está executada, junto à Prefeitura Municipal de Capão da Canoa – RS, para a devida obtenção do HABITE-SE. É necessário PAGAR o I.N.S.S. DA OBRA, para fins de efetuar a averbação da obra – prédio – na Matrícula unificada no Ofício de Registro de Imóveis da Comarca de Capão da Canoa – RS. Dos bens imóveis instalados sobre a propriedade da empresa, carecem de regularização: A EDIFICAÇÃO DA PRÉDIO DO HOTEL (04 ANDARES), ÁREA DAS PISCINAS EXTERNAS E SALÃO DE CONVENÇÕES/EVENTOS: APROVAR o PROJETO junto à Prefeitura de Capão da Canoa - RS, pagar o I.N.S.S. resultante sobre a obra – HOTEL E DEPENDÊNCIAS ADJACENTES – para fins de averbação das benfeitorias na Matrícula do Imóvel Unificada, junto o Ofício de Registro de Imóveis da Comarca de Capão da Canoa – RS. Conforme cálculo realizado para projetar o custo do imposto – I.N.S.S. – resulta numa importância de aproximadamente R$ 1.601.357,90 (Hum milhão, seiscentos e um mil, trezentos e cinquenta e sete reais e noventa centavos), afora ainda os custos de: A.P.P.C.I., A.R.T., ENGENHEIRO CIVIL, TAXAS PARA UNIFICAÇÃO DOS LOTES E APROVAÇÕES, EMOLUMENTOS DE REGISTRO, dentre outras despesas afins. O valor real acima apontado não é líquido, à medida que: a) O valor patrimonial lançado no “ÍTEM 01 DO INVENTÁRIO”, sofrerá redução pela regularização do imóvel, o que se estima numa redução de aproximadamente 4,00% = R$ 2.000.000,00 (DOIS MILHÕES DE REAIS) do valor avalizado do HOTEL ARAÇÁ LTDA., afora os ônus de eventual dissolução da empresa em relação a parte de algum(ns) sócio(s). b) Há que se ter em mente, que haverá ônus de eventual dissolução da empresa em relação a parte de algum(ns) sócio(s), não podendo serem considerados como líquidos os valores alcançados na avaliação patrimonial.

Sheet 7.Rádio
B1: ESTUDO SIVIERO | C1: 2018: apresentado | D1: 2018: atualizado | E1: dezembro 2024 | G1: outubro 2025 | H1: Estudo Rafael | I1: Diferença | J1: OBSERVAÇÕES
A2: 1 | B2: Dezoito (18) terrenos urbanos, localizados dentro da Quadra 37, registrados junto ao Ofício de Registros de Imóveis em 12 (Doze) Matrículas, com a área total de 6.900,00m² (Seis mil e novecentos metros quadrados), localizado na Rua Miguel Main Felo, nº 333, na Praia do Araçá, todos devidamente registrados no Ofício de Registro de Imóveis da Comarca de Capão da Canoa – RS, sob Matrículas nº.: 34.768, 34.769, 34.770, 34.771, 6.411, 29.855, 24.584, 24.585, 33.101, 29.856, 0672 e 34.772, onde está instalado o HOTEL, prédio de 04 andares, composto por 144 apartamentos, restaurante, cozinha, sala de convenções, duas piscinas, bar interno e externo, sala de jogos, sauna, mezanino, etc., totalmente equipado e em pleno funcionamento. 04 lotes de 450,00m², cada um. (Lotes nº 01-02-03-04 – Matrícula nº 34.768). 13 lotes de 360,00m², cada um. (Lotes nº 05-22 – Matrícula nº 34.769). (Lotes nº 06-21 – Matrícula nº 34.770). (Lote nº 07 – Matrícula nº 34.771). (Lote nº 08 – Matrícula nº 6.411). (Lote nº 09 – Matrícula nº 29.855). (Lote nº 10 – Matrícula nº 24.584). (Lote nº 11 – Matrícula nº 24.585). (Lote nº 12 – Matrícula nº 33.101). (Lote nº 18 – Matrícula nº 29.856). (Lote nº 19 – Matrícula nº 0672). (Lote nº 20 – Matrícula nº 34.772). 01 lote de 420,00m² - lote da Nesga – sobra com muro. (Parte do Lote nº 12 – Matrícula nº 33.101). | C2: =SUM(C4:C9) -> 45274243 | D2: =SUM(D4:D9) -> 49606823 | F2: 53320460 | G2: =SUM(G4:G9) -> 49606823 | I2: =G2-D2 -> 0
C3: valores 2018 -> 2025: | D3: =(D2/C2)-1 -> 0.095696354
A4: 1.1 | B4: Considerado o valor comercial de R$ 1.000,00, ao metro quadrado. Valor do terreno onde está construído o Edifício – HOTEL = 6.900,00m² de terreno = R$ 6.900.000,00 (considerado o valor ao metro quadrado do mercado no Bairro Araçá e o valor da área conforme sua localização comercial). | C4: 3800000 | D4: =G4 -> 6900000 | G4: 6900000 | I4: =G4-D4 -> 0
A5: 1.2 | B5: Móveis e Equipamentos – novos, instalados nos 36 apartamentos do HOTEL, no valor unitário de R$ 42.000,00, cada apartamento = sem depreciação = R$ 1.512.000,00. | C5: 1800000 | D5: =G5 -> 1512000 | G5: 1512000 | I5: =G5-D5 -> 0
A6: 1.3 | B6: Móveis e Equipamentos, instalados nos 108 apartamentos do HOTEL, no valor unitário de R$ 30.000,00, cada apartamento = R$ 3.240.000,00 = com depreciação de 20,00% = (-) R$ 648.000,00 = R$ 2.592.000,00. | C6: 3024000 | D6: =G6 -> 2592000 | G6: 2592000 | I6: =G6-D6 -> 0
A7: 1.4 | B7: Valor do Edifício Construído – obra civil = 04 andares, com 144 apartamentos do HOTEL, cozinha, restaurante, sala de convenções, lavanderia, bares, piscinas, sala de jogos, sauna, mezanino, = 10.500,00m² de área construída X R$ 3.170,52 = R$ 33.290.460,00 (considerado o valor ao metro quadrado da construção – CUB/DEZEMBRO DE 2022 e o valor da área conforme sua localização comercial) = com depreciação de 20,00% = (-) R$ 6.658.092,00 = R$ 26.632.368,00. | C7: 20679264 | D7: =G7 -> 26632368 | G7: 26632368 | I7: =G7-D7 -> 0
A8: 1.5 | B8: Móveis e Equipamentos Diversos instalados no HOTEL: cozinha, restaurante, sala de convenções, lavanderia, recepção, poço artesiano com outorga, etc. = R$ 8.000.000,00 = com depreciação de 20,00% = (-) R$ 1.600.000,00 = R$ 6.400.000,00. | C8: 6400000 | D8: =G8 -> 6400000 | G8: 6400000 | I8: =G8-D8 -> 0
A9: 1.6 | B9: Valor do Edifício Construído – obra civil = 04 andares = 15,00% (Quinze por cento) da obra feita: R$ 37.136.368,00 (considerado o valor agregado à coisa feita, como tal se encontra) = R$ 5.570.455,20. | C9: 9570979.2 | D9: =G9 -> 5570455.2 | G9: 5570455.2 | I9: =G9-D9 -> 0
B10: Lotes | C10: =SUM(C12:C32) -> 4210000 | D10: =SUM(D12:D32) -> 6970000 | E10: =SUM(E12:E32) -> 0 | F10: =SUM(F12:F32) -> 8470000 | G10: =SUM(G12:G32) -> 8470000 | I10: =SUM(I12:I32) -> 1500000
C11: valores 2018 -> 2025: | D11: =(D10/C10)-1 -> 0.65558195
A12: 2 | B12: Um lote urbano nº 03 – Quadra nº 19, com área de 450,00m², devidamente registrado no Ofício de Registro de Imóveis da Comarca de Capão da Canoa – RS, sob Matrícula nº 77.832 (antiga matrícula 37.549), com a Inscrição Imobiliária nº 360.0019.003.000 e Código de Imóvel nº 038998, localizado nas proximidades do Hotel Araçá Ltda. – Casa da Praça. | C12: 250000 | D12: =G12 -> 400000 | F12: 400000 | G12: 400000 | I12: =G12-D12 -> 0
A13: 3 | B13: Um lote urbano nº 16 – Quadra nº 37, com área de 360,00m², devidamente registrado no Ofício de Registro de Imóveis da Comarca de Capão da Canoa – RS, sob Matrícula nº 64.782, com a Inscrição Imobiliária nº 360.0037.016.000 e Código de Imóvel nº 039395 localizado nas proximidades do Hotel Araçá Ltda. – Fundos do Hotel. | C13: 180000 | D13: =G13 -> 360000 | F13: 360000 | G13: 360000 | I13: =G13-D13 -> 0
A14: 4 | B14: Um lote urbano nº 23 – Quadra nº 37, com área de 360,00m², devidamente registrado no Ofício de Registro de Imóveis da Comarca de Capão da Canoa – RS, sob Matrícula nº 26.373, com a Inscrição Imobiliária nº 360.0071.023.000 e Código de Imóvel nº 039839 localizado nas proximidades do Hotel Araçá Ltda. – Fundos do Hotel. | C14: 180000 | D14: =G14 -> 360000 | F14: 360000 | G14: 360000 | I14: =G14-D14 -> 0
A15: 5 | B15: Um lote urbano nº 24 – Quadra nº 37, com área de 307,80m², devidamente registrado no Ofício de Registro de Imóveis da Comarca de Capão da Canoa – RS, sob Matrícula nº 26.374, com a Inscrição Imobiliária nº 360.0071.024.000 e Código de Imóvel nº 039840 localizado nas proximidades do Hotel Araçá Ltda. – Fundos do Hotel. | C15: 180000 | D15: =G15 -> 360000 | F15: 360000 | G15: 360000 | I15: =G15-D15 -> 0
A16: 6 | B16: Um lote urbano nº 25 – Quadra nº 37, com área de 307,80m², devidamente registrado no Ofício de Registro de Imóveis da Comarca de Capão da Canoa – RS, sob Matrícula nº 26.375, com a Inscrição Imobiliária nº 360.0071.025.000 e Código de Imóvel nº 039841 localizado nas proximidades do Hotel Araçá Ltda. – Fundos do Hotel. | C16: 180000 | D16: =G16 -> 360000 | F16: 360000 | G16: 360000 | I16: =G16-D16 -> 0
A17: 7 | B17: Um lote urbano nº 26 – Quadra nº 37, com área de 307,80m², devidamente registrado no Ofício de Registro de Imóveis da Comarca de Capão da Canoa – RS, sob Matrícula nº 26.376, com a Inscrição Imobiliária nº 360.0071.026.000 e Código de Imóvel nº 039842 localizado nas proximidades do Hotel Araçá Ltda. – Fundos do Hotel. | C17: 180000 | D17: =G17 -> 360000 | F17: 360000 | G17: 360000 | I17: =G17-D17 -> 0
A18: 8 | B18: Um lote urbano nº 27 – Quadra nº 37, com área de 307,80m², devidamente registrado no Ofício de Registro de Imóveis da Comarca de Capão da Canoa – RS, sob Matrícula nº 26.377, com a Inscrição Imobiliária nº 360.0071.027.000 e Código de Imóvel nº 039843 localizado nas proximidades do Hotel Araçá Ltda. – Fundos do Hotel. | C18: 180000 | D18: =G18 -> 360000 | F18: 360000 | G18: 360000 | I18: =G18-D18 -> 0
A19: 9 | B19: Um lote urbano nº 28 – Quadra nº 37, com área de 307,80m², devidamente registrado no Ofício de Registro de Imóveis da Comarca de Capão da Canoa – RS, sob Matrícula nº 26.378, com a Inscrição Imobiliária nº 360.0071.028.000 e Código de Imóvel nº 039844 localizado nas proximidades do Hotel Araçá Ltda. – Fundos do Hotel. | C19: 180000 | D19: =G19 -> 360000 | F19: 360000 | G19: 360000 | I19: =G19-D19 -> 0
A20: 10 | B20: Um lote urbano nº 29 – Quadra nº 37, com área de 360,00m², devidamente registrado no Ofício de Registro de Imóveis da Comarca de Capão da Canoa – RS, sob Matrícula nº 26.379, com a Inscrição Imobiliária nº 360.0071.029.000 e Código de Imóvel nº 039845 localizado nas proximidades do Hotel Araçá Ltda. – Fundos do Hotel. | C20: 180000 | D20: =G20 -> 360000 | F20: 360000 | G20: 360000 | I20: =G20-D20 -> 0
A21: 11 | B21: Um lote urbano nº 09 – Quadra nº 38, com área de 360,00m², devidamente registrado no Ofício de Registro de Imóveis da Comarca de Capão da Canoa – RS, sob Matrícula nº 37.846, com a Inscrição Imobiliária nº 360.0038.009.000 e Código de Imóvel nº 039410 localizado nas proximidades do Hotel Araçá Ltda. Adquirido do Senhor Hugo Ferri. | C21: 220000 | D21: =G21 -> 390000 | F21: 390000 | G21: 390000 | I21: =G21-D21 -> 0
A22: 12 | B22: Um lote urbano nº 10 – Quadra nº 38, com área de 360,00m², devidamente registrado no Ofício de Registro de Imóveis da Comarca de Capão da Canoa – RS, sob Matrícula nº 11.990, com a Inscrição Imobiliária nº 360.0038.010.000 e Código de Imóvel nº 039411 localizado nas proximidades do Hotel Araçá Ltda. Adquirido do Senhor Hugo Ferri. | C22: 220000 | D22: =G22 -> 390000 | F22: 390000 | G22: 390000 | I22: =G22-D22 -> 0
A23: 13 | B23: Um lote urbano nº 11 – Quadra nº 38, com área de 360,00m², devidamente registrado no Ofício de Registro de Imóveis da Comarca de Capão da Canoa – RS, sob Matrícula nº 43.389, com a Inscrição Imobiliária nº 360.0038.011.000 e Código de Imóvel nº 039412 localizado nas proximidades do Hotel Araçá Ltda. Adquirido do Senhor Hugo Ferri. | C23: 220000 | D23: =G23 -> 390000 | F23: 390000 | G23: 390000 | I23: =G23-D23 -> 0
... A26: 16 | B26: Um lote urbano nº 14 – Quadra nº 38, com área de 360,00m², devidamente registrado no Ofício de Registro de Imóveis da Comarca de Capão da Canoa – RS, sob Matrícula nº 29.802, com a Inscrição Imobiliária nº 360.0038.014.000 e Código de Imóvel nº 039415 localizado nas proximidades do Hotel Araçá Ltda. Adquirido do Senhor Hugo Ferri. | C26: 220000 | D26: =G26 -> 390000 | F26: 390000 | G26: 390000 | I26: =G26-D26 -> 0
A27: 17 | B27: Um lote urbano nº 15 – Quadra nº 38, com área de 360,00m², devidamente registrado no Ofício de Registro de Imóveis da Comarca de Capão da Canoa – RS, sob Matrícula nº 33.003, com a Inscrição Imobiliária nº 360.0038.015.000 e Código de Imóvel nº 039416 localizado nas proximidades do Hotel Araçá Ltda. Adquirido do Senhor Hugo Ferri. | C27: 0 | D27: 0 | F27: 390000 | G27: 390000 | I27: =G27-D27 -> 390000
A28: 18 | B28: Um lote urbano nº 27 – Quadra nº 38, com área de 360,00m², devidamente registrado no Ofício de Registro de Imóveis da Comarca de Capão da Canoa – RS, sob Matrícula nº 73.482, com a Inscrição Imobiliária nº 360.0038.027.000 e Código de Imóvel nº 039426 localizado nas proximidades do Hotel Araçá Ltda. Lote Estacionamento do Bigode. | C28: 200000 | D28: =G28 -> 350000 | F28: 350000 | G28: 350000 | I28: =G28-D28 -> 0
A29: 19 | B29: Um lote urbano nº 28 – Quadra nº 38, com área de 360,00m², devidamente registrado no Ofício de Registro de Imóveis da Comarca de Capão da Canoa – RS, sob Matrícula nº 73.482, com a Inscrição Imobiliária nº 360.0038.028.000 e Código de Imóvel nº 039427 localizado nas proximidades do Hotel Araçá Ltda. Lote Estacionamento do Bigode. | C29: 0 | D29: 0 | F29: 350000 | G29: 350000 | I29: =G29-D29 -> 350000
A30: 20 | B30: Um lote urbano denominado de lote nº 15, da quadra nº 02, com área total de 725,39m², devidamente registrado no Ofício de Registro de Imóveis da Comarca de Capão da Canoa – RS, sob Matrícula nº 69.488, com a Inscrição Imobiliária nº 645.0027.015.000 e Código de Imóvel nº 076891 localizado no CONDADO DE CAPÃO, com casa de alvenaria com 158,18m² de área construída, adquirida em maio de 2014, por Contrato de Particular Compra e Venda, com móveis e utensílios, no valor total global de R$ 750.000,00, totalmente quitada | C30: 1000000 | D30: =G30 -> 1000000 | F30: 1000000 | G30: 1000000 | I30: =G30-D30 -> 0
A31: 21 | B31: Um lote urbano nº 15 – Quadra nº 37, com área de 360,00m², devidamente registrado no Ofício de Registro de Imóveis da Comarca de Capão da Canoa – RS, sob Matrícula nº 86.669, com a Inscrição Imobiliária nº 360.0037.015.000.000 e Código de Imóvel nº 39394, localizado nas proximidades do Hotel Araçá Ltda. – Lateral do Hotel. | C31: 0 | D31: 0 | F31: 380000 | G31: 380000 | I31: =G31-D31 -> 380000
A32: 22 | B32: Um lote urbano nº 17 – Quadra nº 37, com área de 360,00m², devidamente registrado no Ofício de Registro de Imóveis da Comarca de Osório – RS, sob Matrícula nº 124.906, com a Inscrição Imobiliária nº 360.0037.017.000.000 e Código de Imóvel nº 39396, localizado nas proximidades do Hotel Araçá Ltda. – Lateral do Hotel. | C32: 0 | D32: 0 | F32: 380000 | G32: 380000 | I32: =G32-D32 -> 380000
A33: - | B33: OBSERVAÇÕES: É necessário UNIFICAR OS LOTES ONDE ESTÁ CONSTRUÍDO O HOTEL, com mais os lotes que fazem parte do mesmo quarteirão, conforme o interesse e necessidade, para fins de efetuar a averbação da obra – prédio – na Matrícula unificada no Ofício de Registro de Imóveis da Comarca de Capão da Canoa – RS. É necessário APROVAR todos os PROJETOS DO HOTEL (arquitetônico, elétrico, hidrossanitário, etc.), conforme como a obra está executada, junto à Prefeitura Municipal de Capão da Canoa – RS, para a devida obtenção do HABITE-SE. É necessário PAGAR o I.N.S.S. DA OBRA, para fins de efetuar a averbação da obra – prédio – na Matrícula unificada no Ofício de Registro de Imóveis da Comarca de Capão da Canoa – RS. Dos bens imóveis instalados sobre a propriedade da empresa, carecem de regularização: A EDIFICAÇÃO DA PRÉDIO DO HOTEL (04 ANDARES), ÁREA DAS PISCINAS EXTERNAS E SALÃO DE CONVENÇÕES/EVENTOS: APROVAR o PROJETO junto à Prefeitura de Capão da Canoa - RS, pagar o I.N.S.S. resultante sobre a obra – HOTEL E DEPENDÊNCIAS ADJACENTES – para fins de averbação das benfeitorias na Matrícula do Imóvel Unificada, junto o Ofício de Registro de Imóveis da Comarca de Capão da Canoa – RS. Conforme cálculo realizado para projetar o custo do imposto – I.N.S.S. – resulta numa importância de aproximadamente R$ 1.601.357,90 (Hum milhão, seiscentos e um mil, trezentos e cinquenta e sete reais e noventa centavos), afora ainda os custos de: A.P.P.C.I., A.R.T., ENGENHEIRO CIVIL, TAXAS PARA UNIFICAÇÃO DOS LOTES E APROVAÇÕES, EMOLUMENTOS DE REGISTRO, dentre outras despesas afins. O valor real acima apontado não é líquido, à medida que: a) O valor patrimonial lançado no “ÍTEM 01 DO INVENTÁRIO”, sofrerá redução pela regularização do imóvel, o que se estima numa redução de aproximadamente 4,00% = R$ 2.000.000,00 (DOIS MILHÕES DE REAIS) do valor avalizado do HOTEL ARAÇÁ LTDA., afora os ônus de eventual dissolução da empresa em relação a parte de algum(ns) sócio(s). b) Há que se ter em mente, que haverá ônus de eventual dissolução da empresa em relação a parte de algum(ns) sócio(s), não podendo serem considerados como líquidos os valores alcançados na avaliação patrimonial.
A35: 7 | B35: RÁDIO COMUNIDADE PRINCESA DOS VALES FM LTDA | C35: =SUM(C37:C43) -> 2338000 | D35: =SUM(D37:D43) -> 2698000 | E35: =SUM(E37:E43) -> 0 | F35: =SUM(F37:F43) -> 2698000 | G35: =SUM(G37:G43) -> 2698000 | H35: =SUM(H36:H43) -> 70000 | I35: =SUM(I37:I43) -> 0
C36: valores 2018 -> 2025: | D36: =(D35/C35)-1 -> 0.15397776 | F36: =SUM(F37:F42) -> 2628000 | I36: mesmo patrimônio
A37: 1 | B37: Uma sala comercial nº 311 – ESTÚDIO – localizada na Avenida Osvaldo Aranha, nº 1395, Sala nº 311, Bairro Palugana, do Edifício Centro Comercial e Profissional Comendador José de Mello, na cidade de Veranópolis – RS. Área total de 94,51m². Imóvel devidamente registrado no Ofício de Registro de Imóveis da Comarca de Veranópolis – RS, sob Matrícula nº 11.382. Adquirida pelo valor de R$ 100.000,00. | C37: 120000 | D37: =G37 -> 210000 | F37: 210000 | G37: 210000 | I37: =G37-D37 -> 0
A38: 2 | B38: Móveis, instalações e utensílios. | C38: 150000 | D38: =G38 -> 150000 | F38: 150000 | G38: 150000 | I38: =G38-D38 -> 0
A39: 3 | B39: Equipamentos instalados no ESTÚDIO, como: computadores, telefones, demais equipamentos eletrônicos e de transmissão. Considerado o canal FM 96.1 + a concessão junto ao Ministério das Comunicações e clientes. | C39: 1700000 | D39: =G39 -> 1900000 | F39: 1900000 | G39: 1900000 | I39: =G39-D39 -> 0
A40: 4 | B40: Antena de transmissão, casa de equipamentos e gerador (não considerado o imóvel onde estão instalados estes itens. | C40: 300000 | D40: =G40 -> 300000 | F40: 300000 | G40: 300000 | I40: =G40-D40 -> 0
A41: 5 | B41: Um BOX de estacionamento de carro, localizado na Avenida Osvaldo Aranha, nº 1395, Sala nº 311, Bairro Palugana, do Edifício Centro Comercial e Profissional Comendador José de Mello, na cidade de Veranópolis – RS. Área de 17,28², devidamente Registrado no Ofício de Registro de Imóveis da Comarca de Veranópolis – RS, sob Matrícula nº 11.324. | C41: 20000 | D41: =G41 -> 40000 | F41: 40000 | G41: 40000 | I41: =G41-D41 -> 0
A42: 6 | B42: Um veículo carro FOX, marca-modelo VOLKS, combustível gasolina/álcool, ano 2011, modelo 2011, cor predominante preta, placa IRO 2562, emplacado na cidade de Veranópolis – RS. | C42: 28000 | D42: =G42 -> 28000 | F42: 28000 | G42: 28000 | I42: =G42-D42 -> 0
A43: 7 | B43: Um veículo TOYOTA / BANDEIRANTE, marca-modelo TOYOTA, combustível diesel, ano 1980, modelo 1980, cor predominante verde, placa IHW 0285, emplacado na cidade de Veranópolis – RS. | C43: 20000 | D43: 70000 | F43: 70000 | G43: 70000 | H43: 70000 | I43: =G43-D43 -> 0
A44: - | B44: Observações: O valor do canal da concessão da Rádio foi estimado por algumas informações verbais, no passado, do Senhor Élcio Siviero, com referência ao valor comercial da mesma – canal de concessão e outorga do mesmo junto ao Ministério das Comunicações. A antena de transmissão está instalada em um lote urbano localizado na Rodovia BR 470, ao lado da Abastecedora de Combustíveis Siviero Ltda., devidamente registrado no Ofício de Registro de Imóveis da Comarca de Veranópolis, sob Matrícula nº 3.751, com área de 7.200,00m², de propriedade da empresa Siviero Empreendimentos Imobiliários Ltda., HAVENDO UM CUSTO PARA O DESLOCAMENTO DA ANTENA (DESMONTAGEM E MONTAGEM + CASA DE TRANSMISSÃO + INSTALAÇÃO ELÉTRICA, ETC) E O CUSTO PARA A AQUISIÇÃO DE UM TERRENO APROPRIADO PARA TAL FINALIDADE. O valor real acima apontado não é líquido, à medida que: a) O valor patrimonial lançado sofrerá redução pela regularização dos imóveis, o que se estima numa redução de 8,0% (OITO POR CENTO) do valor acima apontado, afora os ônus de eventual dissolução da empresa em relação a parte de algum(ns) sócio(s). b) Há que se ter em mente, que haverá ônus de eventual dissolução da empresa em relação a parte de algum(ns) sócio(s), não podendo serem considerados como líquidos os valores alcançados na avaliação patrimonial.

Sheet 8.Transportadora
B1: ESTUDO SIVIERO | C1: 2018: apresentado | D1: 2018: atualizado | E1: dezembro 2024 | G1: outubro 2025 | H1: Diferença | I1: OBSERVAÇÕES
A2: 8 | B2: TRANSPORTADORA IRMÃOS SIVIERO LTDA. | C2: =SUM(C4:C18) -> 12285999 | D2: =SUM(D4:D18) -> 16553986 | E2: =SUM(E4:E18) -> 0 | F2: =SUM(F4:F18) -> 16374986 | G2: =SUM(G4:G18) -> 16374986 | H2: =SUM(H4:H18) -> -179000
C3: valores 2018 -> 2025: | D3: =(D2/C2)-1 -> 0.34738626 | F3: =SUM(F4:F9) -> 11924986 | H3: =IF(H2<0,"patrimônio diminuiu","patrimônio aumentou") -> patrimônio diminuiu
A4: 1 | B4: Um terreno urbano, com a área de 8.700,00m², localizado na Rodovia BR 470, Km 175,4, no Bairro São Pelegrino, devidamente registrado no Ofício de Registro de Imóveis da Comarca de Veranópolis, sob Matrícula nº 3.753, que faz fundos e acesso na lateral com a área da Abastecedora de Combustíveis Siviero Ltda., onde está instalada a OFICINA MECÂNICA = considerado o valor de R$ 992,78, ao metro quadrado. | C4: 8637186 | D4: =G4 -> 8637186 | F4: 8637186 | G4: 8637186 | H4: =G4-D4 -> 0
A5: 2 | B5: Um pavilhão novo – em fase FINAL de construção – onde está sendo instalada a OFICINA MECÂNICA, não sendo considerado o valor da construção do mezanino com área construída de 1.298,00m² - valor de R$ 1.100,00, ao metro = R$ 1.427.800,00. Valor do Pavilhão construído – obra civil = 30,00% (Trinta por cento) da obra feita: R$ 0,00 (considerado o valor agregado à coisa feita, como tal se encontra). NÃO FOI CALCULADO – CARECE AINDA DE REGULARIZAÇÃO DA OBRA JUNTO À PREFEITURA MUNICIPAL (APROVAÇÃO DO PROJETO), A.P.P.C.I. E PAGAMENTO DO I.N.S.S. DA OBRA. | C5: 1259812.8 | D5: =G5 -> 1427800 | F5: 1427800 | G5: 1427800 | H5: =G5-D5 -> 0
A6: 3 | B6: Equipamentos em geral, como: macacos, guindastes; ferramentas em geral de todas as espécies e de necessidade para o funcionamento da oficina mecânica, peças, óleos e graxas – todo o estoque existente na oficina, telefone, câmeras de monitoramento, etc. | C6: 500000 | D6: =G6 -> 500000 | F6: 500000 | G6: 500000 | H6: =G6-D6 -> 0
A7: 4 | B7: Uma rampa de lavagem devidamente licenciada para lavagem de caminhões pesados e carros, que pode ser utilizada para fins próprios ou manter locada para terceiros. Os equipamentos são de propriedade da empresa locatária. Valor do Pavilhão construído – obra civil = 30,00% (Trinta por cento) da obra feita: R$ 0,00 (considerado o valor agregado à coisa feita, como tal se encontra). NÃO FOI CALCULADO – CARECE AINDA DE REGULARIZAÇÃO DA OBRA JUNTO À PREFEITURA MUNICIPAL (APROVAÇÃO DO PROJETO), A.P.P.C.I. E PAGAMENTO DO I.N.S.S. DA OBRA. | C7: 300000 | D7: =G7 -> 300000 | F7: 300000 | G7: 300000 | H7: =G7-D7 -> 0
A8: 5 | B8: Uma borracharia, que pode ser utilizada para fins próprios ou manter locada para terceiros. Os equipamentos são de propriedade da empresa locatária. Valor do Pavilhão construído – obra civil = 30,00% (Trinta por cento) da obra feita: R$ 0,00 (considerado o valor agregado à coisa feita, como tal se encontra). NÃO FOI CALCULADO – CARECE AINDA DE REGULARIZAÇÃO DA OBRA JUNTO À PREFEITURA MUNICIPAL (APROVAÇÃO DO PROJETO), A.P.P.C.I. E PAGAMENTO DO I.N.S.S. DA OBRA. | C8: 25000 | D8: =G8 -> 220000 | F8: 220000 | G8: 220000 | H8: =G8-D8 -> 0
A9: 6 | B9: Uma sala comercial, utilizada com o escritório das empresas, localizada na Avenida Pinheiro Machado, nº 710, Sala nº 01, Bairro Centro, no Edifício Luiz Siviero, na cidade de Veranópolis – RS, com área de 243,30m², devidamente registrada no Ofício de Registros de Imóveis da Comarca de Veranópolis – RS, sob Matrícula nº 7.393. CUB ao metro quadrado X R$ 3.236,85 + instalações. | C9: 685000 | D9: =G9 -> 840000 | F9: 840000 | G9: 840000 | H9: =G9-D9 -> 0
A10: 7 | B10: Uma área de terras rurais, denominada de LOTES RURAIS Nº 63, 65, 66 e LETRA “N”, com área total de 69,8 hectares, localizada na Linha Júlio de Castilhos, Capela de São Brás, no Município de Cotiporã – RS, área esta registrada sob Matrículas nº.: 459, 460, 461 e 558. Considerado o valor médio de R$ 50.000,00, ao ha. Matrículas nº 459, 460, 461 e 558 = 69,8 hectares. Cadastrada no CCIR – Receita Federal sob nº 2.898.227-4 | C10: ? | D10: =G10 -> 3500000 | F10: 3500000 | G10: 3500000 | H10: =G10-D10 -> 0
A11: 8 | B11: Uma área de terras rurais, denominada de Parte do lote Rural nº 63, da Linha Dr. Júlio de Castilhos, com área total de 4,5 hectares, DENTRO DE UM TODO MAIOR, localizada ao lado das terras na Capela de São Brás, no Município de Cotiporã – RS, adquirida do Senhor Tercílio Dal Más, área está registrada sob Registro nº.: 15.922 = 4,5 hectares. Considerado o valor médio de R$ 50.000,00, ao ha. Cadastrada no CCIR – Receita Federal sob nº ......... Adquirida por CONTRATO DE COMPRA E VENDA, datado de 25 setembro de 2008, pelo valor de R$ 50.000,00. | C11: ? | D11: =G11 -> 250000 | F11: 250000 | G11: 250000 | H11: =G11-D11 -> 0
A12: 9 | B12: Um apartamento residencial, localizado na Avenida Pinheiro Machado, nº 710, denominado de nº 401, Bairro Centro, no Edifício Luiz Siviero, na cidade de Veranópolis – RS, com área total de 168,91m², área privativa de 127,05m², devidamente registrado no Ofício de Registros de Imóveis da Comarca de Veranópolis – RS, sob Matrícula nº 7.400. | C12: 360000 | D12: =G12 -> 360000 | F12: 360000 | G12: 360000 | H12: =G12-D12 -> 0
A13: 10 | B13: Um veículo caminhão SCANIA = PLACA IKR 2054, ano 2002. Trabalha para a JBS – Thiago Binda. | C13: 140000 | D13: =G13 -> 140000 | F13: 140000 | G13: 140000 | H13: =G13-D13 -> 0
A14: 11 | B14: Uma carreta RANDON = PLACA IQB 0612, ano 2009. | C14: 30000 | D14: =G14 -> 30000 | F14: 30000 | G14: 30000 | H14: =G14-D14 -> 0
A15: 12 | B15: Um veículo caminhão SCANIA = PLACA IJZ 5399, ano 2001. Trabalha para a SEI – prancha. | C15: 140000 | D15: =G15 -> 140000 | F15: 140000 | G15: 140000 | H15: =G15-D15 -> 0
A16: 13 | B16: Uma carreta RANDON = PLACA IJZ 8207, ano 2001. | C16: 30000 | D16: =G16 -> 30000 | F16: 30000 | G16: 30000 | H16: =G16-D16 -> 0
A17: A.1 | B17: Uma sala comercial, utilizada com o consultório da Fisioterapeuta Araceli Siviero, localizada na Avenida Dr. José Montaury, nº 1678, Sala nº 01, Bairro Palugana, no Edifício Dona Ângela Siviero, na cidade de Veranópolis – RS, com área de 52,91m², devidamente registrada no Ofício de Registros de Imóveis da Comarca de Veranópolis – RS, sob Matrícula nº 18.952. 02 CUB ao metro quadrado X R$ 1.407,45. | C17: 149000 | D17: 149000 | G17: 0 | H17: =G17-D17 -> -149000
A18: A.2 | B18: Móveis, materiais diversos (mesas, cadeiras, telefone, etc...), equipamentos de informática e outros equipamentos instalados no Escritório das empresas Siviero, na cidade de Veranópolis – RS, na Avenida Pinheiro Machado, nº 710 – Sala nº 01, Bairro Centro. | C18: 30000 | D18: 30000 | G18: 0 | H18: =G18-D18 -> -30000
A19: - | B19: OBSERVAÇÕES: Conforme INSTRUMENTO PARTICULAR DE COMPRA E VENDA DE QUOTAS DE CAPITAL, NA SOCIEDADE DE EMPRESAS DE RESPONSABILIDADE LIMITADA, datado de 28 de agosto de 2025, o Sócio ROVÍLIO SIVIERO, brasileiro, natural de Veranópolis – RS, Odontólogo, residente e domiciliado na Rua Carijós, nº 427, Bairro Vila Fátima, na cidade de Passo Fundo – RS, CEP.: 99.020-110, inscrito no CPF/MF sob nº 225.676.150-91 e portador da Carteira de Identidade nº 4017098015, emitida pela SSP – RS, casado pelo Regime de Comunhão Universal de Bens com Maristela Pretto Siviero, brasileira, professora, filha de Alberto José Pretto e de Iracema Antônia Pretto, inscrita no CPF/MF sob nº 260.949.670/20 e portadora da Carteira de Identidade nº 22.827.317-1, emitida pela SSP – SC, efetuaram a VENDA das quotas que lhes pertenciam à empresa, diluídas em partes iguais aos demais sócios remanescentes. A empresa possui um PROCESSO JUDICIAL em tramitação para cobrança de um valor de aproximadamente R$ 340.000,00 (Trezentos e quarenta mil reais), corrigidos e tratando-se de acordo judicial, NÃO significa que este será o valor ajustado, podendo sofrer consideráveis alterações para viabilização do acordo, contra as empresas: JOVENI TRANSPORTES LTDA. x JBS x FRANGOSUL, referente aos meses de dezembro de 2011, janeiro, fevereiro, março e abril de 2012). O ingresso deu-se, faz-se de não aceitarmos a proposta de pagamento, em 76 (Setenta e seis) parcelas, sem correção. PROCESSO SOTTILI – BAHIA O processo está com o Juiz desde novembro de 2024 para homologar ou não o acordo, que a seguradora fez com a autora. Em caso de condenação, o pedido é 01 (um) salário mínimo até que o menino completasse 25 anos. Ele nasceu em 23.05.1996, ou seja, completaria os 25 anos em maio de 2021 e, + 1.000 salários mínimos de dano moral. Cálculo: PENSÃO R$ 1.518,00 x 12 meses = R$ 18.216,00 x 20 anos = R$ 364.320,00 (considerado o valor atualizado do salário mínimo e por isso não incluso os juros). DANO MORAL R$ 1.518,00 x 1.000 = R$ 1.518.000,00. O dano moral não seria deferido nesse patamar, mas se o Juiz julgar a condenação de 150 salários mínimos na época do acidente com juros desde então (02.04.2001), teremos: O valor do salário mínimo da época de R$ 180,00 x 150 = R$ 27.000,00 com juros de 12,00% ao ano + correção monetária = R$ 627.000,00. Trata-se de uma condenação superior a R$ 1.000.000,00 (HUM MILHÃO DE REAIS). Dos bens imóveis instalados sobre uma das propriedades da empresa, carecem ainda de regularização: PAVILHÃO DA OFICINA MECÂNICA: APROVAR o PROJETO do PAVILHÃO junto à Prefeitura de Veranópolis, pagar o I.N.S.S. resultante sobre a obra – Pavilhão da Oficina – para fins de averbação da benfeitoria na Matrícula do Imóvel, junto o Ofício de Registro de Imóveis da Comarca de Veranópolis – RS. Conforme cálculo realizado para projetar o custo do imposto – I.N.S.S. – resulta numa importância de aproximadamente R$ 122.254,73 (Cento e vinte e dois mil, duzentos e cinquenta e quatro reais e setenta e três centavos), afora ainda os custos de: A.P.P.C.I., A.R.T., ENGENHEIRO CIVIL, TAXA DE APROVAÇÃO, EMOLUMENTOS DE REGISTRO, dentre outras despesas afins. PAVILHÃO DA BORRACHARIA E RAMPA DE LAVAGEM: APROVAR o PROJETO destes PAVILHÕES junto à Prefeitura de Veranópolis, pagar o I.N.S.S. resultantes sobre as obras – para fins de averbação das benfeitorias na Matrícula do Imóvel, junto o Ofício de Registro de Imóveis da Comarca de Veranópolis – RS. Conforme cálculo realizado para projetar o custo do imposto – I.N.S.S. – resulta numa importância de aproximadamente R$ 62.555,51 (Sessenta e dois mil, quinhentos e cinquenta e cinco reais e cinquenta e um centavos), afora ainda os custos de: A.P.P.C.I., A.R.T., ENGENHEIRO CIVIL, TAXA DE APROVAÇÃO, EMOLUMENTOS DE REGISTRO, dentre outras despesas afins. O valor real acima apontado não é líquido, à medida que: O valor patrimonial lançado sofrerá redução pela regularização dos imóveis, o que se estima numa redução de 1,50% (HUM VÍRGULA CINQUENTA POR CENTO) do valor acima apontado, afora os ônus de eventual dissolução da empresa em relação a parte de algum(ns) sócio(s). Há que se ter em mente, que haverá ônus de eventual dissolução da empresa em relação a parte de algum(ns) sócio(s), não podendo serem considerados como líquidos os valores alcançados na avaliação patrimonial. FOI ACRESCENTADO O VALOR DO CAPITAL DE BENS A IMPORTÂNCIA DE R$ 1.135.000,00 AO VALOR CONSTANTE NO BALANÇO PATRIMONIAL (CÓDIGO 1060) – ITENS 03 – 04 – 05.

Sheet 10.Transportes
B1: ESTUDO SIVIERO | C1: 2018: apresentado | D1: 2018: atualizado | E1: dezembro 2024 | G1: outubro 2025 | H1: Diferença | I1: OBSERVAÇÕES
A2: 10 | B2: SIVIERO TRANSPORTES LTDA. | C2: =SUM(C5:C7) -> 908000 | D2: =SUM(D5:D7) -> 908000 | E2: =SUM(E5:E7) -> 0 | F2: =SUM(F5:F7) -> 0 | G2: =SUM(G5:G7) -> 0 | H2: =SUM(H5:H7) -> -908000
C3: valores 2018 -> 2025: | D3: =(D2/C2)-1 -> 0 | F3: =SUM(F14:F15) -> 0 | H3: =IF(H2<0,"patrimônio diminuiu","patrimônio aumentou") -> patrimônio diminuiu
A5: A.1 | B5: Um veículo ônibus PLACA IUY 8068 – MARCOPOLO VOLARE, ano 2014, no valor comercial de R$ 250.000,00 (está financiado). | C5: 250000 | D5: =C5 -> 250000 | G5: 0 | H5: =G5-D5 -> -250000
A6: A.2 | B6: Um veículo ônibus PLACA IAZ 0281 – MERCEDES BENZ, ano 1993, no valor comercial de R$ 70.000,00 (está quitado) – carro que fazia a Linha de Cotiporã. | C6: 70000 | D6: =C6 -> 70000 | G6: 0 | H6: =G6-D6 -> -70000
A7: A.3 | B7: Um veículo ônibus PLACA ISS 7019 – SCANIA / MPOLO PARADISO, ano 2011, no valor comercial de R$ 588.000,00. | C7: 588000 | D7: =C7 -> 588000 | G7: 0 | H7: =G7-D7 -> -588000
A14: - | B14: Observações: Conforme INSTRUMENTO PARTICULAR DE COMPRA E VENDA DE QUOTAS DE CAPITAL, NA SOCIEDADE DE EMPRESAS DE RESPONSABILIDADE LIMITADA, datado de 28 de agosto de 2025, o Sócio ROVÍLIO SIVIERO, brasileiro, natural de Veranópolis – RS, Odontólogo, residente e domiciliado na Rua Carijós, nº 427, Bairro Vila Fátima, na cidade de Passo Fundo – RS, CEP.: 99.020-110, inscrito no CPF/MF sob nº 225.676.150-91 e portador da Carteira de Identidade nº 4017098015, emitida pela SSP – RS, casado pelo Regime de Comunhão Universal de Bens com Maristela Pretto Siviero, brasileira, professora, filha de Alberto José Pretto e de Iracema Antônia Pretto, inscrita no CPF/MF sob nº 260.949.670/20 e portadora da Carteira de Identidade nº 22.827.317-1, emitida pela SSP – SC, efetuaram a VENDA das quotas que lhes pertenciam à empresa, diluídas em partes iguais aos demais sócios remanescentes. O BALANÇO PATRIMONIAL E CONTÁBIL ESTÁ PRONTO E CONFERIDO, PELA ESCRITA CONTÁBIL NESSA DATA, QUE NÃO CORRESPONDE À REALIDADE FÁTICA DA EMPRESA. EMPRESA BAIXADA EM 08 DE ABRIL DE 2024, CONFORME CERTIDÃO................. É necessário fazer a rescisão do Contrato Particular das Quotas Societárias e dar baixa dos lançamentos na Declaração do Imposto de Renda das Pessoas Físicas, junto à Receita Federal. Observações: O valor real acima apontado não é líquido, à medida que: a) O valor patrimonial lançado sofrerá redução pela regularização dos imóveis, o que se estima numa redução de 0,00% (ZERO POR CENTO) do valor acima apontado, afora os ônus de eventual dissolução da empresa em relação a parte de algum(ns) sócio(s). b) Há que se ter em mente, que haverá ônus de eventual dissolução da empresa em relação a parte de algum(ns) sócio(s), não podendo serem considerados como líquidos os valores alcançados na avaliação patrimonial. c) Existe pendente um PROCESSO JUDICIAL referente a venda do Ônibus IXO 6000, acordado pelo valor de R$ 115.000,00, sendo pagos de forma parcelada: R$ 20.000,00 (Despesas judiciais e advocatícias) e o saldo em parcelas de R$ 5.000,00, cada, a contar de novembro de 2024.

Sheet 11.Empreendimentos
B1: ESTUDO SIVIERO | C1: 2018: apresentado | D1: 2018: atualizado | E1: dezembro 2024 | G1: outubro 2025 | H1: Estudo Rafael | I1: Diferença | J1: OBSERVAÇÕES
A2: 11 | B2: SIVIERO EMPREENDIMENTOS IMOBILIÁRIOS LTDA. | C2: =C4+C665 -> 1.3747126e+08 | D2: =D4 -> 2.6628e+08 | G2: =G4 -> 1.5266026e+08 | H2: =SUM(H3:H759) -> 39288379
C3: valores 2018 -> 2025: | F3: =SUM(F4:F10) -> 987000 | I3: =IF(I2<0,"patrimônio diminuiu","patrimônio aumentou") -> patrimônio aumentou
A4: 11.1 | B4: PATRIMÔNIO | C4: =C6+C30+C48+C63+C67+C74+C93 -> 1.3747126e+08 | D4: =D6+D30+D48+D67+D74+D93 -> 2.6628e+08 | G4: =G6+G30+G48+G67+G74+G93 -> 1.5266026e+08 | I4: =G4-D4 -> -1.1361974e+08
D5: =(D4/C4)-1 -> 0.93698666 | I5: =IF(#REF!<0,"patrimônio diminuiu","patrimônio aumentou") -> #REF!
A6: 11.1.1 | B6: Veículos | C6: =SUM(C8:C28) -> 983000 | D6: =SUM(D8:D28) -> 963000 | F6: =SUM(E8:E22) -> 987000 | G6: =SUM(G8:G28) -> 1217000 | I6: =SUM(I8:I28) -> 254000
C7: =COUNTIF(C8:C29,">1") -> 18 | D7: =(D6/C6)-1 -> -0.02034588 | G7: =COUNTIF(G8:G29,">1") -> 15
A8: 1 | B8: Um veículo caminhão basculante, marca VW = PLACA IUV 8D25, cor branca, ano 2013, adquirido da empresa Dalfovo. | valor: R$ 198.000,00 | C8: 198000 | D8: 198000 | E8: 198000 | G8: 198000 | I8: =G8-D8 -> 0
A9: 2 | B9: Um veículo caminhão basculante, marca VW = PLACA IUV 8D09, cor branca, ano 2013, adquirido da empresa Dalfovo. | valor: R$ 198.000,00 | C9: 198000 | D9: 198000 | E9: 198000 | G9: 198000 | I9: =G9-D9 -> 0
A10: 3 | B10: Um veículo caminhão basculante, marca MERCEDES BENZ, L1620 = PLACA ILQ 1739, cor cinza, ano 2003. | valor: R$ 98.000,00 | C10: 98000 | D10: 98000 | E10: 98000 | G10: 98000 | I10: =G10-D10 -> 0
A11: 4 | B11: Um veículo caminhão basculante, marca MERCEDES BENZ, = PLACA IBP 3873, cor vermelha, ano 1990. | valor: R$ 53.000,00 | C11: 53000 | D11: 53000 | E11: 53000 | G11: 53000 | I11: =G11-D11 -> 0
A12: 5 | B12: Um veículo caminhão SCANIA = PLACA IIQ 0751, cor laranja, ano 1963. | valor: R$ 28.000,00 | C12: 28000 | D12: 28000 | E12: 28000 | G12: 25000 | I12: =G12-D12 -> -3000
A13: 6 | B13: Um semirreboque RANDON = PLACA IHP 6632, cor amarelo, ano 1990. | valor: R$ 25.000,00 | C13: 25000 | D13: 25000 | E13: 25000 | G13: 25000 | I13: =G13-D13 -> 0
A14: 7 | B14: Um veículo Mercedinha, marca MERCEDES BENZ, L608 = PLACA BWF 0672, cor vermelha, ano 1979. | valor: R$ 20.000,00 | C14: 20000 | D14: 20000 | E14: 20000 | G14: 20000 | I14: =G14-D14 -> 0
A15: 8 | B15: Um veículo caminhão basculante, marca MERCEDES BENZ, L1316 = PLACA IHZ 0172, cor vermelha, ano 1984. | valor: R$ 50.000,00 | C15: 50000 | D15: 50000 | E15: 50000 | G15: 50000 | I15: =G15-D15 -> 0
A16: 9 | B16: Um veículo caminhão basculante, marca MERCDES BENZ = PLACA IHW 8294, cor grená, ano 1974. | valor: R$ 30.000,00 | C16: 30000 | D16: 30000 | E16: 30000 | G16: 30000 | I16: =G16-D16 -> 0
A17: 10 | B17: Um veículo caminhão, marca SCÂNIA = PLACA IHK 2435, cor laranja, ano 1967. | valor: R$ 0.000,00 | C17: 40000 | D17: 25000 | E17: 0 | G17: 25000 | I17: =G17-D17 -> 0 | J17: Em 2018 valia R$40mil. Diferença provável depreciação
A18: 11 | B18: Uma camionete TOYOTA HILUX, cor preta, ano 2018 = PLACA IYJ 8I14. | valor: R$ 188.000,00 | C18: 0 | D18: 0 | E18: 0 | G18: 188000 | I18: =G18-D18 -> 188000
A19: 12 | B19: Um veículo caminhão, marca SCÂNIA = PLACA IIX 8288, cor laranja, ano 1963. | valor: R$ 30.000,00 | C19: 30000 | D19: 25000 | E19: 30000 | G19: 25000 | I19: =G19-D19 -> 0 | J19: Em 2018 valia R$35mil. Diferença provável depreciação
A20: 13 | B20: Um carro automóvel FORD, cor vermelha, ano 1929 = PLACA IKR 3B22 – FUBICA. | valor: R$ 40.000,00 | C20: 40000 | D20: 40000 | E20: 40000 | G20: 60000 | I20: =G20-D20 -> 20000
A21: 14 | B21: Uma camionete FORD RANGER, cor prata, ano 2010 = PLACA NPQ OI67. | valor: R$ 67.000,00 | C21: 0 | D21: 0 | E21: 67000 | G21: 67000 | H21: 67000 | I21: =G21-D21 -> 67000
A22: 15 | B22: Um veículo JEEP COMPASS = PLACA GHX 9I84, cor cinza, ano 2022. | valor: R$ 150.000,00 | C22: 0 | D22: 0 | E22: 150000 | G22: 155000 | I22: =G22-D22 -> 155000
A23: 1 | B23: Um veículo DODGE = PLACA IQJ 5001, cor azul, ano 1978. VENDIDO PELO VALOR DE R$ 30.000,00, EM TROCA DE PALANQUES E POSTES DE MADEIRA. | C23: 30000 | D23: 30000 | E23: 0 | G23: 0 | I23: =G23-D23 -> -30000
A24: =A23+1 -> 2 | B24: Um semirreboque ARTESANAL = PLACA IIH 6326, cor branca, ano 1986. | valor: R$ 20.000,00 | C24: 20000 | D24: 20000 | E24: 20000 | G24: 0 | I24: =G24-D24 -> -20000
A25: =A24+1 -> 3 | B25: Um veículo camionete, marca FORD, F1000 TURBO XL = PLACA IIO 5901, cor prata, ano 1998 – Pedro Siviero. | C25: 35000 | D25: 35000 | E25: 0 | G25: 0 | I25: =G25-D25 -> -35000
A26: =A25+1 -> 4 | B26: Um veículo camionete, marca FORD, F1000 4x4 = PLACA IHP 6607, cor prata, ano 1994 – Válter Siviero. | C26: 33000 | D26: 33000 | E26: 0 | G26: 0 | I26: =G26-D26 -> -33000
A27: =A26+1 -> 5 | B27: Um veículo GOL, marca VW 1.6 = PLACA IQS 7696, cor cinza, ano 2010 – João Lunelli. | C27: 25000 | D27: 25000 | E27: 0 | G27: 0 | I27: =G27-D27 -> -25000
A28: =A27+1 -> 6 | B28: Um veículo caminhão, marca SCÂNIA = PLACA IIX 8288, cor laranja, ano 1963. | valor: R$ 30.000,00 | C28: 30000 | D28: 30000 | E28: 0 | G28: 0 | I28: =G28-D28 -> -30000
I29: =IF(or(#REF!=0,#REF!=""),"",IF((#REF!-#REF!)=0,"",IF(AND(#REF!<>0,or(#REF!=0,#REF!="")),"verificar situação",IF((#REF!-#REF!)<>0,#REF!-#REF!,"ERRO")))) -> #REF!
A30: 11.1.2 | B30: Máquinas | C30: =SUM(C32:C46) -> 1350000 | D30: =SUM(D32:D46) -> 1180000 | F30: =SUM(F32:F46) -> 2637000 | G30: =SUM(G32:G46) -> 2517000 | I30: =G30-D30 -> 1337000
C31: =COUNTIF(C32:C46,">1") -> 12 | D31: =(D30/C30)-1 -> -0.12592593 | G31: =COUNTIF(G32:G46,">1") -> 14
A32: 1 | B32: Uma Escavadeira Hidráulica, ano 2024, modelo 320, CATERPILLAR. | valor: R$ 887.000,00 | C32: 0 | D32: 0 | F32: 887000 | G32: 887000 | I32: =G32-D32 -> 887000
A33: =A32+1 -> 2 | B33: Uma Escavadeira Hidráulica, ano 2014, modelo 320DL, CATERPILLAR. | valor: R$ 400.000,00 | C33: 400000 | D33: 350000 | F33: 400000 | G33: 350000 | I33: =G33-D33 -> 0 | J33: Em 2018 valia R$400mil. Diferença provável depreciação
A34: =A33+1 -> 3 | B34: Uma Escavadeira Hidráulica, ano 2009, modelo 320D, CATERPILLAR – SEI. | valor: R$ 200.000,00 | C34: 250000 | D34: 200000 | F34: 200000 | G34: 200000 | I34: =G34-D34 -> 0 | J34: Em 2018 valia R$250mil. Diferença provável depreciação
A35: =A34+1 -> 4 | B35: Um Trator de Esteira D6, ano 1980. | valor: R$ 80.000,00 | C35: 80000 | D35: 80000 | F35: 80000 | G35: 80000 | I35: =G35-D35 -> 0
A36: =A35+1 -> 5 | B36: Um Trator de Esteira D6, ano..... | valor: R$ 100.000,00 | C36: 100000 | D36: 80000 | F36: 100000 | G36: 80000 | I36: =G36-D36 -> 0 | J36: Em 2018 valia R$100mil. Diferença provável depreciação
A37: =A36+1 -> 6 | B37: Um Trator de Esteira D6, ano..... | valor: R$ 100.000,00 | C37: 100000 | D37: 50000 | F37: 100000 | G37: 50000 | I37: =G37-D37 -> 0 | J37: Em 2018 valia R$100mil. Diferença provável depreciação
A38: =A37+1 -> 7 | B38: Uma Retroescavadeira CASE 580L, ano 2001, PLACA IKI 4827. | valor: R$ 60.000,00 | C38: 60000 | D38: 60000 | F38: 60000 | G38: 60000 | I38: =G38-D38 -> 0
A39: =A38+1 -> 8 | B39: Uma Pá carregadeira, ano 1980. | valor: R$ 60.000,00 | C39: 60000 | D39: 60000 | F39: 60000 | G39: 60000 | I39: =G39-D39 -> 0
A40: =A39+1 -> 9 | B40: Um Compressor, ano 2012, marca ATLAS COPCO. | valor: R$ 150.000,00 | C40: 150000 | D40: 150000 | F40: 150000 | G40: 150000 | I40: =G40-D40 -> 0
A41: =A40+1 -> 10 | B41: Um Compressor, ano 1980, a ar, CA80, marca ATLAS COPCO. Adquirido por leilão da Prefeitura de Bento Gonçalves. | valor: R$ 10.000,00 | C41: 10000 | D41: 10000 | F41: 10000 | G41: 10000 | I41: =G41-D41 -> 0
A42: =A41+1 -> 11 | B42: Um Compressor, ano....., cor verde. | valor: R$ 30.000,00 | C42: 30000 | D42: 30000 | F42: 30000 | G42: 30000 | I42: =G42-D42 -> 0
A43: =A42+1 -> 12 | B43: Uma Perfuratriz, ano..... | valor: R$ 10.000,00 | C43: 10000 | D43: 10000 | F43: 10000 | G43: 10000 | I43: =G43-D43 -> 0
A44: =A43+1 -> 13 | B44: Um Rompedor Hidráulico, ano 2014, adquirido da ATLAS COPCO, modelo MB 1700. | valor: R$ 100.000,00 | C44: 100000 | D44: 100000 | F44: 100000 | G44: 100000 | I44: =G44-D44 -> 0
A45: =A44+1 -> 14 | B45: Um Trator de Esteira, ano 2014, modelo D6N XL, CATERPILLAR, adquirido em setembro de 2025. | C45: 0 | D45: 0 | F45: 450000 | G45: 450000 | I45: =G45-D45 -> 450000
A48: 11.1.3 | B48: Lotes urbanos em Veranópolis e Bento Gonçalves | C48: =SUM(C50:C61) -> 2820000 | D48: =SUM(D50:D61) -> 3070000 | F48: =SUM(E50:E65) -> 0 | G48: =SUM(G50:G61) -> 3290000 | I48: =SUM(I50:I61) -> 220000
C49: =COUNTIF(C50:C61,">1") -> 11 | D49: =(D48/C48)-1 -> 0.088652482 | G49: =COUNTIF(G50:G61,">1") -> 8
A50: 1 | B50: Um lote urbano, localizado na Avenida Pinheiro Machado, Bairro Centro – Casa da Nina – Casa onde mora o Senhor Rubens Baldissera. Área de 330,00m², devidamente Registrado no Ofício de Registro de Imóveis da Comarca de Veranópolis – RS, sob Matrícula nº 1.597. | valor: R$ 150.000,00 | C50: 150000 | D50: 280000 | F50: 280000 | G50: 280000 | I50: =G50-D50 -> 0
A51: =A50+1 -> 2 | B51: Um lote urbano com casa, localizado na Avenida Dr. José Montaury, Bairro São Pelegrino – Casa da Nona – onde morava a Senhora Geni Siviero Mattiuz. 14,50m X 25,00m = área de 362,50m², devidamente Registrado no Ofício de Registro de Imóveis da Comarca de Veranópolis – RS, sob Matrícula nº 1.335. | valor: R$ 220.000,00 | C51: 220000 | D51: 250000 | F51: 250000 | G51: 250000 | I51: =G51-D51 -> 0
A52: =A51+1 -> 3 | B52: Um lote urbano com casa/prédio, localizado na Avenida Osvaldo Aranha, nº 1398, Bairro Palugana – escritório velho – alugado para o Senhor André – BAR DO ANDRÉ. 19,00m X 30,00 = área de 570,00m², devidamente Registrado no Ofício de Registro de Imóveis da Comarca de Veranópolis – RS, sob Matrícula nº 9. | valor: R$ 850.000,00 | C52: 850000 | D52: 850000 | F52: 850000 | G52: 850000 | H52: 850000 | I52: =G52-D52 -> 0
A53: =A52+1 -> 4 | B53: Um lote urbano, localizado na Rua General Flores da Cunha, que era do Mercali, na subida para o Bairro Femaçã – Hipotecado em favor da Receita Estadual – Dívida do ICMS. 13,00m X 20,00m = área de 260,00m², devidamente Registrado no Ofício de Registro de Imóveis da Comarca de Veranópolis – RS, sob Matrícula nº 1.053. | valor: R$ 60.000,00 | C53: 60000 | D53: 60000 | F53: 60000 | G53: 60000 | I53: =G53-D53 -> 0
A54: =A53+1 -> 5 | B54: Um lote urbano, localizado na Avenida Osvaldo Aranha, esquina com a Rua Eduardo Duarte, alugado para o Sr. Paulinho, das baterias. 23,00m X 15,00m = área de 345,00m², devidamente Registrado no Ofício de Registro de Imóveis da Comarca de Veranópolis – RS, sob Matrícula nº 1.507. | valor: R$ 850.000,00 | C54: 850000 | D54: 850000 | F54: 550000 | G54: 550000 | H54: 550000 | I54: =G54-D54 -> -300000
A55: =A54+1 -> 6 | B55: Um lote urbano, localizado na Rua General Flores da Cunha, Bairro Centro, na cidade de Veranópolis – RS, adquirido da Família Dal Ponte, denominado de lote nº 0092, da quadra nº 020, zona nº 02, distrito nº 01, com área de 750,00m², devidamente registrado no Ofício de Registro de Imóveis da Comarca de Veranópolis, sob Matrícula nº 3.788. | valor: R$ 1.010.000,00 | C55: 0 | D55: 0 | F55: 1010000 | G55: 1010000 | H55: 1010000 | I55: =G55-D55 -> 1010000 | J55: Quando foi Adquirido?
A56: =A55+1 -> 7 | B56: Um lote urbano, localizado na cidade de Bento Gonçalves – RS, denominado de lote nº 569/46 – Quadra 216 /D – Cadastro na P. M. de Bento Gonçalves sob nº 13082200, no LOTEAMENTO OURO VERDE II. Área de .........m², Registrado no Ofício de Registro de Imóveis da Comarca de Bento Gonçalves – RS, sob Matrícula nº ........... | valor: R$ 159.000,00 | C56: 100000 | D56: 130000 | F56: 159000 | G56: 130000 | I56: =G56-D56 -> 0
A57: =A56+1 -> 8 | B57: Um lote urbano, localizado na cidade de Bento Gonçalves – RS, denominado de lote nº 188/62 – Quadra 163/G – Cadastro na P. M. de Bento Gonçalves sob nº 12482700, no LOTEAMENTO VERONA. Área de .........m², Registrado no Ofício de Registro de Imóveis da Comarca de Bento Gonçalves – RS, sob Matrícula nº ........... | valor: R$ 100.000,00 | C57: 100000 | D57: 160000 | F57: 100000 | G57: 160000 | H57: 160000 | I57: =G57-D57 -> 0
A58: A.1 | B58: Um lote urbano, localizado na Rua Bento Gonçalves, Bairro São Pelegrino – Fundos da Casa da Nona – adquirido de Michelle Tedesco, medindo: 12,50m X 30,00m = área de 375,00m², devidamente Registrado no Ofício de Registro de Imóveis da Comarca de Veranópolis – RS, sob Matrícula nº 2325. | valor: R$ 220.000,00 | C58: 220000 | D58: 220000 | F58: 220000 | G58: 0 | I58: =G58-D58 -> -220000
A59: A.2 | B59: Um lote urbano, localizado na Rua Fioravante Boff, no Bairro Femaçã – que ainda está em nome da Senhora Cleri Fávero. LOTEAMENTO BOFF. ........,.....m X .........,......m = área de .................m², devidamente Registrado no Ofício de Registro de Imóveis da Comarca de Veranópolis – RS, sob Matrícula nº ..................... | C59: 70000 | D59: 70000 | F59: 0 | G59: 0 | I59: =G59-D59 -> -70000
A60: A.3 | B60: Um lote urbano, localizado na cidade de Bento Gonçalves – RS, denominado de lote nº 559/47 – Quadra 216 – Cadastro na P. M. de Bento Gonçalves sob nº 13082100, no LOTEAMENTO OURO VERDE. Área de .........m², Registrado no Ofício de Registro de Imóveis da Comarca de Bento Gonçalves – RS, sob Matrícula nº ........... | C60: 100000 | D60: 100000 | F60: 0 | G60: 0 | I60: =G60-D60 -> -100000
A61: A.4 | B61: Um lote urbano, localizado na cidade de Bento Gonçalves – RS, denominado de lote nº 247/169 – Quadra 221 – Cadastro na P. M. de Bento Gonçalves sob nº 13092200, no LOTEAMENTO OURO VERDE. Área de .........m², Registrado no Ofício de Registro de Imóveis da Comarca de Bento Gonçalves – RS, sob Matrícula nº ........... | C61: 100000 | D61: 100000 | F61: 0 | G61: 0 | I61: =G61-D61 -> -100000
A63: 11.1.3.A | B63: Descrição do(s) bem(ns) - Imóveis e Móveis | C63: =SUM(C65:C66) -> 110000 | D63: =SUM(D65:D66) -> 110000 | G63: =SUM(G65:G66) -> 0 | I63: =SUM(I65:I66) -> -110000
C64: 2 | D64: =(D63/C63)-1 -> 0 | G64: 0
A65: 1 | B65: Um apartamento residencial denominado de nº 303, do Edifício BOA ESPERANÇA, localizado na Rua Eduardo Reginato, n° 48, Bairro Valverde, na cidade de Veranópolis – RS, adquirido do Senhor Valmir Antônio Sottili. Área de 89,73m², devidamente Registrado no Ofício de Registro de Imóveis da Comarca de Veranópolis – RS, sob Matrícula nº 17.399, adquirido por R$ 85.000,00. | C65: 100000 | D65: 100000 | G65: 0 | I65: =G65-D65 -> -100000
A66: 2 | B66: Móveis, materiais diversos (mesas, cadeiras, telefone, impressora, etc...), informática e outros equipamentos instalados no Escritório da empresa Siviero, na cidade de Caxias do Sul – RS, na Rua Feijó Júnior, nº 318 – Sala nº 01, Bairro São Pelegrino – SALA ALUGADA. - E, no decorrer do ano de 2018, foi transferido o Escritório para outra Sala, de propriedade do Senhor Válter Siviero. - Os móveis e divisórias instalados no Escritório permaneceram, como forma de pagamento pelas obras de conservação da sala. - Mesas e cadeiras foram transferidas para uma casa localizada no Loteamento Zanandréa. - Impressoras e computadores foram para o novo endereço. | C66: 10000 | D66: 10000 | G66: 0 | I66: =G66-D66 -> -10000
A67: 11.1.4 | B67: Áreas urbanas em Veranópolis | C67: =SUM(C69:C73) -> 26629395 | D67: =SUM(D69:D73) -> 26929395 | F67: =SUM(E69:E72) -> 26629395 | G67: =SUM(G69:G73) -> 26929395 | I67: =SUM(I69:I73) -> 0
C68: =COUNTIF(C69:C72,">1") -> 4 | D68: =(D67/C67)-1 -> 0.011265746 | G68: =COUNTIF(G69:G72,">1") -> 4
A69: 1 | B69: Uma área de terras urbanas, denominada de LOTE Nº 1054, com área total de 16.913,9670m², ou 1,6 hectares, localizada no Município de Veranópolis – RS, próximo a Abastecedora de Combustíveis Siviero Ltda., adquirida do Senhor MOACIR ZANINI, área esta registrada sob Matrícula nº.: 17.038. Matrícula nº 17.038 = 1,60 hectares. 95,00 metros de frente. | valor: R$ 900.000,00 | C69: 900000 | D69: 1200000 | E69: 900000 | G69: 1200000 | I69: =G69-D69 -> 0
A70: 2 | B70: Um terreno – lote urbano, localizado na Rodovia BR 470, ao lado da Abastecedora de Combustíveis Siviero Ltda., devidamente registrado no Ofício de Registro de Imóveis da Comarca de Veranópolis, sob Matrícula nº 3.751, com área de 7.200,00m², onde está instalada a ANTENA de TRANSMISSÃO da RÁDIO, ao valor de mercado considerado sua localização e referência comercial = R$ 992,78, ao metro quadrado. | valor: R$ 7.148.016,00 | C70: 7148016 | D70: 7148016 | E70: 7148016 | G70: 7148016 | I70: =G70-D70 -> 0 | J70: Em 2018 estava na relação "9.1. RÁDIO COMUNIDADE..."
A71: 3 | B71: Um terreno urbano, com a área de 4.986,00m², localizado na Rodovia BR 470, Km 175,4, no Bairro São Pelegrino, devidamente registrado no Ofício de Registro de Imóveis da Comarca de Veranópolis, sob Matrícula nº 3.754, localizado na lateral da Abastecedora de Combustíveis Siviero Ltda., onde estava instalada a SERRARIA, considerado o valor de R$ 992,78, ao metro quadrado, conforme sua localização e referência comercial. | valor: R$ 4.950.000,00 | C71: 4950000 | D71: 4950000 | E71: 4950000 | G71: 4950000 | I71: =G71-D71 -> 0
A72: 4 | B72: Um imóvel urbano, com a área de 4.792,03m², localizado na Rodovia BR 470, Km 175,4, no Bairro Valverde, devidamente registrado no Ofício de Registro de Imóveis da Comarca de Veranópolis, sob a Matrícula nº 29.954 – (oriunda da unificação das Matrículas nº 17.409 e 6.136), ao lado da empresa Oleoplan S/A, considerado o valor de R$ 2.000,00, ao metro quadrado, conforme sua localização e referência comercial. = R$ 9.584.060,00. Sob estes imóveis estão construídos os PAVILHÕES, com área total construída de 4.170,00m², atualmente locados para a empresa Oleoplan S/A, avaliado conforme o CUB da construção civil referente ao mês de AGOSTO/2017 = R$ 746,60, ao metro quadrado = R$ 3.113.322,00. Valor dos Pavilhões construídos – obra civil = 30,00% (Trinta por cento) da obra feita: R$ 933.996,60 (considerado o valor agregado à coisa feita, como tal se encontra). | C72: 13631379 | D72: 13631379 | E72: 13631379 | G72: 13631379 | H72: 10631379 | I72: =G72-D72 -> 0 | J72: Valor do aluguel?
A74: 11.1.5 | B74: Áreas rurais em Veranópolis, Cotiporã, Fagundes Varela e Caxias do Sul | C74: =SUM(C76:C90) -> 7838866 | D74: =SUM(D76:D90) -> 8155866 | F74: =SUM(E76:E87) -> 6007366 | G74: =SUM(G76:G90) -> 7663866 | I74: =SUM(I76:I90) -> -492000
C75: =COUNTIF(C76:C91,">1") -> 11 | D75: =(D74/C74)-1 -> 0.040439523 | G75: =COUNTIF(G76:G91,">1") -> 12
A76: 1 | B76: Uma área de terras rurais, denominada de PARTES DOS LOTES RURAIS Nº 05, 06 e 76/A, com área total de 3,4 hectares, localizada na Linha Tomás Flores e Linha Afonso Pena, no Município de Veranópolis – RS, adquirida da Senhora ERMELINDA MOSSI REMOR, área esta registrada sob Matrícula nº.: Matrícula nº 14.443, 14.444, 14.576 = 3,4 hectares. Cadastrada no CCIR – Receita Federal sob nº 6.206.801-6. 90,00 metros de frente. | valor: R$ 1.200.000,00 | C76: 1200000 | D76: 1200000 | E76: 1200000 | G76: 1200000 | I76: =G76-D76 -> 0
A77: 2 | B77: Uma área de terras URBANAS, denominada de UM IMÓVEL URBANO, com a denominação administrativa de lote nº 0292, da quadra nº 009, zona 12, distrito 01, com área total de 4,0 hectares, conforme Registro e área medida, com 40.027,41m², localizada na Linha Tomaz Flores, Estrada Velha da Vacaria, no Município de Veranópolis – RS, na localidade de Sapopema, próxima ao CTG Rincão da Roça Reúna, adquirida da FAMÍLIA LAGO, área registrada sob Matrícula nº.: 33.516 | C77: 0 | D77: 0 | E77: 0 | G77: 1500000 | H77: 1500000 | I77: =G77-D77 -> 1500000
A78: 3 | B78: Uma área de terras rurais, denominada de PARTE DO LOTE RURAL Nº 14, da linha Dr. Júlio de Castilhos, com área total de 7,5 hectares, ou 75.550,00m², localizada no Município de Veranópolis – RS, na localidade de Santa Rita, adquirida da FAMÍLIA SANGALI – VALDIR SANGALI, área registrada sob Matrícula nº.: 4.194. Matrícula nº 4.194 = 7,5 hectares, adquirida pelo valor de R$ 50.000,00. | valor: R$ 280.000,00 | C78: 280000 | D78: 220000 | E78: 280000 | G78: 220000 | I78: =G78-D78 -> 0
A79: 4 | B79: Uma área de terras rurais, denominada de PARTE DO LOTE RURAL Nº 12, com área total de 13,0 hectares, localizada na Linha Júlio de Castilhos, no Município de Veranópolis – RS, adquirida da FAMÍLIA SANGALI, área registrada sob Matrícula nº.: 3.062. Matrícula nº 3.062 = 13,0 hectares X 40.000,00 Cadastrada no CCIR – Receita Federal sob nº 2.481.950-6 | C79: =13*11000 -> 143000 | D79: 520000 | E79: 143000 | G79: 520000 | I79: =G79-D79 -> 0 | J79: Mudou valor
A80: 5 | B80: Uma área de terras rurais, denominada de PARTE DO LOTE RURAL LETRA B, com área total de 1,8 hectares, ou 18.326,89m², localizada na Linha Carlos Gomes, no Município de Veranópolis – RS, na localidade de Vila Azul, adquirida da FAMÍLIA FOGALI, área esta registrada sob Matrícula nº.: 14.945. Matrícula nº 14.945 = 1,8 hectares, adquirida pelo valor de R$ 305.000,00. | valor: R$ 1.000.000,00 | C80: 1000000 | D80: 1000000 | E80: 1000000 | G80: 1000000 | I80: =G80-D80 -> 0
A81: 6 | B81: Uma área de terras rurais, denominada de PARTE DO LOTE RURAL nº 73, da Linha Tomaz Flores, Vila Azul, no Município de Veranópolis, registrada na Matrícula nº 30.390, do Ofício de Registro de Imóveis da Comarca de Veranópolis – RS, com área de 202.435,22m², adquirida da FAMÍLIA ANSOLIN, adquirida a área total, da seguinte forma: área de 6,0 hectares = 60.000,00m², pelo valor de R$ 525.000,00, do Senhor Antônio Ansolin. área de 7,0 hectares = 70.519,78m², pelo valor de R$ 586.666,00, do Senhor Antônio Ansolin. área de 4,9 hectares = 49.787,44m², pelo valor de R$ 714.000,00, da Senhora Inês Ansolin Pessutto. área de 0,67 hectares = 6.700,00m², pelo valor de R$ 388.000,00, do Senhor Ivo José Frainer. área de 0,2 hectares = 2.128,00m², pelo valor de R$ 50.000,00, do Senhor Antônio Ansolin. área pertencente ao Senhor Antônio Ansolin.....................2,0 hectares = 20.000,00m². Área da empresa Siviero Empreendimentos Imobiliários Ltda. é de 18,2 hectares = 182.435,22m². | valor: R$ 2.263.666,00 | C81: 2263666 | D81: 2263666 | E81: 2263666 | G81: 2263666 | I81: =G81-D81 -> 0
A82: 7 | B82: Uma área de terras rurais, denominadas de LOTES RURAIS Nº 26 e 27, CONDOMÍNIO HORIZONTAL, composto por chácaras, localizadas na Linha Tiradentes, na Barra do Jabuticaba, no Rio das Antas, no Município de Veranópolis – RS, composto por 25 (vinte e cinco) chácaras, sendo já vendidas 15 chácaras. Matrícula nº 36 = 10 chácaras. R$ 2.000,00 cada chácara. | C82: 0 | D82: 0 | E82: 100000 | G82: 20000 | I82: =G82-D82 -> 20000 | J82: data da compra?
A83: 8 | B83: Uma área de terras rurais, denominada de PARTE DO LOTE RURAL Nº 89, com área total de 27,8 hectares, localizada na Linha Barão do Triunfo, no Município de Fagundes Varela – RS, adquirida do Senhor SÉRGIO BALDISSERA, área esta registrada sob Matrícula nº.: 8.486. Matrícula nº 8.486 = 27,8 hectares X R$ 9.000,00 Cadastrada no CCIR – Receita Federal sob nº 2.481.951-4 | valor: R$ 250.200,00 | C83: =27.8*9000 -> 250200 | D83: 250200 | E83: 250200 | G83: 250200 | I83: =G83-D83 -> 0
A84: 9 | B84: Uma área de terras rurais de MATO NATIVO, denominada de LOTE Nº 33, com área total de 15,1 hectares, localizada no Município de Cotiporã – RS, na Linha Júlio de Castilhos, adquirida do Senhor ARMELINDO CALZA, área esta registrada sob Matrícula nº.: 1.218. Matrícula nº 1.218 = 15,1 hectares X R$ 2.650,00 | C84: 75500 | D84: 75500 | E84: 75500 | G84: 40000 | I84: =G84-D84 -> -35500
A85: 10 | B85: Uma área de terras rurais, ADQUIRIDA em 2014, DA FAMÍLIA CECCONELLO, localizada no Município de Caxias do Sul – RS, composto por 2,0 (Dois) hectares, dentro de um todo maior, que compõem o Loteamento = 130.446,00m². | valor: R$ 600.000,00 | C85: 600000 | D85: 600000 | E85: 600000 | G85: 600000 | I85: =G85-D85 -> 0
A86: 11 | B86: Uma área de terras rurais, denominada de PARTE DO LOTE RURAL Nº 47, com área total de 7,5 hectares = 75.625,00m², localizada na Linha Ernesto Alves, no Município de Veranópolis – RS, adquirida da FAMÍLIA PICCOLO, por contrato em 06 de outubro de 2022, área ainda não registrada em nome da empresa, com título da propriedade através de Escritura Pública de Cessão de Direitos de Posse nº 4.856 - 092, datada de 13 de março de 2006, lavrada no Serviço Notarial de Veranópolis. Cadastrada no ITR – Receita Federal sob nº 1.893.570-2 INCRA/CCIR nº 854.093.042.013-5 Adquirida pelo valor de R$ 45.000,00. Parte da área foi destinada para compensação ambiental do Loteamento Colina do Retiro II. | C86: 0 | D86: 0 | E86: 45000 | G86: 20000 | I86: =G86-D86 -> 20000 | J86: data da compra?
A87: 12 | B87: Uma área de terras rurais, denominada de PARTE DO LOTE RURAL Nº 47, com área total de 7,5 hectares = 75.625,00m², localizada na Linha Ernesto Alves, no Município de Veranópolis – RS, adquirida da FAMÍLIA SCALCO, por contrato em 01 de novembro de 2022, área ainda não registrada em nome da empresa, com título da propriedade através de Escritura Pública de Cessão de Direitos de Posse nº 5.857 - 045, datada de 06 de outubro de 2009, lavrada no Serviço Notarial de Veranópolis. Cadastrada no ITR – Receita Federal sob nº 1.731.666-9 INCRA/CCIR nº 854.093.030.619-7 Adquirida pelo valor de R$ 50.000,00. Parte da área foi destinada para compensação ambiental do Loteamento Colina do Retiro II. | C87: 0 | D87: 0 | E87: 50000 | G87: 30000 | I87: =G87-D87 -> 30000 | J87: data da compra?
A88: A.1 | B88: Uma área de terras urbanas, denominada de LOTE Nº 1543, com área total de 1,9 hectares, localizada no Município de Veranópolis – RS, na Rodovia BR 470, esquina com a Estrada da Linha República, próximo a empresa Oleoplan S/A, adquirida da FAMÍLIA BISSANI, área esta registrada sob Matrícula nº.: 21.819. Matrícula nº 21.819 = 1,9 hectares. Adquirida por R$ 400.000,00. 17.604,00m² + 2.000,00m² = 19.604,00m². | valor: R$ 900.000,00 | C88: 900000 | D88: 900000 | E88: 900000 | G88: 0 | I88: =G88-D88 -> -900000
A89: A.2 | B89: Uma área de terras rurais, denominada de PARTE DO LOTE RURAL LETRA “M”, com área total de 3,6 hectares, conforme contrato e área medida conforme croqui, com 33.742,78m², localizada na Linha Tomaz Flores, no Município de Veranópolis – RS, na localidade de Sapopema, próxima ao CTG Rincão da Roça Reiuna, adquirida da FAMÍLIA LAGO, área esta registrada sob Matrícula nº.: 14.319. Matrícula nº 14.319 = 3,6 hectares. | valor: R$ 900.000,00 | C89: 900000 | D89: 900000 | E89: 900000 | G89: 0 | I89: =G89-D89 -> -900000 | J89: Mesma área do item 2?
A90: A.3 | B90: Uma área de terras rurais, denominada de PARTE DO LOTE RURAL Nº 52, com área total de 15,1 hectares, localizada na Linha Júlio de Castilhos, no Município de Cotiporã – RS, adquirida da Senhora GLORIA E GERALDO BASSANI, área esta registrada sob Matrícula nº.: 7.391 - Matrícula nº 7.391 = 15,1 hectares X R$ 15.000,00 Cadastrada no CCIR – Receita Federal sob nº 2.481.952-2 | valor: R$ 226.500,00 | C90: 226500 | D90: 226500 | E90: 226500 | G90: 0 | I90: =G90-D90 -> -226500
A93: 11.1.6 | B93: Loteamentos executados e registrados | C93: =C95+C116+C121+C128+C137+C155+C171+C208+C317+C351+C355+C363+C380+C386+C393+C397+C404+C420+C426+C440+C452+C458+C462+C470+C500+C513+C576+C583+C600+C634+C638 -> 97740000 | D93: =D95+D116+D121+D128+D137+D155+D171+D208+D317+D351+D355+D363+D380+D386+D393+D397+D404+D420+D426+D440+D452+D458+D462+D470+D500+D513+D576+D583+D600+D634+D638 -> 2.2598174e+08 | E93: =E95+E116+E121+E128+E137+E155+E171+E208+E317+E351+E355+E363+E380+E386+E393+E397+E404+E420+E426+E440+E452+E458+E462+E470+E500+E513+E576+E583+E600+E634+E638 -> 9 | F93: =F95+F116+F121+F128+F137+F155+F171+F208+F317+F351+F355+F363+F380+F386+F393+F397+F404+F420+F426+F440+F452+F458+F462+F470+F500+F513+F576+F583+F600+F634+F638 -> 89200000 | G93: =G95+G116+G121+G128+G137+G155+G171+G208+G317+G351+G355+G363+G380+G386+G393+G397+G404+G420+G426+G440+G452+G458+G462+G470+G500+G513+G576+G583+G600+G634+G638 -> 111043000 | I93: =I95+I116+I121+I128+I137+I155+I171+I208+I317+I351+I355+I363+I380+I386+I393+I397+I404+I420+I426+I440+I452+I458+I462+I470+I500+I513+I576+I583+I600+I634+I638 -> -1.0842874e+08 | J93: Comparação com 2018: 48.14% do patrimônio e 55.73% do número de lotes
C94: =C96+C113+C117+C122+C129+C138+C156+C172+C209+C318+C352+C356+C364+C381+C387+C394+C398+C405+C421+C427+C441+C453+C459+C463+C471+C501+C514+C577+C584+C601+C635+C639 -> 750 | D94: =(D93/C93)-1 -> 1.3120702 | G94: =G96+G113+G117+G122+G129+G138+G156+G172+G209+G318+G352+G356+G364+G381+G387+G394+G398+G405+G421+G427+G441+G453+G459+G463+G471+G501+G514+G577+G584+G601+G635+G639 -> 418
A95: 1 | B95: Loteamento Sol Nascente I, localizado na cidade de Antônio Prado – RS, num saldo de 11 lotes. | C95: =B96*C96 -> 2800000 | D95: =C96*I96 -> 5130363.6 | F95: =SUM(E97:E107) -> 4031000 | G95: =SUM(G97:G107) -> 4031000 | I95: =G95-D95 -> -1099363.6
B96: 200000 | C96: 14 | D96: =(D95/C95)-1 -> 0.83227273 | G96: =COUNT(G97:G107) -> 11 | I96: =G95/G96 -> 366454.55
A97: 1.1 | B97: Lote:1 | Quadra:A | valor:R$ 351.000,00 | E97: 351000 | G97: 351000
A98: 1.2 | B98: Lote:2 | Quadra:A | valor:R$ 351.000,00 | E98: 351000 | G98: 351000
A99: 1.3 | B99: Lote:3 | Quadra:A | valor:R$ 351.000,00 | E99: 351000 | G99: 351000
A100: 1.4 | B100: Lote:10 | Quadra:B | valor:R$ 369.000,00 | E100: 369000 | G100: 369000
A101: 1.5 | B101: Lote:11 | Quadra:B | valor:R$ 369.000,00 | E101: 369000 | G101: 369000
A102: 1.6 | B102: Lote:12 | Quadra:B | valor:R$ 389.000,00 | E102: 389000 | G102: 389000
A103: 1.7 | B103: Lote:20 | Quadra:C | valor:R$ 389.000,00 | E103: 389000 | G103: 389000
A104: 1.8 | B104: Lote:21 | Quadra:D | valor:R$ 389.000,00 | E104: 389000 | G104: 389000 | H104: 389000
A105: 1.9 | B105: Lote:22 | Quadra:D | valor:R$ 354.000,00 | E105: 354000 | G105: 354000 | H105: 354000
A106: 1.10 | B106: Lote:30 | Quadra:E | valor:R$ 389.000,00 | E106: 389000 | G106: 389000
...

Sheet Valor médio dos lotes
A1: Valor médio dos lotes por loteamento
A2: Fonte: aba 11.Empreendimentos, item 11.1.6 (loteamentos executados e registrados). 2018 = valor apresentado no estudo de 2018. Out/2025 = coluna "outubro 2025", contando só lotes com valor atribuído (ficam fora os lotes de APP, vendidos e da Família Siviero, que estão com valor zero).
A4: Nº | B4: Loteamento | C4: Cidade | D4: Lotes 2018 | E4: Valor total 2018 | F4: Valor médio/lote 2018 | G4: Lotes com valor out/2025 | H4: Valor total out/2025 | I4: Valor médio/lote out/2025 | J4: Menor valor out/2025 | K4: Maior valor out/2025 | L4: Variação do valor médio
A5: 1 | B5: Sol Nascente I | C5: Antônio Prado | D5: =IF(ISNUMBER('11.Empreendimentos'!C95),N('11.Empreendimentos'!C96),0) -> 14 | E5: =IF(ISNUMBER('11.Empreendimentos'!C95),'11.Empreendimentos'!C95,0) -> 2800000 | F5: =IF(D5=0,0,E5/D5) -> 200000 | G5: =COUNTIF('11.Empreendimentos'!$G$97:$G$110,">0") -> 11 | H5: =SUMIF('11.Empreendimentos'!$G$97:$G$110,">0") -> 4031000 | I5: =IF(G5=0,0,H5/G5) -> 366454.55 | J5: =IF(G5=0,0,MINIFS('11.Empreendimentos'!$G$97:$G$110,'11.Empreendimentos'!$G$97:$G$110,">0")) -> 330000 | K5: =IF(G5=0,0,MAXIFS('11.Empreendimentos'!$G$97:$G$110,'11.Empreendimentos'!$G$97:$G$110,">0")) -> 389000 | L5: =IF(OR(F5=0,I5=0),0,I5/F5-1) -> 0.83227273
A6: 2 | B6: Boito | C6: Nova Prata | D6: =IF(ISNUMBER('11.Empreendimentos'!C112),N('11.Empreendimentos'!C113),0) -> 0 | E6: =IF(ISNUMBER('11.Empreendimentos'!C112),'11.Empreendimentos'!C112,0) -> 0 | F6: =IF(D6=0,0,E6/D6) -> 0 | G6: =COUNTIF('11.Empreendimentos'!$G$114,">0") -> 1 | H6: =SUMIF('11.Empreendimentos'!$G$114,">0") -> 136000 | I6: =IF(G6=0,0,H6/G6) -> 136000 | J6: =IF(G6=0,0,MINIFS('11.Empreendimentos'!$G$114,'11.Empreendimentos'!$G$114,">0")) -> 136000 | K6: =IF(G6=0,0,MAXIFS('11.Empreendimentos'!$G$114,'11.Empreendimentos'!$G$114,">0")) -> 136000 | L6: =IF(OR(F6=0,I6=0),0,I6/F6-1) -> 0
A7: 3 | B7: Condomínio Morada do Ipê I | C7: Passo Fundo | D7: =IF(ISNUMBER('11.Empreendimentos'!C116),N('11.Empreendimentos'!C117),0) -> 29 | E7: =IF(ISNUMBER('11.Empreendimentos'!C116),'11.Empreendimentos'!C116,0) -> 4350000 | F7: =IF(D7=0,0,E7/D7) -> 150000 | G7: =COUNTIF('11.Empreendimentos'!$G$118:$G$119,">0") -> 1 | H7: =SUMIF('11.Empreendimentos'!$G$118:$G$119,">0") -> 629000 | I7: =IF(G7=0,0,H7/G7) -> 629000 | J7: =IF(G7=0,0,MINIFS('11.Empreendimentos'!$G$118:$G$119,'11.Empreendimentos'!$G$118:$G$119,">0")) -> 629000 | K7: =IF(G7=0,0,MAXIFS('11.Empreendimentos'!$G$118:$G$119,'11.Empreendimentos'!$G$118:$G$119,">0")) -> 629000 | L7: =IF(OR(F7=0,I7=0),0,I7/F7-1) -> 3.1933333
A8: 4 | B8: Fracionamento Simioni | C8: Veranópolis | D8: =IF(ISNUMBER('11.Empreendimentos'!C121),N('11.Empreendimentos'!C122),0) -> 4 | E8: =IF(ISNUMBER('11.Empreendimentos'!C121),'11.Empreendimentos'!C121,0) -> 1000000 | F8: =IF(D8=0,0,E8/D8) -> 250000 | G8: =COUNTIF('11.Empreendimentos'!$G$123:$G$126,">0") -> 0 | H8: =SUMIF('11.Empreendimentos'!$G$123:$G$126,">0") -> 0 | I8: =IF(G8=0,0,H8/G8) -> 0 | J8: =IF(G8=0,0,MINIFS('11.Empreendimentos'!$G$123:$G$126,'11.Empreendimentos'!$G$123:$G$126,">0")) -> 0 | K8: =IF(G8=0,0,MAXIFS('11.Empreendimentos'!$G$123:$G$126,'11.Empreendimentos'!$G$123:$G$126,">0")) -> 0 | L8: =IF(OR(F8=0,I8=0),0,I8/F8-1) -> 0
A9: 5 | B9: Solar Norte I e II | C9: Veranópolis | D9: =IF(ISNUMBER('11.Empreendimentos'!C128),N('11.Empreendimentos'!C129),0) -> 10 | E9: =IF(ISNUMBER('11.Empreendimentos'!C128),'11.Empreendimentos'!C128,0) -> 1330000 | F9: =IF(D9=0,0,E9/D9) -> 133000 | G9: =COUNTIF('11.Empreendimentos'!$G$130:$G$135,">0") -> 6 | H9: =SUMIF('11.Empreendimentos'!$G$130:$G$135,">0") -> 1171000 | I9: =IF(G9=0,0,H9/G9) -> 195166.67 | J9: =IF(G9=0,0,MINIFS('11.Empreendimentos'!$G$130:$G$135,'11.Empreendimentos'!$G$130:$G$135,">0")) -> 169000 | K9: =IF(G9=0,0,MAXIFS('11.Empreendimentos'!$G$130:$G$135,'11.Empreendimentos'!$G$130:$G$135,">0")) -> 232000 | L9: =IF(OR(F9=0,I9=0),0,I9/F9-1) -> 0.46741855
A10: 6 | B10: Aditivo Medianeira | C10: Veranópolis | D10: =IF(ISNUMBER('11.Empreendimentos'!C137),N('11.Empreendimentos'!C138),0) -> 20 | E10: =IF(ISNUMBER('11.Empreendimentos'!C137),'11.Empreendimentos'!C137,0) -> 2000000 | F10: =IF(D10=0,0,E10/D10) -> 100000 | G10: =COUNTIF('11.Empreendimentos'!$G$139:$G$153,">0") -> 15 | H10: =SUMIF('11.Empreendimentos'!$G$139:$G$153,">0") -> 2647000 | I10: =IF(G10=0,0,H10/G10) -> 176466.67 | J10: =IF(G10=0,0,MINIFS('11.Empreendimentos'!$G$139:$G$153,'11.Empreendimentos'!$G$139:$G$153,">0")) -> 152000 | K10: =IF(G10=0,0,MAXIFS('11.Empreendimentos'!$G$139:$G$153,'11.Empreendimentos'!$G$139:$G$153,">0")) -> 220000 | L10: =IF(OR(F10=0,I10=0),0,I10/F10-1) -> 0.76466667
A11: 7 | B11: Colina do Retiro I | C11: Veranópolis | D11: =IF(ISNUMBER('11.Empreendimentos'!C155),N('11.Empreendimentos'!C156),0) -> 23 | E11: =IF(ISNUMBER('11.Empreendimentos'!C155),'11.Empreendimentos'!C155,0) -> 2460000 | F11: =IF(D11=0,0,E11/D11) -> 106956.52 | G11: =COUNTIF('11.Empreendimentos'!$G$157:$G$169,">0") -> 13 | H11: =SUMIF('11.Empreendimentos'!$G$157:$G$169,">0") -> 2585000 | I11: =IF(G11=0,0,H11/G11) -> 198846.15 | J11: =IF(G11=0,0,MINIFS('11.Empreendimentos'!$G$157:$G$169,'11.Empreendimentos'!$G$157:$G$169,">0")) -> 149000 | K11: =IF(G11=0,0,MAXIFS('11.Empreendimentos'!$G$157:$G$169,'11.Empreendimentos'!$G$157:$G$169,">0")) -> 437000 | L11: =IF(OR(F11=0,I11=0),0,I11/F11-1) -> 0.85913071
A12: 8 | B12: Salvador (Alberto Salvador) – Femaçã II | C12: Veranópolis | D12: =IF(ISNUMBER('11.Empreendimentos'!C171),N('11.Empreendimentos'!C172),0) -> 36 | E12: =IF(ISNUMBER('11.Empreendimentos'!C171),'11.Empreendimentos'!C171,0) -> 5160000 | F12: =IF(D12=0,0,E12/D12) -> 143333.33 | G12: =COUNTIF('11.Empreendimentos'!$G$173:$G$206,">0") -> 26 | H12: =SUMIF('11.Empreendimentos'!$G$173:$G$206,">0") -> 8374000 | I12: =IF(G12=0,0,H12/G12) -> 322076.92 | J12: =IF(G12=0,0,MINIFS('11.Empreendimentos'!$G$173:$G$206,'11.Empreendimentos'!$G$173:$G$206,">0")) -> 189000 | K12: =IF(G12=0,0,MAXIFS('11.Empreendimentos'!$G$173:$G$206,'11.Empreendimentos'!$G$173:$G$206,">0")) -> 440000 | L12: =IF(OR(F12=0,I12=0),0,I12/F12-1) -> 1.2470483
A13: 9 | B13: Colina do Retiro II | C13: Veranópolis | D13: =IF(ISNUMBER('11.Empreendimentos'!C208),N('11.Empreendimentos'!C209),0) -> 105 | E13: =IF(ISNUMBER('11.Empreendimentos'!C208),'11.Empreendimentos'!C208,0) -> 9450000 | F13: =IF(D13=0,0,E13/D13) -> 90000 | G13: =COUNTIF('11.Empreendimentos'!$G$210:$G$315,">0") -> 102 | H13: =SUMIF('11.Empreendimentos'!$G$210:$G$315,">0") -> 20181000 | I13: =IF(G13=0,0,H13/G13) -> 197852.94 | J13: =IF(G13=0,0,MINIFS('11.Empreendimentos'!$G$210:$G$315,'11.Empreendimentos'!$G$210:$G$315,">0")) -> 162000 | K13: =IF(G13=0,0,MAXIFS('11.Empreendimentos'!$G$210:$G$315,'11.Empreendimentos'!$G$210:$G$315,">0")) -> 310000 | L13: =IF(OR(F13=0,I13=0),0,I13/F13-1) -> 1.198366
A14: 10 | B14: Industrial Pedra Lisa | C14: Veranópolis | D14: =IF(ISNUMBER('11.Empreendimentos'!C317),N('11.Empreendimentos'!C318),0) -> 39 | E14: =IF(ISNUMBER('11.Empreendimentos'!C317),'11.Empreendimentos'!C317,0) -> 9510000 | F14: =IF(D14=0,0,E14/D14) -> 243846.15 | G14: =COUNTIF('11.Empreendimentos'!$G$319:$G$349,">0") -> 31 | H14: =SUMIF('11.Empreendimentos'!$G$319:$G$349,">0") -> 10985000 | I14: =IF(G14=0,0,H14/G14) -> 354354.84 | J14: =IF(G14=0,0,MINIFS('11.Empreendimentos'!$G$319:$G$349,'11.Empreendimentos'!$G$319:$G$349,">0")) -> 273000 | K14: =IF(G14=0,0,MAXIFS('11.Empreendimentos'!$G$319:$G$349,'11.Empreendimentos'!$G$319:$G$349,">0")) -> 943000 | L14: =IF(OR(F14=0,I14=0),0,I14/F14-1) -> 0.45319019
A15: 11 | B15: Monte Vêneto | C15: Carlos Barbosa | D15: =IF(ISNUMBER('11.Empreendimentos'!C351),N('11.Empreendimentos'!C352),0) -> 1 | E15: =IF(ISNUMBER('11.Empreendimentos'!C351),'11.Empreendimentos'!C351,0) -> 110000 | F15: =IF(D15=0,0,E15/D15) -> 110000 | G15: =COUNTIF('11.Empreendimentos'!$G$353,">0") -> 1 | H15: =SUMIF('11.Empreendimentos'!$G$353,">0") -> 241000 | I15: =IF(G15=0,0,H15/G15) -> 241000 | J15: =IF(G15=0,0,MINIFS('11.Empreendimentos'!$G$353,'11.Empreendimentos'!$G$353,">0")) -> 241000 | K15: =IF(G15=0,0,MAXIFS('11.Empreendimentos'!$G$353,'11.Empreendimentos'!$G$353,">0")) -> 241000 | L15: =IF(OR(F15=0,I15=0),0,I15/F15-1) -> 1.1909091
A16: 12 | B16: Baldasso | C16: Carlos Barbosa | D16: =IF(ISNUMBER('11.Empreendimentos'!C355),N('11.Empreendimentos'!C356),0) -> 15 | E16: =IF(ISNUMBER('11.Empreendimentos'!C355),'11.Empreendimentos'!C355,0) -> 1800000 | F16: =IF(D16=0,0,E16/D16) -> 120000 | G16: =COUNTIF('11.Empreendimentos'!$G$357:$G$361,">0") -> 5 | H16: =SUMIF('11.Empreendimentos'!$G$357:$G$361,">0") -> 1419000 | I16: =IF(G16=0,0,H16/G16) -> 283800 | J16: =IF(G16=0,0,MINIFS('11.Empreendimentos'!$G$357:$G$361,'11.Empreendimentos'!$G$357:$G$361,">0")) -> 262000 | K16: =IF(G16=0,0,MAXIFS('11.Empreendimentos'!$G$357:$G$361,'11.Empreendimentos'!$G$357:$G$361,">0")) -> 304000 | L16: =IF(OR(F16=0,I16=0),0,I16/F16-1) -> 1.365
A17: 13 | B17: Colina do Basalto | C17: Nova Prata | D17: =IF(ISNUMBER('11.Empreendimentos'!C363),N('11.Empreendimentos'!C364),0) -> 14 | E17: =IF(ISNUMBER('11.Empreendimentos'!C363),'11.Empreendimentos'!C363,0) -> 1260000 | F17: =IF(D17=0,0,E17/D17) -> 90000 | G17: =COUNTIF('11.Empreendimentos'!$G$365:$G$378,">0") -> 14 | H17: =SUMIF('11.Empreendimentos'!$G$365:$G$378,">0") -> 2180000 | I17: =IF(G17=0,0,H17/G17) -> 155714.29 | J17: =IF(G17=0,0,MINIFS('11.Empreendimentos'!$G$365:$G$378,'11.Empreendimentos'!$G$365:$G$378,">0")) -> 125000 | K17: =IF(G17=0,0,MAXIFS('11.Empreendimentos'!$G$365:$G$378,'11.Empreendimentos'!$G$365:$G$378,">0")) -> 220000 | L17: =IF(OR(F17=0,I17=0),0,I17/F17-1) -> 0.73015873
A18: 14 | B18: Carnevalli | C18: Nova Prata | D18: =IF(ISNUMBER('11.Empreendimentos'!C380),N('11.Empreendimentos'!C381),0) -> 17 | E18: =IF(ISNUMBER('11.Empreendimentos'!C380),'11.Empreendimentos'!C380,0) -> 1530000 | F18: =IF(D18=0,0,E18/D18) -> 90000 | G18: =COUNTIF('11.Empreendimentos'!$G$382:$G$384,">0") -> 3 | H18: =SUMIF('11.Empreendimentos'!$G$382:$G$384,">0") -> 617000 | I18: =IF(G18=0,0,H18/G18) -> 205666.67 | J18: =IF(G18=0,0,MINIFS('11.Empreendimentos'!$G$382:$G$384,'11.Empreendimentos'!$G$382:$G$384,">0")) -> 188000 | K18: =IF(G18=0,0,MAXIFS('11.Empreendimentos'!$G$382:$G$384,'11.Empreendimentos'!$G$382:$G$384,">0")) -> 241000 | L18: =IF(OR(F18=0,I18=0),0,I18/F18-1) -> 1.2851852
A19: 15 | B19: Barbiero | C19: Nova Prata | D19: =IF(ISNUMBER('11.Empreendimentos'!C386),N('11.Empreendimentos'!C387),0) -> 20 | E19: =IF(ISNUMBER('11.Empreendimentos'!C386),'11.Empreendimentos'!C386,0) -> 2600000 | F19: =IF(D19=0,0,E19/D19) -> 130000 | G19: =COUNTIF('11.Empreendimentos'!$G$388:$G$391,">0") -> 4 | H19: =SUMIF('11.Empreendimentos'!$G$388:$G$391,">0") -> 822000 | I19: =IF(G19=0,0,H19/G19) -> 205500 | J19: =IF(G19=0,0,MINIFS('11.Empreendimentos'!$G$388:$G$391,'11.Empreendimentos'!$G$388:$G$391,">0")) -> 170000 | K19: =IF(G19=0,0,MAXIFS('11.Empreendimentos'!$G$388:$G$391,'11.Empreendimentos'!$G$388:$G$391,">0")) -> 241000 | L19: =IF(OR(F19=0,I19=0),0,I19/F19-1) -> 0.58076923
A20: 16 | B20: Araçá | C20: Nova Araçá | D20: =IF(ISNUMBER('11.Empreendimentos'!C393),N('11.Empreendimentos'!C394),0) -> 1 | E20: =IF(ISNUMBER('11.Empreendimentos'!C393),'11.Empreendimentos'!C393,0) -> 60000 | F20: =IF(D20=0,0,E20/D20) -> 60000 | G20: =COUNTIF('11.Empreendimentos'!$G$395,">0") -> 1 | H20: =SUMIF('11.Empreendimentos'!$G$395,">0") -> 142000 | I20: =IF(G20=0,0,H20/G20) -> 142000 | J20: =IF(G20=0,0,MINIFS('11.Empreendimentos'!$G$395,'11.Empreendimentos'!$G$395,">0")) -> 142000 | K20: =IF(G20=0,0,MAXIFS('11.Empreendimentos'!$G$395,'11.Empreendimentos'!$G$395,">0")) -> 142000 | L20: =IF(OR(F20=0,I20=0),0,I20/F20-1) -> 1.3666667
A21: 17 | B21: Dalla Costa | C21: Nova Bassano | D21: =IF(ISNUMBER('11.Empreendimentos'!C397),N('11.Empreendimentos'!C398),0) -> 5 | E21: =IF(ISNUMBER('11.Empreendimentos'!C397),'11.Empreendimentos'!C397,0) -> 375000 | F21: =IF(D21=0,0,E21/D21) -> 75000 | G21: =COUNTIF('11.Empreendimentos'!$G$399:$G$402,">0") -> 4 | H21: =SUMIF('11.Empreendimentos'!$G$399:$G$402,">0") -> 650000 | I21: =IF(G21=0,0,H21/G21) -> 162500 | J21: =IF(G21=0,0,MINIFS('11.Empreendimentos'!$G$399:$G$402,'11.Empreendimentos'!$G$399:$G$402,">0")) -> 148000 | K21: =IF(G21=0,0,MAXIFS('11.Empreendimentos'!$G$399:$G$402,'11.Empreendimentos'!$G$399:$G$402,">0")) -> 178000 | L21: =IF(OR(F21=0,I21=0),0,I21/F21-1) -> 1.1666667
A22: 18 | B22: Lago Negro | C22: Gramado | D22: =IF(ISNUMBER('11.Empreendimentos'!C404),N('11.Empreendimentos'!C405),0) -> 27 | E22: =IF(ISNUMBER('11.Empreendimentos'!C404),'11.Empreendimentos'!C404,0) -> 8650000 | F22: =IF(D22=0,0,E22/D22) -> 320370.37 | G22: =COUNTIF('11.Empreendimentos'!$G$406:$G$418,">0") -> 5 | H22: =SUMIF('11.Empreendimentos'!$G$406:$G$418,">0") -> 4021000 | I22: =IF(G22=0,0,H22/G22) -> 804200 | J22: =IF(G22=0,0,MINIFS('11.Empreendimentos'!$G$406:$G$418,'11.Empreendimentos'!$G$406:$G$418,">0")) -> 720000 | K22: =IF(G22=0,0,MAXIFS('11.Empreendimentos'!$G$406:$G$418,'11.Empreendimentos'!$G$406:$G$418,">0")) -> 879000 | L22: =IF(OR(F22=0,I22=0),0,I22/F22-1) -> 1.5102197
A23: 19 | B23: Perini | C23: Farroupilha | D23: =IF(ISNUMBER('11.Empreendimentos'!C420),N('11.Empreendimentos'!C421),0) -> 10 | E23: =IF(ISNUMBER('11.Empreendimentos'!C420),'11.Empreendimentos'!C420,0) -> 2570000 | F23: =IF(D23=0,0,E23/D23) -> 257000 | G23: =COUNTIF('11.Empreendimentos'!$G$422:$G$424,">0") -> 3 | H23: =SUMIF('11.Empreendimentos'!$G$422:$G$424,">0") -> 4560000 | I23: =IF(G23=0,0,H23/G23) -> 1520000 | J23: =IF(G23=0,0,MINIFS('11.Empreendimentos'!$G$422:$G$424,'11.Empreendimentos'!$G$422:$G$424,">0")) -> 1520000 | K23: =IF(G23=0,0,MAXIFS('11.Empreendimentos'!$G$422:$G$424,'11.Empreendimentos'!$G$422:$G$424,">0")) -> 1520000 | L23: =IF(OR(F23=0,I23=0),0,I23/F23-1) -> 4.9143969
A24: 20 | B24: San Marino | C24: Farroupilha | D24: =IF(ISNUMBER('11.Empreendimentos'!C426),N('11.Empreendimentos'!C427),0) -> 30 | E24: =IF(ISNUMBER('11.Empreendimentos'!C426),'11.Empreendimentos'!C426,0) -> 3300000 | F24: =IF(D24=0,0,E24/D24) -> 110000 | G24: =COUNTIF('11.Empreendimentos'!$G$428:$G$438,">0") -> 8 | H24: =SUMIF('11.Empreendimentos'!$G$428:$G$438,">0") -> 2080000 | I24: =IF(G24=0,0,H24/G24) -> 260000 | J24: =IF(G24=0,0,MINIFS('11.Empreendimentos'!$G$428:$G$438,'11.Empreendimentos'!$G$428:$G$438,">0")) -> 253000 | K24: =IF(G24=0,0,MAXIFS('11.Empreendimentos'!$G$428:$G$438,'11.Empreendimentos'!$G$428:$G$438,">0")) -> 266000 | L24: =IF(OR(F24=0,I24=0),0,I24/F24-1) -> 1.3636364
A25: 21 | B25: Firminio Dalzóchio | C25: Farroupilha | D25: =IF(ISNUMBER('11.Empreendimentos'!C440),N('11.Empreendimentos'!C441),0) -> 15 | E25: =IF(ISNUMBER('11.Empreendimentos'!C440),'11.Empreendimentos'!C440,0) -> 1500000 | F25: =IF(D25=0,0,E25/D25) -> 100000 | G25: =COUNTIF('11.Empreendimentos'!$G$442:$G$450,">0") -> 8 | H25: =SUMIF('11.Empreendimentos'!$G$442:$G$450,">0") -> 1790000 | I25: =IF(G25=0,0,H25/G25) -> 223750 | J25: =IF(G25=0,0,MINIFS('11.Empreendimentos'!$G$442:$G$450,'11.Empreendimentos'!$G$442:$G$450,">0")) -> 102000 | K25: =IF(G25=0,0,MAXIFS('11.Empreendimentos'!$G$442:$G$450,'11.Empreendimentos'!$G$442:$G$450,">0")) -> 385000 | L25: =IF(OR(F25=0,I25=0),0,I25/F25-1) -> 1.2375
A26: 22 | B26: Primavera | C26: Farroupilha | D26: =IF(ISNUMBER('11.Empreendimentos'!C452),N('11.Empreendimentos'!C453),0) -> 2 | E26: =IF(ISNUMBER('11.Empreendimentos'!C452),'11.Empreendimentos'!C452,0) -> 160000 | F26: =IF(D26=0,0,E26/D26) -> 80000 | G26: =COUNTIF('11.Empreendimentos'!$G$454:$G$456,">0") -> 1 | H26: =SUMIF('11.Empreendimentos'!$G$454:$G$456,">0") -> 148000 | I26: =IF(G26=0,0,H26/G26) -> 148000 | J26: =IF(G26=0,0,MINIFS('11.Empreendimentos'!$G$454:$G$456,'11.Empreendimentos'!$G$454:$G$456,">0")) -> 148000 | K26: =IF(G26=0,0,MAXIFS('11.Empreendimentos'!$G$454:$G$456,'11.Empreendimentos'!$G$454:$G$456,">0")) -> 148000 | L26: =IF(OR(F26=0,I26=0),0,I26/F26-1) -> 0.85
A27: 23 | B27: Vila Vicenza | C27: Farroupilha | D27: =IF(ISNUMBER('11.Empreendimentos'!C458),N('11.Empreendimentos'!C459),0) -> 2 | E27: =IF(ISNUMBER('11.Empreendimentos'!C458),'11.Empreendimentos'!C458,0) -> 90000 | F27: =IF(D27=0,0,E27/D27) -> 45000 | G27: =COUNTIF('11.Empreendimentos'!$G$460,">0") -> 1 | H27: =SUMIF('11.Empreendimentos'!$G$460,">0") -> 157000 | I27: =IF(G27=0,0,H27/G27) -> 157000 | J27: =IF(G27=0,0,MINIFS('11.Empreendimentos'!$G$460,'11.Empreendimentos'!$G$460,">0")) -> 157000 | K27: =IF(G27=0,0,MAXIFS('11.Empreendimentos'!$G$460,'11.Empreendimentos'!$G$460,">0")) -> 157000 | L27: =IF(OR(F27=0,I27=0),0,I27/F27-1) -> 2.4888889
A28: 24 | B28: Industrial Vicentino | C28: Farroupilha | D28: =IF(ISNUMBER('11.Empreendimentos'!C462),N('11.Empreendimentos'!C463),0) -> 11 | E28: =IF(ISNUMBER('11.Empreendimentos'!C462),'11.Empreendimentos'!C462,0) -> 8800000 | F28: =IF(D28=0,0,E28/D28) -> 800000 | G28: =COUNTIF('11.Empreendimentos'!$G$464:$G$468,">0") -> 4 | H28: =SUMIF('11.Empreendimentos'!$G$464:$G$468,">0") -> 5420000 | I28: =IF(G28=0,0,H28/G28) -> 1355000 | J28: =IF(G28=0,0,MINIFS('11.Empreendimentos'!$G$464:$G$468,'11.Empreendimentos'!$G$464:$G$468,">0")) -> 1355000 | K28: =IF(G28=0,0,MAXIFS('11.Empreendimentos'!$G$464:$G$468,'11.Empreendimentos'!$G$464:$G$468,">0")) -> 1355000 | L28: =IF(OR(F28=0,I28=0),0,I28/F28-1) -> 0.69375
A29: 25 | B29: Jardim Itália I – II – III | C29: Farroupilha | D29: =IF(ISNUMBER('11.Empreendimentos'!C470),N('11.Empreendimentos'!C471),0) -> 40 | E29: =IF(ISNUMBER('11.Empreendimentos'!C470),'11.Empreendimentos'!C470,0) -> 4000000 | F29: =IF(D29=0,0,E29/D29) -> 100000 | G29: =COUNTIF('11.Empreendimentos'!$G$472:$G$498,">0") -> 27 | H29: =SUMIF('11.Empreendimentos'!$G$472:$G$498,">0") -> 5823000 | I29: =IF(G29=0,0,H29/G29) -> 215666.67 | J29: =IF(G29=0,0,MINIFS('11.Empreendimentos'!$G$472:$G$498,'11.Empreendimentos'!$G$472:$G$498,">0")) -> 192000 | K29: =IF(G29=0,0,MAXIFS('11.Empreendimentos'!$G$472:$G$498,'11.Empreendimentos'!$G$472:$G$498,">0")) -> 264000 | L29: =IF(OR(F29=0,I29=0),0,I29/F29-1) -> 1.1566667
A30: 26 | B30: Altos da Julieta I – II | C30: Farroupilha | D30: =IF(ISNUMBER('11.Empreendimentos'!C500),N('11.Empreendimentos'!C501),0) -> 40 | E30: =IF(ISNUMBER('11.Empreendimentos'!C500),'11.Empreendimentos'!C500,0) -> 3600000 | F30: =IF(D30=0,0,E30/D30) -> 90000 | G30: =COUNTIF('11.Empreendimentos'!$G$502:$G$511,">0") -> 10 | H30: =SUMIF('11.Empreendimentos'!$G$502:$G$511,">0") -> 2086000 | I30: =IF(G30=0,0,H30/G30) -> 208600 | J30: =IF(G30=0,0,MINIFS('11.Empreendimentos'!$G$502:$G$511,'11.Empreendimentos'!$G$502:$G$511,">0")) -> 148000 | K30: =IF(G30=0,0,MAXIFS('11.Empreendimentos'!$G$502:$G$511,'11.Empreendimentos'!$G$502:$G$511,">0")) -> 432000 | L30: =IF(OR(F30=0,I30=0),0,I30/F30-1) -> 1.3177778
A31: 27 | B31: Monte Vêneto I – II | C31: Cotiporã | D31: =IF(ISNUMBER('11.Empreendimentos'!C513),N('11.Empreendimentos'!C514),0) -> 80 | E31: =IF(ISNUMBER('11.Empreendimentos'!C513),'11.Empreendimentos'!C513,0) -> 5600000 | F31: =IF(D31=0,0,E31/D31) -> 70000 | G31: =COUNTIF('11.Empreendimentos'!$G$515:$G$574,">0") -> 60 | H31: =SUMIF('11.Empreendimentos'!$G$515:$G$574,">0") -> 5336000 | I31: =IF(G31=0,0,H31/G31) -> 88933.333 | J31: =IF(G31=0,0,MINIFS('11.Empreendimentos'!$G$515:$G$574,'11.Empreendimentos'!$G$515:$G$574,">0")) -> 77000 | K31: =IF(G31=0,0,MAXIFS('11.Empreendimentos'!$G$515:$G$574,'11.Empreendimentos'!$G$515:$G$574,">0")) -> 106000 | L31: =IF(OR(F31=0,I31=0),0,I31/F31-1) -> 0.27047619
A32: 28 | B32: Nossa Senhora da Saúde | C32: Guaporé | D32: =IF(ISNUMBER('11.Empreendimentos'!C576),N('11.Empreendimentos'!C577),0) -> 4 | E32: =IF(ISNUMBER('11.Empreendimentos'!C576),'11.Empreendimentos'!C576,0) -> 320000 | F32: =IF(D32=0,0,E32/D32) -> 80000 | G32: =COUNTIF('11.Empreendimentos'!$G$578:$G$581,">0") -> 4 | H32: =SUMIF('11.Empreendimentos'!$G$578:$G$581,">0") -> 533000 | I32: =IF(G32=0,0,H32/G32) -> 133250 | J32: =IF(G32=0,0,MINIFS('11.Empreendimentos'!$G$578:$G$581,'11.Empreendimentos'!$G$578:$G$581,">0")) -> 110000 | K32: =IF(G32=0,0,MAXIFS('11.Empreendimentos'!$G$578:$G$581,'11.Empreendimentos'!$G$578:$G$581,">0")) -> 146000 | L32: =IF(OR(F32=0,I32=0),0,I32/F32-1) -> 0.665625
A33: 29 | B33: Alto das Graças I | C33: Caxias do Sul | D33: =IF(ISNUMBER('11.Empreendimentos'!C583),N('11.Empreendimentos'!C584),0) -> 51 | E33: =IF(ISNUMBER('11.Empreendimentos'!C583),'11.Empreendimentos'!C583,0) -> 5100000 | F33: =IF(D33=0,0,E33/D33) -> 100000 | G33: =COUNTIF('11.Empreendimentos'!$G$585:$G$598,">0") -> 14 | H33: =SUMIF('11.Empreendimentos'!$G$585:$G$598,">0") -> 3699000 | I33: =IF(G33=0,0,H33/G33) -> 264214.29 | J33: =IF(G33=0,0,MINIFS('11.Empreendimentos'!$G$585:$G$598,'11.Empreendimentos'!$G$585:$G$598,">0")) -> 141000 | K33: =IF(G33=0,0,MAXIFS('11.Empreendimentos'!$G$585:$G$598,'11.Empreendimentos'!$G$585:$G$598,">0")) -> 416000 | L33: =IF(OR(F33=0,I33=0),0,I33/F33-1) -> 1.6421429
A34: 30 | B34: Família Falavigna | C34: Flores da Cunha | D34: =IF(ISNUMBER('11.Empreendimentos'!C600),N('11.Empreendimentos'!C601),0) -> 50 | E34: =IF(ISNUMBER('11.Empreendimentos'!C600),'11.Empreendimentos'!C600,0) -> 5000000 | F34: =IF(D34=0,0,E34/D34) -> 100000 | G34: =COUNTIF('11.Empreendimentos'!$G$602:$G$631,">0") -> 30 | H34: =SUMIF('11.Empreendimentos'!$G$602:$G$631,">0") -> 18216000 | I34: =IF(G34=0,0,H34/G34) -> 607200 | J34: =IF(G34=0,0,MINIFS('11.Empreendimentos'!$G$602:$G$631,'11.Empreendimentos'!$G$602:$G$631,">0")) -> 405000 | K34: =IF(G34=0,0,MAXIFS('11.Empreendimentos'!$G$602:$G$631,'11.Empreendimentos'!$G$602:$G$631,">0")) -> 934000 | L34: =IF(OR(F34=0,I34=0),0,I34/F34-1) -> 5.072
A35: 31 | B35: Reserva Paradiso | C35: Carlos Barbosa | D35: =IF(ISNUMBER('11.Empreendimentos'!C634),N('11.Empreendimentos'!C635),0) -> 0 | E35: =IF(ISNUMBER('11.Empreendimentos'!C634),'11.Empreendimentos'!C634,0) -> 0 | F35: =IF(D35=0,0,E35/D35) -> 0 | G35: =COUNTIF('11.Empreendimentos'!$G$636,">0") -> 1 | H35: =SUMIF('11.Empreendimentos'!$G$636,">0") -> 500000 | I35: =IF(G35=0,0,H35/G35) -> 500000 | J35: =IF(G35=0,0,MINIFS('11.Empreendimentos'!$G$636,'11.Empreendimentos'!$G$636,">0")) -> 500000 | K35: =IF(G35=0,0,MAXIFS('11.Empreendimentos'!$G$636,'11.Empreendimentos'!$G$636,">0")) -> 500000 | L35: =IF(OR(F35=0,I35=0),0,I35/F35-1) -> 0
B36: Total / média geral | D36: =SUM(D5:D35) -> 715 | E36: =SUM(E5:E35) -> 94485000 | F36: =IF(D36=0,0,E36/D36) -> 132146.85 | G36: =SUM(G5:G35) -> 414 | H36: =SUM(H5:H35) -> 111179000 | I36: =IF(G36=0,0,H36/G36) -> 268548.31 | J36: =MINIFS(J5:J35,J5:J35,">0") -> 77000 | K36: =MAX(K5:K35) -> 1520000 | L36: =IF(OR(F36=0,I36=0),0,I36/F36-1) -> 1.032196

Sheet Lotes que saíram 2018-2025
A1: Lotes que existiam em 2018 e não constam em out/2025
A2: Lista montada cruzando a aba 11.Empreendimentos (inventário de 2018 e lista de outubro 2025) com o arquivo 17 (lotes vendidos de jan/2018 a out/2025, rev. 13/08/2026) e o arquivo 18 (lotes vendidos e pagamentos de Válter Siviero), ambos da pasta "2026-08-13 — [siviero] respostas docs". O inventário de 2018 só informa a quantidade de lotes por loteamento, por isso o resumo compara essa quantidade com os lotes identificados.
A4: Resumo por loteamento
A5: Loteamento | B5: Cidade | C5: Lotes 2018 | D5: Lotes out/2025 | E5: Redução 2018 → 2025 | F5: Lotes na lista | G5: Na lista com data anterior a 2018 | H5: Diferença (lista − redução) | I5: Observação
A6: Sol Nascente I | B6: Antônio Prado | C6: =N('11.Empreendimentos'!C96) -> 14 | D6: =N('11.Empreendimentos'!G96) -> 11 | E6: =C6-D6 -> 3 | F6: =COUNTIF($A$61:$A$469,A6) -> 6 | G6: =COUNTIFS($A$61:$A$469,A6,$E$61:$E$469,"<"&DATE(2018,1,1)) -> 0 | H6: =F6-E6 -> 3 | I6: Os 3 lotes do arquivo 18 (5/C, 6/C e 8/F, de 04/12/2018) provavelmente já estavam fora da contagem de 2018. O mesmo registro cita os lotes 1/A e 2/A, que ainda constam em out/2025.
A7: Boito | B7: Nova Prata | C7: =N('11.Empreendimentos'!C113) -> 1 | D7: =N('11.Empreendimentos'!G113) -> 1 | E7: =C7-D7 -> 0 | F7: =COUNTIF($A$61:$A$469,A7) -> 0 | G7: =COUNTIFS($A$61:$A$469,A7,$E$61:$E$469,"<"&DATE(2018,1,1)) -> 0 | H7: =F7-E7 -> 0
A8: Condomínio Morada do Ipê I | B8: Passo Fundo | C8: =N('11.Empreendimentos'!C117) -> 29 | D8: =N('11.Empreendimentos'!G117) -> 1 | E8: =C8-D8 -> 28 | F8: =COUNTIF($A$61:$A$469,A8) -> 31 | G8: =COUNTIFS($A$61:$A$469,A8,$E$61:$E$469,"<"&DATE(2018,1,1)) -> 0 | H8: =F8-E8 -> 3 | I8: O arquivo 17 lista 30 vendas para 29 lotes em 2018, e o lote O01/2 saiu entre dez/2024 e out/2025 sem registro de venda. A aba 11.Empreendimentos já pede para verificar quantos lotes a Siviero recebeu.
A9: Fracionamento Simioni | B9: Veranópolis | C9: =N('11.Empreendimentos'!C122) -> 4 | D9: =N('11.Empreendimentos'!G122) -> 4 | E9: =C9-D9 -> 0 | F9: =COUNTIF($A$61:$A$469,A9) -> 0 | G9: =COUNTIFS($A$61:$A$469,A9,$E$61:$E$469,"<"&DATE(2018,1,1)) -> 0 | H9: =F9-E9 -> 0
A10: Solar Norte I e II | B10: Veranópolis | C10: =N('11.Empreendimentos'!C129) -> 10 | D10: =N('11.Empreendimentos'!G129) -> 6 | E10: =C10-D10 -> 4 | F10: =COUNTIF($A$61:$A$469,A10) -> 4 | G10: =COUNTIFS($A$61:$A$469,A10,$E$61:$E$469,"<"&DATE(2018,1,1)) -> 0 | H10: =F10-E10 -> 0
A11: Aditivo Medianeira | B11: Veranópolis | C11: =N('11.Empreendimentos'!C138) -> 20 | D11: =N('11.Empreendimentos'!G138) -> 15 | E11: =C11-D11 -> 5 | F11: =COUNTIF($A$61:$A$469,A11) -> 4 | G11: =COUNTIFS($A$61:$A$469,A11,$E$61:$E$469,"<"&DATE(2018,1,1)) -> 1 | H11: =F11-E11 -> -1 | I11: Falta 1 lote: o 2/7 foi vendido à Solar Serra em 24/04/2024 (arquivo 17), mas ainda consta em out/2025.
A12: Colina do Retiro I | B12: Veranópolis | C12: =N('11.Empreendimentos'!C156) -> 23 | D12: =N('11.Empreendimentos'!G156) -> 13 | E12: =C12-D12 -> 10 | F12: =COUNTIF($A$61:$A$469,A12) -> 10 | G12: =COUNTIFS($A$61:$A$469,A12,$E$61:$E$469,"<"&DATE(2018,1,1)) -> 0 | H12: =F12-E12 -> 0
A13: Salvador (Alberto Salvador) – Femaçã II | B13: Veranópolis | C13: =N('11.Empreendimentos'!C172) -> 36 | D13: =N('11.Empreendimentos'!G172) -> 26 | E13: =C13-D13 -> 10 | F13: =COUNTIF($A$61:$A$469,A13) -> 13 | G13: =COUNTIFS($A$61:$A$469,A13,$E$61:$E$469,"<"&DATE(2018,1,1)) -> 2 | H13: =F13-E13 -> 3 | I13: As 2 vendas anteriores a 2018 (1992 e 2006) provavelmente estão entre os 4 lotes vendidos já descontados em 2018. A aba de origem tem ainda uma linha "lotx (vendido)" sem identificação. Os 6 lotes da Família Siviero continuam em out/2025.
A14: Colina do Retiro II | B14: Veranópolis | C14: =N('11.Empreendimentos'!C209) -> 105 | D14: =N('11.Empreendimentos'!G209) -> 102 | E14: =C14-D14 -> 3 | F14: =COUNTIF($A$61:$A$469,A14) -> 6 | G14: =COUNTIFS($A$61:$A$469,A14,$E$61:$E$469,"<"&DATE(2018,1,1)) -> 2 | H14: =F14-E14 -> 3 | I14: Os lotes 1/7, 12/8 e 15/8 aparecem como saída na aba de origem, sem registro de venda. Duas vendas são de 2006 e 2009.
A15: Industrial Pedra Lisa | B15: Veranópolis | C15: =N('11.Empreendimentos'!C318) -> 39 | D15: =N('11.Empreendimentos'!G318) -> 31 | E15: =C15-D15 -> 8 | F15: =COUNTIF($A$61:$A$469,A15) -> 9 | G15: =COUNTIFS($A$61:$A$469,A15,$E$61:$E$469,"<"&DATE(2018,1,1)) -> 4 | H15: =F15-E15 -> 1 | I15: 1 lote a mais que a redução; 4 das vendas têm data anterior a 2018.
A16: Monte Vêneto | B16: Carlos Barbosa | C16: =N('11.Empreendimentos'!C352) -> 1 | D16: =N('11.Empreendimentos'!G352) -> 1 | E16: =C16-D16 -> 0 | F16: =COUNTIF($A$61:$A$469,A16) -> 0 | G16: =COUNTIFS($A$61:$A$469,A16,$E$61:$E$469,"<"&DATE(2018,1,1)) -> 0 | H16: =F16-E16 -> 0
A17: Baldasso | B17: Carlos Barbosa | C17: =N('11.Empreendimentos'!C356) -> 15 | D17: =N('11.Empreendimentos'!G356) -> 5 | E17: =C17-D17 -> 10 | F17: =COUNTIF($A$61:$A$469,A17) -> 12 | G17: =COUNTIFS($A$61:$A$469,A17,$E$61:$E$469,"<"&DATE(2018,1,1)) -> 0 | H17: =F17-E17 -> 2 | I17: O arquivo 17 lista 12 vendas para uma redução de 10. O inventário de 2018 fala em 15 lotes, de um total de 34.
A18: Colina do Basalto | B18: Nova Prata | C18: =N('11.Empreendimentos'!C364) -> 14 | D18: =N('11.Empreendimentos'!G364) -> 14 | E18: =C18-D18 -> 0 | F18: =COUNTIF($A$61:$A$469,A18) -> 0 | G18: =COUNTIFS($A$61:$A$469,A18,$E$61:$E$469,"<"&DATE(2018,1,1)) -> 0 | H18: =F18-E18 -> 0
A19: Carnevalli | B19: Nova Prata | C19: =N('11.Empreendimentos'!C381) -> 17 | D19: =N('11.Empreendimentos'!G381) -> 3 | E19: =C19-D19 -> 14 | F19: =COUNTIF($A$61:$A$469,A19) -> 14 | G19: =COUNTIFS($A$61:$A$469,A19,$E$61:$E$469,"<"&DATE(2018,1,1)) -> 0 | H19: =F19-E19 -> 0
A20: Barbiero | B20: Nova Prata | C20: =N('11.Empreendimentos'!C387) -> 20 | D20: =N('11.Empreendimentos'!G387) -> 4 | E20: =C20-D20 -> 16 | F20: =COUNTIF($A$61:$A$469,A20) -> 16 | G20: =COUNTIFS($A$61:$A$469,A20,$E$61:$E$469,"<"&DATE(2018,1,1)) -> 5 | H20: =F20-E20 -> 0
A21: Araçá | B21: Nova Araçá | C21: =N('11.Empreendimentos'!C394) -> 1 | D21: =N('11.Empreendimentos'!G394) -> 1 | E21: =C21-D21 -> 0 | F21: =COUNTIF($A$61:$A$469,A21) -> 0 | G21: =COUNTIFS($A$61:$A$469,A21,$E$61:$E$469,"<"&DATE(2018,1,1)) -> 0 | H21: =F21-E21 -> 0 | I21: O arquivo 17 cita o lote 30/C, mas informa que ele não foi vendido.
A22: Dalla Costa | B22: Nova Bassano | C22: =N('11.Empreendimentos'!C398) -> 5 | D22: =N('11.Empreendimentos'!G398) -> 4 | E22: =C22-D22 -> 1 | F22: =COUNTIF($A$61:$A$469,A22) -> 2 | G22: =COUNTIFS($A$61:$A$469,A22,$E$61:$E$469,"<"&DATE(2018,1,1)) -> 2 | H22: =F22-E22 -> 1 | I22: As 2 vendas são de 2014 e 2017, para uma redução de 1 lote.
A23: Lago Negro | B23: Gramado | C23: =N('11.Empreendimentos'!C405) -> 27 | D23: =N('11.Empreendimentos'!G405) -> 5 | E23: =C23-D23 -> 22 | F23: =COUNTIF($A$61:$A$469,A23) -> 48 | G23: =COUNTIFS($A$61:$A$469,A23,$E$61:$E$469,"<"&DATE(2018,1,1)) -> 2 | H23: =F23-E23 -> 26 | I23: O arquivo 17 lista 46 saídas (12 delas em 2018) para uma redução de 22. O inventário de 2018 indicava 35 lotes; a aba usa 27, sem 7 lotes de APP e 1 em processo. Os 2 lotes do arquivo 18 são de 2017.
A24: Perini | B24: Farroupilha | C24: =N('11.Empreendimentos'!C421) -> 10 | D24: =N('11.Empreendimentos'!G421) -> 3 | E24: =C24-D24 -> 7 | F24: =COUNTIF($A$61:$A$469,A24) -> 7 | G24: =COUNTIFS($A$61:$A$469,A24,$E$61:$E$469,"<"&DATE(2018,1,1)) -> 0 | H24: =F24-E24 -> 0
A25: San Marino | B25: Farroupilha | C25: =N('11.Empreendimentos'!C427) -> 30 | D25: =N('11.Empreendimentos'!G427) -> 8 | E25: =C25-D25 -> 22 | F25: =COUNTIF($A$61:$A$469,A25) -> 19 | G25: =COUNTIFS($A$61:$A$469,A25,$E$61:$E$469,"<"&DATE(2018,1,1)) -> 0 | H25: =F25-E25 -> -3 | I25: Faltam 3 lotes sem registro de saída. A contagem de 2018 (30) já desconta 3 lotes de possível APP.
A26: Firminio Dalzóchio | B26: Farroupilha | C26: =N('11.Empreendimentos'!C441) -> 15 | D26: =N('11.Empreendimentos'!G441) -> 8 | E26: =C26-D26 -> 7 | F26: =COUNTIF($A$61:$A$469,A26) -> 7 | G26: =COUNTIFS($A$61:$A$469,A26,$E$61:$E$469,"<"&DATE(2018,1,1)) -> 0 | H26: =F26-E26 -> 0
A27: Primavera | B27: Farroupilha | C27: =N('11.Empreendimentos'!C453) -> 2 | D27: =N('11.Empreendimentos'!G453) -> 1 | E27: =C27-D27 -> 1 | F27: =COUNTIF($A$61:$A$469,A27) -> 1 | G27: =COUNTIFS($A$61:$A$469,A27,$E$61:$E$469,"<"&DATE(2018,1,1)) -> 0 | H27: =F27-E27 -> 0
A28: Vila Vicenza | B28: Farroupilha | C28: =N('11.Empreendimentos'!C459) -> 2 | D28: =N('11.Empreendimentos'!G459) -> 1 | E28: =C28-D28 -> 1 | F28: =COUNTIF($A$61:$A$469,A28) -> 1 | G28: =COUNTIFS($A$61:$A$469,A28,$E$61:$E$469,"<"&DATE(2018,1,1)) -> 0 | H28: =F28-E28 -> 0
A29: Industrial Vicentino | B29: Farroupilha | C29: =N('11.Empreendimentos'!C463) -> 11 | D29: =N('11.Empreendimentos'!G463) -> 4 | E29: =C29-D29 -> 7 | F29: =COUNTIF($A$61:$A$469,A29) -> 7 | G29: =COUNTIFS($A$61:$A$469,A29,$E$61:$E$469,"<"&DATE(2018,1,1)) -> 2 | H29: =F29-E29 -> 0
A30: Jardim Itália I – II – III | B30: Farroupilha | C30: =N('11.Empreendimentos'!C471) -> 40 | D30: =N('11.Empreendimentos'!G471) -> 27 | E30: =C30-D30 -> 13 | F30: =COUNTIF($A$61:$A$469,A30) -> 13 | G30: =COUNTIFS($A$61:$A$469,A30,$E$61:$E$469,"<"&DATE(2018,1,1)) -> 0 | H30: =F30-E30 -> 0
A31: Altos da Julieta I – II | B31: Farroupilha | C31: =N('11.Empreendimentos'!C501) -> 40 | D31: =N('11.Empreendimentos'!G501) -> 10 | E31: =C31-D31 -> 30 | F31: =COUNTIF($A$61:$A$469,A31) -> 41 | G31: =COUNTIFS($A$61:$A$469,A31,$E$61:$E$469,"<"&DATE(2018,1,1)) -> 0 | H31: =F31-E31 -> 11 | I31: O arquivo 17 lista 41 saídas para uma redução de 30. A contagem de 2018 era aproximada: cerca de 20 lotes em cada etapa (de 47 e 42 lotes no total).
A32: Monte Vêneto I – II | B32: Cotiporã | C32: =N('11.Empreendimentos'!C514) -> 80 | D32: =N('11.Empreendimentos'!G514) -> 60 | E32: =C32-D32 -> 20 | F32: =COUNTIF($A$61:$A$469,A32) -> 21 | G32: =COUNTIFS($A$61:$A$469,A32,$E$61:$E$469,"<"&DATE(2018,1,1)) -> 2 | H32: =F32-E32 -> 1 | I32: 1 lote a mais que a redução; 2 vendas têm data anterior a 2018. O lote 6/4, vendido em 28/03/2025, ainda consta em out/2025 e não entra na lista.
A33: Nossa Senhora da Saúde | B33: Guaporé | C33: =N('11.Empreendimentos'!C577) -> 4 | D33: =N('11.Empreendimentos'!G577) -> 4 | E33: =C33-D33 -> 0 | F33: =COUNTIF($A$61:$A$469,A33) -> 0 | G33: =COUNTIFS($A$61:$A$469,A33,$E$61:$E$469,"<"&DATE(2018,1,1)) -> 0 | H33: =F33-E33 -> 0
A34: Alto das Graças I | B34: Caxias do Sul | C34: =N('11.Empreendimentos'!C584) -> 51 | D34: =N('11.Empreendimentos'!G584) -> 14 | E34: =C34-D34 -> 37 | F34: =COUNTIF($A$61:$A$469,A34) -> 59 | G34: =COUNTIFS($A$61:$A$469,A34,$E$61:$E$469,"<"&DATE(2018,1,1)) -> 7 | H34: =F34-E34 -> 22 | I34: O arquivo 17 lista 47 saídas (7 antes de 2018) e o arquivo 18 mais 12 lotes consignados a Válter Siviero, para uma redução de 37. Em 2018 a Siviero tinha 51 dos 102 lotes (50%).
A35: Família Falavigna | B35: Flores da Cunha | C35: =N('11.Empreendimentos'!C601) -> 50 | D35: =N('11.Empreendimentos'!G601) -> 30 | E35: =C35-D35 -> 20 | F35: =COUNTIF($A$61:$A$469,A35) -> 20 | G35: =COUNTIFS($A$61:$A$469,A35,$E$61:$E$469,"<"&DATE(2018,1,1)) -> 0 | H35: =F35-E35 -> 0 | I35: Inclui o lote 28/322, vendido em 2026 mas já fora da lista de out/2025. O lote 8/876, vendido em 2026, ainda consta em out/2025 e não entra.
A36: Reserva Paradiso | B36: Carlos Barbosa | C36: =N('11.Empreendimentos'!C635) -> 0 | D36: =N('11.Empreendimentos'!G635) -> 1 | E36: =C36-D36 -> -1 | F36: =COUNTIF($A$61:$A$469,A36) -> 0 | G36: =COUNTIFS($A$61:$A$469,A36,$E$61:$E$469,"<"&DATE(2018,1,1)) -> 0 | H36: =F36-E36 -> 1 | I36: Não existia em 2018: o lote 623/104 foi recebido em 19/09/2025 e vendido em 07/01/2026.
A37: Cichelero | B37: Carlos Barbosa | C37: 10 | D37: 0 | E37: =C37-D37 -> 10 | F37: =COUNTIF($A$61:$A$469,A37) -> 10 | G37: =COUNTIFS($A$61:$A$469,A37,$E$61:$E$469,"<"&DATE(2018,1,1)) -> 0 | H37: =F37-E37 -> 0
